Workbook

Sheet Start Here
B2: Basket: Produce & Recipe Library
B3: Nigerian-market produce catalogue, seasonal calendar and a recipe library of stews & sauces, breakfast plates, salads & cooked sides, fruit plates & desserts, and bowls & snacks, each scored for Basket coverage and vitamins. Version 2, 24 Oct 2026. Drinks, smoothies, juices and soups removed.
B5: Settings
B6: Basket coverage target | C6: 0.8 | D6: Share of a recipe's non-staple ingredients that should come from Basket. Set at 80% from the positioning brief. Change it and every recipe re-scores.
B8: Daily values used for the '% daily' columns
B9: Nutrient | C9: Daily value | D9: Source / note
B10: Fibre (g) | C10: 25 | D10: WHO / EFSA adult guidance of 25 g a day.
B11: Vitamin C (mg) | C11: 80 | D11: EU nutrient reference value (Reg. 1169/2011). US uses 90 mg.
B12: Vitamin A (mcg) | C12: 800 | D12: EU NRV, micrograms retinol activity equivalent. Beta-carotene in carrot, pawpaw and mango is converted at the USDA RAE rate.
B13: Vitamin K (mcg) | C13: 75 | D13: EU NRV. Leafy greens (ugu, efo, kale, spinach) dominate this column.
B14: Folate (mcg) | C14: 200 | D14: EU NRV. US uses 400 mcg DFE; pregnancy guidance is higher.
B15: Potassium (mg) | C15: 2000 | D15: EU NRV. WHO suggests 3,510 mg for adults; change here if you prefer the WHO figure.
B16: Vitamin E (mg) | C16: 12 | D16: EU NRV. Avocado, groundnut and leafy greens are the main produce sources.
B17: Vitamin B6 (mg) | C17: 1.4 | D17: EU NRV. Banana, avocado, sweet potato and garlic contribute most.
B18: Magnesium (mg) | C18: 375 | D18: EU NRV.
B19: Iron (mg) | C19: 14 | D19: EU NRV. Plant iron from greens absorbs better eaten with vitamin C (tomato, tatashe, citrus), which is why stews pair the two.
B21: At a glance
B22: Produce items catalogued | C22: =COUNTA(Produce!A2:A500) -> 84
B23: Recipes | C23: =COUNTA(Recipes!A2:A500) -> 156
B24: Stews & Sauces | C24: =COUNTIF(Recipes!C2:C500,"Stews & Sauces") -> 32
B25: Breakfast Plates | C25: =COUNTIF(Recipes!C2:C500,"Breakfast Plates") -> 24
B26: Salads & Cooked Sides | C26: =COUNTIF(Recipes!C2:C500,"Salads & Cooked Sides") -> 42
B27: Fruit Plates & Desserts | C27: =COUNTIF(Recipes!C2:C500,"Fruit Plates & Desserts") -> 24
B28: Bowls & Snacks | C28: =COUNTIF(Recipes!C2:C500,"Bowls & Snacks") -> 34
B29: Recipes hitting the coverage target | C29: =COUNTIF(Recipes!AX2:AX500,"Yes") -> 60
B30: Average Basket coverage | C30: =AVERAGE(Recipes!AW2:AW500) -> 0.73825651
B31: Recipes giving 50%+ of daily vitamin C | C31: =COUNTIF(Recipes!AG2:AG500,">=0.5") -> 92
B32: Recipes giving 50%+ of daily vitamin A | C32: =COUNTIF(Recipes!AH2:AH500,">=0.5") -> 28
B33: Recipes with a reference image | C33: =COUNTIF(Recipes!I2:I500,"http*") -> 140
B34: Produce in season this month | C34: =COUNTIF(Produce!J2:J500,"Peak")+COUNTIF(Produce!J2:J500,"In") -> 69
B35: Vegan / plant-based recipes | C35: =COUNTIF(Recipes!M2:M500,"Vegan") -> 74
B36: No-cook recipes | C36: =COUNTIF(Recipes!Q2:Q500,"No-cook") -> 45
B38: What's in each tab
B39: Produce | C39: Every fruit, vegetable, herb and nut worth stocking: local names, season, role, sell unit, benchmark price, storage, launch tier, and how many recipes use it.
B40: Seasonal Calendar | C40: Month-by-month availability. The Produce tab reads this to show what is in season today.
B41: Nutrition | C41: Per-100 g vitamins and minerals for every produce item (USDA / FAO), plus typical piece and cup weights. Recipe nutrition is computed from this.
B42: Recipes | C42: The library. Five categories, the global dish each is based on, source page and reference image, what changed for Lagos, what the customer adds (rice, protein, bread), timings, kcal, vitamins per serving, % of daily values, an auto-generated health tagline, the other nutrients above 25% of a day, method and Basket coverage.
B43: Recipe Ingredients | C43: One row per ingredient with quantity, unit, source (Basket / Protein / Pantry / Staple) and an estimated gram weight. Coverage scores and vitamins are built from this table.
B44: Box Ideas | C44: Seasonal drops and themed baskets, each linked to the recipes it unlocks.
B45: Market Scan | C45: What the Lagos players and the international meal kits do, what to borrow, and the gap Basket can own.
B46: Sources | C46: Every recipe page, nutrition database and document used.
B48: How to edit
B49: Yellow cells | C49: Your inputs: coverage target, daily values, Basket price and Stock it? on Produce, Status on Recipes, Est. g on Recipe Ingredients. Everything else updates from them.
B50: Add a recipe | C50: Add a row on Recipes and copy the formulas from the row above (Total, Effort tier, Produce g, every nutrient and % daily column, Strongest nutrient, Health tagline, Basket items, Other items, coverage, Hits target). Then add its ingredients on Recipe Ingredients with the same Recipe ID, the Produce ID for anything Basket sells, and an estimated gram weight.
B51: Add produce | C51: Add a row on Produce, a matching row on Seasonal Calendar, and a matching row on Nutrition with per-100 g values.
B52: Source column | C52: Basket = produce we sell. Protein and Pantry count against coverage and are what the customer adds. Staple (salt, oil, water, seasoning cube) is ignored.
B53: Vitamins | C53: Computed from Basket produce only, per serving, using Est. g x Nutrition per 100 g. Protein, oil, bread and rice are not counted, so kcal (a manual estimate of the whole plate) and vitamins are on different bases on purpose: the vitamin story is the produce story.
B54: Images | C54: Reference image URL points at the source site's photo for art direction only. Shoot or generate Basket's own photos before publishing; do not reuse the source images in the app.
B56: What changed in version 2
B57: • Removed every smoothie, juice, drink and soup (19 recipes), plantain-led plates (chips, plantain frittata, bean & plantain burrito), frozen juice pops, and two protein-led mains (sheet-pan chicken, foil-baked fish). Basket is fruit and vegetables; recipes exist to make them more interesting.
B58: • Reorganised into five categories: Stews & Sauces (chunky, stir-fried, eaten with rice, yam, pasta or bread the customer already has), Breakfast Plates, Salads & Cooked Sides, Fruit Plates & Desserts, Bowls & Snacks. Mango salsa and scent-leaf chimichurri became sauces; the fish and chicken moved to 'you add'.
B59: • Added recipes from recipe sites worldwide, each adapted to Lagos produce and names (tatashe, ata rodo, ugu, efo tete, garden egg, scent leaf), with the source page and a reference image link.
B60: • New Nutrition tab and ten vitamin / mineral columns per recipe, each as a % of a daily value, plus a formula-written health tagline ('Best for better vitamin C intake...') for the health path in the app.
B61: • 'Serve with / you add' column states what the customer brings (rice, protein, eggs, bread) so a stew or sauce reads as an idea to add to the food Nigerians already eat.
B63: Caveats
B64: • Calories and protein are rough per-serving estimates of the whole plate for filtering and planning. Vitamins are computed from produce weights that are themselves estimates (a 'medium tomato', a 'cup of leaves'). Treat both as indicative; have a nutritionist check the figures before they go into the app.
B65: • Vitamin A is in micrograms RAE. Beta-carotene foods (carrot, pawpaw, mango, ugu) convert at the USDA rate; cooking and oil improve absorption, so a cooked stew with oil may deliver more than a raw plate shows.
B66: • Reference images belong to the source sites. They are here for art direction and to brief a photographer or image generator, not for publishing.
B67: • Season confidence: 'Sourced' rows on Produce come from the Kitchen Butterfly calendar; 'Verify' rows are market knowledge. Confirm both with suppliers in the pilot.
B68: • Benchmark prices are competitor retail prices captured on 11 Oct 2026, not wholesale cost.

Sheet Produce
A1: ID | B1: Produce | C1: Local names | D1: Category | E1: Origin | F1: Role | G1: Availability | H1: Season | I1: Peak | J1: In season now? | K1: Season confidence | L1: Sell unit | M1: Benchmark price (N) | N1: Benchmark unit | O1: Benchmark source | P1: Basket price (N) | Q1: Stock it? | R1: Launch tier | S1: Used in # recipes | T1: Storage | U1: Shelf life | V1: Sourcing region | W1: Best for | X1: Notes
A2: P001 | B2: Banana | C2: Ogede wewe (Yor), Ayaba (Hau) | D2: Fruit | E2: Local | F2: Eat as-is + recipes | G2: Year-round | H2: All year | J2: =IFERROR(IF(INDEX('Seasonal Calendar'!$C$2:$N$500,MATCH(A2,'Seasonal Calendar'!$A$2:$A$500,0),MONTH(TODAY()))="","Out",INDEX('Seasonal Calendar'!$C$2:$N$500,MATCH(A2,'Seasonal Calendar'!$A$2:$A$500,0),MONTH(TODAY()))),"") -> In | K2: Verify | L2: Hand (~1kg) | M2: 1850 | N2: 1kg | O2: The Fresh Place (thefreshplace.ng), 11 Oct 2026 | Q2: Y | R2: Core | S2: =COUNTIF('Recipe Ingredients'!$F$2:$F$2000,A2) -> 8 | T2: Room temp; fridge once fully ripe (skin darkens, flesh holds) | U2: 3-5 days | V2: Ondo, Ogun, Cross River, Edo | W2: Training, Energy | X2: Most-used fruit in the recipe library. Sell spotty, very ripe bananas as discounted 'smoothie bananas' rather than writing them off.
A3: P002 | B3: Plantain (ripe & unripe) | C3: Ogede agbagba (Yor), Agade (Hau) | D3: Fruit (cooking) | E3: Local | F3: Recipe ingredient | G3: Year-round | H3: All year | J3: =IFERROR(IF(INDEX('Seasonal Calendar'!$C$2:$N$500,MATCH(A3,'Seasonal Calendar'!$A$2:$A$500,0),MONTH(TODAY()))="","Out",INDEX('Seasonal Calendar'!$C$2:$N$500,MATCH(A3,'Seasonal Calendar'!$A$2:$A$500,0),MONTH(TODAY()))),"") -> In | K3: Verify | L3: Finger / bunch | Q3: Y | R3: Core | S3: =COUNTIF('Recipe Ingredients'!$F$2:$F$2000,A3) -> 2 | T3: Room temp; ripens in 3-6 days | U3: 5-10 days | V3: Ondo, Edo, Ogun, Cross River | W3: Training, Energy | X3: Sell by ripeness stage (green, yellow, black-spotted) so recipes get the right one.
A4: P003 | B4: Pineapple | C4: Ope oyinbo (Yor), Abarba (Hau) | D4: Fruit | E4: Local | F4: Eat as-is + recipes | G4: Year-round | H4: All year | J4: =IFERROR(IF(INDEX('Seasonal Calendar'!$C$2:$N$500,MATCH(A4,'Seasonal Calendar'!$A$2:$A$500,0),MONTH(TODAY()))="","Out",INDEX('Seasonal Calendar'!$C$2:$N$500,MATCH(A4,'Seasonal Calendar'!$A$2:$A$500,0),MONTH(TODAY()))),"") -> In | K4: Verify | L4: Piece | M4: 1300 | N4: 1 pc | O4: Mint Foods (mintfoods.store), 11 Oct 2026; Bendel pineapple N3,000/pc at The Fresh Place (thefreshplace.ng), 11 Oct 2026 | Q4: Y | R4: Core | S4: =COUNTIF('Recipe Ingredients'!$F$2:$F$2000,A4) -> 13 | T4: Room temp until fragrant; fridge once cut | U4: 3-5 days whole, 3 days cut | V4: Edo (Bendel), Ogun, Oyo, Delta | W4: Hydration, Wellness | X4: Bendel and sugarloaf types are sweeter than imported. Price gap between sellers is wide (N1,300 vs N3,000).
A5: P004 | B5: Watermelon | C5: Bara (Yor), Kankana (Hau) | D5: Fruit | E5: Local | F5: Eat as-is + recipes | G5: Year-round | H5: All year | I5: Dec-Apr | J5: =IFERROR(IF(INDEX('Seasonal Calendar'!$C$2:$N$500,MATCH(A5,'Seasonal Calendar'!$A$2:$A$500,0),MONTH(TODAY()))="","Out",INDEX('Seasonal Calendar'!$C$2:$N$500,MATCH(A5,'Seasonal Calendar'!$A$2:$A$500,0),MONTH(TODAY()))),"") -> In | K5: Verify | L5: Piece (S/M/L) or half | Q5: Y | R5: Core | S5: =COUNTIF('Recipe Ingredients'!$F$2:$F$2000,A5) -> 4 | T5: Whole at room temp; cut in fridge, wrapped | U5: 1-2 weeks whole, 3 days cut | V5: Kano, Kaduna, Jigawa, Plateau | W5: Hydration, Weight management | X5: Listed by Kitchen Butterfly as available all year; northern supply heaviest in the dry season.
A6: P005 | B6: Pawpaw (papaya) | C6: Ibepe (Yor), Gwanda (Hau) | D6: Fruit | E6: Local | F6: Eat as-is + recipes | G6: Year-round | H6: All year | J6: =IFERROR(IF(INDEX('Seasonal Calendar'!$C$2:$N$500,MATCH(A6,'Seasonal Calendar'!$A$2:$A$500,0),MONTH(TODAY()))="","Out",INDEX('Seasonal Calendar'!$C$2:$N$500,MATCH(A6,'Seasonal Calendar'!$A$2:$A$500,0),MONTH(TODAY()))),"") -> In | K6: Verify | L6: Piece | Q6: Y | R6: Core | S6: =COUNTIF('Recipe Ingredients'!$F$2:$F$2000,A6) -> 9 | T6: Ripen at room temp; fridge when soft | U6: 2-4 days ripe | V6: Nationwide | W6: Gut health, Weight management | X6: Unripe (green) pawpaw is a recipe ingredient too (green papaya salad).
A7: P006 | B7: Mango | C7: Mangoro (Yor/Hau) | D7: Fruit | E7: Local | F7: Eat as-is + recipes | G7: Seasonal | H7: Feb-May, Aug-Sep | I7: Mar-Apr | J7: =IFERROR(IF(INDEX('Seasonal Calendar'!$C$2:$N$500,MATCH(A7,'Seasonal Calendar'!$A$2:$A$500,0),MONTH(TODAY()))="","Out",INDEX('Seasonal Calendar'!$C$2:$N$500,MATCH(A7,'Seasonal Calendar'!$A$2:$A$500,0),MONTH(TODAY()))),"") -> Out | K7: Sourced | L7: Piece / 1kg | M7: 500 | N7: 1 pc (cherry mango) | O7: The Fresh Place (thefreshplace.ng), 11 Oct 2026 | Q7: Seasonal | R7: Seasonal drop | S7: =COUNTIF('Recipe Ingredients'!$F$2:$F$2000,A7) -> 15 | T7: Room temp to ripen; fridge when ripe | U7: 3-5 days ripe | V7: Oyo (Ogbomoso), Benue, Kaduna, Niger | W7: Energy, Wellness | X7: Main season Feb-May with a smaller Aug-Sep run. Varieties worth naming on the app: Ogbomoso, Julie, cherry, 'German'.
A8: P007 | B8: Orange | C8: Osan (Yor), Oroma (Igbo), Lemu (Hau) | D8: Fruit (citrus) | E8: Local + imported | F8: Eat as-is + recipes | G8: Year-round | H8: All year | I8: Oct-Jan | J8: =IFERROR(IF(INDEX('Seasonal Calendar'!$C$2:$N$500,MATCH(A8,'Seasonal Calendar'!$A$2:$A$500,0),MONTH(TODAY()))="","Out",INDEX('Seasonal Calendar'!$C$2:$N$500,MATCH(A8,'Seasonal Calendar'!$A$2:$A$500,0),MONTH(TODAY()))),"") -> Peak | K8: Sourced | L8: Piece / dozen | M8: 950 | N8: 1 pc imported | O8: The Fresh Place (thefreshplace.ng), 11 Oct 2026; South African 5 pcs N4,750 at Mint Foods (mintfoods.store), 11 Oct 2026 | Q8: Y | R8: Core | S8: =COUNTIF('Recipe Ingredients'!$F$2:$F$2000,A8) -> 7 | T8: Room temp 1 week; fridge 2-3 weeks | U8: 1-3 weeks | V8: Benue (citrus belt), Ogun, Oyo | W8: Wellness, Hydration | X8: Available all year with varying quality; best fruit Oct-Dec per Kitchen Butterfly.
A9: P008 | B9: Tangerine | D9: Fruit (citrus) | E9: Local + imported | F9: Eat as-is + recipes | G9: Year-round | H9: All year | I9: Oct-Jan | J9: =IFERROR(IF(INDEX('Seasonal Calendar'!$C$2:$N$500,MATCH(A9,'Seasonal Calendar'!$A$2:$A$500,0),MONTH(TODAY()))="","Out",INDEX('Seasonal Calendar'!$C$2:$N$500,MATCH(A9,'Seasonal Calendar'!$A$2:$A$500,0),MONTH(TODAY()))),"") -> Peak | K9: Sourced | L9: Piece | M9: 300 | N9: 1 pc local | O9: The Fresh Place (thefreshplace.ng), 11 Oct 2026; imported clementine N850 | Q9: Y | R9: Core | S9: =COUNTIF('Recipe Ingredients'!$F$2:$F$2000,A9) -> 2 | T9: Room temp 1 week; fridge 2 weeks | U9: 1-2 weeks | V9: Benue, Ogun | W9: Wellness | X9: Local vs imported price is nearly 3x.
A10: P009 | B10: Lemon | D10: Fruit (citrus) | E10: Local + imported | F10: Recipe ingredient | G10: Year-round | H10: All year | I10: Oct-Jan | J10: =IFERROR(IF(INDEX('Seasonal Calendar'!$C$2:$N$500,MATCH(A10,'Seasonal Calendar'!$A$2:$A$500,0),MONTH(TODAY()))="","Out",INDEX('Seasonal Calendar'!$C$2:$N$500,MATCH(A10,'Seasonal Calendar'!$A$2:$A$500,0),MONTH(TODAY()))),"") -> Peak | K10: Verify | L10: Piece | M10: 300 | N10: 1 pc local | O10: The Fresh Place (thefreshplace.ng), 11 Oct 2026; imported N950/pc; Mint Foods (mintfoods.store), 11 Oct 2026: 4 local N1,900 vs 5 Dutch N13,800 | Q10: Y | R10: Core | S10: =COUNTIF('Recipe Ingredients'!$F$2:$F$2000,A10) -> 33 | T10: Fridge | U10: 2-3 weeks | V10: Benue, Plateau | W10: Wellness | X10: Used in more recipes than almost anything else. Strong case for local-only.
A11: P010 | B11: Lime | C11: Osan wewe (Yor) | D11: Fruit (citrus) | E11: Local | F11: Recipe ingredient | G11: Year-round | H11: All year | I11: Oct-Jan | J11: =IFERROR(IF(INDEX('Seasonal Calendar'!$C$2:$N$500,MATCH(A11,'Seasonal Calendar'!$A$2:$A$500,0),MONTH(TODAY()))="","Out",INDEX('Seasonal Calendar'!$C$2:$N$500,MATCH(A11,'Seasonal Calendar'!$A$2:$A$500,0),MONTH(TODAY()))),"") -> Peak | K11: Sourced | L11: Piece / pack of 4 | Q11: Y | R11: Core | S11: =COUNTIF('Recipe Ingredients'!$F$2:$F$2000,A11) -> 59 | T11: Fridge | U11: 2-3 weeks | V11: Benue, Ogun, Oyo | W11: Wellness | X11: Best fruit Oct-Dec (Kitchen Butterfly). Workhorse acid for salsas, dressings and drinks.
A12: P011 | B12: Grapefruit | D12: Fruit (citrus) | E12: Local | F12: Eat as-is + recipes | G12: Year-round | H12: All year | I12: Oct-Jan | J12: =IFERROR(IF(INDEX('Seasonal Calendar'!$C$2:$N$500,MATCH(A12,'Seasonal Calendar'!$A$2:$A$500,0),MONTH(TODAY()))="","Out",INDEX('Seasonal Calendar'!$C$2:$N$500,MATCH(A12,'Seasonal Calendar'!$A$2:$A$500,0),MONTH(TODAY()))),"") -> Peak | K12: Verify | L12: Piece | Q12: N | R12: Later | S12: =COUNTIF('Recipe Ingredients'!$F$2:$F$2000,A12) -> 2 | T12: Room temp / fridge | U12: 2-3 weeks | V12: Benue | W12: Weight management | X12: Niche but cheap locally. Good add-on for citrus boxes.
A13: P012 | B13: Avocado | C13: Pia (Yor) | D13: Fruit | E13: Local + imported | F13: Eat as-is + recipes | G13: Year-round | H13: All year | J13: =IFERROR(IF(INDEX('Seasonal Calendar'!$C$2:$N$500,MATCH(A13,'Seasonal Calendar'!$A$2:$A$500,0),MONTH(TODAY()))="","Out",INDEX('Seasonal Calendar'!$C$2:$N$500,MATCH(A13,'Seasonal Calendar'!$A$2:$A$500,0),MONTH(TODAY()))),"") -> In | K13: Verify | L13: Piece | M13: 2000 | N13: 1 pc medium | O13: The Fresh Place (thefreshplace.ng), 11 Oct 2026; big N2,500; Mint Foods (mintfoods.store), 11 Oct 2026: local N1,050, imported 2-pack N7,300 | Q13: Y | R13: Core | S13: =COUNTIF('Recipe Ingredients'!$F$2:$F$2000,A13) -> 16 | T13: Room temp to ripen; fridge once ripe | U13: 2-3 days ripe | V13: Southwest, Cross River, Plateau | W13: Training, Wellness | X13: Local supply and quality swing through the year. Confirm local peak months with suppliers. Mint sells a ready-to-eat 'eat me' pack, worth copying.
A14: P013 | B14: Guava | C14: Gova (Yor), Gwaba (Hau) | D14: Fruit | E14: Local + imported | F14: Eat as-is + recipes | G14: Seasonal | H14: Feb-Mar, Aug-Sep | I14: Feb-Mar | J14: =IFERROR(IF(INDEX('Seasonal Calendar'!$C$2:$N$500,MATCH(A14,'Seasonal Calendar'!$A$2:$A$500,0),MONTH(TODAY()))="","Out",INDEX('Seasonal Calendar'!$C$2:$N$500,MATCH(A14,'Seasonal Calendar'!$A$2:$A$500,0),MONTH(TODAY()))),"") -> Out | K14: Sourced | L14: Piece / 1kg | M14: 16000 | N14: 1kg imported | O14: The Fresh Place (thefreshplace.ng), 11 Oct 2026 | Q14: Seasonal | R14: Seasonal drop | S14: =COUNTIF('Recipe Ingredients'!$F$2:$F$2000,A14) -> 2 | T14: Room temp; fridge when soft | U14: 3-4 days | V14: Nationwide | W14: Wellness | X14: Two short local windows. Imported guava sells at a premium.
A15: P014 | B15: Soursop | D15: Fruit | E15: Local | F15: Eat as-is + recipes | G15: Seasonal | H15: Dec-Mar, May-Aug, Oct | I15: Feb-Mar | J15: =IFERROR(IF(INDEX('Seasonal Calendar'!$C$2:$N$500,MATCH(A15,'Seasonal Calendar'!$A$2:$A$500,0),MONTH(TODAY()))="","Out",INDEX('Seasonal Calendar'!$C$2:$N$500,MATCH(A15,'Seasonal Calendar'!$A$2:$A$500,0),MONTH(TODAY()))),"") -> In | K15: Sourced | L15: Piece / 1kg | M15: 5500 | N15: 1kg | O15: The Fresh Place (thefreshplace.ng), 11 Oct 2026 | Q15: Seasonal | R15: Seasonal drop | S15: =COUNTIF('Recipe Ingredients'!$F$2:$F$2000,A15) -> 0 | T15: Room temp until soft; fridge after | U15: 2-3 days ripe | V15: Southwest, South-south | W15: Wellness | X15: Seeds must be removed before blending.
A16: P015 | B16: Passion fruit | D16: Fruit | E16: Local + imported | F16: Recipe ingredient | G16: Seasonal | H16: Jan-Mar, May-Jun, Aug-Nov | J16: =IFERROR(IF(INDEX('Seasonal Calendar'!$C$2:$N$500,MATCH(A16,'Seasonal Calendar'!$A$2:$A$500,0),MONTH(TODAY()))="","Out",INDEX('Seasonal Calendar'!$C$2:$N$500,MATCH(A16,'Seasonal Calendar'!$A$2:$A$500,0),MONTH(TODAY()))),"") -> In | K16: Sourced | L16: Pack of 4 | M16: 7280 | N16: 4 pcs imported | O16: Mint Foods (mintfoods.store), 11 Oct 2026; imported 1kg N40,000 at The Fresh Place (thefreshplace.ng), 11 Oct 2026 | Q16: N | R16: Premium | S16: =COUNTIF('Recipe Ingredients'!$F$2:$F$2000,A16) -> 3 | T16: Room temp; fridge when wrinkled | U16: 1-2 weeks | V16: Plateau | W16: Wellness | X16: Local supply exists (Plateau). Imported is very expensive, so source locally.
A17: P016 | B17: Coconut | C17: Agbon (Yor), Kwakwa (Hau) | D17: Fruit | E17: Local | F17: Eat as-is + recipes | G17: Year-round | H17: All year | J17: =IFERROR(IF(INDEX('Seasonal Calendar'!$C$2:$N$500,MATCH(A17,'Seasonal Calendar'!$A$2:$A$500,0),MONTH(TODAY()))="","Out",INDEX('Seasonal Calendar'!$C$2:$N$500,MATCH(A17,'Seasonal Calendar'!$A$2:$A$500,0),MONTH(TODAY()))),"") -> In | K17: Verify | L17: Piece | M17: 1300 | N17: 1 dry coconut | O17: Mint Foods (mintfoods.store), 11 Oct 2026 | Q17: Y | R17: Core | S17: =COUNTIF('Recipe Ingredients'!$F$2:$F$2000,A17) -> 14 | T17: Room temp | U17: 2-3 weeks whole | V17: Lagos (Badagry), Ogun, Ondo coast | W17: Plant-based, Hydration | X17: Fresh coconut milk replaces canned in most recipes here.
A18: P017 | B18: Agbalumo (African star apple) | C18: Agbalumo (Yor), Udara (Igbo), 'cherry' (Lagos) | D18: Fruit | E18: Local | F18: Eat as-is only | G18: Seasonal | H18: Dec-May | I18: Jan-Mar | J18: =IFERROR(IF(INDEX('Seasonal Calendar'!$C$2:$N$500,MATCH(A18,'Seasonal Calendar'!$A$2:$A$500,0),MONTH(TODAY()))="","Out",INDEX('Seasonal Calendar'!$C$2:$N$500,MATCH(A18,'Seasonal Calendar'!$A$2:$A$500,0),MONTH(TODAY()))),"") -> Out | K18: Sourced | L18: Pack of 10 / 20 | Q18: Seasonal | R18: Seasonal drop | S18: =COUNTIF('Recipe Ingredients'!$F$2:$F$2000,A18) -> 0 | T18: Room temp | U18: 3-5 days | V18: Southwest and Southeast forest zones | W18: Wellness | X18: Hero of the seasonal drop calendar. Wild-harvested, so grade by size and sell by count.
A19: P018 | B19: Cashew apple | C19: Kaju (Yor), Kanju (Hau) | D19: Fruit | E19: Local | F19: Eat as-is only | G19: Seasonal | H19: Feb-Mar | I19: Feb-Mar | J19: =IFERROR(IF(INDEX('Seasonal Calendar'!$C$2:$N$500,MATCH(A19,'Seasonal Calendar'!$A$2:$A$500,0),MONTH(TODAY()))="","Out",INDEX('Seasonal Calendar'!$C$2:$N$500,MATCH(A19,'Seasonal Calendar'!$A$2:$A$500,0),MONTH(TODAY()))),"") -> Out | K19: Sourced | L19: Pack | Q19: N | R19: Later | S19: =COUNTIF('Recipe Ingredients'!$F$2:$F$2000,A19) -> 0 | T19: Fridge; bruises fast | U19: 1-2 days | V19: Kogi, Oyo, Enugu | W19: Wellness | X19: Very short shelf life. Test only.
A20: P019 | B20: Velvet tamarind | C20: Awin (Yor), Icheku (Igbo), Tsamiyar kurmi (Hau) | D20: Fruit | E20: Local | F20: Eat as-is only | G20: Seasonal | H20: Jan-May | I20: Feb-Mar | J20: =IFERROR(IF(INDEX('Seasonal Calendar'!$C$2:$N$500,MATCH(A20,'Seasonal Calendar'!$A$2:$A$500,0),MONTH(TODAY()))="","Out",INDEX('Seasonal Calendar'!$C$2:$N$500,MATCH(A20,'Seasonal Calendar'!$A$2:$A$500,0),MONTH(TODAY()))),"") -> Out | K20: Sourced | L20: Cup / 100g pack | Q20: Seasonal | R20: Seasonal drop | S20: =COUNTIF('Recipe Ingredients'!$F$2:$F$2000,A20) -> 0 | T20: Dry, airtight | U20: Weeks | V20: Southwest, Southeast, North | W20: Snack | X20: Shelf-stable and nostalgic. Natural checkout add-on.
A21: P020 | B21: Hog plum | C21: Iyeye (Yor) | D21: Fruit | E21: Local | F21: Eat as-is only | G21: Seasonal | H21: Jul, Dec | I21: Jul | J21: =IFERROR(IF(INDEX('Seasonal Calendar'!$C$2:$N$500,MATCH(A21,'Seasonal Calendar'!$A$2:$A$500,0),MONTH(TODAY()))="","Out",INDEX('Seasonal Calendar'!$C$2:$N$500,MATCH(A21,'Seasonal Calendar'!$A$2:$A$500,0),MONTH(TODAY()))),"") -> Out | K21: Sourced | L21: Pack | Q21: N | R21: Later | S21: =COUNTIF('Recipe Ingredients'!$F$2:$F$2000,A21) -> 0 | T21: Fridge | U21: 1-2 days | V21: Southwest | W21: Snack | X21: Very short season and shelf life.
A22: P021 | B22: Pepper fruit | C22: Mmimi (Igbo) | D22: Fruit | E22: Local | F22: Eat as-is only | G22: Seasonal | H22: Feb-May | J22: =IFERROR(IF(INDEX('Seasonal Calendar'!$C$2:$N$500,MATCH(A22,'Seasonal Calendar'!$A$2:$A$500,0),MONTH(TODAY()))="","Out",INDEX('Seasonal Calendar'!$C$2:$N$500,MATCH(A22,'Seasonal Calendar'!$A$2:$A$500,0),MONTH(TODAY()))),"") -> Out | K22: Sourced | L22: Cup | Q22: N | R22: Later | S22: =COUNTIF('Recipe Ingredients'!$F$2:$F$2000,A22) -> 0 | T22: Room temp | U22: 3-5 days | V22: Southeast | W22: Snack
A23: P022 | B23: Monkey kola | C23: Ochicha (Igbo), Obi edun (Yor) | D23: Fruit | E23: Local | F23: Eat as-is only | G23: Seasonal | H23: May-Aug | J23: =IFERROR(IF(INDEX('Seasonal Calendar'!$C$2:$N$500,MATCH(A23,'Seasonal Calendar'!$A$2:$A$500,0),MONTH(TODAY()))="","Out",INDEX('Seasonal Calendar'!$C$2:$N$500,MATCH(A23,'Seasonal Calendar'!$A$2:$A$500,0),MONTH(TODAY()))),"") -> Out | K23: Sourced | L23: Pack | Q23: N | R23: Later | S23: =COUNTIF('Recipe Ingredients'!$F$2:$F$2000,A23) -> 0 | T23: Room temp | U23: 3-5 days | V23: Southeast, Southwest | W23: Snack
A24: P023 | B24: African pear | C24: Ube (Igbo) | D24: Fruit | E24: Local | F24: Eat as-is only | G24: Seasonal | H24: May-Sep | I24: Jun-Aug | J24: =IFERROR(IF(INDEX('Seasonal Calendar'!$C$2:$N$500,MATCH(A24,'Seasonal Calendar'!$A$2:$A$500,0),MONTH(TODAY()))="","Out",INDEX('Seasonal Calendar'!$C$2:$N$500,MATCH(A24,'Seasonal Calendar'!$A$2:$A$500,0),MONTH(TODAY()))),"") -> Out | K24: Sourced | L24: Pack of 10 | Q24: Seasonal | R24: Seasonal drop | S24: =COUNTIF('Recipe Ingredients'!$F$2:$F$2000,A24) -> 0 | T24: Room temp | U24: 2-3 days | V24: Southeast, South-south | W24: Snack | X24: Classic pairing with roasted corn. Bundle the two as a rainy season drop.
A25: P024 | B25: Tiger nut | C25: Ofio (Yor), Aki Hausa (Igbo), Aya (Hau) | D25: Nut / tuber | E25: Local | F25: Eat as-is + recipes | G25: Seasonal | H25: Nov-May, Jul-Sep | J25: =IFERROR(IF(INDEX('Seasonal Calendar'!$C$2:$N$500,MATCH(A25,'Seasonal Calendar'!$A$2:$A$500,0),MONTH(TODAY()))="","Out",INDEX('Seasonal Calendar'!$C$2:$N$500,MATCH(A25,'Seasonal Calendar'!$A$2:$A$500,0),MONTH(TODAY()))),"") -> Out | K25: Sourced | L25: Cup / 250g | Q25: Y | R25: Core | S25: =COUNTIF('Recipe Ingredients'!$F$2:$F$2000,A25) -> 3 | T25: Dry, airtight | U25: Weeks dried | V25: Kano, Kaduna, Niger | W25: Plant-based, Gut health | X25: Snack on its own or blend into kunun aya / horchata.
A26: P025 | B26: Sugarcane | C26: Ireke (Yor), Okpete (Igbo), Rake (Hau) | D26: Fruit (cane) | E26: Local | F26: Eat as-is only | G26: Seasonal | H26: Aug-Mar | J26: =IFERROR(IF(INDEX('Seasonal Calendar'!$C$2:$N$500,MATCH(A26,'Seasonal Calendar'!$A$2:$A$500,0),MONTH(TODAY()))="","Out",INDEX('Seasonal Calendar'!$C$2:$N$500,MATCH(A26,'Seasonal Calendar'!$A$2:$A$500,0),MONTH(TODAY()))),"") -> In | K26: Sourced | L26: Stick / pre-cut pack | Q26: Seasonal | R26: Seasonal drop | S26: =COUNTIF('Recipe Ingredients'!$F$2:$F$2000,A26) -> 0 | T26: Room temp; cut pieces in fridge | U26: 3-5 days | V26: North, Southwest | W26: Snack | X26: Pre-cut, peeled pieces are the only realistic delivery format.
A27: P026 | B27: Custard apple (sweetsop) | D27: Fruit | E27: Local | F27: Eat as-is only | G27: Seasonal | H27: Feb, Aug-Sep | J27: =IFERROR(IF(INDEX('Seasonal Calendar'!$C$2:$N$500,MATCH(A27,'Seasonal Calendar'!$A$2:$A$500,0),MONTH(TODAY()))="","Out",INDEX('Seasonal Calendar'!$C$2:$N$500,MATCH(A27,'Seasonal Calendar'!$A$2:$A$500,0),MONTH(TODAY()))),"") -> Out | K27: Sourced | L27: Piece | Q27: N | R27: Later | S27: =COUNTIF('Recipe Ingredients'!$F$2:$F$2000,A27) -> 0 | T27: Room temp until soft | U27: 1-2 days ripe | V27: Southwest | W27: Snack
A28: P027 | B28: Jackfruit | D28: Fruit | E28: Local | F28: Eat as-is + recipes | G28: Seasonal | H28: May-Jun | I28: May | J28: =IFERROR(IF(INDEX('Seasonal Calendar'!$C$2:$N$500,MATCH(A28,'Seasonal Calendar'!$A$2:$A$500,0),MONTH(TODAY()))="","Out",INDEX('Seasonal Calendar'!$C$2:$N$500,MATCH(A28,'Seasonal Calendar'!$A$2:$A$500,0),MONTH(TODAY()))),"") -> Out | K28: Sourced | L28: Pre-cut pods | Q28: N | R28: Later | S28: =COUNTIF('Recipe Ingredients'!$F$2:$F$2000,A28) -> 0 | T28: Fridge once cut | U28: 2-3 days cut | V28: South | W28: Snack | X28: Sell as cleaned pods, never whole.
A29: P028 | B29: June plum | D29: Fruit | E29: Local | F29: Eat as-is only | G29: Seasonal | H29: Dec-Jan | J29: =IFERROR(IF(INDEX('Seasonal Calendar'!$C$2:$N$500,MATCH(A29,'Seasonal Calendar'!$A$2:$A$500,0),MONTH(TODAY()))="","Out",INDEX('Seasonal Calendar'!$C$2:$N$500,MATCH(A29,'Seasonal Calendar'!$A$2:$A$500,0),MONTH(TODAY()))),"") -> Out | K29: Sourced | L29: Pack | Q29: N | R29: Later | S29: =COUNTIF('Recipe Ingredients'!$F$2:$F$2000,A29) -> 0 | T29: Room temp | U29: 3-5 days | V29: South | W29: Snack
A30: P029 | B30: Sweet melon (golden / cantaloupe) | D30: Fruit | E30: Local + imported | F30: Eat as-is + recipes | G30: Year-round | H30: All year | I30: Jan, May-Jun | J30: =IFERROR(IF(INDEX('Seasonal Calendar'!$C$2:$N$500,MATCH(A30,'Seasonal Calendar'!$A$2:$A$500,0),MONTH(TODAY()))="","Out",INDEX('Seasonal Calendar'!$C$2:$N$500,MATCH(A30,'Seasonal Calendar'!$A$2:$A$500,0),MONTH(TODAY()))),"") -> In | K30: Sourced | L30: Piece | M30: 15950 | N30: 1 imported galia | O30: Mint Foods (mintfoods.store), 11 Oct 2026 | Q30: N | R30: Premium | S30: =COUNTIF('Recipe Ingredients'!$F$2:$F$2000,A30) -> 2 | T30: Room temp to ripen; fridge cut | U30: 3-5 days ripe | V30: North | W30: Hydration | X30: Local golden melon in Jan and May-Jun; imported the rest of the year at a high price.
A31: P030 | B31: Dates | C31: Dabino (Hau) | D31: Fruit | E31: Local + imported | F31: Eat as-is + recipes | G31: Year-round | H31: All year | I31: Apr-Jul | J31: =IFERROR(IF(INDEX('Seasonal Calendar'!$C$2:$N$500,MATCH(A31,'Seasonal Calendar'!$A$2:$A$500,0),MONTH(TODAY()))="","Out",INDEX('Seasonal Calendar'!$C$2:$N$500,MATCH(A31,'Seasonal Calendar'!$A$2:$A$500,0),MONTH(TODAY()))),"") -> In | K31: Sourced | L31: 250g pack | Q31: Y | R31: Core | S31: =COUNTIF('Recipe Ingredients'!$F$2:$F$2000,A31) -> 6 | T31: Airtight, cool | U31: Months dried | V31: North (Borno, Yobe) + imports | W31: Training, Energy | X31: Fresh dates Apr-Jul; dried all year. Used as the natural sweetener across the library.
A32: P031 | B32: Apple (red & green) | D32: Fruit | E32: Imported | F32: Eat as-is + recipes | G32: Year-round | H32: All year | J32: =IFERROR(IF(INDEX('Seasonal Calendar'!$C$2:$N$500,MATCH(A32,'Seasonal Calendar'!$A$2:$A$500,0),MONTH(TODAY()))="","Out",INDEX('Seasonal Calendar'!$C$2:$N$500,MATCH(A32,'Seasonal Calendar'!$A$2:$A$500,0),MONTH(TODAY()))),"") -> In | K32: Verify | L32: Piece / 6-pack | M32: 500 | N32: 1 pc small | O32: The Fresh Place (thefreshplace.ng), 11 Oct 2026; Mint Foods (mintfoods.store), 11 Oct 2026 6 red N4,200, 6 green N5,000 | Q32: Y | R32: Core (imported) | S32: =COUNTIF('Recipe Ingredients'!$F$2:$F$2000,A32) -> 5 | T32: Fridge | U32: 2-4 weeks | V32: Imported (South Africa, EU) | W32: Weight management | X32: Imported, but a basket expectation in Lagos. Every competitor bundle includes it.
A33: P032 | B33: Pear | D33: Fruit | E33: Imported | F33: Eat as-is + recipes | G33: Year-round | H33: All year | J33: =IFERROR(IF(INDEX('Seasonal Calendar'!$C$2:$N$500,MATCH(A33,'Seasonal Calendar'!$A$2:$A$500,0),MONTH(TODAY()))="","Out",INDEX('Seasonal Calendar'!$C$2:$N$500,MATCH(A33,'Seasonal Calendar'!$A$2:$A$500,0),MONTH(TODAY()))),"") -> In | K33: Verify | L33: Piece | Q33: N | R33: Premium | S33: =COUNTIF('Recipe Ingredients'!$F$2:$F$2000,A33) -> 1 | T33: Fridge once ripe | U33: 1-2 weeks | V33: Imported | W33: Weight management | X33: Included in The Fresh Place bundles (10 English pears).
A34: P033 | B34: Grapes (red / black seedless) | D34: Fruit | E34: Imported | F34: Eat as-is + recipes | G34: Year-round | H34: All year | J34: =IFERROR(IF(INDEX('Seasonal Calendar'!$C$2:$N$500,MATCH(A34,'Seasonal Calendar'!$A$2:$A$500,0),MONTH(TODAY()))="","Out",INDEX('Seasonal Calendar'!$C$2:$N$500,MATCH(A34,'Seasonal Calendar'!$A$2:$A$500,0),MONTH(TODAY()))),"") -> In | K34: Verify | L34: 500g | M34: 7500 | N34: 500g | O34: Mint Foods (mintfoods.store), 11 Oct 2026; The Fresh Place (thefreshplace.ng), 11 Oct 2026 N7,500 | Q34: N | R34: Premium | S34: =COUNTIF('Recipe Ingredients'!$F$2:$F$2000,A34) -> 5 | T34: Fridge, unwashed | U34: 5-7 days | V34: Imported | W34: Snack
A35: P034 | B35: Strawberry | D35: Fruit (berry) | E35: Local + imported | F35: Eat as-is + recipes | G35: Seasonal | H35: Nov-Apr | I35: Dec-Feb | J35: =IFERROR(IF(INDEX('Seasonal Calendar'!$C$2:$N$500,MATCH(A35,'Seasonal Calendar'!$A$2:$A$500,0),MONTH(TODAY()))="","Out",INDEX('Seasonal Calendar'!$C$2:$N$500,MATCH(A35,'Seasonal Calendar'!$A$2:$A$500,0),MONTH(TODAY()))),"") -> Out | K35: Verify | L35: 250g punnet | M35: 4550 | N35: 250g Ethiopian | O35: Mint Foods (mintfoods.store), 11 Oct 2026; Dutch 400g N17,500 | Q35: N | R35: Premium | S35: =COUNTIF('Recipe Ingredients'!$F$2:$F$2000,A35) -> 7 | T35: Fridge, unwashed | U35: 2-4 days | V35: Plateau (Jos) + imports | W35: Wellness | X35: Jos strawberries are a real local story. Season window needs supplier confirmation.
A36: P035 | B36: Blueberry | D36: Fruit (berry) | E36: Imported | F36: Eat as-is + recipes | G36: Year-round | H36: All year | J36: =IFERROR(IF(INDEX('Seasonal Calendar'!$C$2:$N$500,MATCH(A36,'Seasonal Calendar'!$A$2:$A$500,0),MONTH(TODAY()))="","Out",INDEX('Seasonal Calendar'!$C$2:$N$500,MATCH(A36,'Seasonal Calendar'!$A$2:$A$500,0),MONTH(TODAY()))),"") -> In | K36: Verify | L36: 125g | M36: 5720 | N36: 125g | O36: Mint Foods (mintfoods.store), 11 Oct 2026; The Fresh Place (thefreshplace.ng), 11 Oct 2026 N6,000 | Q36: N | R36: Premium | S36: =COUNTIF('Recipe Ingredients'!$F$2:$F$2000,A36) -> 1 | T36: Fridge | U36: 5-7 days | V36: Imported | W36: Wellness
A37: P036 | B37: Kiwi | D37: Fruit | E37: Imported | F37: Eat as-is + recipes | G37: Year-round | H37: All year | J37: =IFERROR(IF(INDEX('Seasonal Calendar'!$C$2:$N$500,MATCH(A37,'Seasonal Calendar'!$A$2:$A$500,0),MONTH(TODAY()))="","Out",INDEX('Seasonal Calendar'!$C$2:$N$500,MATCH(A37,'Seasonal Calendar'!$A$2:$A$500,0),MONTH(TODAY()))),"") -> In | K37: Verify | L37: 3-pack | M37: 3450 | N37: 3 pcs | O37: Mint Foods (mintfoods.store), 11 Oct 2026 | Q37: N | R37: Premium | S37: =COUNTIF('Recipe Ingredients'!$F$2:$F$2000,A37) -> 4 | T37: Fridge | U37: 1-2 weeks | V37: Imported | W37: Wellness
A38: P037 | B38: Pomegranate | D38: Fruit | E38: Imported | F38: Eat as-is + recipes | G38: Year-round | H38: All year | J38: =IFERROR(IF(INDEX('Seasonal Calendar'!$C$2:$N$500,MATCH(A38,'Seasonal Calendar'!$A$2:$A$500,0),MONTH(TODAY()))="","Out",INDEX('Seasonal Calendar'!$C$2:$N$500,MATCH(A38,'Seasonal Calendar'!$A$2:$A$500,0),MONTH(TODAY()))),"") -> In | K38: Verify | L38: Piece | Q38: N | R38: Later | S38: =COUNTIF('Recipe Ingredients'!$F$2:$F$2000,A38) -> 1 | T38: Fridge | U38: 2-3 weeks | V38: Imported | W38: Wellness
A39: P038 | B39: Dragon fruit | D39: Fruit | E39: Local (limited) + imported | F39: Eat as-is + recipes | G39: Year-round | H39: All year | J39: =IFERROR(IF(INDEX('Seasonal Calendar'!$C$2:$N$500,MATCH(A39,'Seasonal Calendar'!$A$2:$A$500,0),MONTH(TODAY()))="","Out",INDEX('Seasonal Calendar'!$C$2:$N$500,MATCH(A39,'Seasonal Calendar'!$A$2:$A$500,0),MONTH(TODAY()))),"") -> In | K39: Verify | L39: Piece | M39: 40000 | N39: 1kg | O39: The Fresh Place (thefreshplace.ng), 11 Oct 2026 | Q39: N | R39: Later | S39: =COUNTIF('Recipe Ingredients'!$F$2:$F$2000,A39) -> 0 | T39: Fridge | U39: 5-7 days | V39: A few local farms + imports | W39: Wellness | X39: Price makes it a showpiece, not a staple.
A40: P039 | B40: Star fruit (carambola) | D40: Fruit | E40: Local | F40: Eat as-is + recipes | G40: Year-round | H40: All year | J40: =IFERROR(IF(INDEX('Seasonal Calendar'!$C$2:$N$500,MATCH(A40,'Seasonal Calendar'!$A$2:$A$500,0),MONTH(TODAY()))="","Out",INDEX('Seasonal Calendar'!$C$2:$N$500,MATCH(A40,'Seasonal Calendar'!$A$2:$A$500,0),MONTH(TODAY()))),"") -> In | K40: Verify | L40: Piece | Q40: N | R40: Later | S40: =COUNTIF('Recipe Ingredients'!$F$2:$F$2000,A40) -> 0 | T40: Room temp / fridge | U40: 3-5 days | V40: South | W40: Snack | X40: Availability is patchy. Verify with suppliers.
A41: P040 | B41: Groundnut (fresh or roasted) | C41: Epa (Yor), Gyada (Hau) | D41: Nut / legume | E41: Local | F41: Recipe ingredient | G41: Year-round | H41: All year | I41: May-Oct | J41: =IFERROR(IF(INDEX('Seasonal Calendar'!$C$2:$N$500,MATCH(A41,'Seasonal Calendar'!$A$2:$A$500,0),MONTH(TODAY()))="","Out",INDEX('Seasonal Calendar'!$C$2:$N$500,MATCH(A41,'Seasonal Calendar'!$A$2:$A$500,0),MONTH(TODAY()))),"") -> Peak | K41: Sourced | L41: Cup / 250g | Q41: Y | R41: Core | S41: =COUNTIF('Recipe Ingredients'!$F$2:$F$2000,A41) -> 23 | T41: Airtight | U41: Weeks roasted | V41: Kano, Kaduna, Niger | W41: Training, Plant-based | X41: Fresh groundnuts May-Oct; roasted all year. Replaces pine nuts, walnuts and tahini across the library.
A42: P041 | B42: African walnut | C42: Asala (Yor), Ukpa (Igbo) | D42: Nut | E42: Local | F42: Eat as-is only | G42: Seasonal | H42: Mar-May, Jul-Aug, Oct | J42: =IFERROR(IF(INDEX('Seasonal Calendar'!$C$2:$N$500,MATCH(A42,'Seasonal Calendar'!$A$2:$A$500,0),MONTH(TODAY()))="","Out",INDEX('Seasonal Calendar'!$C$2:$N$500,MATCH(A42,'Seasonal Calendar'!$A$2:$A$500,0),MONTH(TODAY()))),"") -> In | K42: Sourced | L42: Pack | Q42: Seasonal | R42: Seasonal drop | S42: =COUNTIF('Recipe Ingredients'!$F$2:$F$2000,A42) -> 0 | T42: Cool, dry | U42: 1 week cooked | V42: Southwest, Southeast | W42: Snack | X42: Sold boiled.
A43: P042 | B43: Tomato (plum) | C43: Tumatir (Hau) | D43: Vegetable | E43: Local | F43: Recipe ingredient | G43: Year-round | H43: All year | I43: Dec-Jan, Aug-Sep | J43: =IFERROR(IF(INDEX('Seasonal Calendar'!$C$2:$N$500,MATCH(A43,'Seasonal Calendar'!$A$2:$A$500,0),MONTH(TODAY()))="","Out",INDEX('Seasonal Calendar'!$C$2:$N$500,MATCH(A43,'Seasonal Calendar'!$A$2:$A$500,0),MONTH(TODAY()))),"") -> In | K43: Sourced | L43: 1kg | M43: 4600 | N43: 1kg | O43: Mint Foods (mintfoods.store), 11 Oct 2026; beef tomato N4,375/kg | Q43: Y | R43: Core | S43: =COUNTIF('Recipe Ingredients'!$F$2:$F$2000,A43) -> 62 | T43: Room temp; fridge only when very ripe | U43: 3-7 days | V43: Kano, Kaduna, Katsina, Plateau | W43: Wellness | X43: Jos tomatoes peak Aug-Sep and Dec-Jan (Kitchen Butterfly). Prices spike in parts of the rainy season, so build price alerts around it.
A44: P043 | B44: Cherry tomato | D44: Vegetable | E44: Local + imported | F44: Eat as-is + recipes | G44: Year-round | H44: All year | J44: =IFERROR(IF(INDEX('Seasonal Calendar'!$C$2:$N$500,MATCH(A44,'Seasonal Calendar'!$A$2:$A$500,0),MONTH(TODAY()))="","Out",INDEX('Seasonal Calendar'!$C$2:$N$500,MATCH(A44,'Seasonal Calendar'!$A$2:$A$500,0),MONTH(TODAY()))),"") -> In | K44: Verify | L44: 250g | M44: 9000 | N44: 250g yellow | O44: Mint Foods (mintfoods.store), 11 Oct 2026 | Q44: N | R44: Premium | S44: =COUNTIF('Recipe Ingredients'!$F$2:$F$2000,A44) -> 7 | T44: Room temp | U44: 5-7 days | V44: Greenhouses (Lagos, Ogun, Plateau) | W44: Wellness | X44: Plum tomatoes work in every recipe that lists cherry tomatoes.
A45: P044 | B45: Red bell pepper | C45: Tatashe (Yor) | D45: Vegetable | E45: Local | F45: Recipe ingredient | G45: Year-round | H45: All year | J45: =IFERROR(IF(INDEX('Seasonal Calendar'!$C$2:$N$500,MATCH(A45,'Seasonal Calendar'!$A$2:$A$500,0),MONTH(TODAY()))="","Out",INDEX('Seasonal Calendar'!$C$2:$N$500,MATCH(A45,'Seasonal Calendar'!$A$2:$A$500,0),MONTH(TODAY()))),"") -> In | K45: Verify | L45: Piece / 6-pack | M45: 10350 | N45: 6 pcs local | O45: Mint Foods (mintfoods.store), 11 Oct 2026 | Q45: Y | R45: Core | S45: =COUNTIF('Recipe Ingredients'!$F$2:$F$2000,A45) -> 29 | T45: Fridge | U45: 1 week | V45: Plateau, Kaduna, Kano | W45: Wellness
A46: P045 | B46: Green / yellow bell pepper | D46: Vegetable | E46: Local | F46: Recipe ingredient | G46: Year-round | H46: All year | J46: =IFERROR(IF(INDEX('Seasonal Calendar'!$C$2:$N$500,MATCH(A46,'Seasonal Calendar'!$A$2:$A$500,0),MONTH(TODAY()))="","Out",INDEX('Seasonal Calendar'!$C$2:$N$500,MATCH(A46,'Seasonal Calendar'!$A$2:$A$500,0),MONTH(TODAY()))),"") -> In | K46: Verify | L46: Piece / 6-pack | M46: 8500 | N46: 6 pcs green, local | O46: Mint Foods (mintfoods.store), 11 Oct 2026; yellow N10,350 | Q46: Y | R46: Core | S46: =COUNTIF('Recipe Ingredients'!$F$2:$F$2000,A46) -> 15 | T46: Fridge | U46: 1 week | V46: Plateau, Kaduna | W46: Wellness
A47: P046 | B47: Scotch bonnet | C47: Ata rodo (Yor) | D47: Vegetable | E47: Local | F47: Recipe ingredient | G47: Year-round | H47: All year | J47: =IFERROR(IF(INDEX('Seasonal Calendar'!$C$2:$N$500,MATCH(A47,'Seasonal Calendar'!$A$2:$A$500,0),MONTH(TODAY()))="","Out",INDEX('Seasonal Calendar'!$C$2:$N$500,MATCH(A47,'Seasonal Calendar'!$A$2:$A$500,0),MONTH(TODAY()))),"") -> In | K47: Verify | L47: Cup / 100g | Q47: Y | R47: Core | S47: =COUNTIF('Recipe Ingredients'!$F$2:$F$2000,A47) -> 40 | T47: Fridge | U47: 1-2 weeks | V47: Nationwide | W47: Wellness | X47: Every recipe lists a small amount. Let customers dial heat up or down.
A48: P047 | B48: Long red chilli | C48: Shombo (Yor) | D48: Vegetable | E48: Local | F48: Recipe ingredient | G48: Year-round | H48: All year | J48: =IFERROR(IF(INDEX('Seasonal Calendar'!$C$2:$N$500,MATCH(A48,'Seasonal Calendar'!$A$2:$A$500,0),MONTH(TODAY()))="","Out",INDEX('Seasonal Calendar'!$C$2:$N$500,MATCH(A48,'Seasonal Calendar'!$A$2:$A$500,0),MONTH(TODAY()))),"") -> In | K48: Verify | L48: Cup | Q48: N | R48: Later | S48: =COUNTIF('Recipe Ingredients'!$F$2:$F$2000,A48) -> 16 | T48: Fridge | U48: 1-2 weeks | V48: North | X48: Milder swap for ata rodo.
A49: P048 | B49: Onion (red & white) | C49: Alubosa (Yor), Yabasi (Igbo), Albasa (Hau) | D49: Vegetable | E49: Local | F49: Recipe ingredient | G49: Year-round | H49: All year | J49: =IFERROR(IF(INDEX('Seasonal Calendar'!$C$2:$N$500,MATCH(A49,'Seasonal Calendar'!$A$2:$A$500,0),MONTH(TODAY()))="","Out",INDEX('Seasonal Calendar'!$C$2:$N$500,MATCH(A49,'Seasonal Calendar'!$A$2:$A$500,0),MONTH(TODAY()))),"") -> In | K49: Verify | L49: 1kg / 3 pcs | Q49: Y | R49: Core | S49: =COUNTIF('Recipe Ingredients'!$F$2:$F$2000,A49) -> 67 | T49: Cool, dry, ventilated | U49: 3-4 weeks | V49: Kano, Sokoto, Kebbi | X49: Red onions for raw dishes, white for cooking.
A50: P049 | B50: Spring onion | C50: Alubosa elewe (Yor) | D50: Vegetable | E50: Local | F50: Recipe ingredient | G50: Year-round | H50: All year | J50: =IFERROR(IF(INDEX('Seasonal Calendar'!$C$2:$N$500,MATCH(A50,'Seasonal Calendar'!$A$2:$A$500,0),MONTH(TODAY()))="","Out",INDEX('Seasonal Calendar'!$C$2:$N$500,MATCH(A50,'Seasonal Calendar'!$A$2:$A$500,0),MONTH(TODAY()))),"") -> In | K50: Verify | L50: Bunch | Q50: Y | R50: Core | S50: =COUNTIF('Recipe Ingredients'!$F$2:$F$2000,A50) -> 30 | T50: Fridge, wrapped | U50: 5-7 days | V50: Plateau, Lagos
A51: P050 | B51: Shallots | D51: Vegetable | E51: Local + imported | F51: Recipe ingredient | G51: Year-round | H51: All year | J51: =IFERROR(IF(INDEX('Seasonal Calendar'!$C$2:$N$500,MATCH(A51,'Seasonal Calendar'!$A$2:$A$500,0),MONTH(TODAY()))="","Out",INDEX('Seasonal Calendar'!$C$2:$N$500,MATCH(A51,'Seasonal Calendar'!$A$2:$A$500,0),MONTH(TODAY()))),"") -> In | K51: Verify | L51: 250g | M51: 6500 | N51: 250g | O51: Mint Foods (mintfoods.store), 11 Oct 2026 | Q51: N | R51: Later | S51: =COUNTIF('Recipe Ingredients'!$F$2:$F$2000,A51) -> 2 | T51: Cool, dry | U51: 3-4 weeks | V51: North + imports | X51: Red onion covers every use in this library.
A52: P051 | B52: Garlic | C52: Ayu (Yor), Tafarnuwa (Hau) | D52: Aromatic | E52: Local + imported | F52: Recipe ingredient | G52: Year-round | H52: All year | J52: =IFERROR(IF(INDEX('Seasonal Calendar'!$C$2:$N$500,MATCH(A52,'Seasonal Calendar'!$A$2:$A$500,0),MONTH(TODAY()))="","Out",INDEX('Seasonal Calendar'!$C$2:$N$500,MATCH(A52,'Seasonal Calendar'!$A$2:$A$500,0),MONTH(TODAY()))),"") -> In | K52: Verify | L52: Bulb / 5 bulbs | M52: 1320 | N52: 5 bulbs | O52: Mint Foods (mintfoods.store), 11 Oct 2026 | Q52: Y | R52: Core | S52: =COUNTIF('Recipe Ingredients'!$F$2:$F$2000,A52) -> 76 | T52: Cool, dry | U52: 1-2 months | V52: Kano, Sokoto + imports | W52: Wellness
A53: P052 | B53: Ginger | C53: Ata ile (Yor), Jinja (Igbo), Citta (Hau) | D53: Aromatic | E53: Local | F53: Recipe ingredient | G53: Year-round | H53: All year | I53: Sep-Oct | J53: =IFERROR(IF(INDEX('Seasonal Calendar'!$C$2:$N$500,MATCH(A53,'Seasonal Calendar'!$A$2:$A$500,0),MONTH(TODAY()))="","Out",INDEX('Seasonal Calendar'!$C$2:$N$500,MATCH(A53,'Seasonal Calendar'!$A$2:$A$500,0),MONTH(TODAY()))),"") -> Peak | K53: Sourced | L53: 100g / hand | Q53: Y | R53: Core | S53: =COUNTIF('Recipe Ingredients'!$F$2:$F$2000,A53) -> 23 | T53: Cool, dry; fridge | U53: 2-3 weeks | V53: Southern Kaduna (Kafanchan) | W53: Wellness | X53: Fresh harvest Sep-Oct (Kitchen Butterfly); stored ginger all year.
A54: P053 | B54: Turmeric (fresh) | C54: Ata ile pupa (Yor) | D54: Aromatic | E54: Local | F54: Recipe ingredient | G54: Seasonal | H54: Sep-Jun | J54: =IFERROR(IF(INDEX('Seasonal Calendar'!$C$2:$N$500,MATCH(A54,'Seasonal Calendar'!$A$2:$A$500,0),MONTH(TODAY()))="","Out",INDEX('Seasonal Calendar'!$C$2:$N$500,MATCH(A54,'Seasonal Calendar'!$A$2:$A$500,0),MONTH(TODAY()))),"") -> In | K54: Sourced | L54: 100g | Q54: N | R54: Later | S54: =COUNTIF('Recipe Ingredients'!$F$2:$F$2000,A54) -> 6 | T54: Fridge | U54: 2-3 weeks | V54: Southern Kaduna, Southwest | W54: Wellness | X54: Stains everything. Pack separately.
A55: P054 | B55: Cucumber | C55: Kukumba | D55: Vegetable | E55: Local | F55: Eat as-is + recipes | G55: Year-round | H55: All year | I55: Jan-May | J55: =IFERROR(IF(INDEX('Seasonal Calendar'!$C$2:$N$500,MATCH(A55,'Seasonal Calendar'!$A$2:$A$500,0),MONTH(TODAY()))="","Out",INDEX('Seasonal Calendar'!$C$2:$N$500,MATCH(A55,'Seasonal Calendar'!$A$2:$A$500,0),MONTH(TODAY()))),"") -> In | K55: Sourced | L55: Piece / 3-pack | Q55: Y | R55: Core | S55: =COUNTIF('Recipe Ingredients'!$F$2:$F$2000,A55) -> 32 | T55: Fridge | U55: 1 week | V55: Plateau, Kaduna, greenhouses | W55: Hydration, Weight management | X55: Second most-used vegetable in the library.
A56: P055 | B56: Carrot | D56: Vegetable | E56: Local | F56: Eat as-is + recipes | G56: Year-round | H56: All year | I56: Sep-May | J56: =IFERROR(IF(INDEX('Seasonal Calendar'!$C$2:$N$500,MATCH(A56,'Seasonal Calendar'!$A$2:$A$500,0),MONTH(TODAY()))="","Out",INDEX('Seasonal Calendar'!$C$2:$N$500,MATCH(A56,'Seasonal Calendar'!$A$2:$A$500,0),MONTH(TODAY()))),"") -> Peak | K56: Sourced | L56: 1kg / 500g | M56: 3150 | N56: 1kg local | O56: Mint Foods (mintfoods.store), 11 Oct 2026; The Fresh Place (thefreshplace.ng), 11 Oct 2026 N4,500/kg | Q56: Y | R56: Core | S56: =COUNTIF('Recipe Ingredients'!$F$2:$F$2000,A56) -> 28 | T56: Fridge, dry | U56: 2-3 weeks | V56: Plateau (Jos) | W56: Wellness
A57: P056 | B57: Cabbage (white) | D57: Vegetable | E57: Local | F57: Recipe ingredient | G57: Year-round | H57: All year | J57: =IFERROR(IF(INDEX('Seasonal Calendar'!$C$2:$N$500,MATCH(A57,'Seasonal Calendar'!$A$2:$A$500,0),MONTH(TODAY()))="","Out",INDEX('Seasonal Calendar'!$C$2:$N$500,MATCH(A57,'Seasonal Calendar'!$A$2:$A$500,0),MONTH(TODAY()))),"") -> In | K57: Verify | L57: Head | M57: 1800 | N57: 1 head | O57: Mint Foods (mintfoods.store), 11 Oct 2026; The Fresh Place (thefreshplace.ng), 11 Oct 2026 N2,000/kg | Q57: Y | R57: Core | S57: =COUNTIF('Recipe Ingredients'!$F$2:$F$2000,A57) -> 11 | T57: Fridge | U57: 2 weeks | V57: Plateau | W57: Weight management | X57: Cheap, slow to spoil, used in slaws, wraps and soups.
A58: P057 | B58: Purple cabbage | D58: Vegetable | E58: Local | F58: Recipe ingredient | G58: Year-round | H58: All year | J58: =IFERROR(IF(INDEX('Seasonal Calendar'!$C$2:$N$500,MATCH(A58,'Seasonal Calendar'!$A$2:$A$500,0),MONTH(TODAY()))="","Out",INDEX('Seasonal Calendar'!$C$2:$N$500,MATCH(A58,'Seasonal Calendar'!$A$2:$A$500,0),MONTH(TODAY()))),"") -> In | K58: Verify | L58: Head | M58: 4000 | N58: 1 head | O58: Mint Foods (mintfoods.store), 11 Oct 2026 | Q58: Y | R58: Core | S58: =COUNTIF('Recipe Ingredients'!$F$2:$F$2000,A58) -> 4 | T58: Fridge | U58: 2 weeks | V58: Plateau | W58: Wellness
A59: P058 | B59: Lettuce (iceberg / romaine / local) | D59: Leafy green | E59: Local | F59: Recipe ingredient | G59: Year-round | H59: All year | J59: =IFERROR(IF(INDEX('Seasonal Calendar'!$C$2:$N$500,MATCH(A59,'Seasonal Calendar'!$A$2:$A$500,0),MONTH(TODAY()))="","Out",INDEX('Seasonal Calendar'!$C$2:$N$500,MATCH(A59,'Seasonal Calendar'!$A$2:$A$500,0),MONTH(TODAY()))),"") -> In | K59: Verify | L59: Head | M59: 3820 | N59: local iceberg, 300-320g | O59: Mint Foods (mintfoods.store), 11 Oct 2026; romaine N9,828 | Q59: Y | R59: Core | S59: =COUNTIF('Recipe Ingredients'!$F$2:$F$2000,A59) -> 13 | T59: Fridge, wrapped | U59: 4-7 days | V59: Plateau, Lagos hydroponics | W59: Weight management | X59: Local iceberg costs a fraction of romaine. Default recipes to local lettuce.
A60: P059 | B60: Green beans | D60: Vegetable | E60: Local | F60: Recipe ingredient | G60: Year-round | H60: All year | J60: =IFERROR(IF(INDEX('Seasonal Calendar'!$C$2:$N$500,MATCH(A60,'Seasonal Calendar'!$A$2:$A$500,0),MONTH(TODAY()))="","Out",INDEX('Seasonal Calendar'!$C$2:$N$500,MATCH(A60,'Seasonal Calendar'!$A$2:$A$500,0),MONTH(TODAY()))),"") -> In | K60: Verify | L60: 250g | Q60: Y | R60: Core | S60: =COUNTIF('Recipe Ingredients'!$F$2:$F$2000,A60) -> 7 | T60: Fridge | U60: 5-7 days | V60: Plateau | W60: Weight management
A61: P060 | B61: Sweet corn | C61: Agbado (Yor), Oka (Igbo), Masara (Hau) | D61: Vegetable | E61: Local | F61: Eat as-is + recipes | G61: Seasonal | H61: Apr-Aug | I61: Jun-Jul | J61: =IFERROR(IF(INDEX('Seasonal Calendar'!$C$2:$N$500,MATCH(A61,'Seasonal Calendar'!$A$2:$A$500,0),MONTH(TODAY()))="","Out",INDEX('Seasonal Calendar'!$C$2:$N$500,MATCH(A61,'Seasonal Calendar'!$A$2:$A$500,0),MONTH(TODAY()))),"") -> Out | K61: Sourced | L61: 3 cobs | M61: 3900 | N61: 3 cobs, peeled | O61: Mint Foods (mintfoods.store), 11 Oct 2026 | Q61: Seasonal | R61: Seasonal drop | S61: =COUNTIF('Recipe Ingredients'!$F$2:$F$2000,A61) -> 12 | T61: Fridge, in husk | U61: 2-3 days | V61: Nationwide | W61: Energy | X61: Fresh corn Apr-Aug (Kitchen Butterfly). Pair with ube.
A62: P061 | B62: Garden egg | C62: Igba (Yor), Anara (Igbo), Gauta (Hau) | D62: Vegetable | E62: Local | F62: Eat as-is + recipes | G62: Seasonal | H62: Jan-Oct | J62: =IFERROR(IF(INDEX('Seasonal Calendar'!$C$2:$N$500,MATCH(A62,'Seasonal Calendar'!$A$2:$A$500,0),MONTH(TODAY()))="","Out",INDEX('Seasonal Calendar'!$C$2:$N$500,MATCH(A62,'Seasonal Calendar'!$A$2:$A$500,0),MONTH(TODAY()))),"") -> In | K62: Sourced | L62: Pack of 6 | Q62: Y | R62: Core | S62: =COUNTIF('Recipe Ingredients'!$F$2:$F$2000,A62) -> 8 | T62: Room temp / fridge | U62: 5-7 days | V62: Nationwide | W62: Weight management | X62: Eaten raw as a snack and stands in for aubergine in global recipes.
A63: P062 | B63: Okra | C63: Ila (Yor), Okwuru (Igbo), Kubewa (Hau) | D63: Vegetable | E63: Local | F63: Recipe ingredient | G63: Year-round | H63: All year | J63: =IFERROR(IF(INDEX('Seasonal Calendar'!$C$2:$N$500,MATCH(A63,'Seasonal Calendar'!$A$2:$A$500,0),MONTH(TODAY()))="","Out",INDEX('Seasonal Calendar'!$C$2:$N$500,MATCH(A63,'Seasonal Calendar'!$A$2:$A$500,0),MONTH(TODAY()))),"") -> In | K63: Verify | L63: 250g | Q63: Y | R63: Core | S63: =COUNTIF('Recipe Ingredients'!$F$2:$F$2000,A63) -> 4 | T63: Fridge, dry | U63: 3-4 days | V63: Nationwide | W63: Gut health
A64: P063 | B64: Broccoli | D64: Vegetable | E64: Local (limited) + imported | F64: Recipe ingredient | G64: Year-round | H64: All year | J64: =IFERROR(IF(INDEX('Seasonal Calendar'!$C$2:$N$500,MATCH(A64,'Seasonal Calendar'!$A$2:$A$500,0),MONTH(TODAY()))="","Out",INDEX('Seasonal Calendar'!$C$2:$N$500,MATCH(A64,'Seasonal Calendar'!$A$2:$A$500,0),MONTH(TODAY()))),"") -> In | K64: Verify | L64: Head | M64: 8100 | N64: 300-550g head | O64: Mint Foods (mintfoods.store), 11 Oct 2026; The Fresh Place (thefreshplace.ng), 11 Oct 2026 N10,000/kg | Q64: N | R64: Premium | S64: =COUNTIF('Recipe Ingredients'!$F$2:$F$2000,A64) -> 5 | T64: Fridge | U64: 5-7 days | V64: Plateau + imports | W64: Training, Weight management | X64: Green beans are the budget swap in every recipe.
A65: P064 | B65: Cauliflower | D65: Vegetable | E65: Local + imported | F65: Recipe ingredient | G65: Year-round | H65: All year | J65: =IFERROR(IF(INDEX('Seasonal Calendar'!$C$2:$N$500,MATCH(A65,'Seasonal Calendar'!$A$2:$A$500,0),MONTH(TODAY()))="","Out",INDEX('Seasonal Calendar'!$C$2:$N$500,MATCH(A65,'Seasonal Calendar'!$A$2:$A$500,0),MONTH(TODAY()))),"") -> In | K65: Verify | L65: Head | M65: 2750 | N65: 1 local head | O65: Mint Foods (mintfoods.store), 11 Oct 2026; imported ~1kg N16,900 | Q65: N | R65: Premium | S65: =COUNTIF('Recipe Ingredients'!$F$2:$F$2000,A65) -> 2 | T65: Fridge | U65: 1 week | V65: Plateau + imports | W65: Weight management | X65: Local heads are 6x cheaper than imported when available.
A66: P065 | B66: Beetroot | D66: Vegetable | E66: Local | F66: Recipe ingredient | G66: Year-round | H66: All year | J66: =IFERROR(IF(INDEX('Seasonal Calendar'!$C$2:$N$500,MATCH(A66,'Seasonal Calendar'!$A$2:$A$500,0),MONTH(TODAY()))="","Out",INDEX('Seasonal Calendar'!$C$2:$N$500,MATCH(A66,'Seasonal Calendar'!$A$2:$A$500,0),MONTH(TODAY()))),"") -> In | K66: Verify | L66: 500g / 1kg | M66: 4500 | N66: 1kg | O66: The Fresh Place (thefreshplace.ng), 11 Oct 2026 | Q66: Y | R66: Core | S66: =COUNTIF('Recipe Ingredients'!$F$2:$F$2000,A66) -> 1 | T66: Fridge | U66: 2-3 weeks | V66: Plateau | W66: Training (endurance)
A67: P066 | B67: Zucchini (courgette) | D67: Vegetable | E67: Local (limited) + imported | F67: Recipe ingredient | G67: Year-round | H67: All year | J67: =IFERROR(IF(INDEX('Seasonal Calendar'!$C$2:$N$500,MATCH(A67,'Seasonal Calendar'!$A$2:$A$500,0),MONTH(TODAY()))="","Out",INDEX('Seasonal Calendar'!$C$2:$N$500,MATCH(A67,'Seasonal Calendar'!$A$2:$A$500,0),MONTH(TODAY()))),"") -> In | K67: Verify | L67: Piece | Q67: N | R67: Later | S67: =COUNTIF('Recipe Ingredients'!$F$2:$F$2000,A67) -> 6 | T67: Fridge | U67: 5-7 days | V67: Plateau + imports | W67: Weight management | X67: Optional in every recipe that lists it.
A68: P067 | B68: Mushrooms (oyster / button) | D68: Vegetable | E68: Local + imported | F68: Recipe ingredient | G68: Year-round | H68: All year | J68: =IFERROR(IF(INDEX('Seasonal Calendar'!$C$2:$N$500,MATCH(A68,'Seasonal Calendar'!$A$2:$A$500,0),MONTH(TODAY()))="","Out",INDEX('Seasonal Calendar'!$C$2:$N$500,MATCH(A68,'Seasonal Calendar'!$A$2:$A$500,0),MONTH(TODAY()))),"") -> In | K68: Verify | L68: 250g | M68: 5980 | N68: 250g white button | O68: Mint Foods (mintfoods.store), 11 Oct 2026 | Q68: N | R68: Premium | S68: =COUNTIF('Recipe Ingredients'!$F$2:$F$2000,A68) -> 9 | T68: Fridge, paper bag | U68: 4-5 days | V68: Local oyster growers + imports | W68: Plant-based | X68: Local oyster mushrooms are the cheaper default.
A69: P068 | B69: Pumpkin (squash) | C69: Elegede (Yor), Kabewa (Hau) | D69: Vegetable | E69: Local | F69: Recipe ingredient | G69: Year-round | H69: All year | J69: =IFERROR(IF(INDEX('Seasonal Calendar'!$C$2:$N$500,MATCH(A69,'Seasonal Calendar'!$A$2:$A$500,0),MONTH(TODAY()))="","Out",INDEX('Seasonal Calendar'!$C$2:$N$500,MATCH(A69,'Seasonal Calendar'!$A$2:$A$500,0),MONTH(TODAY()))),"") -> In | K69: Verify | L69: Wedge / 1kg | Q69: Y | R69: Core | S69: =COUNTIF('Recipe Ingredients'!$F$2:$F$2000,A69) -> 2 | T69: Whole at room temp | U69: Weeks whole, 5 days cut | V69: North, Southwest | W69: Wellness | X69: Sell as wedges. Season window needs supplier confirmation.
A70: P069 | B70: Sweet potato | C70: Odunkun (Yor), Dankali (Hau) | D70: Tuber | E70: Local | F70: Recipe ingredient | G70: Year-round | H70: All year | J70: =IFERROR(IF(INDEX('Seasonal Calendar'!$C$2:$N$500,MATCH(A70,'Seasonal Calendar'!$A$2:$A$500,0),MONTH(TODAY()))="","Out",INDEX('Seasonal Calendar'!$C$2:$N$500,MATCH(A70,'Seasonal Calendar'!$A$2:$A$500,0),MONTH(TODAY()))),"") -> In | K70: Verify | L70: 1kg | M70: 1200 | N70: ~1kg | O70: Mint Foods (mintfoods.store), 11 Oct 2026 | Q70: Y | R70: Core | S70: =COUNTIF('Recipe Ingredients'!$F$2:$F$2000,A70) -> 6 | T70: Cool, dry | U70: 2-3 weeks | V70: Benue, Kwara, Kaduna | W70: Training, Energy | X70: Cheap, filling, and the default starch swap for potatoes across the library.
A71: P070 | B71: Irish potato | C71: Dankalin turawa (Hau) | D71: Tuber | E71: Local | F71: Recipe ingredient | G71: Year-round | H71: All year | J71: =IFERROR(IF(INDEX('Seasonal Calendar'!$C$2:$N$500,MATCH(A71,'Seasonal Calendar'!$A$2:$A$500,0),MONTH(TODAY()))="","Out",INDEX('Seasonal Calendar'!$C$2:$N$500,MATCH(A71,'Seasonal Calendar'!$A$2:$A$500,0),MONTH(TODAY()))),"") -> In | K71: Verify | L71: 1kg | M71: 3650 | N71: ~1kg | O71: Mint Foods (mintfoods.store), 11 Oct 2026 | Q71: Y | R71: Core | S71: =COUNTIF('Recipe Ingredients'!$F$2:$F$2000,A71) -> 6 | T71: Cool, dark | U71: 3-4 weeks | V71: Plateau (Jos) | W71: Training
A72: P071 | B72: Yam | C72: Isu (Yor), Ji (Igbo), Doya (Hau) | D72: Tuber | E72: Local | F72: Recipe ingredient | G72: Year-round | H72: All year | I72: Aug-Oct | J72: =IFERROR(IF(INDEX('Seasonal Calendar'!$C$2:$N$500,MATCH(A72,'Seasonal Calendar'!$A$2:$A$500,0),MONTH(TODAY()))="","Out",INDEX('Seasonal Calendar'!$C$2:$N$500,MATCH(A72,'Seasonal Calendar'!$A$2:$A$500,0),MONTH(TODAY()))),"") -> Peak | K72: Sourced | L72: Tuber | Q72: N | R72: Later | S72: =COUNTIF('Recipe Ingredients'!$F$2:$F$2000,A72) -> 2 | T72: Cool, dry | U72: Weeks | V72: Benue, Niger, Oyo | W72: Energy | X72: New yam Aug-Oct. Not used in the light-recipe library yet.
A73: P072 | B73: Fluted pumpkin leaf | C73: Ugu (Igbo) | D73: Leafy green | E73: Local | F73: Recipe ingredient | G73: Year-round | H73: All year | J73: =IFERROR(IF(INDEX('Seasonal Calendar'!$C$2:$N$500,MATCH(A73,'Seasonal Calendar'!$A$2:$A$500,0),MONTH(TODAY()))="","Out",INDEX('Seasonal Calendar'!$C$2:$N$500,MATCH(A73,'Seasonal Calendar'!$A$2:$A$500,0),MONTH(TODAY()))),"") -> In | K73: Verify | L73: Bunch | Q73: Y | R73: Core | S73: =COUNTIF('Recipe Ingredients'!$F$2:$F$2000,A73) -> 5 | T73: Fridge, wrapped | U73: 3-4 days | V73: Southeast, Lagos | W73: Wellness | X73: Becomes pesto, curry greens and smoothie greens in this library.
A74: P073 | B74: Amaranth greens (Nigerian spinach) | C74: Efo tete (Yor), Alayyahu (Hau) | D74: Leafy green | E74: Local | F74: Recipe ingredient | G74: Year-round | H74: All year | J74: =IFERROR(IF(INDEX('Seasonal Calendar'!$C$2:$N$500,MATCH(A74,'Seasonal Calendar'!$A$2:$A$500,0),MONTH(TODAY()))="","Out",INDEX('Seasonal Calendar'!$C$2:$N$500,MATCH(A74,'Seasonal Calendar'!$A$2:$A$500,0),MONTH(TODAY()))),"") -> In | K74: Verify | L74: Bunch | M74: 1000 | N74: bunch | O74: The Fresh Place (thefreshplace.ng), 11 Oct 2026 | Q74: Y | R74: Core | S74: =COUNTIF('Recipe Ingredients'!$F$2:$F$2000,A74) -> 8 | T74: Fridge, wrapped | U74: 3-4 days | V74: Nationwide | W74: Wellness, Training | X74: Local swap for imported baby spinach and kale in almost every recipe.
A75: P074 | B75: Waterleaf | C75: Gbure (Yor), Mgbolodi (Igbo) | D75: Leafy green | E75: Local | F75: Recipe ingredient | G75: Year-round | H75: All year | J75: =IFERROR(IF(INDEX('Seasonal Calendar'!$C$2:$N$500,MATCH(A75,'Seasonal Calendar'!$A$2:$A$500,0),MONTH(TODAY()))="","Out",INDEX('Seasonal Calendar'!$C$2:$N$500,MATCH(A75,'Seasonal Calendar'!$A$2:$A$500,0),MONTH(TODAY()))),"") -> In | K75: Verify | L75: Bunch | Q75: N | R75: Later | S75: =COUNTIF('Recipe Ingredients'!$F$2:$F$2000,A75) -> 0 | T75: Fridge | U75: 2-3 days | V75: South | X75: Mostly a soup green. Not in the current library.
A76: P075 | B76: Baby spinach | D76: Leafy green | E76: Local hydroponic + imported | F76: Recipe ingredient | G76: Year-round | H76: All year | J76: =IFERROR(IF(INDEX('Seasonal Calendar'!$C$2:$N$500,MATCH(A76,'Seasonal Calendar'!$A$2:$A$500,0),MONTH(TODAY()))="","Out",INDEX('Seasonal Calendar'!$C$2:$N$500,MATCH(A76,'Seasonal Calendar'!$A$2:$A$500,0),MONTH(TODAY()))),"") -> In | K76: Verify | L76: 125g | M76: 4950 | N76: 125g | O76: Mint Foods (mintfoods.store), 11 Oct 2026 | Q76: N | R76: Premium | S76: =COUNTIF('Recipe Ingredients'!$F$2:$F$2000,A76) -> 7 | T76: Fridge | U76: 4-5 days | V76: Lagos hydroponics + imports | W76: Wellness | X76: Efo tete works anywhere this is listed.
A77: P076 | B77: Kale | D77: Leafy green | E77: Local hydroponic + imported | F77: Recipe ingredient | G77: Year-round | H77: All year | J77: =IFERROR(IF(INDEX('Seasonal Calendar'!$C$2:$N$500,MATCH(A77,'Seasonal Calendar'!$A$2:$A$500,0),MONTH(TODAY()))="","Out",INDEX('Seasonal Calendar'!$C$2:$N$500,MATCH(A77,'Seasonal Calendar'!$A$2:$A$500,0),MONTH(TODAY()))),"") -> In | K77: Verify | L77: 125g | M77: 4940 | N77: 125g | O77: Mint Foods (mintfoods.store), 11 Oct 2026 | Q77: N | R77: Later | S77: =COUNTIF('Recipe Ingredients'!$F$2:$F$2000,A77) -> 1 | T77: Fridge | U77: 5-7 days | V77: Hydroponic farms | W77: Wellness | X77: Not needed while efo tete and ugu cover the same jobs.
A78: P077 | B78: Scent leaf (African basil) | C78: Efirin (Yor), Nchanwu (Igbo), Daidoya (Hau) | D78: Herb | E78: Local | F78: Recipe ingredient | G78: Year-round | H78: All year | J78: =IFERROR(IF(INDEX('Seasonal Calendar'!$C$2:$N$500,MATCH(A78,'Seasonal Calendar'!$A$2:$A$500,0),MONTH(TODAY()))="","Out",INDEX('Seasonal Calendar'!$C$2:$N$500,MATCH(A78,'Seasonal Calendar'!$A$2:$A$500,0),MONTH(TODAY()))),"") -> In | K78: Verify | L78: Bunch | Q78: Y | R78: Core | S78: =COUNTIF('Recipe Ingredients'!$F$2:$F$2000,A78) -> 9 | T78: Stems in water, room temp | U78: 3-4 days | V78: Nationwide | W78: Wellness | X78: Stands in for Thai basil and parsley in chimichurri. A real point of difference.
A79: P078 | B79: Bitter leaf | C79: Ewuro (Yor), Onugbu (Igbo), Shiwaka (Hau) | D79: Leafy green | E79: Local | F79: Recipe ingredient | G79: Year-round | H79: All year | J79: =IFERROR(IF(INDEX('Seasonal Calendar'!$C$2:$N$500,MATCH(A79,'Seasonal Calendar'!$A$2:$A$500,0),MONTH(TODAY()))="","Out",INDEX('Seasonal Calendar'!$C$2:$N$500,MATCH(A79,'Seasonal Calendar'!$A$2:$A$500,0),MONTH(TODAY()))),"") -> In | K79: Verify | L79: Bunch (washed) | Q79: N | R79: Later | S79: =COUNTIF('Recipe Ingredients'!$F$2:$F$2000,A79) -> 0 | T79: Fridge | U79: 3-4 days | V79: Nationwide | X79: Soup green. Not in the current library.
A80: P079 | B80: Mint | C80: Na'a na'a (Hau) | D80: Herb | E80: Local | F80: Recipe ingredient | G80: Year-round | H80: All year | J80: =IFERROR(IF(INDEX('Seasonal Calendar'!$C$2:$N$500,MATCH(A80,'Seasonal Calendar'!$A$2:$A$500,0),MONTH(TODAY()))="","Out",INDEX('Seasonal Calendar'!$C$2:$N$500,MATCH(A80,'Seasonal Calendar'!$A$2:$A$500,0),MONTH(TODAY()))),"") -> In | K80: Verify | L80: Bunch | Q80: Y | R80: Core | S80: =COUNTIF('Recipe Ingredients'!$F$2:$F$2000,A80) -> 16 | T80: Stems in water, fridge | U80: 4-5 days | V80: North, Lagos hydroponics | W80: Hydration
A81: P080 | B81: Coriander (cilantro) | D81: Herb | E81: Local | F81: Recipe ingredient | G81: Year-round | H81: All year | J81: =IFERROR(IF(INDEX('Seasonal Calendar'!$C$2:$N$500,MATCH(A81,'Seasonal Calendar'!$A$2:$A$500,0),MONTH(TODAY()))="","Out",INDEX('Seasonal Calendar'!$C$2:$N$500,MATCH(A81,'Seasonal Calendar'!$A$2:$A$500,0),MONTH(TODAY()))),"") -> In | K81: Verify | L81: Bunch / 100g | M81: 3550 | N81: 100g | O81: Mint Foods (mintfoods.store), 11 Oct 2026 | Q81: Y | R81: Core | S81: =COUNTIF('Recipe Ingredients'!$F$2:$F$2000,A81) -> 27 | T81: Stems in water, fridge | U81: 4-5 days | V81: Plateau, Lagos
A82: P081 | B82: Parsley | D82: Herb | E82: Local | F82: Recipe ingredient | G82: Year-round | H82: All year | J82: =IFERROR(IF(INDEX('Seasonal Calendar'!$C$2:$N$500,MATCH(A82,'Seasonal Calendar'!$A$2:$A$500,0),MONTH(TODAY()))="","Out",INDEX('Seasonal Calendar'!$C$2:$N$500,MATCH(A82,'Seasonal Calendar'!$A$2:$A$500,0),MONTH(TODAY()))),"") -> In | K82: Verify | L82: Bunch | Q82: Y | R82: Core | S82: =COUNTIF('Recipe Ingredients'!$F$2:$F$2000,A82) -> 20 | T82: Stems in water, fridge | U82: 5-7 days | V82: Plateau, hydroponics
A83: P082 | B83: Basil (sweet) | D83: Herb | E83: Local hydroponic + imported | F83: Recipe ingredient | G83: Year-round | H83: All year | J83: =IFERROR(IF(INDEX('Seasonal Calendar'!$C$2:$N$500,MATCH(A83,'Seasonal Calendar'!$A$2:$A$500,0),MONTH(TODAY()))="","Out",INDEX('Seasonal Calendar'!$C$2:$N$500,MATCH(A83,'Seasonal Calendar'!$A$2:$A$500,0),MONTH(TODAY()))),"") -> In | K83: Verify | L83: 150g | M83: 3550 | N83: 150g hydroponic | O83: Mint Foods (mintfoods.store), 11 Oct 2026 | Q83: N | R83: Premium | S83: =COUNTIF('Recipe Ingredients'!$F$2:$F$2000,A83) -> 9 | T83: Room temp, stems in water | U83: 3-4 days | V83: Lagos hydroponics | X83: Scent leaf is the local swap in every recipe.
A84: P083 | B84: Lemongrass | C84: Fever grass | D84: Herb | E84: Local | F84: Recipe ingredient | G84: Year-round | H84: All year | J84: =IFERROR(IF(INDEX('Seasonal Calendar'!$C$2:$N$500,MATCH(A84,'Seasonal Calendar'!$A$2:$A$500,0),MONTH(TODAY()))="","Out",INDEX('Seasonal Calendar'!$C$2:$N$500,MATCH(A84,'Seasonal Calendar'!$A$2:$A$500,0),MONTH(TODAY()))),"") -> In | K84: Verify | L84: Bunch | Q84: Y | R84: Core | S84: =COUNTIF('Recipe Ingredients'!$F$2:$F$2000,A84) -> 1 | T84: Fridge | U84: 1-2 weeks | V84: Nationwide | W84: Wellness
A85: P084 | B85: Rosemary | D85: Herb | E85: Local hydroponic + imported | F85: Recipe ingredient | G85: Year-round | H85: All year | J85: =IFERROR(IF(INDEX('Seasonal Calendar'!$C$2:$N$500,MATCH(A85,'Seasonal Calendar'!$A$2:$A$500,0),MONTH(TODAY()))="","Out",INDEX('Seasonal Calendar'!$C$2:$N$500,MATCH(A85,'Seasonal Calendar'!$A$2:$A$500,0),MONTH(TODAY()))),"") -> In | K85: Verify | L85: 100g | M85: 5950 | N85: 100g | O85: Mint Foods (mintfoods.store), 11 Oct 2026 | Q85: N | R85: Later | S85: =COUNTIF('Recipe Ingredients'!$F$2:$F$2000,A85) -> 5 | T85: Fridge | U85: 1-2 weeks | V85: Hydroponics + imports | X85: Scent leaf or dried thyme covers it.

Sheet Seasonal Calendar
A1: ID | B1: Produce | C1: Jan | D1: Feb | E1: Mar | F1: Apr | G1: May | H1: Jun | I1: Jul | J1: Aug | K1: Sep | L1: Oct | M1: Nov | N1: Dec | O1: Months available | P1: Role
A2: P001 | B2: Banana | C2: In | D2: In | E2: In | F2: In | G2: In | H2: In | I2: In | J2: In | K2: In | L2: In | M2: In | N2: In | O2: =COUNTIF(C2:N2,"Peak")+COUNTIF(C2:N2,"In") -> 12 | P2: Eat as-is + recipes
A3: P002 | B3: Plantain (ripe & unripe) | C3: In | D3: In | E3: In | F3: In | G3: In | H3: In | I3: In | J3: In | K3: In | L3: In | M3: In | N3: In | O3: =COUNTIF(C3:N3,"Peak")+COUNTIF(C3:N3,"In") -> 12 | P3: Recipe ingredient
A4: P003 | B4: Pineapple | C4: In | D4: In | E4: In | F4: In | G4: In | H4: In | I4: In | J4: In | K4: In | L4: In | M4: In | N4: In | O4: =COUNTIF(C4:N4,"Peak")+COUNTIF(C4:N4,"In") -> 12 | P4: Eat as-is + recipes
A5: P004 | B5: Watermelon | C5: Peak | D5: Peak | E5: Peak | F5: Peak | G5: In | H5: In | I5: In | J5: In | K5: In | L5: In | M5: In | N5: Peak | O5: =COUNTIF(C5:N5,"Peak")+COUNTIF(C5:N5,"In") -> 12 | P5: Eat as-is + recipes
A6: P005 | B6: Pawpaw (papaya) | C6: In | D6: In | E6: In | F6: In | G6: In | H6: In | I6: In | J6: In | K6: In | L6: In | M6: In | N6: In | O6: =COUNTIF(C6:N6,"Peak")+COUNTIF(C6:N6,"In") -> 12 | P6: Eat as-is + recipes
A7: P006 | B7: Mango | D7: In | E7: Peak | F7: Peak | G7: In | J7: In | K7: In | O7: =COUNTIF(C7:N7,"Peak")+COUNTIF(C7:N7,"In") -> 6 | P7: Eat as-is + recipes
A8: P007 | B8: Orange | C8: Peak | D8: In | E8: In | F8: In | G8: In | H8: In | I8: In | J8: In | K8: In | L8: Peak | M8: Peak | N8: Peak | O8: =COUNTIF(C8:N8,"Peak")+COUNTIF(C8:N8,"In") -> 12 | P8: Eat as-is + recipes
A9: P008 | B9: Tangerine | C9: Peak | D9: In | E9: In | F9: In | G9: In | H9: In | I9: In | J9: In | K9: In | L9: Peak | M9: Peak | N9: Peak | O9: =COUNTIF(C9:N9,"Peak")+COUNTIF(C9:N9,"In") -> 12 | P9: Eat as-is + recipes
A10: P009 | B10: Lemon | C10: Peak | D10: In | E10: In | F10: In | G10: In | H10: In | I10: In | J10: In | K10: In | L10: Peak | M10: Peak | N10: Peak | O10: =COUNTIF(C10:N10,"Peak")+COUNTIF(C10:N10,"In") -> 12 | P10: Recipe ingredient
A11: P010 | B11: Lime | C11: Peak | D11: In | E11: In | F11: In | G11: In | H11: In | I11: In | J11: In | K11: In | L11: Peak | M11: Peak | N11: Peak | O11: =COUNTIF(C11:N11,"Peak")+COUNTIF(C11:N11,"In") -> 12 | P11: Recipe ingredient
A12: P011 | B12: Grapefruit | C12: Peak | D12: In | E12: In | F12: In | G12: In | H12: In | I12: In | J12: In | K12: In | L12: Peak | M12: Peak | N12: Peak | O12: =COUNTIF(C12:N12,"Peak")+COUNTIF(C12:N12,"In") -> 12 | P12: Eat as-is + recipes
A13: P012 | B13: Avocado | C13: In | D13: In | E13: In | F13: In | G13: In | H13: In | I13: In | J13: In | K13: In | L13: In | M13: In | N13: In | O13: =COUNTIF(C13:N13,"Peak")+COUNTIF(C13:N13,"In") -> 12 | P13: Eat as-is + recipes
A14: P013 | B14: Guava | D14: Peak | E14: Peak | J14: In | K14: In | O14: =COUNTIF(C14:N14,"Peak")+COUNTIF(C14:N14,"In") -> 4 | P14: Eat as-is + recipes
A15: P014 | B15: Soursop | C15: In | D15: Peak | E15: Peak | G15: In | H15: In | I15: In | J15: In | L15: In | N15: In | O15: =COUNTIF(C15:N15,"Peak")+COUNTIF(C15:N15,"In") -> 9 | P15: Eat as-is + recipes
A16: P015 | B16: Passion fruit | C16: In | D16: In | E16: In | G16: In | H16: In | J16: In | K16: In | L16: In | M16: In | O16: =COUNTIF(C16:N16,"Peak")+COUNTIF(C16:N16,"In") -> 9 | P16: Recipe ingredient
A17: P016 | B17: Coconut | C17: In | D17: In | E17: In | F17: In | G17: In | H17: In | I17: In | J17: In | K17: In | L17: In | M17: In | N17: In | O17: =COUNTIF(C17:N17,"Peak")+COUNTIF(C17:N17,"In") -> 12 | P17: Eat as-is + recipes
A18: P017 | B18: Agbalumo (African star apple) | C18: Peak | D18: Peak | E18: Peak | F18: In | G18: In | N18: In | O18: =COUNTIF(C18:N18,"Peak")+COUNTIF(C18:N18,"In") -> 6 | P18: Eat as-is only
A19: P018 | B19: Cashew apple | D19: Peak | E19: Peak | O19: =COUNTIF(C19:N19,"Peak")+COUNTIF(C19:N19,"In") -> 2 | P19: Eat as-is only
A20: P019 | B20: Velvet tamarind | C20: In | D20: Peak | E20: Peak | F20: In | G20: In | O20: =COUNTIF(C20:N20,"Peak")+COUNTIF(C20:N20,"In") -> 5 | P20: Eat as-is only
A21: P020 | B21: Hog plum | I21: Peak | N21: In | O21: =COUNTIF(C21:N21,"Peak")+COUNTIF(C21:N21,"In") -> 2 | P21: Eat as-is only
A22: P021 | B22: Pepper fruit | D22: In | E22: In | F22: In | G22: In | O22: =COUNTIF(C22:N22,"Peak")+COUNTIF(C22:N22,"In") -> 4 | P22: Eat as-is only
A23: P022 | B23: Monkey kola | G23: In | H23: In | I23: In | J23: In | O23: =COUNTIF(C23:N23,"Peak")+COUNTIF(C23:N23,"In") -> 4 | P23: Eat as-is only
A24: P023 | B24: African pear | G24: In | H24: Peak | I24: Peak | J24: Peak | K24: In | O24: =COUNTIF(C24:N24,"Peak")+COUNTIF(C24:N24,"In") -> 5 | P24: Eat as-is only
A25: P024 | B25: Tiger nut | C25: In | D25: In | E25: In | F25: In | G25: In | I25: In | J25: In | K25: In | M25: In | N25: In | O25: =COUNTIF(C25:N25,"Peak")+COUNTIF(C25:N25,"In") -> 10 | P25: Eat as-is + recipes
A26: P025 | B26: Sugarcane | C26: In | D26: In | E26: In | J26: In | K26: In | L26: In | M26: In | N26: In | O26: =COUNTIF(C26:N26,"Peak")+COUNTIF(C26:N26,"In") -> 8 | P26: Eat as-is only
A27: P026 | B27: Custard apple (sweetsop) | D27: In | J27: In | K27: In | O27: =COUNTIF(C27:N27,"Peak")+COUNTIF(C27:N27,"In") -> 3 | P27: Eat as-is only
A28: P027 | B28: Jackfruit | G28: Peak | H28: In | O28: =COUNTIF(C28:N28,"Peak")+COUNTIF(C28:N28,"In") -> 2 | P28: Eat as-is + recipes
A29: P028 | B29: June plum | C29: In | N29: In | O29: =COUNTIF(C29:N29,"Peak")+COUNTIF(C29:N29,"In") -> 2 | P29: Eat as-is only
A30: P029 | B30: Sweet melon (golden / cantaloupe) | C30: Peak | D30: In | E30: In | F30: In | G30: Peak | H30: Peak | I30: In | J30: In | K30: In | L30: In | M30: In | N30: In | O30: =COUNTIF(C30:N30,"Peak")+COUNTIF(C30:N30,"In") -> 12 | P30: Eat as-is + recipes
A31: P030 | B31: Dates | C31: In | D31: In | E31: In | F31: Peak | G31: Peak | H31: Peak | I31: Peak | J31: In | K31: In | L31: In | M31: In | N31: In | O31: =COUNTIF(C31:N31,"Peak")+COUNTIF(C31:N31,"In") -> 12 | P31: Eat as-is + recipes
A32: P031 | B32: Apple (red & green) | C32: In | D32: In | E32: In | F32: In | G32: In | H32: In | I32: In | J32: In | K32: In | L32: In | M32: In | N32: In | O32: =COUNTIF(C32:N32,"Peak")+COUNTIF(C32:N32,"In") -> 12 | P32: Eat as-is + recipes
A33: P032 | B33: Pear | C33: In | D33: In | E33: In | F33: In | G33: In | H33: In | I33: In | J33: In | K33: In | L33: In | M33: In | N33: In | O33: =COUNTIF(C33:N33,"Peak")+COUNTIF(C33:N33,"In") -> 12 | P33: Eat as-is + recipes
A34: P033 | B34: Grapes (red / black seedless) | C34: In | D34: In | E34: In | F34: In | G34: In | H34: In | I34: In | J34: In | K34: In | L34: In | M34: In | N34: In | O34: =COUNTIF(C34:N34,"Peak")+COUNTIF(C34:N34,"In") -> 12 | P34: Eat as-is + recipes
A35: P034 | B35: Strawberry | C35: Peak | D35: Peak | E35: In | F35: In | M35: In | N35: Peak | O35: =COUNTIF(C35:N35,"Peak")+COUNTIF(C35:N35,"In") -> 6 | P35: Eat as-is + recipes
A36: P035 | B36: Blueberry | C36: In | D36: In | E36: In | F36: In | G36: In | H36: In | I36: In | J36: In | K36: In | L36: In | M36: In | N36: In | O36: =COUNTIF(C36:N36,"Peak")+COUNTIF(C36:N36,"In") -> 12 | P36: Eat as-is + recipes
A37: P036 | B37: Kiwi | C37: In | D37: In | E37: In | F37: In | G37: In | H37: In | I37: In | J37: In | K37: In | L37: In | M37: In | N37: In | O37: =COUNTIF(C37:N37,"Peak")+COUNTIF(C37:N37,"In") -> 12 | P37: Eat as-is + recipes
A38: P037 | B38: Pomegranate | C38: In | D38: In | E38: In | F38: In | G38: In | H38: In | I38: In | J38: In | K38: In | L38: In | M38: In | N38: In | O38: =COUNTIF(C38:N38,"Peak")+COUNTIF(C38:N38,"In") -> 12 | P38: Eat as-is + recipes
A39: P038 | B39: Dragon fruit | C39: In | D39: In | E39: In | F39: In | G39: In | H39: In | I39: In | J39: In | K39: In | L39: In | M39: In | N39: In | O39: =COUNTIF(C39:N39,"Peak")+COUNTIF(C39:N39,"In") -> 12 | P39: Eat as-is + recipes
A40: P039 | B40: Star fruit (carambola) | C40: In | D40: In | E40: In | F40: In | G40: In | H40: In | I40: In | J40: In | K40: In | L40: In | M40: In | N40: In | O40: =COUNTIF(C40:N40,"Peak")+COUNTIF(C40:N40,"In") -> 12 | P40: Eat as-is + recipes
A41: P040 | B41: Groundnut (fresh or roasted) | C41: In | D41: In | E41: In | F41: In | G41: Peak | H41: Peak | I41: Peak | J41: Peak | K41: Peak | L41: Peak | M41: In | N41: In | O41: =COUNTIF(C41:N41,"Peak")+COUNTIF(C41:N41,"In") -> 12 | P41: Recipe ingredient
A42: P041 | B42: African walnut | E42: In | F42: In | G42: In | I42: In | J42: In | L42: In | O42: =COUNTIF(C42:N42,"Peak")+COUNTIF(C42:N42,"In") -> 6 | P42: Eat as-is only
A43: P042 | B43: Tomato (plum) | C43: Peak | D43: In | E43: In | F43: In | G43: In | H43: In | I43: In | J43: Peak | K43: Peak | L43: In | M43: In | N43: Peak | O43: =COUNTIF(C43:N43,"Peak")+COUNTIF(C43:N43,"In") -> 12 | P43: Recipe ingredient
A44: P043 | B44: Cherry tomato | C44: In | D44: In | E44: In | F44: In | G44: In | H44: In | I44: In | J44: In | K44: In | L44: In | M44: In | N44: In | O44: =COUNTIF(C44:N44,"Peak")+COUNTIF(C44:N44,"In") -> 12 | P44: Eat as-is + recipes
A45: P044 | B45: Red bell pepper | C45: In | D45: In | E45: In | F45: In | G45: In | H45: In | I45: In | J45: In | K45: In | L45: In | M45: In | N45: In | O45: =COUNTIF(C45:N45,"Peak")+COUNTIF(C45:N45,"In") -> 12 | P45: Recipe ingredient
A46: P045 | B46: Green / yellow bell pepper | C46: In | D46: In | E46: In | F46: In | G46: In | H46: In | I46: In | J46: In | K46: In | L46: In | M46: In | N46: In | O46: =COUNTIF(C46:N46,"Peak")+COUNTIF(C46:N46,"In") -> 12 | P46: Recipe ingredient
A47: P046 | B47: Scotch bonnet | C47: In | D47: In | E47: In | F47: In | G47: In | H47: In | I47: In | J47: In | K47: In | L47: In | M47: In | N47: In | O47: =COUNTIF(C47:N47,"Peak")+COUNTIF(C47:N47,"In") -> 12 | P47: Recipe ingredient
A48: P047 | B48: Long red chilli | C48: In | D48: In | E48: In | F48: In | G48: In | H48: In | I48: In | J48: In | K48: In | L48: In | M48: In | N48: In | O48: =COUNTIF(C48:N48,"Peak")+COUNTIF(C48:N48,"In") -> 12 | P48: Recipe ingredient
A49: P048 | B49: Onion (red & white) | C49: In | D49: In | E49: In | F49: In | G49: In | H49: In | I49: In | J49: In | K49: In | L49: In | M49: In | N49: In | O49: =COUNTIF(C49:N49,"Peak")+COUNTIF(C49:N49,"In") -> 12 | P49: Recipe ingredient
A50: P049 | B50: Spring onion | C50: In | D50: In | E50: In | F50: In | G50: In | H50: In | I50: In | J50: In | K50: In | L50: In | M50: In | N50: In | O50: =COUNTIF(C50:N50,"Peak")+COUNTIF(C50:N50,"In") -> 12 | P50: Recipe ingredient
A51: P050 | B51: Shallots | C51: In | D51: In | E51: In | F51: In | G51: In | H51: In | I51: In | J51: In | K51: In | L51: In | M51: In | N51: In | O51: =COUNTIF(C51:N51,"Peak")+COUNTIF(C51:N51,"In") -> 12 | P51: Recipe ingredient
A52: P051 | B52: Garlic | C52: In | D52: In | E52: In | F52: In | G52: In | H52: In | I52: In | J52: In | K52: In | L52: In | M52: In | N52: In | O52: =COUNTIF(C52:N52,"Peak")+COUNTIF(C52:N52,"In") -> 12 | P52: Recipe ingredient
A53: P052 | B53: Ginger | C53: In | D53: In | E53: In | F53: In | G53: In | H53: In | I53: In | J53: In | K53: Peak | L53: Peak | M53: In | N53: In | O53: =COUNTIF(C53:N53,"Peak")+COUNTIF(C53:N53,"In") -> 12 | P53: Recipe ingredient
A54: P053 | B54: Turmeric (fresh) | C54: In | D54: In | E54: In | F54: In | G54: In | H54: In | K54: In | L54: In | M54: In | N54: In | O54: =COUNTIF(C54:N54,"Peak")+COUNTIF(C54:N54,"In") -> 10 | P54: Recipe ingredient
A55: P054 | B55: Cucumber | C55: Peak | D55: Peak | E55: Peak | F55: Peak | G55: Peak | H55: In | I55: In | J55: In | K55: In | L55: In | M55: In | N55: In | O55: =COUNTIF(C55:N55,"Peak")+COUNTIF(C55:N55,"In") -> 12 | P55: Eat as-is + recipes
A56: P055 | B56: Carrot | C56: Peak | D56: Peak | E56: Peak | F56: Peak | G56: Peak | H56: In | I56: In | J56: In | K56: Peak | L56: Peak | M56: Peak | N56: Peak | O56: =COUNTIF(C56:N56,"Peak")+COUNTIF(C56:N56,"In") -> 12 | P56: Eat as-is + recipes
A57: P056 | B57: Cabbage (white) | C57: In | D57: In | E57: In | F57: In | G57: In | H57: In | I57: In | J57: In | K57: In | L57: In | M57: In | N57: In | O57: =COUNTIF(C57:N57,"Peak")+COUNTIF(C57:N57,"In") -> 12 | P57: Recipe ingredient
A58: P057 | B58: Purple cabbage | C58: In | D58: In | E58: In | F58: In | G58: In | H58: In | I58: In | J58: In | K58: In | L58: In | M58: In | N58: In | O58: =COUNTIF(C58:N58,"Peak")+COUNTIF(C58:N58,"In") -> 12 | P58: Recipe ingredient
A59: P058 | B59: Lettuce (iceberg / romaine / local) | C59: In | D59: In | E59: In | F59: In | G59: In | H59: In | I59: In | J59: In | K59: In | L59: In | M59: In | N59: In | O59: =COUNTIF(C59:N59,"Peak")+COUNTIF(C59:N59,"In") -> 12 | P59: Recipe ingredient
A60: P059 | B60: Green beans | C60: In | D60: In | E60: In | F60: In | G60: In | H60: In | I60: In | J60: In | K60: In | L60: In | M60: In | N60: In | O60: =COUNTIF(C60:N60,"Peak")+COUNTIF(C60:N60,"In") -> 12 | P60: Recipe ingredient
A61: P060 | B61: Sweet corn | F61: In | G61: In | H61: Peak | I61: Peak | J61: In | O61: =COUNTIF(C61:N61,"Peak")+COUNTIF(C61:N61,"In") -> 5 | P61: Eat as-is + recipes
A62: P061 | B62: Garden egg | C62: In | D62: In | E62: In | F62: In | G62: In | H62: In | I62: In | J62: In | K62: In | L62: In | O62: =COUNTIF(C62:N62,"Peak")+COUNTIF(C62:N62,"In") -> 10 | P62: Eat as-is + recipes
A63: P062 | B63: Okra | C63: In | D63: In | E63: In | F63: In | G63: In | H63: In | I63: In | J63: In | K63: In | L63: In | M63: In | N63: In | O63: =COUNTIF(C63:N63,"Peak")+COUNTIF(C63:N63,"In") -> 12 | P63: Recipe ingredient
A64: P063 | B64: Broccoli | C64: In | D64: In | E64: In | F64: In | G64: In | H64: In | I64: In | J64: In | K64: In | L64: In | M64: In | N64: In | O64: =COUNTIF(C64:N64,"Peak")+COUNTIF(C64:N64,"In") -> 12 | P64: Recipe ingredient
A65: P064 | B65: Cauliflower | C65: In | D65: In | E65: In | F65: In | G65: In | H65: In | I65: In | J65: In | K65: In | L65: In | M65: In | N65: In | O65: =COUNTIF(C65:N65,"Peak")+COUNTIF(C65:N65,"In") -> 12 | P65: Recipe ingredient
A66: P065 | B66: Beetroot | C66: In | D66: In | E66: In | F66: In | G66: In | H66: In | I66: In | J66: In | K66: In | L66: In | M66: In | N66: In | O66: =COUNTIF(C66:N66,"Peak")+COUNTIF(C66:N66,"In") -> 12 | P66: Recipe ingredient
A67: P066 | B67: Zucchini (courgette) | C67: In | D67: In | E67: In | F67: In | G67: In | H67: In | I67: In | J67: In | K67: In | L67: In | M67: In | N67: In | O67: =COUNTIF(C67:N67,"Peak")+COUNTIF(C67:N67,"In") -> 12 | P67: Recipe ingredient
A68: P067 | B68: Mushrooms (oyster / button) | C68: In | D68: In | E68: In | F68: In | G68: In | H68: In | I68: In | J68: In | K68: In | L68: In | M68: In | N68: In | O68: =COUNTIF(C68:N68,"Peak")+COUNTIF(C68:N68,"In") -> 12 | P68: Recipe ingredient
A69: P068 | B69: Pumpkin (squash) | C69: In | D69: In | E69: In | F69: In | G69: In | H69: In | I69: In | J69: In | K69: In | L69: In | M69: In | N69: In | O69: =COUNTIF(C69:N69,"Peak")+COUNTIF(C69:N69,"In") -> 12 | P69: Recipe ingredient
A70: P069 | B70: Sweet potato | C70: In | D70: In | E70: In | F70: In | G70: In | H70: In | I70: In | J70: In | K70: In | L70: In | M70: In | N70: In | O70: =COUNTIF(C70:N70,"Peak")+COUNTIF(C70:N70,"In") -> 12 | P70: Recipe ingredient
A71: P070 | B71: Irish potato | C71: In | D71: In | E71: In | F71: In | G71: In | H71: In | I71: In | J71: In | K71: In | L71: In | M71: In | N71: In | O71: =COUNTIF(C71:N71,"Peak")+COUNTIF(C71:N71,"In") -> 12 | P71: Recipe ingredient
A72: P071 | B72: Yam | C72: In | D72: In | E72: In | F72: In | G72: In | H72: In | I72: In | J72: Peak | K72: Peak | L72: Peak | M72: In | N72: In | O72: =COUNTIF(C72:N72,"Peak")+COUNTIF(C72:N72,"In") -> 12 | P72: Recipe ingredient
A73: P072 | B73: Fluted pumpkin leaf | C73: In | D73: In | E73: In | F73: In | G73: In | H73: In | I73: In | J73: In | K73: In | L73: In | M73: In | N73: In | O73: =COUNTIF(C73:N73,"Peak")+COUNTIF(C73:N73,"In") -> 12 | P73: Recipe ingredient
A74: P073 | B74: Amaranth greens (Nigerian spinach) | C74: In | D74: In | E74: In | F74: In | G74: In | H74: In | I74: In | J74: In | K74: In | L74: In | M74: In | N74: In | O74: =COUNTIF(C74:N74,"Peak")+COUNTIF(C74:N74,"In") -> 12 | P74: Recipe ingredient
... A85: P084 | B85: Rosemary | C85: In | D85: In | E85: In | F85: In | G85: In | H85: In | I85: In | J85: In | K85: In | L85: In | M85: In | N85: In | O85: =COUNTIF(C85:N85,"Peak")+COUNTIF(C85:N85,"In") -> 12 | P85: Recipe ingredient
B87: Peak = best quality and price. In = available. Blank = scarce or out. Nigeria: dry season roughly Oct/Nov-Mar, rainy season Apr-Oct with the 'August break'.

Sheet Nutrition
A1: ID | B1: Produce | C1: kcal | D1: Fibre (g) | E1: Vitamin C (mg) | F1: Vitamin A (mcg RAE) | G1: Vitamin K (mcg) | H1: Folate (mcg) | I1: Potassium (mg) | J1: Vitamin E (mg) | K1: Vitamin B6 (mg) | L1: Magnesium (mg) | M1: Iron (mg) | N1: 1 piece (g) | O1: Piece = | P1: 1 cup (g) | Q1: Cup = | R1: Source | S1: Confidence
A2: P001 | B2: Banana | C2: 89 | D2: 2.6 | E2: 8.7 | F2: 3 | G2: 0.5 | H2: 20 | I2: 358 | J2: 0.1 | K2: 0.367 | L2: 27 | M2: 0.26 | N2: 118 | O2: 1 medium, peeled | P2: 150 | Q2: 1 cup sliced | R2: USDA FDC 173944 (SR 09040) | S2: High
A3: P002 | B3: Plantain (ripe & unripe) | C3: 122 | D3: 2.3 | E3: 18.4 | F3: 56 | G3: 0.7 | H3: 22 | I3: 499 | J3: 0.14 | K3: 0.299 | L3: 37 | M3: 0.6 | N3: 179 | O3: 1 medium, peeled | P3: 148 | Q3: 1 cup sliced | R3: USDA SR Legacy 09277 Plantains, raw | S3: High
A4: P003 | B4: Pineapple | C4: 50 | D4: 1.4 | E4: 47.8 | F4: 3 | G4: 0.7 | H4: 18 | I4: 109 | J4: 0.02 | K4: 0.112 | L4: 12 | M4: 0.29 | N4: 905 | O4: 1 medium pineapple, flesh only | P4: 165 | Q4: 1 cup chunks | R4: USDA FDC 169124 (SR 09266) | S4: High
A5: P004 | B5: Watermelon | C5: 30 | D5: 0.4 | E5: 8.1 | F5: 28 | G5: 0.1 | H5: 3 | I5: 112 | J5: 0.05 | K5: 0.045 | L5: 10 | M5: 0.24 | N5: 286 | O5: 1 wedge (1/16 of melon), flesh | P5: 152 | Q5: 1 cup diced | R5: USDA FDC 167765 (SR 09326) | S5: High
A6: P005 | B6: Pawpaw (papaya) | C6: 43 | D6: 1.7 | E6: 60.9 | F6: 47 | G6: 2.6 | H6: 37 | I6: 182 | J6: 0.3 | K6: 0.038 | L6: 21 | M6: 0.25 | N6: 275 | O6: 1 medium pawpaw, flesh only | P6: 145 | Q6: 1 cup cubed | R6: USDA FDC 169926 (SR 09226) | S6: High
A7: P006 | B7: Mango | C7: 60 | D7: 1.6 | E7: 36.4 | F7: 54 | G7: 4.2 | H7: 43 | I7: 168 | J7: 0.9 | K7: 0.119 | L7: 10 | M7: 0.16 | N7: 336 | O7: 1 medium mango, flesh only | P7: 165 | Q7: 1 cup pieces | R7: USDA FDC 169910 (SR 09176) | S7: High
A8: P007 | B8: Orange | C8: 47 | D8: 2.4 | E8: 53.2 | F8: 11 | G8: 0 | H8: 30 | I8: 181 | J8: 0.18 | K8: 0.06 | L8: 10 | M8: 0.1 | N8: 131 | O8: 1 medium, peeled | P8: 180 | Q8: 1 cup sections | R8: USDA FDC 169097 (SR 09200) | S8: High
A9: P008 | B9: Tangerine | C9: 53 | D9: 1.8 | E9: 26.7 | F9: 34 | G9: 0 | H9: 16 | I9: 166 | J9: 0.2 | K9: 0.078 | L9: 12 | M9: 0.15 | N9: 88 | O9: 1 medium, peeled | P9: 195 | Q9: 1 cup sections | R9: USDA FDC 169105 (SR 09218) | S9: High
A10: P009 | B10: Lemon | C10: 29 | D10: 2.8 | E10: 53 | F10: 1 | G10: 0 | H10: 11 | I10: 138 | J10: 0.15 | K10: 0.08 | L10: 8 | M10: 0.6 | N10: 58 | O10: 1 medium lemon, flesh without peel (juice of 1 lemon ~47 g) | P10: 212 | Q10: 1 cup sections | R10: USDA FDC 167746 (SR 09150) | S10: High
A11: P010 | B11: Lime | C11: 30 | D11: 2.8 | E11: 29.1 | F11: 2 | G11: 0.6 | H11: 8 | I11: 102 | J11: 0.22 | K11: 0.043 | L11: 6 | M11: 0.6 | N11: 67 | O11: 1 lime, flesh without peel (juice of 1 lime ~44 g) | R11: USDA FDC 168155 (SR 09159) | S11: High
A12: P011 | B12: Grapefruit | C12: 42 | D12: 1.6 | E12: 31.2 | F12: 58 | G12: 0 | H12: 13 | I12: 135 | J12: 0.13 | K12: 0.053 | L12: 9 | M12: 0.08 | N12: 246 | O12: 1 whole grapefruit, flesh (half = 123 g) | P12: 230 | Q12: 1 cup sections | R12: USDA FDC 174675 (SR 09112, pink/red) | S12: High
A13: P012 | B13: Avocado | C13: 160 | D13: 6.7 | E13: 10 | F13: 7 | G13: 21 | H13: 81 | I13: 485 | J13: 2.07 | K13: 0.257 | L13: 29 | M13: 0.55 | N13: 201 | O13: 1 medium avocado, flesh only | P13: 150 | Q13: 1 cup cubed | R13: USDA FDC 171705 (SR 09037) | S13: High
A14: P013 | B14: Guava | C14: 68 | D14: 5.4 | E14: 228.3 | F14: 31 | G14: 2.6 | H14: 49 | I14: 417 | J14: 0.73 | K14: 0.11 | L14: 22 | M14: 0.26 | N14: 55 | O14: 1 fruit | P14: 165 | Q14: 1 cup chopped | R14: USDA FDC 173044 (SR 09139) | S14: High
A15: P014 | B15: Soursop | C15: 66 | D15: 3.3 | E15: 20.6 | F15: 0 | G15: 0.4 | H15: 14 | I15: 278 | J15: 0.08 | K15: 0.059 | L15: 21 | M15: 0.6 | N15: 625 | O15: 1 fruit, pulp only | P15: 225 | Q15: 1 cup pulp | R15: USDA FDC 167763 (SR 09315) | S15: High
A16: P015 | B16: Passion fruit | C16: 97 | D16: 10.4 | E16: 30 | F16: 64 | G16: 0.7 | H16: 14 | I16: 348 | J16: 0.02 | K16: 0.1 | L16: 29 | M16: 1.6 | N16: 18 | O16: 1 fruit, pulp & seeds | P16: 236 | Q16: 1 cup pulp | R16: USDA FDC 169108 (SR 09231, purple) | S16: High
A17: P016 | B17: Coconut | C17: 354 | D17: 9 | E17: 3.3 | F17: 0 | G17: 0.2 | H17: 26 | I17: 356 | J17: 0.24 | K17: 0.054 | L17: 32 | M17: 2.43 | N17: 397 | O17: 1 medium coconut, meat only | P17: 80 | Q17: 1 cup shredded | R17: USDA FDC 170169 (SR 12104) | S17: High
A18: P017 | B18: Agbalumo (African star apple) | C18: 91 | D18: 3 | E18: 87 | I18: 654 | M18: 2.2 | N18: 30 | O18: 1 fruit, pulp only (skin & seeds removed; whole fruit ~50 g) | P18: 150 | Q18: 1 cup pulp | R18: Nigerian studies: Adeniji 2012 (3 varieties, fresh pulp: K 666-701 mg, Fe 2.2-2.3 mg, vit C 87-100 mg, moisture 73-76%); Isa 2021 (K 654 mg, Fe 2.16 mg); kcal derived from proximate | S18: Low (vitamin C reported anywhere from 4 to 100+ mg across studies; lower bound of Adeniji used)
A19: P018 | B19: Cashew apple | C19: 43 | D19: 1.7 | E19: 219 | F19: 8 | I19: 124 | L19: 10 | M19: 0.2 | N19: 70 | O19: 1 cashew apple (pseudofruit), flesh | P19: 150 | Q19: 1 cup chopped | R19: TACO Brazilian Food Composition Table 4th ed. (caju, cru); vitamin C range 200-241 mg/100 g confirmed by reviews (yellow 241, red 222 mg) | S19: Medium (vit C, kcal, K, Mg, Fe from TACO; vit A estimated from carotenoid literature)
A20: P019 | B20: Velvet tamarind | C20: 290 | D20: 3 | E20: 15 | F20: 109 | I20: 300 | M20: 4.1 | N20: 2 | O20: 1 fruit, pulp only (whole fruit with shell & seed ~4 g) | R20: Nigerian/Benin studies of Dialium guineense pulp: Nigeria dry pulp 289 kcal, K 260 mg, Fe 4.1 mg; Benin fresh pulp K 366 mg, vit C 4.5 mg; Calabar 2024 vit C 26.4 mg, vit A 109 mcg RAE | S20: Low (pulp is naturally semi-dry ~10% moisture; vit C mid-point of 4.5-26 mg; no reliable Mg/folate/E/K/B6)
A21: P020 | B21: Hog plum | C21: 46 | D21: 1.2 | E21: 28 | F21: 280 | I21: 250 | L21: 20 | M21: 0.4 | N21: 12 | O21: 1 fruit, flesh only (whole fruit ~18 g, large stone) | P21: 150 | Q21: 1 cup pulp | R21: Tiburski et al. 2011 Food Res Int (yellow mombin pulp: notable K; 100 g supplies >37% RDA vit A); Brazilian/Nigerian pulp studies (vit C 25-47 mg); TACO caja for kcal/Fe | S21: Low (vit A back-calculated from % RDA; K, Mg, fibre approximate)
A22: P021 | B22: Pepper fruit | C22: 110 | D22: 4 | I22: 290 | N22: 2 | O22: 1 fruit | R22: Nigerian studies: Ihemeje 2013 (ripe: moisture 18.7%, fibre 14.3% DW); Babcock elemental screening (K 291.5 mg/100 g); Cirad Fruits journal (protein 15%, carb 62% DW) | S22: Low (eaten as a snack in small quantities; most data dry-basis; vit C figures in literature are inconsistent so left null)
A23: P022 | B23: Monkey kola | C23: 150 | D23: 2.5 | E23: 10 | I23: 200 | M23: 1.8 | N23: 50 | O23: 1 fruit, edible pulp segments | P23: 130 | Q23: 1 cup pulp pieces | R23: Ene-Obong et al. 2016 Food Chem 193:154 (C. lepidota dried pulp K 204-209 mg/100 g); Oranusi et al. 2020 Czech J Food Sci (vit C 4.5-14.4 mg, Fe 1.79 mg); Wofu & Tariah (yellow monkey kola pulp proximate) | S23: Low (fresh-basis energy derived from proximate; vitamins mostly unreported)
A24: P023 | B24: African pear | C24: 263 | D24: 4 | E24: 12 | I24: 550 | M24: 2 | N24: 35 | O24: 1 fruit, pulp only (seed removed; whole ~55 g) | P24: 150 | Q24: 1 cup pulp | R24: Nigerian pulp studies (Ajayi & Adesanwo 2009: 138 kcal low-fat sample; Omogbai 2012: K 550.7 mg, vit C 8 mg); Cameroon safou pulp (fat 25-35 g/100 g fresh gives ~260 kcal); vit C 8-13.5 mg range | S24: Low (oily fruit: energy depends on cultivar fat content 15-35 g/100 g; Mg reported value implausible so null)
A25: P024 | B25: Tiger nut | C25: 420 | D25: 12 | E25: 6 | F25: 0 | I25: 710 | J25: 5.2 | L25: 95 | M25: 3.6 | N25: 1 | O25: 1 tuber (a handful is ~30 g) | P25: 150 | Q25: 1 cup whole dried tubers | R25: Sanchez-Zapata et al. 2012 review / PMC4619938 (Burkina Faso tubers: K 557-846 mg, Mg 100-107 mg, Fe 3.6-11.4 mg, vit C 5-27 mg, fat 25-29 g); EU retail nutrition labels (fibre 11-15 g, vit E 5.2 mg, K 783-845 mg) | S25: Medium (dried tuber basis as sold; vit E from label data; soaked 'fresh' tiger nuts will be ~30% lower per 100 g)
A26: P025 | B26: Sugarcane | C26: 60 | D26: 0.6 | E26: 3 | F26: 0 | G26: 0 | I26: 150 | J26: 0 | L26: 13 | M26: 0.6 | N26: 150 | O26: 1 x 30 cm stick, juice/pith chewed (stick weighs ~300 g) | P26: 240 | Q26: 1 cup pressed juice | R26: Indian Food Composition Tables 2017 & FNRI Philippines (sugarcane juice); applied to chewed pith | S26: Low (proxy: sugarcane juice; whole cane is not in USDA)
A27: P026 | B27: Custard apple (sweetsop) | C27: 94 | D27: 4.4 | E27: 36.3 | F27: 0 | H27: 14 | I27: 247 | K27: 0.2 | L27: 21 | M27: 0.6 | N27: 155 | O27: 1 fruit, pulp only | P27: 250 | Q27: 1 cup pulp | R27: USDA SR Legacy 09320 Sugar-apples (sweetsop), raw | S27: High
A28: P027 | B28: Jackfruit | C28: 95 | D28: 1.5 | E28: 13.7 | F28: 5 | H28: 24 | I28: 448 | J28: 0.34 | K28: 0.329 | L28: 29 | M28: 0.23 | N28: 25 | O28: 1 bulb (aril) | P28: 165 | Q28: 1 cup sliced | R28: USDA FDC 174687 (SR 09144) | S28: High
A29: P028 | B29: June plum | C29: 48 | D29: 1.5 | E29: 36 | F29: 12 | I29: 250 | L29: 15 | M29: 0.3 | N29: 70 | O29: 1 fruit, flesh only (whole fruit ~100 g, fibrous stone) | P29: 150 | Q29: 1 cup chopped | R29: Morton 1987 Fruits of Warm Climates (ambarella: vit C 42 mg, carotene ~205 IU, Fe 0.3 mg); FNRI Philippines (Spondias); K/Mg from Spondias genus | S29: Low (K and Mg are genus proxies)
A30: P029 | B30: Sweet melon (golden / cantaloupe) | C30: 34 | D30: 0.9 | E30: 36.7 | F30: 169 | G30: 2.5 | H30: 21 | I30: 267 | J30: 0.05 | K30: 0.072 | L30: 12 | M30: 0.21 | N30: 552 | O30: 1 medium melon, flesh only (1 wedge = 69 g) | P30: 160 | Q30: 1 cup cubed | R30: USDA FDC 169092 (SR 09181) | S30: High
A31: P030 | B31: Dates | C31: 282 | D31: 8 | E31: 0.4 | F31: 0 | G31: 2.7 | H31: 19 | I31: 656 | J31: 0.05 | K31: 0.165 | L31: 43 | M31: 1.02 | N31: 7 | O31: 1 date, pitted (medjool = 24 g) | P31: 147 | Q31: 1 cup chopped | R31: USDA FDC 171726 (SR 09421, deglet noor) | S31: High
A32: P031 | B32: Apple (red & green) | C32: 52 | D32: 2.4 | E32: 4.6 | F32: 3 | G32: 2.2 | H32: 3 | I32: 107 | J32: 0.18 | K32: 0.041 | L32: 5 | M32: 0.12 | N32: 182 | O32: 1 medium, with skin | P32: 125 | Q32: 1 cup chopped | R32: USDA FDC 171688 (SR 09003) | S32: High
A33: P032 | B33: Pear | C33: 57 | D33: 3.1 | E33: 4.3 | F33: 1 | G33: 4.4 | H33: 7 | I33: 116 | J33: 0.12 | K33: 0.029 | L33: 7 | M33: 0.18 | N33: 178 | O33: 1 medium | P33: 140 | Q33: 1 cup sliced | R33: USDA FDC 169118 (SR 09252) | S33: High
A34: P033 | B34: Grapes (red / black seedless) | C34: 69 | D34: 0.9 | E34: 3.2 | F34: 3 | G34: 14.6 | H34: 2 | I34: 191 | J34: 0.19 | K34: 0.086 | L34: 7 | M34: 0.36 | N34: 5 | O34: 1 grape | P34: 151 | Q34: 1 cup | R34: USDA FDC 174683 (SR 09132, red/green) | S34: High
A35: P034 | B35: Strawberry | C35: 32 | D35: 2 | E35: 58.8 | F35: 1 | G35: 2.2 | H35: 24 | I35: 153 | J35: 0.29 | K35: 0.047 | L35: 13 | M35: 0.41 | N35: 12 | O35: 1 medium berry | P35: 152 | Q35: 1 cup halves | R35: USDA FDC 167762 (SR 09316) | S35: High
A36: P035 | B36: Blueberry | C36: 57 | D36: 2.4 | E36: 9.7 | F36: 3 | G36: 19.3 | H36: 6 | I36: 77 | J36: 0.57 | K36: 0.052 | L36: 6 | M36: 0.28 | N36: 148 | O36: 1 cup (approx 100 berries) | P36: 148 | Q36: 1 cup | R36: USDA FDC 171711 (SR 09050) | S36: High
A37: P036 | B37: Kiwi | C37: 61 | D37: 3 | E37: 92.7 | F37: 4 | G37: 40.3 | H37: 25 | I37: 312 | J37: 1.46 | K37: 0.063 | L37: 17 | M37: 0.31 | N37: 69 | O37: 1 fruit, peeled | P37: 180 | Q37: 1 cup sliced | R37: USDA FDC 168153 (SR 09148, green) | S37: High
A38: P037 | B38: Pomegranate | C38: 83 | D38: 4 | E38: 10.2 | F38: 0 | G38: 16.4 | H38: 38 | I38: 236 | J38: 0.6 | K38: 0.075 | L38: 12 | M38: 0.3 | N38: 282 | O38: 1 fruit, arils only | P38: 174 | Q38: 1 cup arils | R38: USDA FDC 169134 (SR 09286) | S38: High
A39: P038 | B39: Dragon fruit | C39: 52 | D39: 2 | E39: 9 | F39: 0 | I39: 260 | L39: 36 | M39: 0.7 | N39: 280 | O39: 1 medium fruit, flesh only | P39: 150 | Q39: 1 cup cubed | R39: Le Bellec et al. 2006 Fruits 61:237 review; Malaysian & Taiwan food composition data (white-flesh Hylocereus undatus) | S39: Low (no USDA SR/Foundation entry; values vary by flesh colour)
A40: P039 | B40: Star fruit (carambola) | C40: 31 | D40: 2.8 | E40: 34.4 | F40: 3 | G40: 0 | H40: 12 | I40: 133 | J40: 0.15 | K40: 0.017 | L40: 10 | M40: 0.08 | N40: 91 | O40: 1 medium fruit | P40: 132 | Q40: 1 cup cubed | R40: USDA FDC 171715 (SR 09060) | S40: High
A41: P040 | B41: Groundnut (fresh or roasted) | C41: 567 | D41: 8.5 | E41: 0 | F41: 0 | G41: 0 | H41: 240 | I41: 705 | J41: 8.33 | K41: 0.348 | L41: 168 | M41: 4.58 | N41: 28 | O41: 1 handful (28 g, ~30 kernels) | P41: 146 | Q41: 1 cup kernels | R41: USDA FDC 172430 (SR 16087) | S41: High
A42: P041 | B42: African walnut | C42: 400 | D42: 3 | I42: 620 | M42: 6 | N42: 8 | O42: 1 nut (kernel) | P42: 130 | Q42: 1 cup kernels | R42: Djikeng et al. 2017 (PMC5849894; dried seed: protein 24%, fat 53%, K 952 mg, Fe 18.5 mg) converted to ~35% moisture raw kernel; Arinola & Adesina 2014 proximate | S42: Low (all published data dry-basis; Mg reported at implausible levels so null; vitamins unreported)
A43: P042 | B43: Tomato (plum) | C43: 18 | D43: 1.2 | E43: 13.7 | F43: 42 | G43: 7.9 | H43: 15 | I43: 237 | J43: 0.54 | K43: 0.08 | L43: 11 | M43: 0.27 | N43: 62 | O43: 1 plum tomato | P43: 180 | Q43: 1 cup chopped | R43: USDA FDC 170457 (SR 11529) | S43: High
A44: P043 | B44: Cherry tomato | C44: 27 | D44: 2.1 | E44: 27.2 | F44: 42 | G44: 7.9 | H44: 15 | I44: 260 | J44: 0.54 | K44: 0.08 | L44: 10 | M44: 0.3 | N44: 17 | O44: 1 cherry tomato | P44: 149 | Q44: 1 cup whole | R44: USDA FDC 1999634 Tomatoes, grape, raw (Foundation) for kcal/fibre/vit C/K/Mg/Fe; red tomato SR 11529 for vit A/K/folate/E/B6 | S44: Medium
A45: P044 | B45: Red bell pepper | C45: 31 | D45: 2.1 | E45: 127.7 | F45: 157 | G45: 4.9 | H45: 46 | I45: 211 | J45: 1.58 | K45: 0.291 | L45: 12 | M45: 0.43 | N45: 119 | O45: 1 medium pepper | P45: 149 | Q45: 1 cup chopped | R45: USDA FDC 170108 (SR 11821) | S45: High
A46: P045 | B46: Green / yellow bell pepper | C46: 20 | D46: 1.7 | E46: 80.4 | F46: 18 | G46: 7.4 | H46: 10 | I46: 175 | J46: 0.37 | K46: 0.224 | L46: 10 | M46: 0.34 | N46: 119 | O46: 1 medium pepper | P46: 149 | Q46: 1 cup chopped | R46: USDA FDC 170427 (SR 11333, green) | S46: High
A47: P046 | B47: Scotch bonnet | C47: 40 | D47: 1.5 | E47: 143.7 | F47: 48 | G47: 14 | H47: 23 | I47: 322 | J47: 0.69 | K47: 0.506 | L47: 23 | M47: 1.03 | N47: 10 | O47: 1 pepper | P47: 150 | Q47: 1 cup chopped | R47: USDA FDC 170106 (SR 11819 Peppers, hot chili, red, raw) | S47: Medium (proxy: USDA red hot chili; no Capsicum chinense entry)
A48: P047 | B48: Long red chilli | C48: 40 | D48: 1.5 | E48: 143.7 | F48: 48 | G48: 14 | H48: 23 | I48: 322 | J48: 0.69 | K48: 0.506 | L48: 23 | M48: 1.03 | N48: 20 | O48: 1 chilli | P48: 150 | Q48: 1 cup chopped | R48: USDA FDC 170106 (SR 11819 Peppers, hot chili, red, raw) | S48: High
A49: P048 | B49: Onion (red & white) | C49: 40 | D49: 1.7 | E49: 7.4 | F49: 0 | G49: 0.4 | H49: 19 | I49: 146 | J49: 0.02 | K49: 0.12 | L49: 10 | M49: 0.21 | N49: 110 | O49: 1 medium onion | P49: 160 | Q49: 1 cup chopped | R49: USDA FDC 170000 (SR 11282) | S49: High
A50: P049 | B50: Spring onion | C50: 32 | D50: 2.6 | E50: 18.8 | F50: 50 | G50: 207 | H50: 64 | I50: 276 | J50: 0.55 | K50: 0.061 | L50: 20 | M50: 1.48 | N50: 15 | O50: 1 stalk | P50: 100 | Q50: 1 cup chopped | R50: USDA FDC 170005 (SR 11291 scallions) | S50: High
A51: P050 | B51: Shallots | C51: 72 | D51: 3.2 | E51: 8 | F51: 0 | G51: 0.8 | H51: 34 | I51: 334 | J51: 0.04 | K51: 0.345 | L51: 21 | M51: 1.2 | N51: 25 | O51: 1 bulb | P51: 160 | Q51: 1 cup chopped | R51: USDA FDC 170500 (SR 11677) | S51: High
A52: P051 | B52: Garlic | C52: 149 | D52: 2.1 | E52: 31.2 | F52: 0 | G52: 1.7 | H52: 3 | I52: 401 | J52: 0.08 | K52: 1.235 | L52: 25 | M52: 1.7 | N52: 3 | O52: 1 clove | P52: 136 | Q52: 1 cup cloves | R52: USDA FDC 169230 (SR 11215) | S52: High
A53: P052 | B53: Ginger | C53: 80 | D53: 2 | E53: 5 | F53: 0 | G53: 0.1 | H53: 11 | I53: 415 | J53: 0.26 | K53: 0.16 | L53: 43 | M53: 0.6 | N53: 15 | O53: 1 thumb (5 cm) | P53: 96 | Q53: 1 cup sliced | R53: USDA FDC 169231 (SR 11216) | S53: High
A54: P053 | B54: Turmeric (fresh) | C54: 78 | D54: 5.7 | E54: 3 | F54: 0 | G54: 3.4 | H54: 5 | I54: 520 | J54: 1.1 | K54: 0.03 | L54: 52 | M54: 13.8 | N54: 15 | O54: 1 thumb (5 cm) | P54: 96 | Q54: 1 cup sliced | R54: USDA FDC 172231 Spices, turmeric, ground (SR 02043) scaled to ~80% moisture fresh rhizome | S54: Low (proxy: ground turmeric x0.25; fresh rhizome not in USDA)
... A72: P071 | B72: Yam | C72: 118 | D72: 4.1 | E72: 17.1 | F72: 7 | G72: 2.3 | H72: 23 | I72: 816 | J72: 0.35 | K72: 0.293 | L72: 21 | M72: 0.54 | N72: 250 | O72: 1 slice (2.5 cm round of a medium tuber), peeled | P72: 150 | Q72: 1 cup cubed | R72: USDA FDC 170071 (SR 11601) | S72: High
A73: P072 | B73: Fluted pumpkin leaf | C73: 39 | D73: 2.6 | E73: 28 | F73: 280 | H73: 85 | I73: 450 | L73: 50 | M73: 2.5 | N73: 150 | O73: 1 bunch, leaves stripped (as sold with stalks ~350 g) | P73: 30 | Q73: 1 cup chopped | R73: West African Food Composition Table (FAO 2012/2019) Telfairia occidentalis leaves raw; Nigerian studies (vit C 28 mg fresh; Fe 2.2-3.6 mg); vit A from beta-carotene ~3300 mcg; folate proxy USDA amaranth leaves | S73: Low (K, Mg, folate approximate/proxy; vit K, E, B6 unreported)
A74: P073 | B74: Amaranth greens (Nigerian spinach) | C74: 23 | D74: 2 | E74: 43.3 | F74: 146 | G74: 1140 | H74: 85 | I74: 611 | K74: 0.192 | L74: 55 | M74: 2.32 | N74: 100 | O74: 1 bunch, leaves only | P74: 28 | Q74: 1 cup raw leaves | R74: USDA FDC 168386 (SR 11003 Amaranth leaves, raw) | S74: High
A75: P074 | B75: Waterleaf | C75: 29 | D75: 2.4 | E75: 6 | F75: 212 | I75: 557 | M75: 1.3 | N75: 150 | O75: 1 bunch, leaves & tender stems | P75: 30 | Q75: 1 cup chopped | R75: FNRI Philippine Food Composition Table (Talinum, raw leaves: 29 kcal, fibre 2.4 g, vit C 6 mg, beta-carotene 2542 mcg, K 557 mg, Fe 1.3 mg); older compilations give vit C 31 mg, Fe 5 mg | S75: Medium (FNRI primary; vit C varies 6-31 mg across sources)
A76: P075 | B76: Baby spinach | C76: 23 | D76: 2.2 | E76: 28.1 | F76: 469 | G76: 482.9 | H76: 194 | I76: 558 | J76: 2.03 | K76: 0.195 | L76: 79 | M76: 2.71 | N76: 30 | O76: 1 handful (1 cup) | P76: 30 | Q76: 1 cup raw leaves | R76: USDA FDC 168462 (SR 11457 Spinach, raw) | S76: High
A77: P076 | B77: Kale | C77: 35 | D77: 4.1 | E77: 93.4 | F77: 241 | G77: 390 | H77: 62 | I77: 348 | J77: 0.66 | K77: 0.147 | L77: 33 | M77: 1.6 | N77: 200 | O77: 1 bunch, leaves stripped | P77: 67 | Q77: 1 cup chopped | R77: USDA FDC 323505 Kale, raw (Foundation Foods) | S77: High
A78: P077 | B78: Scent leaf (African basil) | C78: 23 | D78: 1.6 | E78: 24 | F78: 264 | G78: 414.8 | H78: 68 | I78: 556 | J78: 0.8 | K78: 0.155 | L78: 64 | M78: 3.2 | N78: 50 | O78: 1 bunch, leaves only | P78: 25 | Q78: 1 cup leaves | R78: Nigerian study (O. gratissimum fresh leaf: vit C 23.97 mg, K 556 mg, Ca 426 mg); other values proxy from USDA FDC 172232 Basil, fresh | S78: Low (proxy: USDA sweet basil for kcal, fibre, vit A/K/E/B6, folate, Mg, Fe)
A79: P078 | B79: Bitter leaf | C79: 52 | D79: 3.5 | E79: 50 | F79: 300 | I79: 450 | M79: 3.5 | N79: 150 | O79: 1 bunch, leaves only (before washing) | P79: 30 | Q79: 1 cup chopped | R79: West African Food Composition Table (FAO 2012) Vernonia amygdalina leaves raw; Nigerian/Cameroon studies (vit C 20-197 mg; Fe 1.1-7.5 mg); vit A from beta-carotene | S79: Low (very wide literature ranges; washing/squeezing bitter leaf removes much of the vitamin C)
A80: P079 | B80: Mint | C80: 44 | D80: 6.8 | E80: 13.3 | F80: 203 | H80: 105 | I80: 458 | K80: 0.158 | L80: 63 | M80: 11.87 | N80: 2 | O80: 1 sprig | P80: 25 | Q80: 1 cup loosely packed leaves | R80: USDA FDC 173474 (SR 02064 Spearmint, fresh) | S80: High
A81: P080 | B81: Coriander (cilantro) | C81: 23 | D81: 2.8 | E81: 27 | F81: 337 | G81: 310 | H81: 62 | I81: 521 | J81: 2.5 | K81: 0.149 | L81: 26 | M81: 1.77 | N81: 50 | O81: 1 bunch | P81: 16 | Q81: 1 cup leaves | R81: USDA FDC 169997 (SR 11165) | S81: High
A82: P081 | B82: Parsley | C82: 36 | D82: 3.3 | E82: 133 | F82: 421 | G82: 1640 | H82: 152 | I82: 554 | J82: 0.75 | K82: 0.09 | L82: 50 | M82: 6.2 | N82: 60 | O82: 1 bunch | P82: 60 | Q82: 1 cup chopped | R82: USDA FDC 170416 (SR 11297) | S82: High
A83: P082 | B83: Basil (sweet) | C83: 23 | D83: 1.6 | E83: 18 | F83: 264 | G83: 414.8 | H83: 68 | I83: 295 | J83: 0.8 | K83: 0.155 | L83: 64 | M83: 3.17 | N83: 60 | O83: 1 bunch (5 leaves = 2.5 g) | P83: 24 | Q83: 1 cup whole leaves | R83: USDA FDC 172232 (SR 02044 Basil, fresh) | S83: High
A84: P083 | B84: Lemongrass | C84: 99 | E84: 2.6 | F84: 0 | H84: 75 | I84: 723 | K84: 0.08 | L84: 60 | M84: 8.17 | N84: 20 | O84: 1 stalk, tender white part | P84: 67 | Q84: 1 cup chopped | R84: USDA FDC 168573 (SR 11972 Lemon grass (citronella), raw) | S84: High
A85: P084 | B85: Rosemary | C85: 131 | D85: 14.1 | E85: 21.8 | F85: 146 | H85: 109 | I85: 668 | K85: 0.336 | L85: 91 | M85: 6.65 | N85: 2 | O85: 1 sprig (10 cm) | P85: 27 | Q85: 1 cup leaves (1 tbsp = 1.7 g) | R85: USDA SR Legacy 02063 Rosemary, fresh | S85: High
A87: Values per 100 g raw edible portion. Blue = researched inputs (USDA FoodData Central unless the Source column says otherwise; West African items from FAO/INFOODS West African Food Composition Table or Nigerian studies). Piece and cup weights are typical averages used to convert recipe quantities to grams. Edit here and every recipe's nutrition recalculates.

Sheet Recipes
A1: ID | B1: Recipe | C1: Category | D1: Subtype | E1: Meal | F1: Inspired by | G1: Source | H1: Source URL | I1: Reference image URL | J1: Local adaptation | K1: Serve with / you add | L1: Goal tags | M1: Diet | N1: Prep (min) | O1: Cook (min) | P1: Total (min) | Q1: Effort tier | R1: Servings | S1: Est. kcal / serving | T1: Est. protein (g) / serving | U1: Produce (g) / serving | V1: Fibre (g) | W1: Vitamin C (mg) | X1: Vitamin A (mcg RAE) | Y1: Vitamin K (mcg) | Z1: Folate (mcg) | AA1: Potassium (mg) | AB1: Vitamin E (mg) | AC1: Vitamin B6 (mg) | AD1: Magnesium (mg) | AE1: Iron (mg) | AF1: Fibre % daily | AG1: Vitamin C % daily | AH1: Vitamin A % daily | AI1: Vitamin K % daily | AJ1: Folate % daily | AK1: Potassium % daily | AL1: Vitamin E % daily | AM1: Vitamin B6 % daily | AN1: Magnesium % daily | AO1: Iron % daily | AP1: Strongest nutrient | AQ1: Health tagline | AR1: Also strong in | AS1: Health note | AT1: Hero produce | AU1: Basket items | AV1: Other items | AW1: Basket coverage | AX1: Hits target? | AY1: Seasonal ingredients | AZ1: Method | BA1: Tip | BB1: Status
A2: R015 | B2: Mango & Passion Fruit Overnight Oats | C2: Breakfast Plates | D2: Fruit & oats | E2: Breakfast | F2: Bircher muesli (Switzerland) / overnight oats | G2: BBC Good Food | H2: https://www.bbcgoodfood.com/recipes/overnight-oats | I2: https://images.immediate.co.uk/production/volatile/sites/30/2020/08/overnight-oats-32a2747.jpg?resize=440%2C230 | J2: Mango and passion fruit on top, tiger nut milk as an option. | K2: You add: rolled oats, yoghurt or milk, honey. | L2: Training, Weight management | M2: Vegetarian | N2: 10 | O2: 0 | P2: =N2+O2 -> 10 | Q2: =IF(O2=0,"No-cook",IF(P2<=25,"Quick","Standard")) -> No-cook | R2: 2 | S2: 380 | T2: 14 | U2: =SUMIFS('Recipe Ingredients'!$I$2:$I$2500,'Recipe Ingredients'!$A$2:$A$2500,A2)/R2 -> 186 | V2: =SUMIFS('Recipe Ingredients'!$J$2:$J$2500,'Recipe Ingredients'!$A$2:$A$2500,A2)/R2 -> 4.56 | W2: =SUMIFS('Recipe Ingredients'!$K$2:$K$2500,'Recipe Ingredients'!$A$2:$A$2500,A2)/R2 -> 66.552 | X2: =SUMIFS('Recipe Ingredients'!$L$2:$L$2500,'Recipe Ingredients'!$A$2:$A$2500,A2)/R2 -> 102.24 | Y2: =SUMIFS('Recipe Ingredients'!$M$2:$M$2500,'Recipe Ingredients'!$A$2:$A$2500,A2)/R2 -> 7.182 | Z2: =SUMIFS('Recipe Ingredients'!$N$2:$N$2500,'Recipe Ingredients'!$A$2:$A$2500,A2)/R2 -> 74.76 | AA2: =SUMIFS('Recipe Ingredients'!$O$2:$O$2500,'Recipe Ingredients'!$A$2:$A$2500,A2)/R2 -> 344.88 | AB2: =SUMIFS('Recipe Ingredients'!$P$2:$P$2500,'Recipe Ingredients'!$A$2:$A$2500,A2)/R2 -> 1.5156 | AC2: =SUMIFS('Recipe Ingredients'!$Q$2:$Q$2500,'Recipe Ingredients'!$A$2:$A$2500,A2)/R2 -> 0.21792 | AD2: =SUMIFS('Recipe Ingredients'!$R$2:$R$2500,'Recipe Ingredients'!$A$2:$A$2500,A2)/R2 -> 22.02 | AE2: =SUMIFS('Recipe Ingredients'!$S$2:$S$2500,'Recipe Ingredients'!$A$2:$A$2500,A2)/R2 -> 0.5568 | AF2: =IFERROR(V2/'Start Here'!$C$10,0) -> 0.1824 | AG2: =IFERROR(W2/'Start Here'!$C$11,0) -> 0.8319 | AH2: =IFERROR(X2/'Start Here'!$C$12,0) -> 0.1278 | AI2: =IFERROR(Y2/'Start Here'!$C$13,0) -> 0.09576 | AJ2: =IFERROR(Z2/'Start Here'!$C$14,0) -> 0.3738 | AK2: =IFERROR(AA2/'Start Here'!$C$15,0) -> 0.17244 | AL2: =IFERROR(AB2/'Start Here'!$C$16,0) -> 0.1263 | AM2: =IFERROR(AC2/'Start Here'!$C$17,0) -> 0.15565714 | AN2: =IFERROR(AD2/'Start Here'!$C$18,0) -> 0.05872 | AO2: =IFERROR(AE2/'Start Here'!$C$19,0) -> 0.039771429 | AP2: =IFERROR(SUBSTITUTE(INDEX($AF$1:$AO$1,MATCH(MAX(AF2:AO2),AF2:AO2,0))," % daily",""),"") -> Vitamin C | AQ2: =IF(MAX(AF2:AO2)>=0.15,"Best for better "&IF(LEFT(AP2,7)="Vitamin","vitamin "&MID(AP2,9,3),LOWER(AP2))&" intake: one serving gives about "&TEXT(MAX(AF2:AO2),"0%")&" of your daily "&IF(LEFT(AP2,7)="Vitamin","vitamin "&MID(AP2,9,3),LOWER(AP2))&" from the produce alone.","A lighter plate: top nutrient is "&IF(LEFT(AP2,7)="Vitamin","vitamin "&MID(AP2,9,3),LOWER(AP2))&" at about "&TEXT(MAX(AF2:AO2),"0%")&" of a day.") -> Best for better vitamin C intake: one serving gives about 83% of your daily vitamin C from the produce alone. | AR2: =IF(LEN(IF(AND(AF2>=0.25,"Fibre"<>AP2),"Fibre ("&TEXT(AF2,"0%")&")|","")&IF(AND(AG2>=0.25,"Vitamin C"<>AP2),"Vitamin C ("&TEXT(AG2,"0%")&")|","")&IF(AND(AH2>=0.25,"Vitamin A"<>AP2),"Vitamin A ("&TEXT(AH2,"0%")&")|","")&IF(AND(AI2>=0.25,"Vitamin K"<>AP2),"Vitamin K ("&TEXT(AI2,"0%")&")|","")&IF(AND(AJ2>=0.25,"Folate"<>AP2),"Folate ("&TEXT(AJ2,"0%")&")|","")&IF(AND(AK2>=0.25,"Potassium"<>AP2),"Potassium ("&TEXT(AK2,"0%")&")|","")&IF(AND(AL2>=0.25,"Vitamin E"<>AP2),"Vitamin E ("&TEXT(AL2,"0%")&")|","")&IF(AND(AM2>=0.25,"Vitamin B6"<>AP2),"Vitamin B6 ("&TEXT(AM2,"0%")&")|","")&IF(AND(AN2>=0.25,"Magnesium"<>AP2),"Magnesium ("&TEXT(AN2,"0%")&")|","")&IF(AND(AO2>=0.25,"Iron"<>AP2),"Iron ("&TEXT(AO2,"0%")&")|",""))=0,"",SUBSTITUTE(LEFT(IF(AND(AF2>=0.25,"Fibre"<>AP2),"Fibre ("&TEXT(AF2,"0%")&")|","")&IF(AND(AG2>=0.25,"Vitamin C"<>AP2),"Vitamin C ("&TEXT(AG2,"0%")&")|","")&IF(AND(AH2>=0.25,"Vitamin A"<>AP2),"Vitamin A ("&TEXT(AH2,"0%")&")|","")&IF(AND(AI2>=0.25,"Vitamin K"<>AP2),"Vitamin K ("&TEXT(AI2,"0%")&")|","")&IF(AND(AJ2>=0.25,"Folate"<>AP2),"Folate ("&TEXT(AJ2,"0%")&")|","")&IF(AND(AK2>=0.25,"Potassium"<>AP2),"Potassium ("&TEXT(AK2,"0%")&")|","")&IF(AND(AL2>=0.25,"Vitamin E"<>AP2),"Vitamin E ("&TEXT(AL2,"0%")&")|","")&IF(AND(AM2>=0.25,"Vitamin B6"<>AP2),"Vitamin B6 ("&TEXT(AM2,"0%")&")|","")&IF(AND(AN2>=0.25,"Magnesium"<>AP2),"Magnesium ("&TEXT(AN2,"0%")&")|","")&IF(AND(AO2>=0.25,"Iron"<>AP2),"Iron ("&TEXT(AO2,"0%")&")|",""),LEN(IF(AND(AF2>=0.25,"Fibre"<>AP2),"Fibre ("&TEXT(AF2,"0%")&")|","")&IF(AND(AG2>=0.25,"Vitamin C"<>AP2),"Vitamin C ("&TEXT(AG2,"0%")&")|","")&IF(AND(AH2>=0.25,"Vitamin A"<>AP2),"Vitamin A ("&TEXT(AH2,"0%")&")|","")&IF(AND(AI2>=0.25,"Vitamin K"<>AP2),"Vitamin K ("&TEXT(AI2,"0%")&")|","")&IF(AND(AJ2>=0.25,"Folate"<>AP2),"Folate ("&TEXT(AJ2,"0%")&")|","")&IF(AND(AK2>=0.25,"Potassium"<>AP2),"Potassium ("&TEXT(AK2,"0%")&")|","")&IF(AND(AL2>=0.25,"Vitamin E"<>AP2),"Vitamin E ("&TEXT(AL2,"0%")&")|","")&IF(AND(AM2>=0.25,"Vitamin B6"<>AP2),"Vitamin B6 ("&TEXT(AM2,"0%")&")|","")&IF(AND(AN2>=0.25,"Magnesium"<>AP2),"Magnesium ("&TEXT(AN2,"0%")&")|","")&IF(AND(AO2>=0.25,"Iron"<>AP2),"Iron ("&TEXT(AO2,"0%")&")|",""))-1),"|",", ")) -> Folate (37%) | AS2: Mango brings vitamin A (as beta-carotene), vitamin C and folate. Passion fruit is high in fibre and vitamin A and C. | AT2: Mango, Passion fruit | AU2: =COUNTIFS('Recipe Ingredients'!$A$2:$A$2500,A2,'Recipe Ingredients'!$G$2:$G$2500,"Basket") -> 2 | AV2: =COUNTIFS('Recipe Ingredients'!$A$2:$A$2500,A2,'Recipe Ingredients'!$G$2:$G$2500,"Protein")+COUNTIFS('Recipe Ingredients'!$A$2:$A$2500,A2,'Recipe Ingredients'!$G$2:$G$2500,"Pantry") -> 5 | AW2: =IFERROR(AU2/(AU2+AV2),0) -> 0.28571429 | AX2: =IF(AW2>='Start Here'!$C$6,"Yes","No") -> No | AY2: Mango (Feb-May, Aug-Sep); Passion fruit (Jan-Mar, May-Jun, Aug-Nov) | AZ2: 1. Stir oats, milk, yoghurt and chia together in two jars. 2. Cover and refrigerate overnight. 3. In the morning, top with diced mango and passion fruit pulp. 4. Drizzle with honey if you like. | BA2: Make 3 days at once for a week of grab-and-go breakfasts. | BB2: Draft
A3: R016 | B3: Pawpaw Boats with Yoghurt & Groundnut Crunch | C3: Breakfast Plates | D3: Fruit plate | E3: Breakfast | F3: Papaya boats (Hawaii / Bali brunch spots) | G3: Caroline's Cooking | H3: https://www.carolinescooking.com/papaya-boat/ | I3: https://www.carolinescooking.com/wp-content/uploads/2024/04/papaya-boat-featured-pic-sq.jpg | J3: Crushed groundnuts and pineapple replace imported berries. | K3: You add: yoghurt, honey. Groundnuts from Basket. | L3: Weight management, Wellness | M3: Vegetarian | N3: 5 | O3: 0 | P3: =N3+O3 -> 5 | Q3: =IF(O3=0,"No-cook",IF(P3<=25,"Quick","Standard")) -> No-cook | R3: 2 | S3: 320 | T3: 12 | U3: =SUMIFS('Recipe Ingredients'!$I$2:$I$2500,'Recipe Ingredients'!$A$2:$A$2500,A3)/R3 -> 219.5 | V3: =SUMIFS('Recipe Ingredients'!$J$2:$J$2500,'Recipe Ingredients'!$A$2:$A$2500,A3)/R3 -> 4.487 | W3: =SUMIFS('Recipe Ingredients'!$K$2:$K$2500,'Recipe Ingredients'!$A$2:$A$2500,A3)/R3 -> 113.084 | X3: =SUMIFS('Recipe Ingredients'!$L$2:$L$2500,'Recipe Ingredients'!$A$2:$A$2500,A3)/R3 -> 66.525 | Y3: =SUMIFS('Recipe Ingredients'!$M$2:$M$2500,'Recipe Ingredients'!$A$2:$A$2500,A3)/R3 -> 4.063 | Z3: =SUMIFS('Recipe Ingredients'!$N$2:$N$2500,'Recipe Ingredients'!$A$2:$A$2500,A3)/R3 -> 78.935 | AA3: =SUMIFS('Recipe Ingredients'!$O$2:$O$2500,'Recipe Ingredients'!$A$2:$A$2500,A3)/R3 -> 381.985 | AB3: =SUMIFS('Recipe Ingredients'!$P$2:$P$2500,'Recipe Ingredients'!$A$2:$A$2500,A3)/R3 -> 1.11915 | AC3: =SUMIFS('Recipe Ingredients'!$Q$2:$Q$2500,'Recipe Ingredients'!$A$2:$A$2500,A3)/R3 -> 0.138675 | AD3: =SUMIFS('Recipe Ingredients'!$R$2:$R$2500,'Recipe Ingredients'!$A$2:$A$2500,A3)/R3 -> 48.405 | AE3: =SUMIFS('Recipe Ingredients'!$S$2:$S$2500,'Recipe Ingredients'!$A$2:$A$2500,A3)/R3 -> 1.00715 | AF3: =IFERROR(V3/'Start Here'!$C$10,0) -> 0.17948 | AG3: =IFERROR(W3/'Start Here'!$C$11,0) -> 1.41355 | AH3: =IFERROR(X3/'Start Here'!$C$12,0) -> 0.08315625 | AI3: =IFERROR(Y3/'Start Here'!$C$13,0) -> 0.054173333 | AJ3: =IFERROR(Z3/'Start Here'!$C$14,0) -> 0.394675 | AK3: =IFERROR(AA3/'Start Here'!$C$15,0) -> 0.1909925 | AL3: =IFERROR(AB3/'Start Here'!$C$16,0) -> 0.0932625 | AM3: =IFERROR(AC3/'Start Here'!$C$17,0) -> 0.099053571 | AN3: =IFERROR(AD3/'Start Here'!$C$18,0) -> 0.12908 | AO3: =IFERROR(AE3/'Start Here'!$C$19,0) -> 0.071939286 | AP3: =IFERROR(SUBSTITUTE(INDEX($AF$1:$AO$1,MATCH(MAX(AF3:AO3),AF3:AO3,0))," % daily",""),"") -> Vitamin C | AQ3: =IF(MAX(AF3:AO3)>=0.15,"Best for better "&IF(LEFT(AP3,7)="Vitamin","vitamin "&MID(AP3,9,3),LOWER(AP3))&" intake: one serving gives about "&TEXT(MAX(AF3:AO3),"0%")&" of your daily "&IF(LEFT(AP3,7)="Vitamin","vitamin "&MID(AP3,9,3),LOWER(AP3))&" from the produce alone.","A lighter plate: top nutrient is "&IF(LEFT(AP3,7)="Vitamin","vitamin "&MID(AP3,9,3),LOWER(AP3))&" at about "&TEXT(MAX(AF3:AO3),"0%")&" of a day.") -> Best for better vitamin C intake: one serving gives about 141% of your daily vitamin C from the produce alone. | AR3: =IF(LEN(IF(AND(AF3>=0.25,"Fibre"<>AP3),"Fibre ("&TEXT(AF3,"0%")&")|","")&IF(AND(AG3>=0.25,"Vitamin C"<>AP3),"Vitamin C ("&TEXT(AG3,"0%")&")|","")&IF(AND(AH3>=0.25,"Vitamin A"<>AP3),"Vitamin A ("&TEXT(AH3,"0%")&")|","")&IF(AND(AI3>=0.25,"Vitamin K"<>AP3),"Vitamin K ("&TEXT(AI3,"0%")&")|","")&IF(AND(AJ3>=0.25,"Folate"<>AP3),"Folate ("&TEXT(AJ3,"0%")&")|","")&IF(AND(AK3>=0.25,"Potassium"<>AP3),"Potassium ("&TEXT(AK3,"0%")&")|","")&IF(AND(AL3>=0.25,"Vitamin E"<>AP3),"Vitamin E ("&TEXT(AL3,"0%")&")|","")&IF(AND(AM3>=0.25,"Vitamin B6"<>AP3),"Vitamin B6 ("&TEXT(AM3,"0%")&")|","")&IF(AND(AN3>=0.25,"Magnesium"<>AP3),"Magnesium ("&TEXT(AN3,"0%")&")|","")&IF(AND(AO3>=0.25,"Iron"<>AP3),"Iron ("&TEXT(AO3,"0%")&")|",""))=0,"",SUBSTITUTE(LEFT(IF(AND(AF3>=0.25,"Fibre"<>AP3),"Fibre ("&TEXT(AF3,"0%")&")|","")&IF(AND(AG3>=0.25,"Vitamin C"<>AP3),"Vitamin C ("&TEXT(AG3,"0%")&")|","")&IF(AND(AH3>=0.25,"Vitamin A"<>AP3),"Vitamin A ("&TEXT(AH3,"0%")&")|","")&IF(AND(AI3>=0.25,"Vitamin K"<>AP3),"Vitamin K ("&TEXT(AI3,"0%")&")|","")&IF(AND(AJ3>=0.25,"Folate"<>AP3),"Folate ("&TEXT(AJ3,"0%")&")|","")&IF(AND(AK3>=0.25,"Potassium"<>AP3),"Potassium ("&TEXT(AK3,"0%")&")|","")&IF(AND(AL3>=0.25,"Vitamin E"<>AP3),"Vitamin E ("&TEXT(AL3,"0%")&")|","")&IF(AND(AM3>=0.25,"Vitamin B6"<>AP3),"Vitamin B6 ("&TEXT(AM3,"0%")&")|","")&IF(AND(AN3>=0.25,"Magnesium"<>AP3),"Magnesium ("&TEXT(AN3,"0%")&")|","")&IF(AND(AO3>=0.25,"Iron"<>AP3),"Iron ("&TEXT(AO3,"0%")&")|",""),LEN(IF(AND(AF3>=0.25,"Fibre"<>AP3),"Fibre ("&TEXT(AF3,"0%")&")|","")&IF(AND(AG3>=0.25,"Vitamin C"<>AP3),"Vitamin C ("&TEXT(AG3,"0%")&")|","")&IF(AND(AH3>=0.25,"Vitamin A"<>AP3),"Vitamin A ("&TEXT(AH3,"0%")&")|","")&IF(AND(AI3>=0.25,"Vitamin K"<>AP3),"Vitamin K ("&TEXT(AI3,"0%")&")|","")&IF(AND(AJ3>=0.25,"Folate"<>AP3),"Folate ("&TEXT(AJ3,"0%")&")|","")&IF(AND(AK3>=0.25,"Potassium"<>AP3),"Potassium ("&TEXT(AK3,"0%")&")|","")&IF(AND(AL3>=0.25,"Vitamin E"<>AP3),"Vitamin E ("&TEXT(AL3,"0%")&")|","")&IF(AND(AM3>=0.25,"Vitamin B6"<>AP3),"Vitamin B6 ("&TEXT(AM3,"0%")&")|","")&IF(AND(AN3>=0.25,"Magnesium"<>AP3),"Magnesium ("&TEXT(AN3,"0%")&")|","")&IF(AND(AO3>=0.25,"Iron"<>AP3),"Iron ("&TEXT(AO3,"0%")&")|",""))-1),"|",", ")) -> Folate (39%) | AS3: Pawpaw is one of the richest local sources of vitamin C and beta-carotene (vitamin A), with papain for digestion. Pineapple is rich in vitamin C and manganese, and bromelain that helps digest protein. | AT3: Pawpaw, Pineapple, Lime, Groundnut | AU3: =COUNTIFS('Recipe Ingredients'!$A$2:$A$2500,A3,'Recipe Ingredients'!$G$2:$G$2500,"Basket") -> 4 | AV3: =COUNTIFS('Recipe Ingredients'!$A$2:$A$2500,A3,'Recipe Ingredients'!$G$2:$G$2500,"Protein")+COUNTIFS('Recipe Ingredients'!$A$2:$A$2500,A3,'Recipe Ingredients'!$G$2:$G$2500,"Pantry") -> 3 | AW3: =IFERROR(AU3/(AU3+AV3),0) -> 0.57142857 | AX3: =IF(AW3>='Start Here'!$C$6,"Yes","No") -> No | AY3: Year-round | AZ3: 1. Halve the pawpaw lengthways and scoop out the seeds. 2. Fill each half with yoghurt. 3. Top with granola, pineapple and crushed groundnuts. 4. Finish with lime zest and a drizzle of honey. | BB3: Draft
A4: R017 | B4: Banana Oat Pancakes with Pineapple Compote | C4: Breakfast Plates | D4: Pancakes | E4: Breakfast | F4: Three-ingredient banana pancakes (US fitness) | G4: BBC Good Food | H4: https://www.bbcgoodfood.com/recipes/banana-pancakes | I4: https://images.immediate.co.uk/production/volatile/sites/30/2020/08/banana-pancakes-6cfd286.jpg?resize=440%2C230 | J4: Warm pineapple compote stands in for maple syrup and berries. | K4: You add: eggs, oats, a little oil. Honey or yoghurt on top. | L4: Training | M4: Vegetarian | N4: 10 | O4: 15 | P4: =N4+O4 -> 25 | Q4: =IF(O4=0,"No-cook",IF(P4<=25,"Quick","Standard")) -> Quick | R4: 2 | S4: 360 | T4: 15 | U4: =SUMIFS('Recipe Ingredients'!$I$2:$I$2500,'Recipe Ingredients'!$A$2:$A$2500,A4)/R4 -> 217.5 | V4: =SUMIFS('Recipe Ingredients'!$J$2:$J$2500,'Recipe Ingredients'!$A$2:$A$2500,A4)/R4 -> 4.699 | W4: =SUMIFS('Recipe Ingredients'!$K$2:$K$2500,'Recipe Ingredients'!$A$2:$A$2500,A4)/R4 -> 54.648 | X4: =SUMIFS('Recipe Ingredients'!$L$2:$L$2500,'Recipe Ingredients'!$A$2:$A$2500,A4)/R4 -> 6.355 | Y4: =SUMIFS('Recipe Ingredients'!$M$2:$M$2500,'Recipe Ingredients'!$A$2:$A$2500,A4)/R4 -> 1.2695 | Z4: =SUMIFS('Recipe Ingredients'!$N$2:$N$2500,'Recipe Ingredients'!$A$2:$A$2500,A4)/R4 -> 39.81 | AA4: =SUMIFS('Recipe Ingredients'!$O$2:$O$2500,'Recipe Ingredients'!$A$2:$A$2500,A4)/R4 -> 529.705 | AB4: =SUMIFS('Recipe Ingredients'!$P$2:$P$2500,'Recipe Ingredients'!$A$2:$A$2500,A4)/R4 -> 0.1719 | AC4: =SUMIFS('Recipe Ingredients'!$Q$2:$Q$2500,'Recipe Ingredients'!$A$2:$A$2500,A4)/R4 -> 0.53277 | AD4: =SUMIFS('Recipe Ingredients'!$R$2:$R$2500,'Recipe Ingredients'!$A$2:$A$2500,A4)/R4 -> 42.78 | AE4: =SUMIFS('Recipe Ingredients'!$S$2:$S$2500,'Recipe Ingredients'!$A$2:$A$2500,A4)/R4 -> 0.64805 | AF4: =IFERROR(V4/'Start Here'!$C$10,0) -> 0.18796 | AG4: =IFERROR(W4/'Start Here'!$C$11,0) -> 0.6831 | AH4: =IFERROR(X4/'Start Here'!$C$12,0) -> 0.00794375 | AI4: =IFERROR(Y4/'Start Here'!$C$13,0) -> 0.016926667 | AJ4: =IFERROR(Z4/'Start Here'!$C$14,0) -> 0.19905 | AK4: =IFERROR(AA4/'Start Here'!$C$15,0) -> 0.2648525 | AL4: =IFERROR(AB4/'Start Here'!$C$16,0) -> 0.014325 | AM4: =IFERROR(AC4/'Start Here'!$C$17,0) -> 0.38055 | AN4: =IFERROR(AD4/'Start Here'!$C$18,0) -> 0.11408 | AO4: =IFERROR(AE4/'Start Here'!$C$19,0) -> 0.046289286 | AP4: =IFERROR(SUBSTITUTE(INDEX($AF$1:$AO$1,MATCH(MAX(AF4:AO4),AF4:AO4,0))," % daily",""),"") -> Vitamin C | AQ4: =IF(MAX(AF4:AO4)>=0.15,"Best for better "&IF(LEFT(AP4,7)="Vitamin","vitamin "&MID(AP4,9,3),LOWER(AP4))&" intake: one serving gives about "&TEXT(MAX(AF4:AO4),"0%")&" of your daily "&IF(LEFT(AP4,7)="Vitamin","vitamin "&MID(AP4,9,3),LOWER(AP4))&" from the produce alone.","A lighter plate: top nutrient is "&IF(LEFT(AP4,7)="Vitamin","vitamin "&MID(AP4,9,3),LOWER(AP4))&" at about "&TEXT(MAX(AF4:AO4),"0%")&" of a day.") -> Best for better vitamin C intake: one serving gives about 68% of your daily vitamin C from the produce alone. | AR4: =IF(LEN(IF(AND(AF4>=0.25,"Fibre"<>AP4),"Fibre ("&TEXT(AF4,"0%")&")|","")&IF(AND(AG4>=0.25,"Vitamin C"<>AP4),"Vitamin C ("&TEXT(AG4,"0%")&")|","")&IF(AND(AH4>=0.25,"Vitamin A"<>AP4),"Vitamin A ("&TEXT(AH4,"0%")&")|","")&IF(AND(AI4>=0.25,"Vitamin K"<>AP4),"Vitamin K ("&TEXT(AI4,"0%")&")|","")&IF(AND(AJ4>=0.25,"Folate"<>AP4),"Folate ("&TEXT(AJ4,"0%")&")|","")&IF(AND(AK4>=0.25,"Potassium"<>AP4),"Potassium ("&TEXT(AK4,"0%")&")|","")&IF(AND(AL4>=0.25,"Vitamin E"<>AP4),"Vitamin E ("&TEXT(AL4,"0%")&")|","")&IF(AND(AM4>=0.25,"Vitamin B6"<>AP4),"Vitamin B6 ("&TEXT(AM4,"0%")&")|","")&IF(AND(AN4>=0.25,"Magnesium"<>AP4),"Magnesium ("&TEXT(AN4,"0%")&")|","")&IF(AND(AO4>=0.25,"Iron"<>AP4),"Iron ("&TEXT(AO4,"0%")&")|",""))=0,"",SUBSTITUTE(LEFT(IF(AND(AF4>=0.25,"Fibre"<>AP4),"Fibre ("&TEXT(AF4,"0%")&")|","")&IF(AND(AG4>=0.25,"Vitamin C"<>AP4),"Vitamin C ("&TEXT(AG4,"0%")&")|","")&IF(AND(AH4>=0.25,"Vitamin A"<>AP4),"Vitamin A ("&TEXT(AH4,"0%")&")|","")&IF(AND(AI4>=0.25,"Vitamin K"<>AP4),"Vitamin K ("&TEXT(AI4,"0%")&")|","")&IF(AND(AJ4>=0.25,"Folate"<>AP4),"Folate ("&TEXT(AJ4,"0%")&")|","")&IF(AND(AK4>=0.25,"Potassium"<>AP4),"Potassium ("&TEXT(AK4,"0%")&")|","")&IF(AND(AL4>=0.25,"Vitamin E"<>AP4),"Vitamin E ("&TEXT(AL4,"0%")&")|","")&IF(AND(AM4>=0.25,"Vitamin B6"<>AP4),"Vitamin B6 ("&TEXT(AM4,"0%")&")|","")&IF(AND(AN4>=0.25,"Magnesium"<>AP4),"Magnesium ("&TEXT(AN4,"0%")&")|","")&IF(AND(AO4>=0.25,"Iron"<>AP4),"Iron ("&TEXT(AO4,"0%")&")|",""),LEN(IF(AND(AF4>=0.25,"Fibre"<>AP4),"Fibre ("&TEXT(AF4,"0%")&")|","")&IF(AND(AG4>=0.25,"Vitamin C"<>AP4),"Vitamin C ("&TEXT(AG4,"0%")&")|","")&IF(AND(AH4>=0.25,"Vitamin A"<>AP4),"Vitamin A ("&TEXT(AH4,"0%")&")|","")&IF(AND(AI4>=0.25,"Vitamin K"<>AP4),"Vitamin K ("&TEXT(AI4,"0%")&")|","")&IF(AND(AJ4>=0.25,"Folate"<>AP4),"Folate ("&TEXT(AJ4,"0%")&")|","")&IF(AND(AK4>=0.25,"Potassium"<>AP4),"Potassium ("&TEXT(AK4,"0%")&")|","")&IF(AND(AL4>=0.25,"Vitamin E"<>AP4),"Vitamin E ("&TEXT(AL4,"0%")&")|","")&IF(AND(AM4>=0.25,"Vitamin B6"<>AP4),"Vitamin B6 ("&TEXT(AM4,"0%")&")|","")&IF(AND(AN4>=0.25,"Magnesium"<>AP4),"Magnesium ("&TEXT(AN4,"0%")&")|","")&IF(AND(AO4>=0.25,"Iron"<>AP4),"Iron ("&TEXT(AO4,"0%")&")|",""))-1),"|",", ")) -> Potassium (26%), Vitamin B6 (38%) | AS4: Banana is the easy potassium and vitamin B6 source. Pineapple is rich in vitamin C and manganese, and bromelain that helps digest protein. | AT4: Banana, Pineapple, Lime | AU4: =COUNTIFS('Recipe Ingredients'!$A$2:$A$2500,A4,'Recipe Ingredients'!$G$2:$G$2500,"Basket") -> 3 | AV4: =COUNTIFS('Recipe Ingredients'!$A$2:$A$2500,A4,'Recipe Ingredients'!$G$2:$G$2500,"Protein")+COUNTIFS('Recipe Ingredients'!$A$2:$A$2500,A4,'Recipe Ingredients'!$G$2:$G$2500,"Pantry") -> 3 | AW4: =IFERROR(AU4/(AU4+AV4),0) -> 0.5 | AX4: =IF(AW4>='Start Here'!$C$6,"Yes","No") -> No | AY4: Year-round | AZ4: 1. Blend bananas, eggs, oats and cinnamon into a thick batter. 2. Cook small pancakes in a lightly oiled pan, 2 minutes a side. 3. Simmer pineapple with lime juice for 5 minutes until jammy. 4. Stack the pancakes and spoon the compote over. | BB4: Draft
A5: R018 | B5: Shakshuka with Tatashe & Efo | C5: Breakfast Plates | D5: Egg sauce | E5: Brunch | F5: Shakshuka (North Africa / Middle East) | G5: BBC Good Food | H5: https://www.bbcgoodfood.com/recipes/shakshuka | I5: https://images.immediate.co.uk/production/volatile/sites/30/2020/08/recipe-image-legacy-id-12141_11-fd804a3.jpg?resize=440%2C230 | J5: The sauce is basically a lighter obe ata. Greens folded in at the end. | K5: Agege bread, toast or boiled yam. You add: eggs, oil. | L5: Training, Weight management | M5: Vegetarian | N5: 10 | O5: 20 | P5: =N5+O5 -> 30 | Q5: =IF(O5=0,"No-cook",IF(P5<=25,"Quick","Standard")) -> Standard | R5: 2 | S5: 330 | T5: 17 | U5: =SUMIFS('Recipe Ingredients'!$I$2:$I$2500,'Recipe Ingredients'!$A$2:$A$2500,A5)/R5 -> 317.5 | V5: =SUMIFS('Recipe Ingredients'!$J$2:$J$2500,'Recipe Ingredients'!$A$2:$A$2500,A5)/R5 -> 5.3025 | W5: =SUMIFS('Recipe Ingredients'!$K$2:$K$2500,'Recipe Ingredients'!$A$2:$A$2500,A5)/R5 -> 183.6115 | X5: =SUMIFS('Recipe Ingredients'!$L$2:$L$2500,'Recipe Ingredients'!$A$2:$A$2500,A5)/R5 -> 260.55 | Y5: =SUMIFS('Recipe Ingredients'!$M$2:$M$2500,'Recipe Ingredients'!$A$2:$A$2500,A5)/R5 -> 175.848 | Z5: =SUMIFS('Recipe Ingredients'!$N$2:$N$2500,'Recipe Ingredients'!$A$2:$A$2500,A5)/R5 -> 96.355 | AA5: =SUMIFS('Recipe Ingredients'!$O$2:$O$2500,'Recipe Ingredients'!$A$2:$A$2500,A5)/R5 -> 730.89 | AB5: =SUMIFS('Recipe Ingredients'!$P$2:$P$2500,'Recipe Ingredients'!$A$2:$A$2500,A5)/R5 -> 2.58045 | AC5: =SUMIFS('Recipe Ingredients'!$Q$2:$Q$2500,'Recipe Ingredients'!$A$2:$A$2500,A5)/R5 -> 0.58807 | AD5: =SUMIFS('Recipe Ingredients'!$R$2:$R$2500,'Recipe Ingredients'!$A$2:$A$2500,A5)/R5 -> 42.445 | AE5: =SUMIFS('Recipe Ingredients'!$S$2:$S$2500,'Recipe Ingredients'!$A$2:$A$2500,A5)/R5 -> 1.36355 | AF5: =IFERROR(V5/'Start Here'!$C$10,0) -> 0.2121 | AG5: =IFERROR(W5/'Start Here'!$C$11,0) -> 2.2951438 | AH5: =IFERROR(X5/'Start Here'!$C$12,0) -> 0.3256875 | AI5: =IFERROR(Y5/'Start Here'!$C$13,0) -> 2.34464 | AJ5: =IFERROR(Z5/'Start Here'!$C$14,0) -> 0.481775 | AK5: =IFERROR(AA5/'Start Here'!$C$15,0) -> 0.365445 | AL5: =IFERROR(AB5/'Start Here'!$C$16,0) -> 0.2150375 | AM5: =IFERROR(AC5/'Start Here'!$C$17,0) -> 0.42005 | AN5: =IFERROR(AD5/'Start Here'!$C$18,0) -> 0.11318667 | AO5: =IFERROR(AE5/'Start Here'!$C$19,0) -> 0.097396429 | AP5: =IFERROR(SUBSTITUTE(INDEX($AF$1:$AO$1,MATCH(MAX(AF5:AO5),AF5:AO5,0))," % daily",""),"") -> Vitamin K | AQ5: =IF(MAX(AF5:AO5)>=0.15,"Best for better "&IF(LEFT(AP5,7)="Vitamin","vitamin "&MID(AP5,9,3),LOWER(AP5))&" intake: one serving gives about "&TEXT(MAX(AF5:AO5),"0%")&" of your daily "&IF(LEFT(AP5,7)="Vitamin","vitamin "&MID(AP5,9,3),LOWER(AP5))&" from the produce alone.","A lighter plate: top nutrient is "&IF(LEFT(AP5,7)="Vitamin","vitamin "&MID(AP5,9,3),LOWER(AP5))&" at about "&TEXT(MAX(AF5:AO5),"0%")&" of a day.") -> Best for better vitamin K intake: one serving gives about 234% of your daily vitamin K from the produce alone. | AR5: =IF(LEN(IF(AND(AF5>=0.25,"Fibre"<>AP5),"Fibre ("&TEXT(AF5,"0%")&")|","")&IF(AND(AG5>=0.25,"Vitamin C"<>AP5),"Vitamin C ("&TEXT(AG5,"0%")&")|","")&IF(AND(AH5>=0.25,"Vitamin A"<>AP5),"Vitamin A ("&TEXT(AH5,"0%")&")|","")&IF(AND(AI5>=0.25,"Vitamin K"<>AP5),"Vitamin K ("&TEXT(AI5,"0%")&")|","")&IF(AND(AJ5>=0.25,"Folate"<>AP5),"Folate ("&TEXT(AJ5,"0%")&")|","")&IF(AND(AK5>=0.25,"Potassium"<>AP5),"Potassium ("&TEXT(AK5,"0%")&")|","")&IF(AND(AL5>=0.25,"Vitamin E"<>AP5),"Vitamin E ("&TEXT(AL5,"0%")&")|","")&IF(AND(AM5>=0.25,"Vitamin B6"<>AP5),"Vitamin B6 ("&TEXT(AM5,"0%")&")|","")&IF(AND(AN5>=0.25,"Magnesium"<>AP5),"Magnesium ("&TEXT(AN5,"0%")&")|","")&IF(AND(AO5>=0.25,"Iron"<>AP5),"Iron ("&TEXT(AO5,"0%")&")|",""))=0,"",SUBSTITUTE(LEFT(IF(AND(AF5>=0.25,"Fibre"<>AP5),"Fibre ("&TEXT(AF5,"0%")&")|","")&IF(AND(AG5>=0.25,"Vitamin C"<>AP5),"Vitamin C ("&TEXT(AG5,"0%")&")|","")&IF(AND(AH5>=0.25,"Vitamin A"<>AP5),"Vitamin A ("&TEXT(AH5,"0%")&")|","")&IF(AND(AI5>=0.25,"Vitamin K"<>AP5),"Vitamin K ("&TEXT(AI5,"0%")&")|","")&IF(AND(AJ5>=0.25,"Folate"<>AP5),"Folate ("&TEXT(AJ5,"0%")&")|","")&IF(AND(AK5>=0.25,"Potassium"<>AP5),"Potassium ("&TEXT(AK5,"0%")&")|","")&IF(AND(AL5>=0.25,"Vitamin E"<>AP5),"Vitamin E ("&TEXT(AL5,"0%")&")|","")&IF(AND(AM5>=0.25,"Vitamin B6"<>AP5),"Vitamin B6 ("&TEXT(AM5,"0%")&")|","")&IF(AND(AN5>=0.25,"Magnesium"<>AP5),"Magnesium ("&TEXT(AN5,"0%")&")|","")&IF(AND(AO5>=0.25,"Iron"<>AP5),"Iron ("&TEXT(AO5,"0%")&")|",""),LEN(IF(AND(AF5>=0.25,"Fibre"<>AP5),"Fibre ("&TEXT(AF5,"0%")&")|","")&IF(AND(AG5>=0.25,"Vitamin C"<>AP5),"Vitamin C ("&TEXT(AG5,"0%")&")|","")&IF(AND(AH5>=0.25,"Vitamin A"<>AP5),"Vitamin A ("&TEXT(AH5,"0%")&")|","")&IF(AND(AI5>=0.25,"Vitamin K"<>AP5),"Vitamin K ("&TEXT(AI5,"0%")&")|","")&IF(AND(AJ5>=0.25,"Folate"<>AP5),"Folate ("&TEXT(AJ5,"0%")&")|","")&IF(AND(AK5>=0.25,"Potassium"<>AP5),"Potassium ("&TEXT(AK5,"0%")&")|","")&IF(AND(AL5>=0.25,"Vitamin E"<>AP5),"Vitamin E ("&TEXT(AL5,"0%")&")|","")&IF(AND(AM5>=0.25,"Vitamin B6"<>AP5),"Vitamin B6 ("&TEXT(AM5,"0%")&")|","")&IF(AND(AN5>=0.25,"Magnesium"<>AP5),"Magnesium ("&TEXT(AN5,"0%")&")|","")&IF(AND(AO5>=0.25,"Iron"<>AP5),"Iron ("&TEXT(AO5,"0%")&")|",""))-1),"|",", ")) -> Vitamin C (230%), Vitamin A (33%), Folate (48%), Potassium (37%), Vitamin B6 (42%) | AS5: Tomatoes bring vitamin C and lycopene; cooking them in a little oil makes the lycopene easier to absorb. Tatashe (red bell pepper) has about twice the vitamin C of an orange by weight, plus beta-carotene. | AT5: Tomato, Red bell pepper, Scotch bonnet, Onion | AU5: =COUNTIFS('Recipe Ingredients'!$A$2:$A$2500,A5,'Recipe Ingredients'!$G$2:$G$2500,"Basket") -> 6 | AV5: =COUNTIFS('Recipe Ingredients'!$A$2:$A$2500,A5,'Recipe Ingredients'!$G$2:$G$2500,"Protein")+COUNTIFS('Recipe Ingredients'!$A$2:$A$2500,A5,'Recipe Ingredients'!$G$2:$G$2500,"Pantry") -> 3 | AW5: =IFERROR(AU5/(AU5+AV5),0) -> 0.66666667 | AX5: =IF(AW5>='Start Here'!$C$6,"Yes","No") -> No | AY5: Year-round | AZ5: 1. Soften chopped onion and garlic in oil. 2. Add chopped tomatoes, tatashe, ata rodo and cumin. Simmer 10 minutes until thick. 3. Stir in the efo tete, then make four wells and crack in the eggs. 4. Cover and cook 5 to 6 minutes until the whites set. Serve with bread. | BB5: Draft
A6: R019 | B6: Avocado Toast with Ata Rodo Salsa | C6: Breakfast Plates | D6: Toast topper | E6: Breakfast | F6: Avocado toast (Australian cafe culture) | G6: Love and Lemons | H6: https://www.loveandlemons.com/avocado-toast-recipe/ | I6: https://cdn.loveandlemons.com/wp-content/uploads/opengraph/2020/01/how-to-make-avocado-toast.jpg | J6: A fresh tomato, onion and ata rodo salsa on top instead of chilli flakes. | K6: You add: bread (sourdough, wholewheat or Agege), optional fried egg. | L6: Wellness, Weight management | M6: Vegetarian | N6: 10 | O6: 3 | P6: =N6+O6 -> 13 | Q6: =IF(O6=0,"No-cook",IF(P6<=25,"Quick","Standard")) -> Quick | R6: 2 | S6: 380 | T6: 13 | U6: =SUMIFS('Recipe Ingredients'!$I$2:$I$2500,'Recipe Ingredients'!$A$2:$A$2500,A6)/R6 -> 211 | V6: =SUMIFS('Recipe Ingredients'!$J$2:$J$2500,'Recipe Ingredients'!$A$2:$A$2500,A6)/R6 -> 8.6685 | W6: =SUMIFS('Recipe Ingredients'!$K$2:$K$2500,'Recipe Ingredients'!$A$2:$A$2500,A6)/R6 -> 30.7655 | X6: =SUMIFS('Recipe Ingredients'!$L$2:$L$2500,'Recipe Ingredients'!$A$2:$A$2500,A6)/R6 -> 34.225 | Y6: =SUMIFS('Recipe Ingredients'!$M$2:$M$2500,'Recipe Ingredients'!$A$2:$A$2500,A6)/R6 -> 26.4 | Z6: =SUMIFS('Recipe Ingredients'!$N$2:$N$2500,'Recipe Ingredients'!$A$2:$A$2500,A6)/R6 -> 96.275 | AA6: =SUMIFS('Recipe Ingredients'!$O$2:$O$2500,'Recipe Ingredients'!$A$2:$A$2500,A6)/R6 -> 692.195 | AB6: =SUMIFS('Recipe Ingredients'!$P$2:$P$2500,'Recipe Ingredients'!$A$2:$A$2500,A6)/R6 -> 2.49855 | AC6: =SUMIFS('Recipe Ingredients'!$Q$2:$Q$2500,'Recipe Ingredients'!$A$2:$A$2500,A6)/R6 -> 0.34415 | AD6: =SUMIFS('Recipe Ingredients'!$R$2:$R$2500,'Recipe Ingredients'!$A$2:$A$2500,A6)/R6 -> 39.605 | AE6: =SUMIFS('Recipe Ingredients'!$S$2:$S$2500,'Recipe Ingredients'!$A$2:$A$2500,A6)/R6 -> 0.96085 | AF6: =IFERROR(V6/'Start Here'!$C$10,0) -> 0.34674 | AG6: =IFERROR(W6/'Start Here'!$C$11,0) -> 0.38456875 | AH6: =IFERROR(X6/'Start Here'!$C$12,0) -> 0.04278125 | AI6: =IFERROR(Y6/'Start Here'!$C$13,0) -> 0.352 | AJ6: =IFERROR(Z6/'Start Here'!$C$14,0) -> 0.481375 | AK6: =IFERROR(AA6/'Start Here'!$C$15,0) -> 0.3460975 | AL6: =IFERROR(AB6/'Start Here'!$C$16,0) -> 0.2082125 | AM6: =IFERROR(AC6/'Start Here'!$C$17,0) -> 0.24582143 | AN6: =IFERROR(AD6/'Start Here'!$C$18,0) -> 0.10561333 | AO6: =IFERROR(AE6/'Start Here'!$C$19,0) -> 0.068632143 | AP6: =IFERROR(SUBSTITUTE(INDEX($AF$1:$AO$1,MATCH(MAX(AF6:AO6),AF6:AO6,0))," % daily",""),"") -> Folate | AQ6: =IF(MAX(AF6:AO6)>=0.15,"Best for better "&IF(LEFT(AP6,7)="Vitamin","vitamin "&MID(AP6,9,3),LOWER(AP6))&" intake: one serving gives about "&TEXT(MAX(AF6:AO6),"0%")&" of your daily "&IF(LEFT(AP6,7)="Vitamin","vitamin "&MID(AP6,9,3),LOWER(AP6))&" from the produce alone.","A lighter plate: top nutrient is "&IF(LEFT(AP6,7)="Vitamin","vitamin "&MID(AP6,9,3),LOWER(AP6))&" at about "&TEXT(MAX(AF6:AO6),"0%")&" of a day.") -> Best for better folate intake: one serving gives about 48% of your daily folate from the produce alone. | AR6: =IF(LEN(IF(AND(AF6>=0.25,"Fibre"<>AP6),"Fibre ("&TEXT(AF6,"0%")&")|","")&IF(AND(AG6>=0.25,"Vitamin C"<>AP6),"Vitamin C ("&TEXT(AG6,"0%")&")|","")&IF(AND(AH6>=0.25,"Vitamin A"<>AP6),"Vitamin A ("&TEXT(AH6,"0%")&")|","")&IF(AND(AI6>=0.25,"Vitamin K"<>AP6),"Vitamin K ("&TEXT(AI6,"0%")&")|","")&IF(AND(AJ6>=0.25,"Folate"<>AP6),"Folate ("&TEXT(AJ6,"0%")&")|","")&IF(AND(AK6>=0.25,"Potassium"<>AP6),"Potassium ("&TEXT(AK6,"0%")&")|","")&IF(AND(AL6>=0.25,"Vitamin E"<>AP6),"Vitamin E ("&TEXT(AL6,"0%")&")|","")&IF(AND(AM6>=0.25,"Vitamin B6"<>AP6),"Vitamin B6 ("&TEXT(AM6,"0%")&")|","")&IF(AND(AN6>=0.25,"Magnesium"<>AP6),"Magnesium ("&TEXT(AN6,"0%")&")|","")&IF(AND(AO6>=0.25,"Iron"<>AP6),"Iron ("&TEXT(AO6,"0%")&")|",""))=0,"",SUBSTITUTE(LEFT(IF(AND(AF6>=0.25,"Fibre"<>AP6),"Fibre ("&TEXT(AF6,"0%")&")|","")&IF(AND(AG6>=0.25,"Vitamin C"<>AP6),"Vitamin C ("&TEXT(AG6,"0%")&")|","")&IF(AND(AH6>=0.25,"Vitamin A"<>AP6),"Vitamin A ("&TEXT(AH6,"0%")&")|","")&IF(AND(AI6>=0.25,"Vitamin K"<>AP6),"Vitamin K ("&TEXT(AI6,"0%")&")|","")&IF(AND(AJ6>=0.25,"Folate"<>AP6),"Folate ("&TEXT(AJ6,"0%")&")|","")&IF(AND(AK6>=0.25,"Potassium"<>AP6),"Potassium ("&TEXT(AK6,"0%")&")|","")&IF(AND(AL6>=0.25,"Vitamin E"<>AP6),"Vitamin E ("&TEXT(AL6,"0%")&")|","")&IF(AND(AM6>=0.25,"Vitamin B6"<>AP6),"Vitamin B6 ("&TEXT(AM6,"0%")&")|","")&IF(AND(AN6>=0.25,"Magnesium"<>AP6),"Magnesium ("&TEXT(AN6,"0%")&")|","")&IF(AND(AO6>=0.25,"Iron"<>AP6),"Iron ("&TEXT(AO6,"0%")&")|",""),LEN(IF(AND(AF6>=0.25,"Fibre"<>AP6),"Fibre ("&TEXT(AF6,"0%")&")|","")&IF(AND(AG6>=0.25,"Vitamin C"<>AP6),"Vitamin C ("&TEXT(AG6,"0%")&")|","")&IF(AND(AH6>=0.25,"Vitamin A"<>AP6),"Vitamin A ("&TEXT(AH6,"0%")&")|","")&IF(AND(AI6>=0.25,"Vitamin K"<>AP6),"Vitamin K ("&TEXT(AI6,"0%")&")|","")&IF(AND(AJ6>=0.25,"Folate"<>AP6),"Folate ("&TEXT(AJ6,"0%")&")|","")&IF(AND(AK6>=0.25,"Potassium"<>AP6),"Potassium ("&TEXT(AK6,"0%")&")|","")&IF(AND(AL6>=0.25,"Vitamin E"<>AP6),"Vitamin E ("&TEXT(AL6,"0%")&")|","")&IF(AND(AM6>=0.25,"Vitamin B6"<>AP6),"Vitamin B6 ("&TEXT(AM6,"0%")&")|","")&IF(AND(AN6>=0.25,"Magnesium"<>AP6),"Magnesium ("&TEXT(AN6,"0%")&")|","")&IF(AND(AO6>=0.25,"Iron"<>AP6),"Iron ("&TEXT(AO6,"0%")&")|",""))-1),"|",", ")) -> Fibre (35%), Vitamin C (38%), Vitamin K (35%), Potassium (35%) | AS6: Avocado gives potassium, folate, vitamin E and heart-friendly fats that help absorb vitamins from the rest of the plate. Tomatoes bring vitamin C and lycopene; cooking them in a little oil makes the lycopene easier to absorb. | AT6: Avocado, Tomato, Onion, Scotch bonnet | AU6: =COUNTIFS('Recipe Ingredients'!$A$2:$A$2500,A6,'Recipe Ingredients'!$G$2:$G$2500,"Basket") -> 5 | AV6: =COUNTIFS('Recipe Ingredients'!$A$2:$A$2500,A6,'Recipe Ingredients'!$G$2:$G$2500,"Protein")+COUNTIFS('Recipe Ingredients'!$A$2:$A$2500,A6,'Recipe Ingredients'!$G$2:$G$2500,"Pantry") -> 2 | AW6: =IFERROR(AU6/(AU6+AV6),0) -> 0.71428571 | AX6: =IF(AW6>='Start Here'!$C$6,"Yes","No") -> No | AY6: Year-round | AZ6: 1. Toast the bread. 2. Mash avocado with half the lime juice and a pinch of salt. 3. Dice tomato, onion and ata rodo and toss with the rest of the lime. 4. Spread avocado, spoon over salsa, top with sliced boiled egg if using. | BB6: Draft
A7: R020 | B7: Sweet Potato Breakfast Hash | C7: Breakfast Plates | D7: Hash | E7: Breakfast | F7: American diner hash | G7: Budget Bytes | H7: https://www.budgetbytes.com/sweet-potato-hash/ | I7: https://www.budgetbytes.com/wp-content/uploads/2023/12/Sweet-Potato-Hash-Plated.jpg | J7: Sweet potato is cheaper locally than Irish potato and keeps you full longer. | K7: You add: eggs, oil. Optional sausage or leftover chicken. | L7: Training | M7: Vegetarian | N7: 10 | O7: 20 | P7: =N7+O7 -> 30 | Q7: =IF(O7=0,"No-cook",IF(P7<=25,"Quick","Standard")) -> Standard | R7: 2 | S7: 420 | T7: 16 | U7: =SUMIFS('Recipe Ingredients'!$I$2:$I$2500,'Recipe Ingredients'!$A$2:$A$2500,A7)/R7 -> 266 | V7: =SUMIFS('Recipe Ingredients'!$J$2:$J$2500,'Recipe Ingredients'!$A$2:$A$2500,A7)/R7 -> 6.5595 | W7: =SUMIFS('Recipe Ingredients'!$K$2:$K$2500,'Recipe Ingredients'!$A$2:$A$2500,A7)/R7 -> 90.6435 | X7: =SUMIFS('Recipe Ingredients'!$L$2:$L$2500,'Recipe Ingredients'!$A$2:$A$2500,A7)/R7 -> 1039.305 | Y7: =SUMIFS('Recipe Ingredients'!$M$2:$M$2500,'Recipe Ingredients'!$A$2:$A$2500,A7)/R7 -> 180.6005 | Z7: =SUMIFS('Recipe Ingredients'!$N$2:$N$2500,'Recipe Ingredients'!$A$2:$A$2500,A7)/R7 -> 68.82 | AA7: =SUMIFS('Recipe Ingredients'!$O$2:$O$2500,'Recipe Ingredients'!$A$2:$A$2500,A7)/R7 -> 750.185 | AB7: =SUMIFS('Recipe Ingredients'!$P$2:$P$2500,'Recipe Ingredients'!$A$2:$A$2500,A7)/R7 -> 1.33035 | AC7: =SUMIFS('Recipe Ingredients'!$Q$2:$Q$2500,'Recipe Ingredients'!$A$2:$A$2500,A7)/R7 -> 0.5423 | AD7: =SUMIFS('Recipe Ingredients'!$R$2:$R$2500,'Recipe Ingredients'!$A$2:$A$2500,A7)/R7 -> 54.34 | AE7: =SUMIFS('Recipe Ingredients'!$S$2:$S$2500,'Recipe Ingredients'!$A$2:$A$2500,A7)/R7 -> 1.60015 | AF7: =IFERROR(V7/'Start Here'!$C$10,0) -> 0.26238 | AG7: =IFERROR(W7/'Start Here'!$C$11,0) -> 1.1330438 | AH7: =IFERROR(X7/'Start Here'!$C$12,0) -> 1.2991313 | AI7: =IFERROR(Y7/'Start Here'!$C$13,0) -> 2.4080067 | AJ7: =IFERROR(Z7/'Start Here'!$C$14,0) -> 0.3441 | AK7: =IFERROR(AA7/'Start Here'!$C$15,0) -> 0.3750925 | AL7: =IFERROR(AB7/'Start Here'!$C$16,0) -> 0.1108625 | AM7: =IFERROR(AC7/'Start Here'!$C$17,0) -> 0.38735714 | AN7: =IFERROR(AD7/'Start Here'!$C$18,0) -> 0.14490667 | AO7: =IFERROR(AE7/'Start Here'!$C$19,0) -> 0.11429643 | AP7: =IFERROR(SUBSTITUTE(INDEX($AF$1:$AO$1,MATCH(MAX(AF7:AO7),AF7:AO7,0))," % daily",""),"") -> Vitamin K | AQ7: =IF(MAX(AF7:AO7)>=0.15,"Best for better "&IF(LEFT(AP7,7)="Vitamin","vitamin "&MID(AP7,9,3),LOWER(AP7))&" intake: one serving gives about "&TEXT(MAX(AF7:AO7),"0%")&" of your daily "&IF(LEFT(AP7,7)="Vitamin","vitamin "&MID(AP7,9,3),LOWER(AP7))&" from the produce alone.","A lighter plate: top nutrient is "&IF(LEFT(AP7,7)="Vitamin","vitamin "&MID(AP7,9,3),LOWER(AP7))&" at about "&TEXT(MAX(AF7:AO7),"0%")&" of a day.") -> Best for better vitamin K intake: one serving gives about 241% of your daily vitamin K from the produce alone. | AR7: =IF(LEN(IF(AND(AF7>=0.25,"Fibre"<>AP7),"Fibre ("&TEXT(AF7,"0%")&")|","")&IF(AND(AG7>=0.25,"Vitamin C"<>AP7),"Vitamin C ("&TEXT(AG7,"0%")&")|","")&IF(AND(AH7>=0.25,"Vitamin A"<>AP7),"Vitamin A ("&TEXT(AH7,"0%")&")|","")&IF(AND(AI7>=0.25,"Vitamin K"<>AP7),"Vitamin K ("&TEXT(AI7,"0%")&")|","")&IF(AND(AJ7>=0.25,"Folate"<>AP7),"Folate ("&TEXT(AJ7,"0%")&")|","")&IF(AND(AK7>=0.25,"Potassium"<>AP7),"Potassium ("&TEXT(AK7,"0%")&")|","")&IF(AND(AL7>=0.25,"Vitamin E"<>AP7),"Vitamin E ("&TEXT(AL7,"0%")&")|","")&IF(AND(AM7>=0.25,"Vitamin B6"<>AP7),"Vitamin B6 ("&TEXT(AM7,"0%")&")|","")&IF(AND(AN7>=0.25,"Magnesium"<>AP7),"Magnesium ("&TEXT(AN7,"0%")&")|","")&IF(AND(AO7>=0.25,"Iron"<>AP7),"Iron ("&TEXT(AO7,"0%")&")|",""))=0,"",SUBSTITUTE(LEFT(IF(AND(AF7>=0.25,"Fibre"<>AP7),"Fibre ("&TEXT(AF7,"0%")&")|","")&IF(AND(AG7>=0.25,"Vitamin C"<>AP7),"Vitamin C ("&TEXT(AG7,"0%")&")|","")&IF(AND(AH7>=0.25,"Vitamin A"<>AP7),"Vitamin A ("&TEXT(AH7,"0%")&")|","")&IF(AND(AI7>=0.25,"Vitamin K"<>AP7),"Vitamin K ("&TEXT(AI7,"0%")&")|","")&IF(AND(AJ7>=0.25,"Folate"<>AP7),"Folate ("&TEXT(AJ7,"0%")&")|","")&IF(AND(AK7>=0.25,"Potassium"<>AP7),"Potassium ("&TEXT(AK7,"0%")&")|","")&IF(AND(AL7>=0.25,"Vitamin E"<>AP7),"Vitamin E ("&TEXT(AL7,"0%")&")|","")&IF(AND(AM7>=0.25,"Vitamin B6"<>AP7),"Vitamin B6 ("&TEXT(AM7,"0%")&")|","")&IF(AND(AN7>=0.25,"Magnesium"<>AP7),"Magnesium ("&TEXT(AN7,"0%")&")|","")&IF(AND(AO7>=0.25,"Iron"<>AP7),"Iron ("&TEXT(AO7,"0%")&")|",""),LEN(IF(AND(AF7>=0.25,"Fibre"<>AP7),"Fibre ("&TEXT(AF7,"0%")&")|","")&IF(AND(AG7>=0.25,"Vitamin C"<>AP7),"Vitamin C ("&TEXT(AG7,"0%")&")|","")&IF(AND(AH7>=0.25,"Vitamin A"<>AP7),"Vitamin A ("&TEXT(AH7,"0%")&")|","")&IF(AND(AI7>=0.25,"Vitamin K"<>AP7),"Vitamin K ("&TEXT(AI7,"0%")&")|","")&IF(AND(AJ7>=0.25,"Folate"<>AP7),"Folate ("&TEXT(AJ7,"0%")&")|","")&IF(AND(AK7>=0.25,"Potassium"<>AP7),"Potassium ("&TEXT(AK7,"0%")&")|","")&IF(AND(AL7>=0.25,"Vitamin E"<>AP7),"Vitamin E ("&TEXT(AL7,"0%")&")|","")&IF(AND(AM7>=0.25,"Vitamin B6"<>AP7),"Vitamin B6 ("&TEXT(AM7,"0%")&")|","")&IF(AND(AN7>=0.25,"Magnesium"<>AP7),"Magnesium ("&TEXT(AN7,"0%")&")|","")&IF(AND(AO7>=0.25,"Iron"<>AP7),"Iron ("&TEXT(AO7,"0%")&")|",""))-1),"|",", ")) -> Fibre (26%), Vitamin C (113%), Vitamin A (130%), Folate (34%), Potassium (38%), Vitamin B6 (39%) | AS7: Sweet potato is one of the best vitamin A sources available, with potassium and fibre. Tatashe (red bell pepper) has about twice the vitamin C of an orange by weight, plus beta-carotene. | AT7: Sweet potato, Onion, Red bell pepper, Amaranth greens | AU7: =COUNTIFS('Recipe Ingredients'!$A$2:$A$2500,A7,'Recipe Ingredients'!$G$2:$G$2500,"Basket") -> 5 | AV7: =COUNTIFS('Recipe Ingredients'!$A$2:$A$2500,A7,'Recipe Ingredients'!$G$2:$G$2500,"Protein")+COUNTIFS('Recipe Ingredients'!$A$2:$A$2500,A7,'Recipe Ingredients'!$G$2:$G$2500,"Pantry") -> 2 | AW7: =IFERROR(AU7/(AU7+AV7),0) -> 0.71428571 | AX7: =IF(AW7>='Start Here'!$C$6,"Yes","No") -> No | AY7: Year-round | AZ7: 1. Dice sweet potatoes small and fry in oil for 10 minutes until golden. 2. Add onion and tatashe, cook 4 minutes. Season with paprika and salt. 3. Stir in efo tete until wilted. 4. Make wells, crack in eggs, cover until set. Finish with spring onion. | BB7: Draft
A8: R022 | B8: Tropical Parfait with Tiger Nut Crumble | C8: Breakfast Plates | D8: Parfait | E8: Breakfast / Snack | F8: Yoghurt parfait (France / US cafes) | G8: Dishes Delish | H8: https://dishesdelish.com/yogurt-parfait/ | I8: https://dishesdelish.com/wp-content/uploads/2025/02/yogurt-parfait-horizontal-1200.jpg | J8: Tiger nut and coconut crumble replaces store-bought granola. | K8: You add: Greek yoghurt, honey, granola or oats. | L8: Weight management, Wellness | M8: Vegetarian | N8: 10 | O8: 0 | P8: =N8+O8 -> 10 | Q8: =IF(O8=0,"No-cook",IF(P8<=25,"Quick","Standard")) -> No-cook | R8: 2 | S8: 340 | T8: 14 | U8: =SUMIFS('Recipe Ingredients'!$I$2:$I$2500,'Recipe Ingredients'!$A$2:$A$2500,A8)/R8 -> 263 | V8: =SUMIFS('Recipe Ingredients'!$J$2:$J$2500,'Recipe Ingredients'!$A$2:$A$2500,A8)/R8 -> 8.083 | W8: =SUMIFS('Recipe Ingredients'!$K$2:$K$2500,'Recipe Ingredients'!$A$2:$A$2500,A8)/R8 -> 76.989 | X8: =SUMIFS('Recipe Ingredients'!$L$2:$L$2500,'Recipe Ingredients'!$A$2:$A$2500,A8)/R8 -> 49.605 | Y8: =SUMIFS('Recipe Ingredients'!$M$2:$M$2500,'Recipe Ingredients'!$A$2:$A$2500,A8)/R8 -> 4.4305 | Z8: =SUMIFS('Recipe Ingredients'!$N$2:$N$2500,'Recipe Ingredients'!$A$2:$A$2500,A8)/R8 -> 66.67 | AA8: =SUMIFS('Recipe Ingredients'!$O$2:$O$2500,'Recipe Ingredients'!$A$2:$A$2500,A8)/R8 -> 655.415 | AB8: =SUMIFS('Recipe Ingredients'!$P$2:$P$2500,'Recipe Ingredients'!$A$2:$A$2500,A8)/R8 -> 2.0375 | AC8: =SUMIFS('Recipe Ingredients'!$Q$2:$Q$2500,'Recipe Ingredients'!$A$2:$A$2500,A8)/R8 -> 0.41699 | AD8: =SUMIFS('Recipe Ingredients'!$R$2:$R$2500,'Recipe Ingredients'!$A$2:$A$2500,A8)/R8 -> 60.405 | AE8: =SUMIFS('Recipe Ingredients'!$S$2:$S$2500,'Recipe Ingredients'!$A$2:$A$2500,A8)/R8 -> 1.70155 | AF8: =IFERROR(V8/'Start Here'!$C$10,0) -> 0.32332 | AG8: =IFERROR(W8/'Start Here'!$C$11,0) -> 0.9623625 | AH8: =IFERROR(X8/'Start Here'!$C$12,0) -> 0.06200625 | AI8: =IFERROR(Y8/'Start Here'!$C$13,0) -> 0.059073333 | AJ8: =IFERROR(Z8/'Start Here'!$C$14,0) -> 0.33335 | AK8: =IFERROR(AA8/'Start Here'!$C$15,0) -> 0.3277075 | AL8: =IFERROR(AB8/'Start Here'!$C$16,0) -> 0.16979167 | AM8: =IFERROR(AC8/'Start Here'!$C$17,0) -> 0.29785 | AN8: =IFERROR(AD8/'Start Here'!$C$18,0) -> 0.16108 | AO8: =IFERROR(AE8/'Start Here'!$C$19,0) -> 0.12153929 | AP8: =IFERROR(SUBSTITUTE(INDEX($AF$1:$AO$1,MATCH(MAX(AF8:AO8),AF8:AO8,0))," % daily",""),"") -> Vitamin C | AQ8: =IF(MAX(AF8:AO8)>=0.15,"Best for better "&IF(LEFT(AP8,7)="Vitamin","vitamin "&MID(AP8,9,3),LOWER(AP8))&" intake: one serving gives about "&TEXT(MAX(AF8:AO8),"0%")&" of your daily "&IF(LEFT(AP8,7)="Vitamin","vitamin "&MID(AP8,9,3),LOWER(AP8))&" from the produce alone.","A lighter plate: top nutrient is "&IF(LEFT(AP8,7)="Vitamin","vitamin "&MID(AP8,9,3),LOWER(AP8))&" at about "&TEXT(MAX(AF8:AO8),"0%")&" of a day.") -> Best for better vitamin C intake: one serving gives about 96% of your daily vitamin C from the produce alone. | AR8: =IF(LEN(IF(AND(AF8>=0.25,"Fibre"<>AP8),"Fibre ("&TEXT(AF8,"0%")&")|","")&IF(AND(AG8>=0.25,"Vitamin C"<>AP8),"Vitamin C ("&TEXT(AG8,"0%")&")|","")&IF(AND(AH8>=0.25,"Vitamin A"<>AP8),"Vitamin A ("&TEXT(AH8,"0%")&")|","")&IF(AND(AI8>=0.25,"Vitamin K"<>AP8),"Vitamin K ("&TEXT(AI8,"0%")&")|","")&IF(AND(AJ8>=0.25,"Folate"<>AP8),"Folate ("&TEXT(AJ8,"0%")&")|","")&IF(AND(AK8>=0.25,"Potassium"<>AP8),"Potassium ("&TEXT(AK8,"0%")&")|","")&IF(AND(AL8>=0.25,"Vitamin E"<>AP8),"Vitamin E ("&TEXT(AL8,"0%")&")|","")&IF(AND(AM8>=0.25,"Vitamin B6"<>AP8),"Vitamin B6 ("&TEXT(AM8,"0%")&")|","")&IF(AND(AN8>=0.25,"Magnesium"<>AP8),"Magnesium ("&TEXT(AN8,"0%")&")|","")&IF(AND(AO8>=0.25,"Iron"<>AP8),"Iron ("&TEXT(AO8,"0%")&")|",""))=0,"",SUBSTITUTE(LEFT(IF(AND(AF8>=0.25,"Fibre"<>AP8),"Fibre ("&TEXT(AF8,"0%")&")|","")&IF(AND(AG8>=0.25,"Vitamin C"<>AP8),"Vitamin C ("&TEXT(AG8,"0%")&")|","")&IF(AND(AH8>=0.25,"Vitamin A"<>AP8),"Vitamin A ("&TEXT(AH8,"0%")&")|","")&IF(AND(AI8>=0.25,"Vitamin K"<>AP8),"Vitamin K ("&TEXT(AI8,"0%")&")|","")&IF(AND(AJ8>=0.25,"Folate"<>AP8),"Folate ("&TEXT(AJ8,"0%")&")|","")&IF(AND(AK8>=0.25,"Potassium"<>AP8),"Potassium ("&TEXT(AK8,"0%")&")|","")&IF(AND(AL8>=0.25,"Vitamin E"<>AP8),"Vitamin E ("&TEXT(AL8,"0%")&")|","")&IF(AND(AM8>=0.25,"Vitamin B6"<>AP8),"Vitamin B6 ("&TEXT(AM8,"0%")&")|","")&IF(AND(AN8>=0.25,"Magnesium"<>AP8),"Magnesium ("&TEXT(AN8,"0%")&")|","")&IF(AND(AO8>=0.25,"Iron"<>AP8),"Iron ("&TEXT(AO8,"0%")&")|",""),LEN(IF(AND(AF8>=0.25,"Fibre"<>AP8),"Fibre ("&TEXT(AF8,"0%")&")|","")&IF(AND(AG8>=0.25,"Vitamin C"<>AP8),"Vitamin C ("&TEXT(AG8,"0%")&")|","")&IF(AND(AH8>=0.25,"Vitamin A"<>AP8),"Vitamin A ("&TEXT(AH8,"0%")&")|","")&IF(AND(AI8>=0.25,"Vitamin K"<>AP8),"Vitamin K ("&TEXT(AI8,"0%")&")|","")&IF(AND(AJ8>=0.25,"Folate"<>AP8),"Folate ("&TEXT(AJ8,"0%")&")|","")&IF(AND(AK8>=0.25,"Potassium"<>AP8),"Potassium ("&TEXT(AK8,"0%")&")|","")&IF(AND(AL8>=0.25,"Vitamin E"<>AP8),"Vitamin E ("&TEXT(AL8,"0%")&")|","")&IF(AND(AM8>=0.25,"Vitamin B6"<>AP8),"Vitamin B6 ("&TEXT(AM8,"0%")&")|","")&IF(AND(AN8>=0.25,"Magnesium"<>AP8),"Magnesium ("&TEXT(AN8,"0%")&")|","")&IF(AND(AO8>=0.25,"Iron"<>AP8),"Iron ("&TEXT(AO8,"0%")&")|",""))-1),"|",", ")) -> Fibre (32%), Folate (33%), Potassium (33%), Vitamin B6 (30%) | AS8: Pineapple is rich in vitamin C and manganese, and bromelain that helps digest protein. Banana is the easy potassium and vitamin B6 source. | AT8: Pineapple, Banana, Mango, Tiger nut | AU8: =COUNTIFS('Recipe Ingredients'!$A$2:$A$2500,A8,'Recipe Ingredients'!$G$2:$G$2500,"Basket") -> 5 | AV8: =COUNTIFS('Recipe Ingredients'!$A$2:$A$2500,A8,'Recipe Ingredients'!$G$2:$G$2500,"Protein")+COUNTIFS('Recipe Ingredients'!$A$2:$A$2500,A8,'Recipe Ingredients'!$G$2:$G$2500,"Pantry") -> 2 | AW8: =IFERROR(AU8/(AU8+AV8),0) -> 0.71428571 | AX8: =IF(AW8>='Start Here'!$C$6,"Yes","No") -> No | AY8: Mango (Feb-May, Aug-Sep); Tiger nut (Nov-May, Jul-Sep) | AZ8: 1. Chop tiger nuts roughly and toast with grated coconut in a dry pan for 3 minutes. 2. Dice pineapple, banana and mango. 3. Layer yoghurt, fruit and crumble in two glasses. 4. Finish with honey. | BA8: Off season, pawpaw replaces mango. | BB8: Draft
A9: R023 | B9: Coconut Chia Pudding with Mango | C9: Breakfast Plates | D9: Fruit & oats | E9: Breakfast / Dessert | F9: Chia pudding (wellness cafes) | G9: Downshiftology | H9: https://downshiftology.com/recipes/how-to-make-chia-seed-pudding/ | I9: https://i2.wp.com/www.downshiftology.com/wp-content/uploads/2020/01/Chia-Pudding-main.jpg | J9: Fresh coconut milk and dates instead of canned milk and maple syrup. | K9: You add: chia seeds, coconut milk, honey. | L9: Plant-based, Wellness | M9: Vegan | N9: 10 | O9: 0 | P9: =N9+O9 -> 10 | Q9: =IF(O9=0,"No-cook",IF(P9<=25,"Quick","Standard")) -> No-cook | R9: 2 | S9: 320 | T9: 7 | U9: =SUMIFS('Recipe Ingredients'!$I$2:$I$2500,'Recipe Ingredients'!$A$2:$A$2500,A9)/R9 -> 307.5 | V9: =SUMIFS('Recipe Ingredients'!$J$2:$J$2500,'Recipe Ingredients'!$A$2:$A$2500,A9)/R9 -> 13.096 | W9: =SUMIFS('Recipe Ingredients'!$K$2:$K$2500,'Recipe Ingredients'!$A$2:$A$2500,A9)/R9 -> 74.1955 | X9: =SUMIFS('Recipe Ingredients'!$L$2:$L$2500,'Recipe Ingredients'!$A$2:$A$2500,A9)/R9 -> 91.39 | Y9: =SUMIFS('Recipe Ingredients'!$M$2:$M$2500,'Recipe Ingredients'!$A$2:$A$2500,A9)/R9 -> 7.644 | Z9: =SUMIFS('Recipe Ingredients'!$N$2:$N$2500,'Recipe Ingredients'!$A$2:$A$2500,A9)/R9 -> 101.99 | AA9: =SUMIFS('Recipe Ingredients'!$O$2:$O$2500,'Recipe Ingredients'!$A$2:$A$2500,A9)/R9 -> 714.77 | AB9: =SUMIFS('Recipe Ingredients'!$P$2:$P$2500,'Recipe Ingredients'!$A$2:$A$2500,A9)/R9 -> 1.8268 | AC9: =SUMIFS('Recipe Ingredients'!$Q$2:$Q$2500,'Recipe Ingredients'!$A$2:$A$2500,A9)/R9 -> 0.279335 | AD9: =SUMIFS('Recipe Ingredients'!$R$2:$R$2500,'Recipe Ingredients'!$A$2:$A$2500,A9)/R9 -> 53.5 | AE9: =SUMIFS('Recipe Ingredients'!$S$2:$S$2500,'Recipe Ingredients'!$A$2:$A$2500,A9)/R9 -> 2.9469 | AF9: =IFERROR(V9/'Start Here'!$C$10,0) -> 0.52384 | AG9: =IFERROR(W9/'Start Here'!$C$11,0) -> 0.92744375 | AH9: =IFERROR(X9/'Start Here'!$C$12,0) -> 0.1142375 | AI9: =IFERROR(Y9/'Start Here'!$C$13,0) -> 0.10192 | AJ9: =IFERROR(Z9/'Start Here'!$C$14,0) -> 0.50995 | AK9: =IFERROR(AA9/'Start Here'!$C$15,0) -> 0.357385 | AL9: =IFERROR(AB9/'Start Here'!$C$16,0) -> 0.15223333 | AM9: =IFERROR(AC9/'Start Here'!$C$17,0) -> 0.199525 | AN9: =IFERROR(AD9/'Start Here'!$C$18,0) -> 0.14266667 | AO9: =IFERROR(AE9/'Start Here'!$C$19,0) -> 0.21049286 | AP9: =IFERROR(SUBSTITUTE(INDEX($AF$1:$AO$1,MATCH(MAX(AF9:AO9),AF9:AO9,0))," % daily",""),"") -> Vitamin C | AQ9: =IF(MAX(AF9:AO9)>=0.15,"Best for better "&IF(LEFT(AP9,7)="Vitamin","vitamin "&MID(AP9,9,3),LOWER(AP9))&" intake: one serving gives about "&TEXT(MAX(AF9:AO9),"0%")&" of your daily "&IF(LEFT(AP9,7)="Vitamin","vitamin "&MID(AP9,9,3),LOWER(AP9))&" from the produce alone.","A lighter plate: top nutrient is "&IF(LEFT(AP9,7)="Vitamin","vitamin "&MID(AP9,9,3),LOWER(AP9))&" at about "&TEXT(MAX(AF9:AO9),"0%")&" of a day.") -> Best for better vitamin C intake: one serving gives about 93% of your daily vitamin C from the produce alone. | AR9: =IF(LEN(IF(AND(AF9>=0.25,"Fibre"<>AP9),"Fibre ("&TEXT(AF9,"0%")&")|","")&IF(AND(AG9>=0.25,"Vitamin C"<>AP9),"Vitamin C ("&TEXT(AG9,"0%")&")|","")&IF(AND(AH9>=0.25,"Vitamin A"<>AP9),"Vitamin A ("&TEXT(AH9,"0%")&")|","")&IF(AND(AI9>=0.25,"Vitamin K"<>AP9),"Vitamin K ("&TEXT(AI9,"0%")&")|","")&IF(AND(AJ9>=0.25,"Folate"<>AP9),"Folate ("&TEXT(AJ9,"0%")&")|","")&IF(AND(AK9>=0.25,"Potassium"<>AP9),"Potassium ("&TEXT(AK9,"0%")&")|","")&IF(AND(AL9>=0.25,"Vitamin E"<>AP9),"Vitamin E ("&TEXT(AL9,"0%")&")|","")&IF(AND(AM9>=0.25,"Vitamin B6"<>AP9),"Vitamin B6 ("&TEXT(AM9,"0%")&")|","")&IF(AND(AN9>=0.25,"Magnesium"<>AP9),"Magnesium ("&TEXT(AN9,"0%")&")|","")&IF(AND(AO9>=0.25,"Iron"<>AP9),"Iron ("&TEXT(AO9,"0%")&")|",""))=0,"",SUBSTITUTE(LEFT(IF(AND(AF9>=0.25,"Fibre"<>AP9),"Fibre ("&TEXT(AF9,"0%")&")|","")&IF(AND(AG9>=0.25,"Vitamin C"<>AP9),"Vitamin C ("&TEXT(AG9,"0%")&")|","")&IF(AND(AH9>=0.25,"Vitamin A"<>AP9),"Vitamin A ("&TEXT(AH9,"0%")&")|","")&IF(AND(AI9>=0.25,"Vitamin K"<>AP9),"Vitamin K ("&TEXT(AI9,"0%")&")|","")&IF(AND(AJ9>=0.25,"Folate"<>AP9),"Folate ("&TEXT(AJ9,"0%")&")|","")&IF(AND(AK9>=0.25,"Potassium"<>AP9),"Potassium ("&TEXT(AK9,"0%")&")|","")&IF(AND(AL9>=0.25,"Vitamin E"<>AP9),"Vitamin E ("&TEXT(AL9,"0%")&")|","")&IF(AND(AM9>=0.25,"Vitamin B6"<>AP9),"Vitamin B6 ("&TEXT(AM9,"0%")&")|","")&IF(AND(AN9>=0.25,"Magnesium"<>AP9),"Magnesium ("&TEXT(AN9,"0%")&")|","")&IF(AND(AO9>=0.25,"Iron"<>AP9),"Iron ("&TEXT(AO9,"0%")&")|",""),LEN(IF(AND(AF9>=0.25,"Fibre"<>AP9),"Fibre ("&TEXT(AF9,"0%")&")|","")&IF(AND(AG9>=0.25,"Vitamin C"<>AP9),"Vitamin C ("&TEXT(AG9,"0%")&")|","")&IF(AND(AH9>=0.25,"Vitamin A"<>AP9),"Vitamin A ("&TEXT(AH9,"0%")&")|","")&IF(AND(AI9>=0.25,"Vitamin K"<>AP9),"Vitamin K ("&TEXT(AI9,"0%")&")|","")&IF(AND(AJ9>=0.25,"Folate"<>AP9),"Folate ("&TEXT(AJ9,"0%")&")|","")&IF(AND(AK9>=0.25,"Potassium"<>AP9),"Potassium ("&TEXT(AK9,"0%")&")|","")&IF(AND(AL9>=0.25,"Vitamin E"<>AP9),"Vitamin E ("&TEXT(AL9,"0%")&")|","")&IF(AND(AM9>=0.25,"Vitamin B6"<>AP9),"Vitamin B6 ("&TEXT(AM9,"0%")&")|","")&IF(AND(AN9>=0.25,"Magnesium"<>AP9),"Magnesium ("&TEXT(AN9,"0%")&")|","")&IF(AND(AO9>=0.25,"Iron"<>AP9),"Iron ("&TEXT(AO9,"0%")&")|",""))-1),"|",", ")) -> Fibre (52%), Folate (51%), Potassium (36%) | AS9: Fresh coconut adds fibre, manganese and satisfying fat. Dates bring potassium, magnesium and fibre with natural sweetness. | AT9: Coconut, Dates, Mango, Lime | AU9: =COUNTIFS('Recipe Ingredients'!$A$2:$A$2500,A9,'Recipe Ingredients'!$G$2:$G$2500,"Basket") -> 4 | AV9: =COUNTIFS('Recipe Ingredients'!$A$2:$A$2500,A9,'Recipe Ingredients'!$G$2:$G$2500,"Protein")+COUNTIFS('Recipe Ingredients'!$A$2:$A$2500,A9,'Recipe Ingredients'!$G$2:$G$2500,"Pantry") -> 1 | AW9: =IFERROR(AU9/(AU9+AV9),0) -> 0.8 | AX9: =IF(AW9>='Start Here'!$C$6,"Yes","No") -> Yes | AY9: Mango (Feb-May, Aug-Sep) | AZ9: 1. Blend coconut flesh with warm water and dates, then strain to get sweet coconut milk. 2. Stir chia seeds into the milk and leave 10 minutes, then stir again. 3. Refrigerate at least 4 hours. 4. Top with diced mango and lime zest. | BB9: Draft
A10: R055 | B10: Egg & Avocado Breakfast Wrap | C10: Breakfast Plates | D10: Wrap | E10: Breakfast | F10: Breakfast burrito (US Southwest) | G10: Love and Lemons | H10: https://www.loveandlemons.com/breakfast-burrito/ | I10: https://cdn.loveandlemons.com/wp-content/uploads/2026/08/breakfast-burrito-recipe.jpg | J10: The filling is a Nigerian egg sauce: tomato, onion and pepper scrambled with eggs. | K10: You add: eggs, tortilla or shawarma bread, cheese if you like. | L10: Training | M10: Vegetarian | N10: 10 | O10: 10 | P10: =N10+O10 -> 20 | Q10: =IF(O10=0,"No-cook",IF(P10<=25,"Quick","Standard")) -> Quick | R10: 2 | S10: 450 | T10: 20 | U10: =SUMIFS('Recipe Ingredients'!$I$2:$I$2500,'Recipe Ingredients'!$A$2:$A$2500,A10)/R10 -> 205 | V10: =SUMIFS('Recipe Ingredients'!$J$2:$J$2500,'Recipe Ingredients'!$A$2:$A$2500,A10)/R10 -> 8.24 | W10: =SUMIFS('Recipe Ingredients'!$K$2:$K$2500,'Recipe Ingredients'!$A$2:$A$2500,A10)/R10 -> 28.078 | X10: =SUMIFS('Recipe Ingredients'!$L$2:$L$2500,'Recipe Ingredients'!$A$2:$A$2500,A10)/R10 -> 53.995 | Y10: =SUMIFS('Recipe Ingredients'!$M$2:$M$2500,'Recipe Ingredients'!$A$2:$A$2500,A10)/R10 -> 185.853 | Z10: =SUMIFS('Recipe Ingredients'!$N$2:$N$2500,'Recipe Ingredients'!$A$2:$A$2500,A10)/R10 -> 108.06 | AA10: =SUMIFS('Recipe Ingredients'!$O$2:$O$2500,'Recipe Ingredients'!$A$2:$A$2500,A10)/R10 -> 763.275 | AB10: =SUMIFS('Recipe Ingredients'!$P$2:$P$2500,'Recipe Ingredients'!$A$2:$A$2500,A10)/R10 -> 2.42755 | AC10: =SUMIFS('Recipe Ingredients'!$Q$2:$Q$2500,'Recipe Ingredients'!$A$2:$A$2500,A10)/R10 -> 0.372825 | AD10: =SUMIFS('Recipe Ingredients'!$R$2:$R$2500,'Recipe Ingredients'!$A$2:$A$2500,A10)/R10 -> 46.645 | AE10: =SUMIFS('Recipe Ingredients'!$S$2:$S$2500,'Recipe Ingredients'!$A$2:$A$2500,A10)/R10 -> 1.113 | AF10: =IFERROR(V10/'Start Here'!$C$10,0) -> 0.3296 | AG10: =IFERROR(W10/'Start Here'!$C$11,0) -> 0.350975 | AH10: =IFERROR(X10/'Start Here'!$C$12,0) -> 0.06749375 | AI10: =IFERROR(Y10/'Start Here'!$C$13,0) -> 2.47804 | AJ10: =IFERROR(Z10/'Start Here'!$C$14,0) -> 0.5403 | AK10: =IFERROR(AA10/'Start Here'!$C$15,0) -> 0.3816375 | AL10: =IFERROR(AB10/'Start Here'!$C$16,0) -> 0.20229583 | AM10: =IFERROR(AC10/'Start Here'!$C$17,0) -> 0.26630357 | AN10: =IFERROR(AD10/'Start Here'!$C$18,0) -> 0.12438667 | AO10: =IFERROR(AE10/'Start Here'!$C$19,0) -> 0.0795 | AP10: =IFERROR(SUBSTITUTE(INDEX($AF$1:$AO$1,MATCH(MAX(AF10:AO10),AF10:AO10,0))," % daily",""),"") -> Vitamin K | AQ10: =IF(MAX(AF10:AO10)>=0.15,"Best for better "&IF(LEFT(AP10,7)="Vitamin","vitamin "&MID(AP10,9,3),LOWER(AP10))&" intake: one serving gives about "&TEXT(MAX(AF10:AO10),"0%")&" of your daily "&IF(LEFT(AP10,7)="Vitamin","vitamin "&MID(AP10,9,3),LOWER(AP10))&" from the produce alone.","A lighter plate: top nutrient is "&IF(LEFT(AP10,7)="Vitamin","vitamin "&MID(AP10,9,3),LOWER(AP10))&" at about "&TEXT(MAX(AF10:AO10),"0%")&" of a day.") -> Best for better vitamin K intake: one serving gives about 248% of your daily vitamin K from the produce alone. | AR10: =IF(LEN(IF(AND(AF10>=0.25,"Fibre"<>AP10),"Fibre ("&TEXT(AF10,"0%")&")|","")&IF(AND(AG10>=0.25,"Vitamin C"<>AP10),"Vitamin C ("&TEXT(AG10,"0%")&")|","")&IF(AND(AH10>=0.25,"Vitamin A"<>AP10),"Vitamin A ("&TEXT(AH10,"0%")&")|","")&IF(AND(AI10>=0.25,"Vitamin K"<>AP10),"Vitamin K ("&TEXT(AI10,"0%")&")|","")&IF(AND(AJ10>=0.25,"Folate"<>AP10),"Folate ("&TEXT(AJ10,"0%")&")|","")&IF(AND(AK10>=0.25,"Potassium"<>AP10),"Potassium ("&TEXT(AK10,"0%")&")|","")&IF(AND(AL10>=0.25,"Vitamin E"<>AP10),"Vitamin E ("&TEXT(AL10,"0%")&")|","")&IF(AND(AM10>=0.25,"Vitamin B6"<>AP10),"Vitamin B6 ("&TEXT(AM10,"0%")&")|","")&IF(AND(AN10>=0.25,"Magnesium"<>AP10),"Magnesium ("&TEXT(AN10,"0%")&")|","")&IF(AND(AO10>=0.25,"Iron"<>AP10),"Iron ("&TEXT(AO10,"0%")&")|",""))=0,"",SUBSTITUTE(LEFT(IF(AND(AF10>=0.25,"Fibre"<>AP10),"Fibre ("&TEXT(AF10,"0%")&")|","")&IF(AND(AG10>=0.25,"Vitamin C"<>AP10),"Vitamin C ("&TEXT(AG10,"0%")&")|","")&IF(AND(AH10>=0.25,"Vitamin A"<>AP10),"Vitamin A ("&TEXT(AH10,"0%")&")|","")&IF(AND(AI10>=0.25,"Vitamin K"<>AP10),"Vitamin K ("&TEXT(AI10,"0%")&")|","")&IF(AND(AJ10>=0.25,"Folate"<>AP10),"Folate ("&TEXT(AJ10,"0%")&")|","")&IF(AND(AK10>=0.25,"Potassium"<>AP10),"Potassium ("&TEXT(AK10,"0%")&")|","")&IF(AND(AL10>=0.25,"Vitamin E"<>AP10),"Vitamin E ("&TEXT(AL10,"0%")&")|","")&IF(AND(AM10>=0.25,"Vitamin B6"<>AP10),"Vitamin B6 ("&TEXT(AM10,"0%")&")|","")&IF(AND(AN10>=0.25,"Magnesium"<>AP10),"Magnesium ("&TEXT(AN10,"0%")&")|","")&IF(AND(AO10>=0.25,"Iron"<>AP10),"Iron ("&TEXT(AO10,"0%")&")|",""),LEN(IF(AND(AF10>=0.25,"Fibre"<>AP10),"Fibre ("&TEXT(AF10,"0%")&")|","")&IF(AND(AG10>=0.25,"Vitamin C"<>AP10),"Vitamin C ("&TEXT(AG10,"0%")&")|","")&IF(AND(AH10>=0.25,"Vitamin A"<>AP10),"Vitamin A ("&TEXT(AH10,"0%")&")|","")&IF(AND(AI10>=0.25,"Vitamin K"<>AP10),"Vitamin K ("&TEXT(AI10,"0%")&")|","")&IF(AND(AJ10>=0.25,"Folate"<>AP10),"Folate ("&TEXT(AJ10,"0%")&")|","")&IF(AND(AK10>=0.25,"Potassium"<>AP10),"Potassium ("&TEXT(AK10,"0%")&")|","")&IF(AND(AL10>=0.25,"Vitamin E"<>AP10),"Vitamin E ("&TEXT(AL10,"0%")&")|","")&IF(AND(AM10>=0.25,"Vitamin B6"<>AP10),"Vitamin B6 ("&TEXT(AM10,"0%")&")|","")&IF(AND(AN10>=0.25,"Magnesium"<>AP10),"Magnesium ("&TEXT(AN10,"0%")&")|","")&IF(AND(AO10>=0.25,"Iron"<>AP10),"Iron ("&TEXT(AO10,"0%")&")|",""))-1),"|",", ")) -> Fibre (33%), Vitamin C (35%), Folate (54%), Potassium (38%), Vitamin B6 (27%) | AS10: Avocado gives potassium, folate, vitamin E and heart-friendly fats that help absorb vitamins from the rest of the plate. Tomatoes bring vitamin C and lycopene; cooking them in a little oil makes the lycopene easier to absorb. | AT10: Avocado, Tomato, Onion, Scotch bonnet | AU10: =COUNTIFS('Recipe Ingredients'!$A$2:$A$2500,A10,'Recipe Ingredients'!$G$2:$G$2500,"Basket") -> 5 | AV10: =COUNTIFS('Recipe Ingredients'!$A$2:$A$2500,A10,'Recipe Ingredients'!$G$2:$G$2500,"Protein")+COUNTIFS('Recipe Ingredients'!$A$2:$A$2500,A10,'Recipe Ingredients'!$G$2:$G$2500,"Pantry") -> 2 | AW10: =IFERROR(AU10/(AU10+AV10),0) -> 0.71428571 | AX10: =IF(AW10>='Start Here'!$C$6,"Yes","No") -> No | AY10: Year-round | AZ10: 1. Saute diced onion, tomatoes and ata rodo in oil for 3 minutes. 2. Add efo, then the beaten eggs. Scramble softly. 3. Warm the wraps and spread with mashed avocado. 4. Fill with eggs and roll. | BB10: Draft
A11: R024 | B11: Chilli-Lime Fruit Cup (Yaji Edition) | C11: Fruit Plates & Desserts | D11: Fruit plate | E11: Snack | F11: Mexican fruit cup with chile and lime (Tajin) | G11: Isabel Eats | H11: https://www.isabeleats.com/mexican-fruit-cups/ | I11: https://www.isabeleats.com/wp-content/uploads/2019/08/mexican-fruit-cups-029-small.jpg | J11: Yaji replaces Tajin. Same salty, spicy, sour hit on cold fruit. | K11: You add: yaji (suya spice) and a pinch of salt. | L11: Hydration, Weight management | M11: Vegan | N11: 10 | O11: 0 | P11: =N11+O11 -> 10 | Q11: =IF(O11=0,"No-cook",IF(P11<=25,"Quick","Standard")) -> No-cook | R11: 2 | S11: 120 | T11: 2 | U11: =SUMIFS('Recipe Ingredients'!$I$2:$I$2500,'Recipe Ingredients'!$A$2:$A$2500,A11)/R11 -> 608.5 | V11: =SUMIFS('Recipe Ingredients'!$J$2:$J$2500,'Recipe Ingredients'!$A$2:$A$2500,A11)/R11 -> 6.968 | W11: =SUMIFS('Recipe Ingredients'!$K$2:$K$2500,'Recipe Ingredients'!$A$2:$A$2500,A11)/R11 -> 150.1865 | X11: =SUMIFS('Recipe Ingredients'!$L$2:$L$2500,'Recipe Ingredients'!$A$2:$A$2500,A11)/R11 -> 133.335 | Y11: =SUMIFS('Recipe Ingredients'!$M$2:$M$2500,'Recipe Ingredients'!$A$2:$A$2500,A11)/R11 -> 31.2265 | Z11: =SUMIFS('Recipe Ingredients'!$N$2:$N$2500,'Recipe Ingredients'!$A$2:$A$2500,A11)/R11 -> 98.25 | AA11: =SUMIFS('Recipe Ingredients'!$O$2:$O$2500,'Recipe Ingredients'!$A$2:$A$2500,A11)/R11 -> 822.81 | AB11: =SUMIFS('Recipe Ingredients'!$P$2:$P$2500,'Recipe Ingredients'!$A$2:$A$2500,A11)/R11 -> 1.25855 | AC11: =SUMIFS('Recipe Ingredients'!$Q$2:$Q$2500,'Recipe Ingredients'!$A$2:$A$2500,A11)/R11 -> 0.37732 | AD11: =SUMIFS('Recipe Ingredients'!$R$2:$R$2500,'Recipe Ingredients'!$A$2:$A$2500,A11)/R11 -> 72.31 | AE11: =SUMIFS('Recipe Ingredients'!$S$2:$S$2500,'Recipe Ingredients'!$A$2:$A$2500,A11)/R11 -> 1.7431 | AF11: =IFERROR(V11/'Start Here'!$C$10,0) -> 0.27872 | AG11: =IFERROR(W11/'Start Here'!$C$11,0) -> 1.8773313 | AH11: =IFERROR(X11/'Start Here'!$C$12,0) -> 0.16666875 | AI11: =IFERROR(Y11/'Start Here'!$C$13,0) -> 0.41635333 | AJ11: =IFERROR(Z11/'Start Here'!$C$14,0) -> 0.49125 | AK11: =IFERROR(AA11/'Start Here'!$C$15,0) -> 0.411405 | AL11: =IFERROR(AB11/'Start Here'!$C$16,0) -> 0.10487917 | AM11: =IFERROR(AC11/'Start Here'!$C$17,0) -> 0.26951429 | AN11: =IFERROR(AD11/'Start Here'!$C$18,0) -> 0.19282667 | AO11: =IFERROR(AE11/'Start Here'!$C$19,0) -> 0.12450714 | AP11: =IFERROR(SUBSTITUTE(INDEX($AF$1:$AO$1,MATCH(MAX(AF11:AO11),AF11:AO11,0))," % daily",""),"") -> Vitamin C | AQ11: =IF(MAX(AF11:AO11)>=0.15,"Best for better "&IF(LEFT(AP11,7)="Vitamin","vitamin "&MID(AP11,9,3),LOWER(AP11))&" intake: one serving gives about "&TEXT(MAX(AF11:AO11),"0%")&" of your daily "&IF(LEFT(AP11,7)="Vitamin","vitamin "&MID(AP11,9,3),LOWER(AP11))&" from the produce alone.","A lighter plate: top nutrient is "&IF(LEFT(AP11,7)="Vitamin","vitamin "&MID(AP11,9,3),LOWER(AP11))&" at about "&TEXT(MAX(AF11:AO11),"0%")&" of a day.") -> Best for better vitamin C intake: one serving gives about 188% of your daily vitamin C from the produce alone. | AR11: =IF(LEN(IF(AND(AF11>=0.25,"Fibre"<>AP11),"Fibre ("&TEXT(AF11,"0%")&")|","")&IF(AND(AG11>=0.25,"Vitamin C"<>AP11),"Vitamin C ("&TEXT(AG11,"0%")&")|","")&IF(AND(AH11>=0.25,"Vitamin A"<>AP11),"Vitamin A ("&TEXT(AH11,"0%")&")|","")&IF(AND(AI11>=0.25,"Vitamin K"<>AP11),"Vitamin K ("&TEXT(AI11,"0%")&")|","")&IF(AND(AJ11>=0.25,"Folate"<>AP11),"Folate ("&TEXT(AJ11,"0%")&")|","")&IF(AND(AK11>=0.25,"Potassium"<>AP11),"Potassium ("&TEXT(AK11,"0%")&")|","")&IF(AND(AL11>=0.25,"Vitamin E"<>AP11),"Vitamin E ("&TEXT(AL11,"0%")&")|","")&IF(AND(AM11>=0.25,"Vitamin B6"<>AP11),"Vitamin B6 ("&TEXT(AM11,"0%")&")|","")&IF(AND(AN11>=0.25,"Magnesium"<>AP11),"Magnesium ("&TEXT(AN11,"0%")&")|","")&IF(AND(AO11>=0.25,"Iron"<>AP11),"Iron ("&TEXT(AO11,"0%")&")|",""))=0,"",SUBSTITUTE(LEFT(IF(AND(AF11>=0.25,"Fibre"<>AP11),"Fibre ("&TEXT(AF11,"0%")&")|","")&IF(AND(AG11>=0.25,"Vitamin C"<>AP11),"Vitamin C ("&TEXT(AG11,"0%")&")|","")&IF(AND(AH11>=0.25,"Vitamin A"<>AP11),"Vitamin A ("&TEXT(AH11,"0%")&")|","")&IF(AND(AI11>=0.25,"Vitamin K"<>AP11),"Vitamin K ("&TEXT(AI11,"0%")&")|","")&IF(AND(AJ11>=0.25,"Folate"<>AP11),"Folate ("&TEXT(AJ11,"0%")&")|","")&IF(AND(AK11>=0.25,"Potassium"<>AP11),"Potassium ("&TEXT(AK11,"0%")&")|","")&IF(AND(AL11>=0.25,"Vitamin E"<>AP11),"Vitamin E ("&TEXT(AL11,"0%")&")|","")&IF(AND(AM11>=0.25,"Vitamin B6"<>AP11),"Vitamin B6 ("&TEXT(AM11,"0%")&")|","")&IF(AND(AN11>=0.25,"Magnesium"<>AP11),"Magnesium ("&TEXT(AN11,"0%")&")|","")&IF(AND(AO11>=0.25,"Iron"<>AP11),"Iron ("&TEXT(AO11,"0%")&")|",""),LEN(IF(AND(AF11>=0.25,"Fibre"<>AP11),"Fibre ("&TEXT(AF11,"0%")&")|","")&IF(AND(AG11>=0.25,"Vitamin C"<>AP11),"Vitamin C ("&TEXT(AG11,"0%")&")|","")&IF(AND(AH11>=0.25,"Vitamin A"<>AP11),"Vitamin A ("&TEXT(AH11,"0%")&")|","")&IF(AND(AI11>=0.25,"Vitamin K"<>AP11),"Vitamin K ("&TEXT(AI11,"0%")&")|","")&IF(AND(AJ11>=0.25,"Folate"<>AP11),"Folate ("&TEXT(AJ11,"0%")&")|","")&IF(AND(AK11>=0.25,"Potassium"<>AP11),"Potassium ("&TEXT(AK11,"0%")&")|","")&IF(AND(AL11>=0.25,"Vitamin E"<>AP11),"Vitamin E ("&TEXT(AL11,"0%")&")|","")&IF(AND(AM11>=0.25,"Vitamin B6"<>AP11),"Vitamin B6 ("&TEXT(AM11,"0%")&")|","")&IF(AND(AN11>=0.25,"Magnesium"<>AP11),"Magnesium ("&TEXT(AN11,"0%")&")|","")&IF(AND(AO11>=0.25,"Iron"<>AP11),"Iron ("&TEXT(AO11,"0%")&")|",""))-1),"|",", ")) -> Fibre (28%), Vitamin K (42%), Folate (49%), Potassium (41%), Vitamin B6 (27%) | AS11: Watermelon is 92% water with potassium and lycopene: a hydration fruit. Pineapple is rich in vitamin C and manganese, and bromelain that helps digest protein. | AT11: Watermelon, Pineapple, Pawpaw, Cucumber | AU11: =COUNTIFS('Recipe Ingredients'!$A$2:$A$2500,A11,'Recipe Ingredients'!$G$2:$G$2500,"Basket") -> 6 | AV11: =COUNTIFS('Recipe Ingredients'!$A$2:$A$2500,A11,'Recipe Ingredients'!$G$2:$G$2500,"Protein")+COUNTIFS('Recipe Ingredients'!$A$2:$A$2500,A11,'Recipe Ingredients'!$G$2:$G$2500,"Pantry") -> 1 | AW11: =IFERROR(AU11/(AU11+AV11),0) -> 0.85714286 | AX11: =IF(AW11>='Start Here'!$C$6,"Yes","No") -> Yes | AY11: Mango (Feb-May, Aug-Sep) | AZ11: 1. Cut all the fruit and cucumber into spears or chunks. 2. Pile into cups. 3. Squeeze lime over generously. 4. Dust with yaji and a pinch of salt just before eating. | BA11: A strong candidate for a ready-to-eat snack box. | BB11: Draft
A12: R084 | B12: Banana Groundnut Nice Cream | C12: Fruit Plates & Desserts | D12: Frozen dessert | E12: Dessert | F12: 'Nice cream' (vegan frozen banana dessert) | G12: Love and Lemons | H12: https://www.loveandlemons.com/banana-ice-cream/ | I12: https://cdn.loveandlemons.com/wp-content/uploads/2025/06/banana-ice-cream-social.jpg | J12: Roasted groundnuts and dates make it taste like a Nigerian childhood treat. | K12: You add: groundnut paste or roasted groundnuts, cocoa if you like. | L12: Plant-based, Training | M12: Vegan | N12: 10 | O12: 0 | P12: =N12+O12 -> 10 | Q12: =IF(O12=0,"No-cook",IF(P12<=25,"Quick","Standard")) -> No-cook | R12: 2 | S12: 280 | T12: 7 | U12: =SUMIFS('Recipe Ingredients'!$I$2:$I$2500,'Recipe Ingredients'!$A$2:$A$2500,A12)/R12 -> 261.5 | V12: =SUMIFS('Recipe Ingredients'!$J$2:$J$2500,'Recipe Ingredients'!$A$2:$A$2500,A12)/R12 -> 8.251 | W12: =SUMIFS('Recipe Ingredients'!$K$2:$K$2500,'Recipe Ingredients'!$A$2:$A$2500,A12)/R12 -> 20.574 | X12: =SUMIFS('Recipe Ingredients'!$L$2:$L$2500,'Recipe Ingredients'!$A$2:$A$2500,A12)/R12 -> 7.08 | Y12: =SUMIFS('Recipe Ingredients'!$M$2:$M$2500,'Recipe Ingredients'!$A$2:$A$2500,A12)/R12 -> 1.4635 | Z12: =SUMIFS('Recipe Ingredients'!$N$2:$N$2500,'Recipe Ingredients'!$A$2:$A$2500,A12)/R12 -> 85.195 | AA12: =SUMIFS('Recipe Ingredients'!$O$2:$O$2500,'Recipe Ingredients'!$A$2:$A$2500,A12)/R12 -> 1019.51 | AB12: =SUMIFS('Recipe Ingredients'!$P$2:$P$2500,'Recipe Ingredients'!$A$2:$A$2500,A12)/R12 -> 1.49075 | AC12: =SUMIFS('Recipe Ingredients'!$Q$2:$Q$2500,'Recipe Ingredients'!$A$2:$A$2500,A12)/R12 -> 0.935645 | AD12: =SUMIFS('Recipe Ingredients'!$R$2:$R$2500,'Recipe Ingredients'!$A$2:$A$2500,A12)/R12 -> 93.435 | AE12: =SUMIFS('Recipe Ingredients'!$S$2:$S$2500,'Recipe Ingredients'!$A$2:$A$2500,A12)/R12 -> 1.4077 | AF12: =IFERROR(V12/'Start Here'!$C$10,0) -> 0.33004 | AG12: =IFERROR(W12/'Start Here'!$C$11,0) -> 0.257175 | AH12: =IFERROR(X12/'Start Here'!$C$12,0) -> 0.00885 | AI12: =IFERROR(Y12/'Start Here'!$C$13,0) -> 0.019513333 | AJ12: =IFERROR(Z12/'Start Here'!$C$14,0) -> 0.425975 | AK12: =IFERROR(AA12/'Start Here'!$C$15,0) -> 0.509755 | AL12: =IFERROR(AB12/'Start Here'!$C$16,0) -> 0.12422917 | AM12: =IFERROR(AC12/'Start Here'!$C$17,0) -> 0.66831786 | AN12: =IFERROR(AD12/'Start Here'!$C$18,0) -> 0.24916 | AO12: =IFERROR(AE12/'Start Here'!$C$19,0) -> 0.10055 | AP12: =IFERROR(SUBSTITUTE(INDEX($AF$1:$AO$1,MATCH(MAX(AF12:AO12),AF12:AO12,0))," % daily",""),"") -> Vitamin B6 | AQ12: =IF(MAX(AF12:AO12)>=0.15,"Best for better "&IF(LEFT(AP12,7)="Vitamin","vitamin "&MID(AP12,9,3),LOWER(AP12))&" intake: one serving gives about "&TEXT(MAX(AF12:AO12),"0%")&" of your daily "&IF(LEFT(AP12,7)="Vitamin","vitamin "&MID(AP12,9,3),LOWER(AP12))&" from the produce alone.","A lighter plate: top nutrient is "&IF(LEFT(AP12,7)="Vitamin","vitamin "&MID(AP12,9,3),LOWER(AP12))&" at about "&TEXT(MAX(AF12:AO12),"0%")&" of a day.") -> Best for better vitamin B6 intake: one serving gives about 67% of your daily vitamin B6 from the produce alone. | AR12: =IF(LEN(IF(AND(AF12>=0.25,"Fibre"<>AP12),"Fibre ("&TEXT(AF12,"0%")&")|","")&IF(AND(AG12>=0.25,"Vitamin C"<>AP12),"Vitamin C ("&TEXT(AG12,"0%")&")|","")&IF(AND(AH12>=0.25,"Vitamin A"<>AP12),"Vitamin A ("&TEXT(AH12,"0%")&")|","")&IF(AND(AI12>=0.25,"Vitamin K"<>AP12),"Vitamin K ("&TEXT(AI12,"0%")&")|","")&IF(AND(AJ12>=0.25,"Folate"<>AP12),"Folate ("&TEXT(AJ12,"0%")&")|","")&IF(AND(AK12>=0.25,"Potassium"<>AP12),"Potassium ("&TEXT(AK12,"0%")&")|","")&IF(AND(AL12>=0.25,"Vitamin E"<>AP12),"Vitamin E ("&TEXT(AL12,"0%")&")|","")&IF(AND(AM12>=0.25,"Vitamin B6"<>AP12),"Vitamin B6 ("&TEXT(AM12,"0%")&")|","")&IF(AND(AN12>=0.25,"Magnesium"<>AP12),"Magnesium ("&TEXT(AN12,"0%")&")|","")&IF(AND(AO12>=0.25,"Iron"<>AP12),"Iron ("&TEXT(AO12,"0%")&")|",""))=0,"",SUBSTITUTE(LEFT(IF(AND(AF12>=0.25,"Fibre"<>AP12),"Fibre ("&TEXT(AF12,"0%")&")|","")&IF(AND(AG12>=0.25,"Vitamin C"<>AP12),"Vitamin C ("&TEXT(AG12,"0%")&")|","")&IF(AND(AH12>=0.25,"Vitamin A"<>AP12),"Vitamin A ("&TEXT(AH12,"0%")&")|","")&IF(AND(AI12>=0.25,"Vitamin K"<>AP12),"Vitamin K ("&TEXT(AI12,"0%")&")|","")&IF(AND(AJ12>=0.25,"Folate"<>AP12),"Folate ("&TEXT(AJ12,"0%")&")|","")&IF(AND(AK12>=0.25,"Potassium"<>AP12),"Potassium ("&TEXT(AK12,"0%")&")|","")&IF(AND(AL12>=0.25,"Vitamin E"<>AP12),"Vitamin E ("&TEXT(AL12,"0%")&")|","")&IF(AND(AM12>=0.25,"Vitamin B6"<>AP12),"Vitamin B6 ("&TEXT(AM12,"0%")&")|","")&IF(AND(AN12>=0.25,"Magnesium"<>AP12),"Magnesium ("&TEXT(AN12,"0%")&")|","")&IF(AND(AO12>=0.25,"Iron"<>AP12),"Iron ("&TEXT(AO12,"0%")&")|",""),LEN(IF(AND(AF12>=0.25,"Fibre"<>AP12),"Fibre ("&TEXT(AF12,"0%")&")|","")&IF(AND(AG12>=0.25,"Vitamin C"<>AP12),"Vitamin C ("&TEXT(AG12,"0%")&")|","")&IF(AND(AH12>=0.25,"Vitamin A"<>AP12),"Vitamin A ("&TEXT(AH12,"0%")&")|","")&IF(AND(AI12>=0.25,"Vitamin K"<>AP12),"Vitamin K ("&TEXT(AI12,"0%")&")|","")&IF(AND(AJ12>=0.25,"Folate"<>AP12),"Folate ("&TEXT(AJ12,"0%")&")|","")&IF(AND(AK12>=0.25,"Potassium"<>AP12),"Potassium ("&TEXT(AK12,"0%")&")|","")&IF(AND(AL12>=0.25,"Vitamin E"<>AP12),"Vitamin E ("&TEXT(AL12,"0%")&")|","")&IF(AND(AM12>=0.25,"Vitamin B6"<>AP12),"Vitamin B6 ("&TEXT(AM12,"0%")&")|","")&IF(AND(AN12>=0.25,"Magnesium"<>AP12),"Magnesium ("&TEXT(AN12,"0%")&")|","")&IF(AND(AO12>=0.25,"Iron"<>AP12),"Iron ("&TEXT(AO12,"0%")&")|",""))-1),"|",", ")) -> Fibre (33%), Vitamin C (26%), Folate (43%), Potassium (51%) | AS12: Banana is the easy potassium and vitamin B6 source. Dates bring potassium, magnesium and fibre with natural sweetness. | AT12: Banana, Groundnut, Dates | AU12: =COUNTIFS('Recipe Ingredients'!$A$2:$A$2500,A12,'Recipe Ingredients'!$G$2:$G$2500,"Basket") -> 3 | AV12: =COUNTIFS('Recipe Ingredients'!$A$2:$A$2500,A12,'Recipe Ingredients'!$G$2:$G$2500,"Protein")+COUNTIFS('Recipe Ingredients'!$A$2:$A$2500,A12,'Recipe Ingredients'!$G$2:$G$2500,"Pantry") -> 2 | AW12: =IFERROR(AU12/(AU12+AV12),0) -> 0.6 | AX12: =IF(AW12>='Start Here'!$C$6,"Yes","No") -> No | AY12: Year-round | AZ12: 1. Slice ripe bananas and freeze for at least 4 hours. 2. Blend frozen banana with dates and a splash of milk until creamy. 3. Pulse in half the groundnuts. 4. Serve straight away, topped with the rest of the groundnuts and cinnamon. | BA12: The best use for overripe bananas. Pairs well with a discounted 'smoothie bananas' SKU. | BB12: Draft
A13: R085 | B13: Grilled Pineapple with Coconut & Lime | C13: Fruit Plates & Desserts | D13: Warm dessert | E13: Dessert | F13: Abacaxi assado (Brazilian churrasco dessert) | G13: This Healthy Table | H13: https://thishealthytable.com/blog/grilled-pineapple/ | I13: https://thishealthytable.com/wp-content/uploads/2022/08/grilled-pineapple.jpg | J13: Toasted fresh coconut and lime zest. | K13: You add: a little honey or brown sugar. Coconut from Basket. | L13: Wellness, Plant-based | M13: Vegetarian | N13: 10 | O13: 10 | P13: =N13+O13 -> 20 | Q13: =IF(O13=0,"No-cook",IF(P13<=25,"Quick","Standard")) -> Quick | R13: 4 | S13: 130 | T13: 1 | U13: =SUMIFS('Recipe Ingredients'!$I$2:$I$2500,'Recipe Ingredients'!$A$2:$A$2500,A13)/R13 -> 267.75 | V13: =SUMIFS('Recipe Ingredients'!$J$2:$J$2500,'Recipe Ingredients'!$A$2:$A$2500,A13)/R13 -> 5.864 | W13: =SUMIFS('Recipe Ingredients'!$K$2:$K$2500,'Recipe Ingredients'!$A$2:$A$2500,A13)/R13 -> 113.8385 | X13: =SUMIFS('Recipe Ingredients'!$L$2:$L$2500,'Recipe Ingredients'!$A$2:$A$2500,A13)/R13 -> 7.1225 | Y13: =SUMIFS('Recipe Ingredients'!$M$2:$M$2500,'Recipe Ingredients'!$A$2:$A$2500,A13)/R13 -> 1.73375 | Z13: =SUMIFS('Recipe Ingredients'!$N$2:$N$2500,'Recipe Ingredients'!$A$2:$A$2500,A13)/R13 -> 48.5 | AA13: =SUMIFS('Recipe Ingredients'!$O$2:$O$2500,'Recipe Ingredients'!$A$2:$A$2500,A13)/R13 -> 351.8075 | AB13: =SUMIFS('Recipe Ingredients'!$P$2:$P$2500,'Recipe Ingredients'!$A$2:$A$2500,A13)/R13 -> 0.1415 | AC13: =SUMIFS('Recipe Ingredients'!$Q$2:$Q$2500,'Recipe Ingredients'!$A$2:$A$2500,A13)/R13 -> 0.2739675 | AD13: =SUMIFS('Recipe Ingredients'!$R$2:$R$2500,'Recipe Ingredients'!$A$2:$A$2500,A13)/R13 -> 36.075 | AE13: =SUMIFS('Recipe Ingredients'!$S$2:$S$2500,'Recipe Ingredients'!$A$2:$A$2500,A13)/R13 -> 1.35805 | AF13: =IFERROR(V13/'Start Here'!$C$10,0) -> 0.23456 | AG13: =IFERROR(W13/'Start Here'!$C$11,0) -> 1.4229812 | AH13: =IFERROR(X13/'Start Here'!$C$12,0) -> 0.008903125 | AI13: =IFERROR(Y13/'Start Here'!$C$13,0) -> 0.023116667 | AJ13: =IFERROR(Z13/'Start Here'!$C$14,0) -> 0.2425 | AK13: =IFERROR(AA13/'Start Here'!$C$15,0) -> 0.17590375 | AL13: =IFERROR(AB13/'Start Here'!$C$16,0) -> 0.011791667 | AM13: =IFERROR(AC13/'Start Here'!$C$17,0) -> 0.19569107 | AN13: =IFERROR(AD13/'Start Here'!$C$18,0) -> 0.0962 | AO13: =IFERROR(AE13/'Start Here'!$C$19,0) -> 0.097003571 | AP13: =IFERROR(SUBSTITUTE(INDEX($AF$1:$AO$1,MATCH(MAX(AF13:AO13),AF13:AO13,0))," % daily",""),"") -> Vitamin C | AQ13: =IF(MAX(AF13:AO13)>=0.15,"Best for better "&IF(LEFT(AP13,7)="Vitamin","vitamin "&MID(AP13,9,3),LOWER(AP13))&" intake: one serving gives about "&TEXT(MAX(AF13:AO13),"0%")&" of your daily "&IF(LEFT(AP13,7)="Vitamin","vitamin "&MID(AP13,9,3),LOWER(AP13))&" from the produce alone.","A lighter plate: top nutrient is "&IF(LEFT(AP13,7)="Vitamin","vitamin "&MID(AP13,9,3),LOWER(AP13))&" at about "&TEXT(MAX(AF13:AO13),"0%")&" of a day.") -> Best for better vitamin C intake: one serving gives about 142% of your daily vitamin C from the produce alone. | AR13: =IF(LEN(IF(AND(AF13>=0.25,"Fibre"<>AP13),"Fibre ("&TEXT(AF13,"0%")&")|","")&IF(AND(AG13>=0.25,"Vitamin C"<>AP13),"Vitamin C ("&TEXT(AG13,"0%")&")|","")&IF(AND(AH13>=0.25,"Vitamin A"<>AP13),"Vitamin A ("&TEXT(AH13,"0%")&")|","")&IF(AND(AI13>=0.25,"Vitamin K"<>AP13),"Vitamin K ("&TEXT(AI13,"0%")&")|","")&IF(AND(AJ13>=0.25,"Folate"<>AP13),"Folate ("&TEXT(AJ13,"0%")&")|","")&IF(AND(AK13>=0.25,"Potassium"<>AP13),"Potassium ("&TEXT(AK13,"0%")&")|","")&IF(AND(AL13>=0.25,"Vitamin E"<>AP13),"Vitamin E ("&TEXT(AL13,"0%")&")|","")&IF(AND(AM13>=0.25,"Vitamin B6"<>AP13),"Vitamin B6 ("&TEXT(AM13,"0%")&")|","")&IF(AND(AN13>=0.25,"Magnesium"<>AP13),"Magnesium ("&TEXT(AN13,"0%")&")|","")&IF(AND(AO13>=0.25,"Iron"<>AP13),"Iron ("&TEXT(AO13,"0%")&")|",""))=0,"",SUBSTITUTE(LEFT(IF(AND(AF13>=0.25,"Fibre"<>AP13),"Fibre ("&TEXT(AF13,"0%")&")|","")&IF(AND(AG13>=0.25,"Vitamin C"<>AP13),"Vitamin C ("&TEXT(AG13,"0%")&")|","")&IF(AND(AH13>=0.25,"Vitamin A"<>AP13),"Vitamin A ("&TEXT(AH13,"0%")&")|","")&IF(AND(AI13>=0.25,"Vitamin K"<>AP13),"Vitamin K ("&TEXT(AI13,"0%")&")|","")&IF(AND(AJ13>=0.25,"Folate"<>AP13),"Folate ("&TEXT(AJ13,"0%")&")|","")&IF(AND(AK13>=0.25,"Potassium"<>AP13),"Potassium ("&TEXT(AK13,"0%")&")|","")&IF(AND(AL13>=0.25,"Vitamin E"<>AP13),"Vitamin E ("&TEXT(AL13,"0%")&")|","")&IF(AND(AM13>=0.25,"Vitamin B6"<>AP13),"Vitamin B6 ("&TEXT(AM13,"0%")&")|","")&IF(AND(AN13>=0.25,"Magnesium"<>AP13),"Magnesium ("&TEXT(AN13,"0%")&")|","")&IF(AND(AO13>=0.25,"Iron"<>AP13),"Iron ("&TEXT(AO13,"0%")&")|",""),LEN(IF(AND(AF13>=0.25,"Fibre"<>AP13),"Fibre ("&TEXT(AF13,"0%")&")|","")&IF(AND(AG13>=0.25,"Vitamin C"<>AP13),"Vitamin C ("&TEXT(AG13,"0%")&")|","")&IF(AND(AH13>=0.25,"Vitamin A"<>AP13),"Vitamin A ("&TEXT(AH13,"0%")&")|","")&IF(AND(AI13>=0.25,"Vitamin K"<>AP13),"Vitamin K ("&TEXT(AI13,"0%")&")|","")&IF(AND(AJ13>=0.25,"Folate"<>AP13),"Folate ("&TEXT(AJ13,"0%")&")|","")&IF(AND(AK13>=0.25,"Potassium"<>AP13),"Potassium ("&TEXT(AK13,"0%")&")|","")&IF(AND(AL13>=0.25,"Vitamin E"<>AP13),"Vitamin E ("&TEXT(AL13,"0%")&")|","")&IF(AND(AM13>=0.25,"Vitamin B6"<>AP13),"Vitamin B6 ("&TEXT(AM13,"0%")&")|","")&IF(AND(AN13>=0.25,"Magnesium"<>AP13),"Magnesium ("&TEXT(AN13,"0%")&")|","")&IF(AND(AO13>=0.25,"Iron"<>AP13),"Iron ("&TEXT(AO13,"0%")&")|",""))-1),"|",", ")) | AS13: Pineapple is rich in vitamin C and manganese, and bromelain that helps digest protein. Fresh coconut adds fibre, manganese and satisfying fat. | AT13: Pineapple, Coconut, Lime | AU13: =COUNTIFS('Recipe Ingredients'!$A$2:$A$2500,A13,'Recipe Ingredients'!$G$2:$G$2500,"Basket") -> 3 | AV13: =COUNTIFS('Recipe Ingredients'!$A$2:$A$2500,A13,'Recipe Ingredients'!$G$2:$G$2500,"Protein")+COUNTIFS('Recipe Ingredients'!$A$2:$A$2500,A13,'Recipe Ingredients'!$G$2:$G$2500,"Pantry") -> 2 | AW13: =IFERROR(AU13/(AU13+AV13),0) -> 0.6 | AX13: =IF(AW13>='Start Here'!$C$6,"Yes","No") -> No | AY13: Year-round | AZ13: 1. Cut pineapple into thick wedges. 2. Brush with honey and dust with cinnamon. 3. Grill or pan-sear until caramelised, 3 minutes a side. 4. Toast grated coconut in a dry pan. Scatter over with lime zest. | BB13: Draft
A14: R086 | B14: Mango Coconut Rice Pudding | C14: Fruit Plates & Desserts | D14: Dessert | E14: Dessert | F14: Khao niao mamuang / mango sticky rice (Thailand) | G14: The Wanderlust Kitchen | H14: https://thewanderlustkitchen.com/thai-mango-sticky-rice/ | I14: https://thewanderlustkitchen.com/wp-content/uploads/2021/10/thai-mango-sticky-rice-square-1200-1.jpg | J14: Local rice cooked in fresh coconut milk and sweetened with dates. | K14: You add: rice, coconut milk, sugar. | L14: Wellness | M14: Vegan | N14: 10 | O14: 30 | P14: =N14+O14 -> 40 | Q14: =IF(O14=0,"No-cook",IF(P14<=25,"Quick","Standard")) -> Standard | R14: 4 | S14: 350 | T14: 5 | U14: =SUMIFS('Recipe Ingredients'!$I$2:$I$2500,'Recipe Ingredients'!$A$2:$A$2500,A14)/R14 -> 291 | V14: =SUMIFS('Recipe Ingredients'!$J$2:$J$2500,'Recipe Ingredients'!$A$2:$A$2500,A14)/R14 -> 12.6495 | W14: =SUMIFS('Recipe Ingredients'!$K$2:$K$2500,'Recipe Ingredients'!$A$2:$A$2500,A14)/R14 -> 69.3295 | X14: =SUMIFS('Recipe Ingredients'!$L$2:$L$2500,'Recipe Ingredients'!$A$2:$A$2500,A14)/R14 -> 91.055 | Y14: =SUMIFS('Recipe Ingredients'!$M$2:$M$2500,'Recipe Ingredients'!$A$2:$A$2500,A14)/R14 -> 7.544 | Z14: =SUMIFS('Recipe Ingredients'!$N$2:$N$2500,'Recipe Ingredients'!$A$2:$A$2500,A14)/R14 -> 100.715 | AA14: =SUMIFS('Recipe Ingredients'!$O$2:$O$2500,'Recipe Ingredients'!$A$2:$A$2500,A14)/R14 -> 698.575 | AB14: =SUMIFS('Recipe Ingredients'!$P$2:$P$2500,'Recipe Ingredients'!$A$2:$A$2500,A14)/R14 -> 1.79055 | AC14: =SUMIFS('Recipe Ingredients'!$Q$2:$Q$2500,'Recipe Ingredients'!$A$2:$A$2500,A14)/R14 -> 0.2722675 | AD14: =SUMIFS('Recipe Ingredients'!$R$2:$R$2500,'Recipe Ingredients'!$A$2:$A$2500,A14)/R14 -> 52.575 | AE14: =SUMIFS('Recipe Ingredients'!$S$2:$S$2500,'Recipe Ingredients'!$A$2:$A$2500,A14)/R14 -> 2.852475 | AF14: =IFERROR(V14/'Start Here'!$C$10,0) -> 0.50598 | AG14: =IFERROR(W14/'Start Here'!$C$11,0) -> 0.86661875 | AH14: =IFERROR(X14/'Start Here'!$C$12,0) -> 0.11381875 | AI14: =IFERROR(Y14/'Start Here'!$C$13,0) -> 0.10058667 | AJ14: =IFERROR(Z14/'Start Here'!$C$14,0) -> 0.503575 | AK14: =IFERROR(AA14/'Start Here'!$C$15,0) -> 0.3492875 | AL14: =IFERROR(AB14/'Start Here'!$C$16,0) -> 0.1492125 | AM14: =IFERROR(AC14/'Start Here'!$C$17,0) -> 0.19447679 | AN14: =IFERROR(AD14/'Start Here'!$C$18,0) -> 0.1402 | AO14: =IFERROR(AE14/'Start Here'!$C$19,0) -> 0.20374821 | AP14: =IFERROR(SUBSTITUTE(INDEX($AF$1:$AO$1,MATCH(MAX(AF14:AO14),AF14:AO14,0))," % daily",""),"") -> Vitamin C | AQ14: =IF(MAX(AF14:AO14)>=0.15,"Best for better "&IF(LEFT(AP14,7)="Vitamin","vitamin "&MID(AP14,9,3),LOWER(AP14))&" intake: one serving gives about "&TEXT(MAX(AF14:AO14),"0%")&" of your daily "&IF(LEFT(AP14,7)="Vitamin","vitamin "&MID(AP14,9,3),LOWER(AP14))&" from the produce alone.","A lighter plate: top nutrient is "&IF(LEFT(AP14,7)="Vitamin","vitamin "&MID(AP14,9,3),LOWER(AP14))&" at about "&TEXT(MAX(AF14:AO14),"0%")&" of a day.") -> Best for better vitamin C intake: one serving gives about 87% of your daily vitamin C from the produce alone. | AR14: =IF(LEN(IF(AND(AF14>=0.25,"Fibre"<>AP14),"Fibre ("&TEXT(AF14,"0%")&")|","")&IF(AND(AG14>=0.25,"Vitamin C"<>AP14),"Vitamin C ("&TEXT(AG14,"0%")&")|","")&IF(AND(AH14>=0.25,"Vitamin A"<>AP14),"Vitamin A ("&TEXT(AH14,"0%")&")|","")&IF(AND(AI14>=0.25,"Vitamin K"<>AP14),"Vitamin K ("&TEXT(AI14,"0%")&")|","")&IF(AND(AJ14>=0.25,"Folate"<>AP14),"Folate ("&TEXT(AJ14,"0%")&")|","")&IF(AND(AK14>=0.25,"Potassium"<>AP14),"Potassium ("&TEXT(AK14,"0%")&")|","")&IF(AND(AL14>=0.25,"Vitamin E"<>AP14),"Vitamin E ("&TEXT(AL14,"0%")&")|","")&IF(AND(AM14>=0.25,"Vitamin B6"<>AP14),"Vitamin B6 ("&TEXT(AM14,"0%")&")|","")&IF(AND(AN14>=0.25,"Magnesium"<>AP14),"Magnesium ("&TEXT(AN14,"0%")&")|","")&IF(AND(AO14>=0.25,"Iron"<>AP14),"Iron ("&TEXT(AO14,"0%")&")|",""))=0,"",SUBSTITUTE(LEFT(IF(AND(AF14>=0.25,"Fibre"<>AP14),"Fibre ("&TEXT(AF14,"0%")&")|","")&IF(AND(AG14>=0.25,"Vitamin C"<>AP14),"Vitamin C ("&TEXT(AG14,"0%")&")|","")&IF(AND(AH14>=0.25,"Vitamin A"<>AP14),"Vitamin A ("&TEXT(AH14,"0%")&")|","")&IF(AND(AI14>=0.25,"Vitamin K"<>AP14),"Vitamin K ("&TEXT(AI14,"0%")&")|","")&IF(AND(AJ14>=0.25,"Folate"<>AP14),"Folate ("&TEXT(AJ14,"0%")&")|","")&IF(AND(AK14>=0.25,"Potassium"<>AP14),"Potassium ("&TEXT(AK14,"0%")&")|","")&IF(AND(AL14>=0.25,"Vitamin E"<>AP14),"Vitamin E ("&TEXT(AL14,"0%")&")|","")&IF(AND(AM14>=0.25,"Vitamin B6"<>AP14),"Vitamin B6 ("&TEXT(AM14,"0%")&")|","")&IF(AND(AN14>=0.25,"Magnesium"<>AP14),"Magnesium ("&TEXT(AN14,"0%")&")|","")&IF(AND(AO14>=0.25,"Iron"<>AP14),"Iron ("&TEXT(AO14,"0%")&")|",""),LEN(IF(AND(AF14>=0.25,"Fibre"<>AP14),"Fibre ("&TEXT(AF14,"0%")&")|","")&IF(AND(AG14>=0.25,"Vitamin C"<>AP14),"Vitamin C ("&TEXT(AG14,"0%")&")|","")&IF(AND(AH14>=0.25,"Vitamin A"<>AP14),"Vitamin A ("&TEXT(AH14,"0%")&")|","")&IF(AND(AI14>=0.25,"Vitamin K"<>AP14),"Vitamin K ("&TEXT(AI14,"0%")&")|","")&IF(AND(AJ14>=0.25,"Folate"<>AP14),"Folate ("&TEXT(AJ14,"0%")&")|","")&IF(AND(AK14>=0.25,"Potassium"<>AP14),"Potassium ("&TEXT(AK14,"0%")&")|","")&IF(AND(AL14>=0.25,"Vitamin E"<>AP14),"Vitamin E ("&TEXT(AL14,"0%")&")|","")&IF(AND(AM14>=0.25,"Vitamin B6"<>AP14),"Vitamin B6 ("&TEXT(AM14,"0%")&")|","")&IF(AND(AN14>=0.25,"Magnesium"<>AP14),"Magnesium ("&TEXT(AN14,"0%")&")|","")&IF(AND(AO14>=0.25,"Iron"<>AP14),"Iron ("&TEXT(AO14,"0%")&")|",""))-1),"|",", ")) -> Fibre (51%), Folate (50%), Potassium (35%) | AS14: Fresh coconut adds fibre, manganese and satisfying fat. Mango brings vitamin A (as beta-carotene), vitamin C and folate. | AT14: Coconut, Mango, Dates, Lime | AU14: =COUNTIFS('Recipe Ingredients'!$A$2:$A$2500,A14,'Recipe Ingredients'!$G$2:$G$2500,"Basket") -> 4 | AV14: =COUNTIFS('Recipe Ingredients'!$A$2:$A$2500,A14,'Recipe Ingredients'!$G$2:$G$2500,"Protein")+COUNTIFS('Recipe Ingredients'!$A$2:$A$2500,A14,'Recipe Ingredients'!$G$2:$G$2500,"Pantry") -> 1 | AW14: =IFERROR(AU14/(AU14+AV14),0) -> 0.8 | AX14: =IF(AW14>='Start Here'!$C$6,"Yes","No") -> Yes | AY14: Mango (Feb-May, Aug-Sep) | AZ14: 1. Make coconut milk from the coconut, blending in the dates. 2. Simmer rice in the coconut milk with a pinch of salt, stirring often, for 25 to 30 minutes until creamy. 3. Cool slightly and stir in lime zest. 4. Serve topped with sliced mango. | BA14: Best Feb to May. | BB14: Draft
A15: R088 | B15: No-Churn Mango Passion Sorbet | C15: Fruit Plates & Desserts | D15: Frozen dessert | E15: Dessert | F15: Sorbet (Italy / France) | G15: Inspired by Charm | H15: https://inspiredbycharm.com/mango-sorbet-no-churn-recipe/ | I15: https://inspiredbycharm.com/wp-content/uploads/2022/07/recipe-for-homemade-mango-sorbet.jpg | J15: Ripe local mangoes need almost no sugar. | K15: You add: honey or condensed milk if the mango is not sweet enough. | L15: Wellness | M15: Vegetarian | N15: 15 | O15: 0 | P15: =N15+O15 -> 15 | Q15: =IF(O15=0,"No-cook",IF(P15<=25,"Quick","Standard")) -> No-cook | R15: 4 | S15: 120 | T15: 1 | U15: =SUMIFS('Recipe Ingredients'!$I$2:$I$2500,'Recipe Ingredients'!$A$2:$A$2500,A15)/R15 -> 282.25 | V15: =SUMIFS('Recipe Ingredients'!$J$2:$J$2500,'Recipe Ingredients'!$A$2:$A$2500,A15)/R15 -> 5.905 | W15: =SUMIFS('Recipe Ingredients'!$K$2:$K$2500,'Recipe Ingredients'!$A$2:$A$2500,A15)/R15 -> 100.65225 | X15: =SUMIFS('Recipe Ingredients'!$L$2:$L$2500,'Recipe Ingredients'!$A$2:$A$2500,A15)/R15 -> 145.055 | Y15: =SUMIFS('Recipe Ingredients'!$M$2:$M$2500,'Recipe Ingredients'!$A$2:$A$2500,A15)/R15 -> 10.779 | Z15: =SUMIFS('Recipe Ingredients'!$N$2:$N$2500,'Recipe Ingredients'!$A$2:$A$2500,A15)/R15 -> 111.59 | AA15: =SUMIFS('Recipe Ingredients'!$O$2:$O$2500,'Recipe Ingredients'!$A$2:$A$2500,A15)/R15 -> 487.425 | AB15: =SUMIFS('Recipe Ingredients'!$P$2:$P$2500,'Recipe Ingredients'!$A$2:$A$2500,A15)/R15 -> 2.30755 | AC15: =SUMIFS('Recipe Ingredients'!$Q$2:$Q$2500,'Recipe Ingredients'!$A$2:$A$2500,A15)/R15 -> 0.3205825 | AD15: =SUMIFS('Recipe Ingredients'!$R$2:$R$2500,'Recipe Ingredients'!$A$2:$A$2500,A15)/R15 -> 30.12 | AE15: =SUMIFS('Recipe Ingredients'!$S$2:$S$2500,'Recipe Ingredients'!$A$2:$A$2500,A15)/R15 -> 0.7197 | AF15: =IFERROR(V15/'Start Here'!$C$10,0) -> 0.2362 | AG15: =IFERROR(W15/'Start Here'!$C$11,0) -> 1.2581531 | AH15: =IFERROR(X15/'Start Here'!$C$12,0) -> 0.18131875 | AI15: =IFERROR(Y15/'Start Here'!$C$13,0) -> 0.14372 | AJ15: =IFERROR(Z15/'Start Here'!$C$14,0) -> 0.55795 | AK15: =IFERROR(AA15/'Start Here'!$C$15,0) -> 0.2437125 | AL15: =IFERROR(AB15/'Start Here'!$C$16,0) -> 0.19229583 | AM15: =IFERROR(AC15/'Start Here'!$C$17,0) -> 0.2289875 | AN15: =IFERROR(AD15/'Start Here'!$C$18,0) -> 0.08032 | AO15: =IFERROR(AE15/'Start Here'!$C$19,0) -> 0.051407143 | AP15: =IFERROR(SUBSTITUTE(INDEX($AF$1:$AO$1,MATCH(MAX(AF15:AO15),AF15:AO15,0))," % daily",""),"") -> Vitamin C | AQ15: =IF(MAX(AF15:AO15)>=0.15,"Best for better "&IF(LEFT(AP15,7)="Vitamin","vitamin "&MID(AP15,9,3),LOWER(AP15))&" intake: one serving gives about "&TEXT(MAX(AF15:AO15),"0%")&" of your daily "&IF(LEFT(AP15,7)="Vitamin","vitamin "&MID(AP15,9,3),LOWER(AP15))&" from the produce alone.","A lighter plate: top nutrient is "&IF(LEFT(AP15,7)="Vitamin","vitamin "&MID(AP15,9,3),LOWER(AP15))&" at about "&TEXT(MAX(AF15:AO15),"0%")&" of a day.") -> Best for better vitamin C intake: one serving gives about 126% of your daily vitamin C from the produce alone. | AR15: =IF(LEN(IF(AND(AF15>=0.25,"Fibre"<>AP15),"Fibre ("&TEXT(AF15,"0%")&")|","")&IF(AND(AG15>=0.25,"Vitamin C"<>AP15),"Vitamin C ("&TEXT(AG15,"0%")&")|","")&IF(AND(AH15>=0.25,"Vitamin A"<>AP15),"Vitamin A ("&TEXT(AH15,"0%")&")|","")&IF(AND(AI15>=0.25,"Vitamin K"<>AP15),"Vitamin K ("&TEXT(AI15,"0%")&")|","")&IF(AND(AJ15>=0.25,"Folate"<>AP15),"Folate ("&TEXT(AJ15,"0%")&")|","")&IF(AND(AK15>=0.25,"Potassium"<>AP15),"Potassium ("&TEXT(AK15,"0%")&")|","")&IF(AND(AL15>=0.25,"Vitamin E"<>AP15),"Vitamin E ("&TEXT(AL15,"0%")&")|","")&IF(AND(AM15>=0.25,"Vitamin B6"<>AP15),"Vitamin B6 ("&TEXT(AM15,"0%")&")|","")&IF(AND(AN15>=0.25,"Magnesium"<>AP15),"Magnesium ("&TEXT(AN15,"0%")&")|","")&IF(AND(AO15>=0.25,"Iron"<>AP15),"Iron ("&TEXT(AO15,"0%")&")|",""))=0,"",SUBSTITUTE(LEFT(IF(AND(AF15>=0.25,"Fibre"<>AP15),"Fibre ("&TEXT(AF15,"0%")&")|","")&IF(AND(AG15>=0.25,"Vitamin C"<>AP15),"Vitamin C ("&TEXT(AG15,"0%")&")|","")&IF(AND(AH15>=0.25,"Vitamin A"<>AP15),"Vitamin A ("&TEXT(AH15,"0%")&")|","")&IF(AND(AI15>=0.25,"Vitamin K"<>AP15),"Vitamin K ("&TEXT(AI15,"0%")&")|","")&IF(AND(AJ15>=0.25,"Folate"<>AP15),"Folate ("&TEXT(AJ15,"0%")&")|","")&IF(AND(AK15>=0.25,"Potassium"<>AP15),"Potassium ("&TEXT(AK15,"0%")&")|","")&IF(AND(AL15>=0.25,"Vitamin E"<>AP15),"Vitamin E ("&TEXT(AL15,"0%")&")|","")&IF(AND(AM15>=0.25,"Vitamin B6"<>AP15),"Vitamin B6 ("&TEXT(AM15,"0%")&")|","")&IF(AND(AN15>=0.25,"Magnesium"<>AP15),"Magnesium ("&TEXT(AN15,"0%")&")|","")&IF(AND(AO15>=0.25,"Iron"<>AP15),"Iron ("&TEXT(AO15,"0%")&")|",""),LEN(IF(AND(AF15>=0.25,"Fibre"<>AP15),"Fibre ("&TEXT(AF15,"0%")&")|","")&IF(AND(AG15>=0.25,"Vitamin C"<>AP15),"Vitamin C ("&TEXT(AG15,"0%")&")|","")&IF(AND(AH15>=0.25,"Vitamin A"<>AP15),"Vitamin A ("&TEXT(AH15,"0%")&")|","")&IF(AND(AI15>=0.25,"Vitamin K"<>AP15),"Vitamin K ("&TEXT(AI15,"0%")&")|","")&IF(AND(AJ15>=0.25,"Folate"<>AP15),"Folate ("&TEXT(AJ15,"0%")&")|","")&IF(AND(AK15>=0.25,"Potassium"<>AP15),"Potassium ("&TEXT(AK15,"0%")&")|","")&IF(AND(AL15>=0.25,"Vitamin E"<>AP15),"Vitamin E ("&TEXT(AL15,"0%")&")|","")&IF(AND(AM15>=0.25,"Vitamin B6"<>AP15),"Vitamin B6 ("&TEXT(AM15,"0%")&")|","")&IF(AND(AN15>=0.25,"Magnesium"<>AP15),"Magnesium ("&TEXT(AN15,"0%")&")|","")&IF(AND(AO15>=0.25,"Iron"<>AP15),"Iron ("&TEXT(AO15,"0%")&")|",""))-1),"|",", ")) -> Folate (56%) | AS15: Mango brings vitamin A (as beta-carotene), vitamin C and folate. Passion fruit is high in fibre and vitamin A and C. | AT15: Mango, Passion fruit, Lime | AU15: =COUNTIFS('Recipe Ingredients'!$A$2:$A$2500,A15,'Recipe Ingredients'!$G$2:$G$2500,"Basket") -> 3 | AV15: =COUNTIFS('Recipe Ingredients'!$A$2:$A$2500,A15,'Recipe Ingredients'!$G$2:$G$2500,"Protein")+COUNTIFS('Recipe Ingredients'!$A$2:$A$2500,A15,'Recipe Ingredients'!$G$2:$G$2500,"Pantry") -> 1 | AW15: =IFERROR(AU15/(AU15+AV15),0) -> 0.75 | AX15: =IF(AW15>='Start Here'!$C$6,"Yes","No") -> No | AY15: Mango (Feb-May, Aug-Sep); Passion fruit (Jan-Mar, May-Jun, Aug-Nov) | AZ15: 1. Peel and cube mangoes and freeze for 4 hours. 2. Blend frozen mango with passion fruit pulp, lime and honey until smooth. 3. Serve soft, or freeze 1 hour for scoops. | BA15: Best Feb to May. | BB15: Draft
A16: R025 | B16: Garden Egg Chopped Salad | C16: Salads & Cooked Sides | D16: Salad | E16: Lunch / Side | F16: Shirazi / Israeli chopped salad | G16: Saveur | H16: https://www.saveur.com/article/Recipes/Israeli-Chopped-Salad/ | I16: https://www.saveur.com/uploads/2019/03/18/VEJGMTPDVYRJWH2QBJJJBROTRI.jpg?auto=webp | J16: Raw garden egg adds a crunchy, slightly bitter bite. | K16: Side for grilled chicken, fish, jollof or fried rice. You add: oil, lemon, salt. | L16: Weight management, Wellness | M16: Vegan | N16: 15 | O16: 0 | P16: =N16+O16 -> 15 | Q16: =IF(O16=0,"No-cook",IF(P16<=25,"Quick","Standard")) -> No-cook | R16: 2 | S16: 140 | T16: 3 | U16: =SUMIFS('Recipe Ingredients'!$I$2:$I$2500,'Recipe Ingredients'!$A$2:$A$2500,A16)/R16 -> 392.5 | V16: =SUMIFS('Recipe Ingredients'!$J$2:$J$2500,'Recipe Ingredients'!$A$2:$A$2500,A16)/R16 -> 6.3605 | W16: =SUMIFS('Recipe Ingredients'!$K$2:$K$2500,'Recipe Ingredients'!$A$2:$A$2500,A16)/R16 -> 60.265 | X16: =SUMIFS('Recipe Ingredients'!$L$2:$L$2500,'Recipe Ingredients'!$A$2:$A$2500,A16)/R16 -> 101.1 | Y16: =SUMIFS('Recipe Ingredients'!$M$2:$M$2500,'Recipe Ingredients'!$A$2:$A$2500,A16)/R16 -> 239.939 | Z16: =SUMIFS('Recipe Ingredients'!$N$2:$N$2500,'Recipe Ingredients'!$A$2:$A$2500,A16)/R16 -> 69.5 | AA16: =SUMIFS('Recipe Ingredients'!$O$2:$O$2500,'Recipe Ingredients'!$A$2:$A$2500,A16)/R16 -> 783.065 | AB16: =SUMIFS('Recipe Ingredients'!$P$2:$P$2500,'Recipe Ingredients'!$A$2:$A$2500,A16)/R16 -> 0.9301 | AC16: =SUMIFS('Recipe Ingredients'!$Q$2:$Q$2500,'Recipe Ingredients'!$A$2:$A$2500,A16)/R16 -> 0.26605 | AD16: =SUMIFS('Recipe Ingredients'!$R$2:$R$2500,'Recipe Ingredients'!$A$2:$A$2500,A16)/R16 -> 53.115 | AE16: =SUMIFS('Recipe Ingredients'!$S$2:$S$2500,'Recipe Ingredients'!$A$2:$A$2500,A16)/R16 -> 2.07925 | AF16: =IFERROR(V16/'Start Here'!$C$10,0) -> 0.25442 | AG16: =IFERROR(W16/'Start Here'!$C$11,0) -> 0.7533125 | AH16: =IFERROR(X16/'Start Here'!$C$12,0) -> 0.126375 | AI16: =IFERROR(Y16/'Start Here'!$C$13,0) -> 3.1991867 | AJ16: =IFERROR(Z16/'Start Here'!$C$14,0) -> 0.3475 | AK16: =IFERROR(AA16/'Start Here'!$C$15,0) -> 0.3915325 | AL16: =IFERROR(AB16/'Start Here'!$C$16,0) -> 0.077508333 | AM16: =IFERROR(AC16/'Start Here'!$C$17,0) -> 0.19003571 | AN16: =IFERROR(AD16/'Start Here'!$C$18,0) -> 0.14164 | AO16: =IFERROR(AE16/'Start Here'!$C$19,0) -> 0.14851786 | AP16: =IFERROR(SUBSTITUTE(INDEX($AF$1:$AO$1,MATCH(MAX(AF16:AO16),AF16:AO16,0))," % daily",""),"") -> Vitamin K | AQ16: =IF(MAX(AF16:AO16)>=0.15,"Best for better "&IF(LEFT(AP16,7)="Vitamin","vitamin "&MID(AP16,9,3),LOWER(AP16))&" intake: one serving gives about "&TEXT(MAX(AF16:AO16),"0%")&" of your daily "&IF(LEFT(AP16,7)="Vitamin","vitamin "&MID(AP16,9,3),LOWER(AP16))&" from the produce alone.","A lighter plate: top nutrient is "&IF(LEFT(AP16,7)="Vitamin","vitamin "&MID(AP16,9,3),LOWER(AP16))&" at about "&TEXT(MAX(AF16:AO16),"0%")&" of a day.") -> Best for better vitamin K intake: one serving gives about 320% of your daily vitamin K from the produce alone. | AR16: =IF(LEN(IF(AND(AF16>=0.25,"Fibre"<>AP16),"Fibre ("&TEXT(AF16,"0%")&")|","")&IF(AND(AG16>=0.25,"Vitamin C"<>AP16),"Vitamin C ("&TEXT(AG16,"0%")&")|","")&IF(AND(AH16>=0.25,"Vitamin A"<>AP16),"Vitamin A ("&TEXT(AH16,"0%")&")|","")&IF(AND(AI16>=0.25,"Vitamin K"<>AP16),"Vitamin K ("&TEXT(AI16,"0%")&")|","")&IF(AND(AJ16>=0.25,"Folate"<>AP16),"Folate ("&TEXT(AJ16,"0%")&")|","")&IF(AND(AK16>=0.25,"Potassium"<>AP16),"Potassium ("&TEXT(AK16,"0%")&")|","")&IF(AND(AL16>=0.25,"Vitamin E"<>AP16),"Vitamin E ("&TEXT(AL16,"0%")&")|","")&IF(AND(AM16>=0.25,"Vitamin B6"<>AP16),"Vitamin B6 ("&TEXT(AM16,"0%")&")|","")&IF(AND(AN16>=0.25,"Magnesium"<>AP16),"Magnesium ("&TEXT(AN16,"0%")&")|","")&IF(AND(AO16>=0.25,"Iron"<>AP16),"Iron ("&TEXT(AO16,"0%")&")|",""))=0,"",SUBSTITUTE(LEFT(IF(AND(AF16>=0.25,"Fibre"<>AP16),"Fibre ("&TEXT(AF16,"0%")&")|","")&IF(AND(AG16>=0.25,"Vitamin C"<>AP16),"Vitamin C ("&TEXT(AG16,"0%")&")|","")&IF(AND(AH16>=0.25,"Vitamin A"<>AP16),"Vitamin A ("&TEXT(AH16,"0%")&")|","")&IF(AND(AI16>=0.25,"Vitamin K"<>AP16),"Vitamin K ("&TEXT(AI16,"0%")&")|","")&IF(AND(AJ16>=0.25,"Folate"<>AP16),"Folate ("&TEXT(AJ16,"0%")&")|","")&IF(AND(AK16>=0.25,"Potassium"<>AP16),"Potassium ("&TEXT(AK16,"0%")&")|","")&IF(AND(AL16>=0.25,"Vitamin E"<>AP16),"Vitamin E ("&TEXT(AL16,"0%")&")|","")&IF(AND(AM16>=0.25,"Vitamin B6"<>AP16),"Vitamin B6 ("&TEXT(AM16,"0%")&")|","")&IF(AND(AN16>=0.25,"Magnesium"<>AP16),"Magnesium ("&TEXT(AN16,"0%")&")|","")&IF(AND(AO16>=0.25,"Iron"<>AP16),"Iron ("&TEXT(AO16,"0%")&")|",""),LEN(IF(AND(AF16>=0.25,"Fibre"<>AP16),"Fibre ("&TEXT(AF16,"0%")&")|","")&IF(AND(AG16>=0.25,"Vitamin C"<>AP16),"Vitamin C ("&TEXT(AG16,"0%")&")|","")&IF(AND(AH16>=0.25,"Vitamin A"<>AP16),"Vitamin A ("&TEXT(AH16,"0%")&")|","")&IF(AND(AI16>=0.25,"Vitamin K"<>AP16),"Vitamin K ("&TEXT(AI16,"0%")&")|","")&IF(AND(AJ16>=0.25,"Folate"<>AP16),"Folate ("&TEXT(AJ16,"0%")&")|","")&IF(AND(AK16>=0.25,"Potassium"<>AP16),"Potassium ("&TEXT(AK16,"0%")&")|","")&IF(AND(AL16>=0.25,"Vitamin E"<>AP16),"Vitamin E ("&TEXT(AL16,"0%")&")|","")&IF(AND(AM16>=0.25,"Vitamin B6"<>AP16),"Vitamin B6 ("&TEXT(AM16,"0%")&")|","")&IF(AND(AN16>=0.25,"Magnesium"<>AP16),"Magnesium ("&TEXT(AN16,"0%")&")|","")&IF(AND(AO16>=0.25,"Iron"<>AP16),"Iron ("&TEXT(AO16,"0%")&")|",""))-1),"|",", ")) -> Fibre (25%), Vitamin C (75%), Folate (35%), Potassium (39%) | AS16: Garden egg is high in fibre and potassium and very low in calories. Tomatoes bring vitamin C and lycopene; cooking them in a little oil makes the lycopene easier to absorb. | AT16: Garden egg, Tomato, Cucumber, Onion | AU16: =COUNTIFS('Recipe Ingredients'!$A$2:$A$2500,A16,'Recipe Ingredients'!$G$2:$G$2500,"Basket") -> 6 | AV16: =COUNTIFS('Recipe Ingredients'!$A$2:$A$2500,A16,'Recipe Ingredients'!$G$2:$G$2500,"Protein")+COUNTIFS('Recipe Ingredients'!$A$2:$A$2500,A16,'Recipe Ingredients'!$G$2:$G$2500,"Pantry") -> 0 | AW16: =IFERROR(AU16/(AU16+AV16),0) -> 1 | AX16: =IF(AW16>='Start Here'!$C$6,"Yes","No") -> Yes | AY16: Garden egg (Jan-Oct) | AZ16: 1. Dice garden eggs, tomatoes, cucumber and onion into small even pieces. 2. Chop the parsley. 3. Dress with lemon juice, olive oil and salt. 4. Rest 5 minutes before serving. | BA16: Scent leaf instead of parsley gives it a distinctly Nigerian finish. | BB16: Draft
