Workbook

Sheet Start Here
B2: Basket: Produce & Recipe Library
B3: Nigerian-market produce catalogue, seasonal calendar and 75 global recipes adapted to local ingredients. Research compiled 11 Oct 2026.
B5: Settings
B6: Basket coverage target | C6: 0.8 | D6: Share of a recipe's non-staple ingredients that should come from Basket. Set at 80% from the positioning brief. Change it and every recipe re-scores.
B8: At a glance
B9: Produce items catalogued | C9: =COUNTA(Produce!A2:A500)
B10: Recipes | C10: =COUNTA(Recipes!A2:A500)
B11: Recipes hitting the coverage target | C11: =COUNTIF(Recipes!T2:T500,"Yes")
B12: Average Basket coverage | C12: =AVERAGE(Recipes!S2:S500)
B13: Produce in season this month | C13: =COUNTIF(Produce!J2:J500,"Peak")+COUNTIF(Produce!J2:J500,"In")
B14: Produce at peak this month | C14: =COUNTIF(Produce!J2:J500,"Peak")
B15: Eat-as-is-only fruits (seasonal drops) | C15: =COUNTIF(Produce!F2:F500,"Eat as-is only")
B16: Vegan / plant-based recipes | C16: =COUNTIF(Recipes!H2:H500,"Vegan")
B17: No-cook recipes | C17: =COUNTIF(Recipes!L2:L500,"No-cook")
B19: What's in each tab
B20: Produce | C20: Every fruit, vegetable, herb and nut worth stocking: local names, origin, season, role (eat as-is / recipes), sell unit, competitor benchmark price, storage, sourcing region, launch tier, and how many recipes use it.
B21: Seasonal Calendar | C21: Month-by-month availability. Peak and In-season cells are colour coded. The Produce tab reads this to show what is in season today.
B22: Recipes | C22: 75 recipes (no drinks): the global dish each is based on, what changed for Nigeria, goal and diet tags, timings, effort tier, estimated nutrition, method, and Basket coverage scored by formula.
B23: Recipe Ingredients | C23: One row per ingredient with quantity, unit and source (Basket / Protein / Pantry / Staple). This is the table the coverage scores and recipe counts are built on. Add or edit rows here.
B24: Box Ideas | C24: Seasonal drops and themed baskets built from the catalogue, each linked to the recipes it unlocks.
B25: Market Scan | C25: What the Lagos players and the four international meal kits do, what to borrow, and the gap Basket can own.
B26: Sources | C26: Every site and document used.
B28: How to edit
B29: Yellow cells | C29: Your inputs: coverage target, Basket price, Stock it?, and recipe Status. Everything else updates from them.
B30: Add a recipe | C30: Add a row on Recipes (copy the formulas in Q to T down), then add its ingredients on Recipe Ingredients with the same Recipe ID. Put the Produce ID in column F for anything Basket sells.
B31: Add produce | C31: Add a row on Produce and a matching row on Seasonal Calendar with the same ID. Mark months 'Peak' or 'In'.
B32: Source column | C32: Basket = produce we sell. Protein and Pantry count against coverage. Staple (salt, oil, water, ice, pepper) is ignored.
B34: Key findings
B35: • Lagos online produce splits two ways: raw grocery (Mint Foods, Home Basket, SwanCape) and finished health products (The Fresh Place juices at N3,500 to N4,500, salad trays at N30,000 to N50,000). Nobody connects raw produce to light, global recipes. That is the lane this library is built for.
B36: • SwanCape already turns a dish into a priced ingredient list, but only for Egusi, Jollof, Ogbono, Pepper soup and Efo riro. The recipe library here deliberately avoids competing on traditional soups.
B37: • Local vs imported is the biggest price lever. Mint Foods lists 4 local lemons at N1,900 and 5 Dutch lemons at N13,800. Local cauliflower N2,750 a head vs imported N16,900. Recipes default to local produce; imported items are premium add-ons.
B38: • Seasonality creates natural drops: agbalumo Dec-May, mango Feb-May, citrus best Oct-Jan, fresh corn Apr-Aug, ube May-Sep, guava Feb-Mar and Aug-Sep (Kitchen Butterfly calendar).
B39: • Meal-kit playbook worth copying: goal menus (HelloFresh), effort tiers and swaps (Home Chef), seasonal editorial and diet filters (Marley Spoon), part-prepped produce (Sunbasket). Every recipe here carries goal, diet and effort tags so the app can filter the same way.
B41: Caveats
B42: • Calories and protein are rough per-serving estimates for filtering and planning. Get them checked before publishing numbers in the app.
B43: • Season confidence: 'Sourced' rows come from the Kitchen Butterfly Nigerian Seasonal Produce Calendar (V1.3). 'Verify' rows are general market knowledge. Confirm both with your suppliers in the pilot.
B44: • Benchmark prices are competitor retail prices captured on 11 Oct 2026, not wholesale cost. Only items with a published price have one. Basket price is left for you to fill.
B45: • Freshcart.ng blocked automated access and has no indexed pages, so it is not in the scan. Home Basket's catalogue loads client-side, so only its positioning was captured.

Sheet Produce
A1: ID | B1: Produce | C1: Local names | D1: Category | E1: Origin | F1: Role | G1: Availability | H1: Season | I1: Peak | J1: In season now? | K1: Season confidence | L1: Sell unit | M1: Benchmark price (N) | N1: Benchmark unit | O1: Benchmark source | P1: Basket price (N) | Q1: Stock it? | R1: Launch tier | S1: Used in # recipes | T1: Storage | U1: Shelf life | V1: Sourcing region | W1: Best for | X1: Notes
A2: P001 | B2: Banana | C2: Ogede wewe (Yor), Ayaba (Hau) | D2: Fruit | E2: Local | F2: Eat as-is + recipes | G2: Year-round | H2: All year | J2: =IFERROR(IF(INDEX('Seasonal Calendar'!$C$2:$N$500,MATCH(A2,'Seasonal Calendar'!$A$2:$A$500,0),MONTH(TODAY()))="","Out",INDEX('Seasonal Calendar'!$C$2:$N$500,MATCH(A2,'Seasonal Calendar'!$A$2:$A$500,0),MONTH(TODAY()))),"") | K2: Verify | L2: Hand (~1kg) | M2: 1850 | N2: 1kg | O2: The Fresh Place (thefreshplace.ng), 17 Oct 2026 | Q2: Y | R2: Core | S2: =COUNTIF('Recipe Ingredients'!$F$2:$F$2000,A2) | T2: Room temp; fridge once fully ripe (skin darkens, flesh holds) | U2: 3-5 days | V2: Ondo, Ogun, Cross River, Edo | W2: Training, Energy | X2: Most-used fruit in the recipe library. Sell spotty, very ripe bananas as discounted 'smoothie bananas' rather than writing them off.
A3: P002 | B3: Plantain (ripe & unripe) | C3: Ogede agbagba (Yor), Agade (Hau) | D3: Fruit (cooking) | E3: Local | F3: Recipe ingredient | G3: Year-round | H3: All year | J3: =IFERROR(IF(INDEX('Seasonal Calendar'!$C$2:$N$500,MATCH(A3,'Seasonal Calendar'!$A$2:$A$500,0),MONTH(TODAY()))="","Out",INDEX('Seasonal Calendar'!$C$2:$N$500,MATCH(A3,'Seasonal Calendar'!$A$2:$A$500,0),MONTH(TODAY()))),"") | K3: Verify | L3: Finger / bunch | Q3: Y | R3: Core | S3: =COUNTIF('Recipe Ingredients'!$F$2:$F$2000,A3) | T3: Room temp; ripens in 3-6 days | U3: 5-10 days | V3: Ondo, Edo, Ogun, Cross River | W3: Training, Energy | X3: Sell by ripeness stage (green, yellow, black-spotted) so recipes get the right one.
A4: P003 | B4: Pineapple | C4: Ope oyinbo (Yor), Abarba (Hau) | D4: Fruit | E4: Local | F4: Eat as-is + recipes | G4: Year-round | H4: All year | J4: =IFERROR(IF(INDEX('Seasonal Calendar'!$C$2:$N$500,MATCH(A4,'Seasonal Calendar'!$A$2:$A$500,0),MONTH(TODAY()))="","Out",INDEX('Seasonal Calendar'!$C$2:$N$500,MATCH(A4,'Seasonal Calendar'!$A$2:$A$500,0),MONTH(TODAY()))),"") | K4: Verify | L4: Piece | M4: 2000 | N4: 1 pc (Cotonou pineapple) | O4: The Fresh Place (thefreshplace.ng), 17 Oct 2026; Bendel pineapple N3,000/pc | Q4: Y | R4: Core | S4: =COUNTIF('Recipe Ingredients'!$F$2:$F$2000,A4) | T4: Room temp until fragrant; fridge once cut | U4: 3-5 days whole, 3 days cut | V4: Edo (Bendel), Ogun, Oyo, Delta | W4: Hydration, Wellness | X4: Bendel and sugarloaf types are sweeter than imported. Price gap between sellers is wide (N1,300 vs N3,000).
A5: P004 | B5: Watermelon | C5: Bara (Yor), Kankana (Hau) | D5: Fruit | E5: Local | F5: Eat as-is + recipes | G5: Year-round | H5: All year | I5: Dec-Apr | J5: =IFERROR(IF(INDEX('Seasonal Calendar'!$C$2:$N$500,MATCH(A5,'Seasonal Calendar'!$A$2:$A$500,0),MONTH(TODAY()))="","Out",INDEX('Seasonal Calendar'!$C$2:$N$500,MATCH(A5,'Seasonal Calendar'!$A$2:$A$500,0),MONTH(TODAY()))),"") | K5: Verify | L5: Piece (S/M/L) or half | M5: 5500 | N5: 1 pc (size not stated) | O5: The Fresh Place (thefreshplace.ng), 17 Oct 2026 | Q5: Y | R5: Core | S5: =COUNTIF('Recipe Ingredients'!$F$2:$F$2000,A5) | T5: Whole at room temp; cut in fridge, wrapped | U5: 1-2 weeks whole, 3 days cut | V5: Kano, Kaduna, Jigawa, Plateau | W5: Hydration, Weight management | X5: Listed by Kitchen Butterfly as available all year; northern supply heaviest in the dry season.
A6: P005 | B6: Pawpaw (papaya) | C6: Ibepe (Yor), Gwanda (Hau) | D6: Fruit | E6: Local | F6: Eat as-is + recipes | G6: Year-round | H6: All year | J6: =IFERROR(IF(INDEX('Seasonal Calendar'!$C$2:$N$500,MATCH(A6,'Seasonal Calendar'!$A$2:$A$500,0),MONTH(TODAY()))="","Out",INDEX('Seasonal Calendar'!$C$2:$N$500,MATCH(A6,'Seasonal Calendar'!$A$2:$A$500,0),MONTH(TODAY()))),"") | K6: Verify | L6: Piece | M6: 3000 | N6: 1 pc | O6: The Fresh Place (thefreshplace.ng), 17 Oct 2026; listed out of stock | Q6: Y | R6: Core | S6: =COUNTIF('Recipe Ingredients'!$F$2:$F$2000,A6) | T6: Ripen at room temp; fridge when soft | U6: 2-4 days ripe | V6: Nationwide | W6: Gut health, Weight management | X6: Unripe (green) pawpaw is a recipe ingredient too (green papaya salad).
A7: P006 | B7: Mango | C7: Mangoro (Yor/Hau) | D7: Fruit | E7: Local | F7: Eat as-is + recipes | G7: Seasonal | H7: Feb-May, Aug-Sep | I7: Mar-Apr | J7: =IFERROR(IF(INDEX('Seasonal Calendar'!$C$2:$N$500,MATCH(A7,'Seasonal Calendar'!$A$2:$A$500,0),MONTH(TODAY()))="","Out",INDEX('Seasonal Calendar'!$C$2:$N$500,MATCH(A7,'Seasonal Calendar'!$A$2:$A$500,0),MONTH(TODAY()))),"") | K7: Sourced | L7: Piece / 1kg | M7: 500 | N7: 1 pc (cherry mango) | O7: The Fresh Place (thefreshplace.ng), 17 Oct 2026; listed out of stock | Q7: Seasonal | R7: Seasonal drop | S7: =COUNTIF('Recipe Ingredients'!$F$2:$F$2000,A7) | T7: Room temp to ripen; fridge when ripe | U7: 3-5 days ripe | V7: Oyo (Ogbomoso), Benue, Kaduna, Niger | W7: Energy, Wellness | X7: Main season Feb-May with a smaller Aug-Sep run. Varieties worth naming on the app: Ogbomoso, Julie, cherry, 'German'.
A8: P007 | B8: Orange | C8: Osan (Yor), Oroma (Igbo), Lemu (Hau) | D8: Fruit (citrus) | E8: Local + imported | F8: Eat as-is + recipes | G8: Year-round | H8: All year | I8: Oct-Jan | J8: =IFERROR(IF(INDEX('Seasonal Calendar'!$C$2:$N$500,MATCH(A8,'Seasonal Calendar'!$A$2:$A$500,0),MONTH(TODAY()))="","Out",INDEX('Seasonal Calendar'!$C$2:$N$500,MATCH(A8,'Seasonal Calendar'!$A$2:$A$500,0),MONTH(TODAY()))),"") | K8: Sourced | L8: Piece / dozen | M8: 200 | N8: 1 pc local | O8: The Fresh Place (thefreshplace.ng), 17 Oct 2026; local dozen N2,400; imported N950/pc, N10,800/dozen | Q8: Y | R8: Core | S8: =COUNTIF('Recipe Ingredients'!$F$2:$F$2000,A8) | T8: Room temp 1 week; fridge 2-3 weeks | U8: 1-3 weeks | V8: Benue (citrus belt), Ogun, Oyo | W8: Wellness, Hydration | X8: Available all year with varying quality; best fruit Oct-Dec per Kitchen Butterfly.
A9: P008 | B9: Tangerine | D9: Fruit (citrus) | E9: Local + imported | F9: Eat as-is + recipes | G9: Year-round | H9: All year | I9: Oct-Jan | J9: =IFERROR(IF(INDEX('Seasonal Calendar'!$C$2:$N$500,MATCH(A9,'Seasonal Calendar'!$A$2:$A$500,0),MONTH(TODAY()))="","Out",INDEX('Seasonal Calendar'!$C$2:$N$500,MATCH(A9,'Seasonal Calendar'!$A$2:$A$500,0),MONTH(TODAY()))),"") | K9: Sourced | L9: Piece | M9: 300 | N9: 1 pc local | O9: The Fresh Place (thefreshplace.ng), 17 Oct 2026; listed out of stock; imported clementine N850/pc, N10,800/dozen | Q9: Y | R9: Core | S9: =COUNTIF('Recipe Ingredients'!$F$2:$F$2000,A9) | T9: Room temp 1 week; fridge 2 weeks | U9: 1-2 weeks | V9: Benue, Ogun | W9: Wellness | X9: Local vs imported price is nearly 3x.
A10: P009 | B10: Lemon | D10: Fruit (citrus) | E10: Local + imported | F10: Recipe ingredient | G10: Year-round | H10: All year | I10: Oct-Jan | J10: =IFERROR(IF(INDEX('Seasonal Calendar'!$C$2:$N$500,MATCH(A10,'Seasonal Calendar'!$A$2:$A$500,0),MONTH(TODAY()))="","Out",INDEX('Seasonal Calendar'!$C$2:$N$500,MATCH(A10,'Seasonal Calendar'!$A$2:$A$500,0),MONTH(TODAY()))),"") | K10: Verify | L10: Piece | M10: 300 | N10: 1 pc local | O10: The Fresh Place (thefreshplace.ng), 17 Oct 2026; local dozen N4,800; imported N950/pc, N10,200/dozen | Q10: Y | R10: Core | S10: =COUNTIF('Recipe Ingredients'!$F$2:$F$2000,A10) | T10: Fridge | U10: 2-3 weeks | V10: Benue, Plateau | W10: Wellness | X10: Used in more recipes than almost anything else. Strong case for local-only.
A11: P010 | B11: Lime | C11: Osan wewe (Yor) | D11: Fruit (citrus) | E11: Local | F11: Recipe ingredient | G11: Year-round | H11: All year | I11: Oct-Jan | J11: =IFERROR(IF(INDEX('Seasonal Calendar'!$C$2:$N$500,MATCH(A11,'Seasonal Calendar'!$A$2:$A$500,0),MONTH(TODAY()))="","Out",INDEX('Seasonal Calendar'!$C$2:$N$500,MATCH(A11,'Seasonal Calendar'!$A$2:$A$500,0),MONTH(TODAY()))),"") | K11: Sourced | L11: Piece / pack of 4 | Q11: Y | R11: Core | S11: =COUNTIF('Recipe Ingredients'!$F$2:$F$2000,A11) | T11: Fridge | U11: 2-3 weeks | V11: Benue, Ogun, Oyo | W11: Wellness | X11: Best fruit Oct-Dec (Kitchen Butterfly). Workhorse acid for salsas, dressings and drinks.
A12: P011 | B12: Grapefruit | D12: Fruit (citrus) | E12: Local | F12: Eat as-is + recipes | G12: Year-round | H12: All year | I12: Oct-Jan | J12: =IFERROR(IF(INDEX('Seasonal Calendar'!$C$2:$N$500,MATCH(A12,'Seasonal Calendar'!$A$2:$A$500,0),MONTH(TODAY()))="","Out",INDEX('Seasonal Calendar'!$C$2:$N$500,MATCH(A12,'Seasonal Calendar'!$A$2:$A$500,0),MONTH(TODAY()))),"") | K12: Verify | L12: Piece | Q12: N | R12: Later | S12: =COUNTIF('Recipe Ingredients'!$F$2:$F$2000,A12) | T12: Room temp / fridge | U12: 2-3 weeks | V12: Benue | W12: Weight management | X12: Niche but cheap locally. Good add-on for citrus boxes.
A13: P012 | B13: Avocado | C13: Pia (Yor) | D13: Fruit | E13: Local + imported | F13: Eat as-is + recipes | G13: Year-round | H13: All year | J13: =IFERROR(IF(INDEX('Seasonal Calendar'!$C$2:$N$500,MATCH(A13,'Seasonal Calendar'!$A$2:$A$500,0),MONTH(TODAY()))="","Out",INDEX('Seasonal Calendar'!$C$2:$N$500,MATCH(A13,'Seasonal Calendar'!$A$2:$A$500,0),MONTH(TODAY()))),"") | K13: Verify | L13: Piece | M13: 2000 | N13: 1 pc medium | O13: The Fresh Place (thefreshplace.ng), 17 Oct 2026; big N2,500, listed out of stock | Q13: Y | R13: Core | S13: =COUNTIF('Recipe Ingredients'!$F$2:$F$2000,A13) | T13: Room temp to ripen; fridge once ripe | U13: 2-3 days ripe | V13: Southwest, Cross River, Plateau | W13: Training, Wellness | X13: Local supply and quality swing through the year. Confirm local peak months with suppliers. Mint sells a ready-to-eat 'eat me' pack, worth copying.
A14: P013 | B14: Guava | C14: Gova (Yor), Gwaba (Hau) | D14: Fruit | E14: Local + imported | F14: Eat as-is + recipes | G14: Seasonal | H14: Feb-Mar, Aug-Sep | I14: Feb-Mar | J14: =IFERROR(IF(INDEX('Seasonal Calendar'!$C$2:$N$500,MATCH(A14,'Seasonal Calendar'!$A$2:$A$500,0),MONTH(TODAY()))="","Out",INDEX('Seasonal Calendar'!$C$2:$N$500,MATCH(A14,'Seasonal Calendar'!$A$2:$A$500,0),MONTH(TODAY()))),"") | K14: Sourced | L14: Piece / 1kg | M14: 16000 | N14: 1kg imported | O14: The Fresh Place (thefreshplace.ng), 17 Oct 2026; listed out of stock | Q14: Seasonal | R14: Seasonal drop | S14: =COUNTIF('Recipe Ingredients'!$F$2:$F$2000,A14) | T14: Room temp; fridge when soft | U14: 3-4 days | V14: Nationwide | W14: Wellness | X14: Two short local windows. Imported guava sells at a premium.
A15: P014 | B15: Soursop | D15: Fruit | E15: Local | F15: Eat as-is + recipes | G15: Seasonal | H15: Dec-Mar, May-Aug, Oct | I15: Feb-Mar | J15: =IFERROR(IF(INDEX('Seasonal Calendar'!$C$2:$N$500,MATCH(A15,'Seasonal Calendar'!$A$2:$A$500,0),MONTH(TODAY()))="","Out",INDEX('Seasonal Calendar'!$C$2:$N$500,MATCH(A15,'Seasonal Calendar'!$A$2:$A$500,0),MONTH(TODAY()))),"") | K15: Sourced | L15: Piece / 1kg | M15: 5500 | N15: 1kg | O15: The Fresh Place (thefreshplace.ng), 17 Oct 2026; listed out of stock | Q15: Seasonal | R15: Seasonal drop | S15: =COUNTIF('Recipe Ingredients'!$F$2:$F$2000,A15) | T15: Room temp until soft; fridge after | U15: 2-3 days ripe | V15: Southwest, South-south | W15: Wellness | X15: Seeds must be removed before blending.
A16: P015 | B16: Passion fruit | D16: Fruit | E16: Local + imported | F16: Recipe ingredient | G16: Seasonal | H16: Jan-Mar, May-Jun, Aug-Nov | J16: =IFERROR(IF(INDEX('Seasonal Calendar'!$C$2:$N$500,MATCH(A16,'Seasonal Calendar'!$A$2:$A$500,0),MONTH(TODAY()))="","Out",INDEX('Seasonal Calendar'!$C$2:$N$500,MATCH(A16,'Seasonal Calendar'!$A$2:$A$500,0),MONTH(TODAY()))),"") | K16: Sourced | L16: Pack of 4 | M16: 40000 | N16: 1kg imported | O16: The Fresh Place (thefreshplace.ng), 17 Oct 2026; listed out of stock | Q16: N | R16: Premium | S16: =COUNTIF('Recipe Ingredients'!$F$2:$F$2000,A16) | T16: Room temp; fridge when wrinkled | U16: 1-2 weeks | V16: Plateau | W16: Wellness | X16: Local supply exists (Plateau). Imported is very expensive, so source locally.
A17: P016 | B17: Coconut | C17: Agbon (Yor), Kwakwa (Hau) | D17: Fruit | E17: Local | F17: Eat as-is + recipes | G17: Year-round | H17: All year | J17: =IFERROR(IF(INDEX('Seasonal Calendar'!$C$2:$N$500,MATCH(A17,'Seasonal Calendar'!$A$2:$A$500,0),MONTH(TODAY()))="","Out",INDEX('Seasonal Calendar'!$C$2:$N$500,MATCH(A17,'Seasonal Calendar'!$A$2:$A$500,0),MONTH(TODAY()))),"") | K17: Verify | L17: Piece | M17: 1500 | N17: 1 pc | O17: The Fresh Place (thefreshplace.ng), 17 Oct 2026 | Q17: Y | R17: Core | S17: =COUNTIF('Recipe Ingredients'!$F$2:$F$2000,A17) | T17: Room temp | U17: 2-3 weeks whole | V17: Lagos (Badagry), Ogun, Ondo coast | W17: Plant-based, Hydration | X17: Fresh coconut milk replaces canned in most recipes here.
A18: P017 | B18: Agbalumo (African star apple) | C18: Agbalumo (Yor), Udara (Igbo), 'cherry' (Lagos) | D18: Fruit | E18: Local | F18: Eat as-is only | G18: Seasonal | H18: Dec-May | I18: Jan-Mar | J18: =IFERROR(IF(INDEX('Seasonal Calendar'!$C$2:$N$500,MATCH(A18,'Seasonal Calendar'!$A$2:$A$500,0),MONTH(TODAY()))="","Out",INDEX('Seasonal Calendar'!$C$2:$N$500,MATCH(A18,'Seasonal Calendar'!$A$2:$A$500,0),MONTH(TODAY()))),"") | K18: Sourced | L18: Pack of 10 / 20 | Q18: Seasonal | R18: Seasonal drop | S18: =COUNTIF('Recipe Ingredients'!$F$2:$F$2000,A18) | T18: Room temp | U18: 3-5 days | V18: Southwest and Southeast forest zones | W18: Wellness | X18: Hero of the seasonal drop calendar. Wild-harvested, so grade by size and sell by count.
A19: P018 | B19: Cashew apple | C19: Kaju (Yor), Kanju (Hau) | D19: Fruit | E19: Local | F19: Eat as-is only | G19: Seasonal | H19: Feb-Mar | I19: Feb-Mar | J19: =IFERROR(IF(INDEX('Seasonal Calendar'!$C$2:$N$500,MATCH(A19,'Seasonal Calendar'!$A$2:$A$500,0),MONTH(TODAY()))="","Out",INDEX('Seasonal Calendar'!$C$2:$N$500,MATCH(A19,'Seasonal Calendar'!$A$2:$A$500,0),MONTH(TODAY()))),"") | K19: Sourced | L19: Pack | Q19: N | R19: Later | S19: =COUNTIF('Recipe Ingredients'!$F$2:$F$2000,A19) | T19: Fridge; bruises fast | U19: 1-2 days | V19: Kogi, Oyo, Enugu | W19: Wellness | X19: Very short shelf life. Test only.
A20: P019 | B20: Velvet tamarind | C20: Awin (Yor), Icheku (Igbo), Tsamiyar kurmi (Hau) | D20: Fruit | E20: Local | F20: Eat as-is only | G20: Seasonal | H20: Jan-May | I20: Feb-Mar | J20: =IFERROR(IF(INDEX('Seasonal Calendar'!$C$2:$N$500,MATCH(A20,'Seasonal Calendar'!$A$2:$A$500,0),MONTH(TODAY()))="","Out",INDEX('Seasonal Calendar'!$C$2:$N$500,MATCH(A20,'Seasonal Calendar'!$A$2:$A$500,0),MONTH(TODAY()))),"") | K20: Sourced | L20: Cup / 100g pack | Q20: Seasonal | R20: Seasonal drop | S20: =COUNTIF('Recipe Ingredients'!$F$2:$F$2000,A20) | T20: Dry, airtight | U20: Weeks | V20: Southwest, Southeast, North | W20: Snack | X20: Shelf-stable and nostalgic. Natural checkout add-on.
A21: P020 | B21: Hog plum | C21: Iyeye (Yor) | D21: Fruit | E21: Local | F21: Eat as-is only | G21: Seasonal | H21: Jul, Dec | I21: Jul | J21: =IFERROR(IF(INDEX('Seasonal Calendar'!$C$2:$N$500,MATCH(A21,'Seasonal Calendar'!$A$2:$A$500,0),MONTH(TODAY()))="","Out",INDEX('Seasonal Calendar'!$C$2:$N$500,MATCH(A21,'Seasonal Calendar'!$A$2:$A$500,0),MONTH(TODAY()))),"") | K21: Sourced | L21: Pack | Q21: N | R21: Later | S21: =COUNTIF('Recipe Ingredients'!$F$2:$F$2000,A21) | T21: Fridge | U21: 1-2 days | V21: Southwest | W21: Snack | X21: Very short season and shelf life.
A22: P021 | B22: Pepper fruit | C22: Mmimi (Igbo) | D22: Fruit | E22: Local | F22: Eat as-is only | G22: Seasonal | H22: Feb-May | J22: =IFERROR(IF(INDEX('Seasonal Calendar'!$C$2:$N$500,MATCH(A22,'Seasonal Calendar'!$A$2:$A$500,0),MONTH(TODAY()))="","Out",INDEX('Seasonal Calendar'!$C$2:$N$500,MATCH(A22,'Seasonal Calendar'!$A$2:$A$500,0),MONTH(TODAY()))),"") | K22: Sourced | L22: Cup | Q22: N | R22: Later | S22: =COUNTIF('Recipe Ingredients'!$F$2:$F$2000,A22) | T22: Room temp | U22: 3-5 days | V22: Southeast | W22: Snack
A23: P022 | B23: Monkey kola | C23: Ochicha (Igbo), Obi edun (Yor) | D23: Fruit | E23: Local | F23: Eat as-is only | G23: Seasonal | H23: May-Aug | J23: =IFERROR(IF(INDEX('Seasonal Calendar'!$C$2:$N$500,MATCH(A23,'Seasonal Calendar'!$A$2:$A$500,0),MONTH(TODAY()))="","Out",INDEX('Seasonal Calendar'!$C$2:$N$500,MATCH(A23,'Seasonal Calendar'!$A$2:$A$500,0),MONTH(TODAY()))),"") | K23: Sourced | L23: Pack | Q23: N | R23: Later | S23: =COUNTIF('Recipe Ingredients'!$F$2:$F$2000,A23) | T23: Room temp | U23: 3-5 days | V23: Southeast, Southwest | W23: Snack
A24: P023 | B24: African pear | C24: Ube (Igbo) | D24: Fruit | E24: Local | F24: Eat as-is only | G24: Seasonal | H24: May-Sep | I24: Jun-Aug | J24: =IFERROR(IF(INDEX('Seasonal Calendar'!$C$2:$N$500,MATCH(A24,'Seasonal Calendar'!$A$2:$A$500,0),MONTH(TODAY()))="","Out",INDEX('Seasonal Calendar'!$C$2:$N$500,MATCH(A24,'Seasonal Calendar'!$A$2:$A$500,0),MONTH(TODAY()))),"") | K24: Sourced | L24: Pack of 10 | Q24: Seasonal | R24: Seasonal drop | S24: =COUNTIF('Recipe Ingredients'!$F$2:$F$2000,A24) | T24: Room temp | U24: 2-3 days | V24: Southeast, South-south | W24: Snack | X24: Classic pairing with roasted corn. Bundle the two as a rainy season drop.
A25: P024 | B25: Tiger nut | C25: Ofio (Yor), Aki Hausa (Igbo), Aya (Hau) | D25: Nut / tuber | E25: Local | F25: Eat as-is + recipes | G25: Seasonal | H25: Nov-May, Jul-Sep | J25: =IFERROR(IF(INDEX('Seasonal Calendar'!$C$2:$N$500,MATCH(A25,'Seasonal Calendar'!$A$2:$A$500,0),MONTH(TODAY()))="","Out",INDEX('Seasonal Calendar'!$C$2:$N$500,MATCH(A25,'Seasonal Calendar'!$A$2:$A$500,0),MONTH(TODAY()))),"") | K25: Sourced | L25: Cup / 250g | Q25: Y | R25: Core | S25: =COUNTIF('Recipe Ingredients'!$F$2:$F$2000,A25) | T25: Dry, airtight | U25: Weeks dried | V25: Kano, Kaduna, Niger | W25: Plant-based, Gut health | X25: Snack on its own or blend into kunun aya / horchata.
A26: P025 | B26: Sugarcane | C26: Ireke (Yor), Okpete (Igbo), Rake (Hau) | D26: Fruit (cane) | E26: Local | F26: Eat as-is only | G26: Seasonal | H26: Aug-Mar | J26: =IFERROR(IF(INDEX('Seasonal Calendar'!$C$2:$N$500,MATCH(A26,'Seasonal Calendar'!$A$2:$A$500,0),MONTH(TODAY()))="","Out",INDEX('Seasonal Calendar'!$C$2:$N$500,MATCH(A26,'Seasonal Calendar'!$A$2:$A$500,0),MONTH(TODAY()))),"") | K26: Sourced | L26: Stick / pre-cut pack | Q26: Seasonal | R26: Seasonal drop | S26: =COUNTIF('Recipe Ingredients'!$F$2:$F$2000,A26) | T26: Room temp; cut pieces in fridge | U26: 3-5 days | V26: North, Southwest | W26: Snack | X26: Pre-cut, peeled pieces are the only realistic delivery format.
A27: P026 | B27: Custard apple (sweetsop) | D27: Fruit | E27: Local | F27: Eat as-is only | G27: Seasonal | H27: Feb, Aug-Sep | J27: =IFERROR(IF(INDEX('Seasonal Calendar'!$C$2:$N$500,MATCH(A27,'Seasonal Calendar'!$A$2:$A$500,0),MONTH(TODAY()))="","Out",INDEX('Seasonal Calendar'!$C$2:$N$500,MATCH(A27,'Seasonal Calendar'!$A$2:$A$500,0),MONTH(TODAY()))),"") | K27: Sourced | L27: Piece | Q27: N | R27: Later | S27: =COUNTIF('Recipe Ingredients'!$F$2:$F$2000,A27) | T27: Room temp until soft | U27: 1-2 days ripe | V27: Southwest | W27: Snack
A28: P027 | B28: Jackfruit | D28: Fruit | E28: Local | F28: Eat as-is + recipes | G28: Seasonal | H28: May-Jun | I28: May | J28: =IFERROR(IF(INDEX('Seasonal Calendar'!$C$2:$N$500,MATCH(A28,'Seasonal Calendar'!$A$2:$A$500,0),MONTH(TODAY()))="","Out",INDEX('Seasonal Calendar'!$C$2:$N$500,MATCH(A28,'Seasonal Calendar'!$A$2:$A$500,0),MONTH(TODAY()))),"") | K28: Sourced | L28: Pre-cut pods | Q28: N | R28: Later | S28: =COUNTIF('Recipe Ingredients'!$F$2:$F$2000,A28) | T28: Fridge once cut | U28: 2-3 days cut | V28: South | W28: Snack | X28: Sell as cleaned pods, never whole.
A29: P028 | B29: June plum | D29: Fruit | E29: Local | F29: Eat as-is only | G29: Seasonal | H29: Dec-Jan | J29: =IFERROR(IF(INDEX('Seasonal Calendar'!$C$2:$N$500,MATCH(A29,'Seasonal Calendar'!$A$2:$A$500,0),MONTH(TODAY()))="","Out",INDEX('Seasonal Calendar'!$C$2:$N$500,MATCH(A29,'Seasonal Calendar'!$A$2:$A$500,0),MONTH(TODAY()))),"") | K29: Sourced | L29: Pack | Q29: N | R29: Later | S29: =COUNTIF('Recipe Ingredients'!$F$2:$F$2000,A29) | T29: Room temp | U29: 3-5 days | V29: South | W29: Snack
A30: P029 | B30: Sweet melon (golden / cantaloupe) | D30: Fruit | E30: Local + imported | F30: Eat as-is + recipes | G30: Year-round | H30: All year | I30: Jan, May-Jun | J30: =IFERROR(IF(INDEX('Seasonal Calendar'!$C$2:$N$500,MATCH(A30,'Seasonal Calendar'!$A$2:$A$500,0),MONTH(TODAY()))="","Out",INDEX('Seasonal Calendar'!$C$2:$N$500,MATCH(A30,'Seasonal Calendar'!$A$2:$A$500,0),MONTH(TODAY()))),"") | K30: Sourced | L30: Piece | M30: 15950 | N30: 1 imported galia | O30: Mint Foods (mintfoods.store), 11 Oct 2026 | Q30: N | R30: Premium | S30: =COUNTIF('Recipe Ingredients'!$F$2:$F$2000,A30) | T30: Room temp to ripen; fridge cut | U30: 3-5 days ripe | V30: North | W30: Hydration | X30: Local golden melon in Jan and May-Jun; imported the rest of the year at a high price.
A31: P030 | B31: Dates | C31: Dabino (Hau) | D31: Fruit | E31: Local + imported | F31: Eat as-is + recipes | G31: Year-round | H31: All year | I31: Apr-Jul | J31: =IFERROR(IF(INDEX('Seasonal Calendar'!$C$2:$N$500,MATCH(A31,'Seasonal Calendar'!$A$2:$A$500,0),MONTH(TODAY()))="","Out",INDEX('Seasonal Calendar'!$C$2:$N$500,MATCH(A31,'Seasonal Calendar'!$A$2:$A$500,0),MONTH(TODAY()))),"") | K31: Sourced | L31: 250g pack | M31: 5200 | N31: 1 pack (size not stated) | O31: The Fresh Place (thefreshplace.ng), 17 Oct 2026; listed out of stock | Q31: Y | R31: Core | S31: =COUNTIF('Recipe Ingredients'!$F$2:$F$2000,A31) | T31: Airtight, cool | U31: Months dried | V31: North (Borno, Yobe) + imports | W31: Training, Energy | X31: Fresh dates Apr-Jul; dried all year. Used as the natural sweetener across the library.
A32: P031 | B32: Apple (red & green) | D32: Fruit | E32: Imported | F32: Eat as-is + recipes | G32: Year-round | H32: All year | J32: =IFERROR(IF(INDEX('Seasonal Calendar'!$C$2:$N$500,MATCH(A32,'Seasonal Calendar'!$A$2:$A$500,0),MONTH(TODAY()))="","Out",INDEX('Seasonal Calendar'!$C$2:$N$500,MATCH(A32,'Seasonal Calendar'!$A$2:$A$500,0),MONTH(TODAY()))),"") | K32: Verify | L32: Piece / 6-pack | M32: 500 | N32: 1 pc small (Granny Smith) | O32: The Fresh Place (thefreshplace.ng), 17 Oct 2026; Golden Delicious N450/pc; Pink Lady big N800/pc; small Granny Smith dozen N5,400 | Q32: Y | R32: Core (imported) | S32: =COUNTIF('Recipe Ingredients'!$F$2:$F$2000,A32) | T32: Fridge | U32: 2-4 weeks | V32: Imported (South Africa, EU) | W32: Weight management | X32: Imported, but a basket expectation in Lagos. Every competitor bundle includes it.
A33: P032 | B33: Pear | D33: Fruit | E33: Imported | F33: Eat as-is + recipes | G33: Year-round | H33: All year | J33: =IFERROR(IF(INDEX('Seasonal Calendar'!$C$2:$N$500,MATCH(A33,'Seasonal Calendar'!$A$2:$A$500,0),MONTH(TODAY()))="","Out",INDEX('Seasonal Calendar'!$C$2:$N$500,MATCH(A33,'Seasonal Calendar'!$A$2:$A$500,0),MONTH(TODAY()))),"") | K33: Verify | L33: Piece | M33: 700 | N33: 1 pc (English pear) | O33: The Fresh Place (thefreshplace.ng), 17 Oct 2026 | Q33: N | R33: Premium | S33: =COUNTIF('Recipe Ingredients'!$F$2:$F$2000,A33) | T33: Fridge once ripe | U33: 1-2 weeks | V33: Imported | W33: Weight management | X33: Included in The Fresh Place bundles (10 English pears).
A34: P033 | B34: Grapes (red / black seedless) | D34: Fruit | E34: Imported | F34: Eat as-is + recipes | G34: Year-round | H34: All year | J34: =IFERROR(IF(INDEX('Seasonal Calendar'!$C$2:$N$500,MATCH(A34,'Seasonal Calendar'!$A$2:$A$500,0),MONTH(TODAY()))="","Out",INDEX('Seasonal Calendar'!$C$2:$N$500,MATCH(A34,'Seasonal Calendar'!$A$2:$A$500,0),MONTH(TODAY()))),"") | K34: Verify | L34: 500g | M34: 7000 | N34: 1 pack, red or green seedless (size not stated) | O34: The Fresh Place (thefreshplace.ng), 17 Oct 2026; black seedless N7,500, listed out of stock | Q34: N | R34: Premium | S34: =COUNTIF('Recipe Ingredients'!$F$2:$F$2000,A34) | T34: Fridge, unwashed | U34: 5-7 days | V34: Imported | W34: Snack
A35: P034 | B35: Strawberry | D35: Fruit (berry) | E35: Local + imported | F35: Eat as-is + recipes | G35: Seasonal | H35: Nov-Apr | I35: Dec-Feb | J35: =IFERROR(IF(INDEX('Seasonal Calendar'!$C$2:$N$500,MATCH(A35,'Seasonal Calendar'!$A$2:$A$500,0),MONTH(TODAY()))="","Out",INDEX('Seasonal Calendar'!$C$2:$N$500,MATCH(A35,'Seasonal Calendar'!$A$2:$A$500,0),MONTH(TODAY()))),"") | K35: Verify | L35: 250g punnet | M35: 5000 | N35: 1 pack (size not stated) | O35: The Fresh Place (thefreshplace.ng), 17 Oct 2026 | Q35: N | R35: Premium | S35: =COUNTIF('Recipe Ingredients'!$F$2:$F$2000,A35) | T35: Fridge, unwashed | U35: 2-4 days | V35: Plateau (Jos) + imports | W35: Wellness | X35: Jos strawberries are a real local story. Season window needs supplier confirmation.
A36: P035 | B36: Blueberry | D36: Fruit (berry) | E36: Imported | F36: Eat as-is + recipes | G36: Year-round | H36: All year | J36: =IFERROR(IF(INDEX('Seasonal Calendar'!$C$2:$N$500,MATCH(A36,'Seasonal Calendar'!$A$2:$A$500,0),MONTH(TODAY()))="","Out",INDEX('Seasonal Calendar'!$C$2:$N$500,MATCH(A36,'Seasonal Calendar'!$A$2:$A$500,0),MONTH(TODAY()))),"") | K36: Verify | L36: 125g | M36: 6000 | N36: 1 pack (size not stated) | O36: The Fresh Place (thefreshplace.ng), 17 Oct 2026 | Q36: N | R36: Premium | S36: =COUNTIF('Recipe Ingredients'!$F$2:$F$2000,A36) | T36: Fridge | U36: 5-7 days | V36: Imported | W36: Wellness
A37: P036 | B37: Kiwi | D37: Fruit | E37: Imported | F37: Eat as-is + recipes | G37: Year-round | H37: All year | J37: =IFERROR(IF(INDEX('Seasonal Calendar'!$C$2:$N$500,MATCH(A37,'Seasonal Calendar'!$A$2:$A$500,0),MONTH(TODAY()))="","Out",INDEX('Seasonal Calendar'!$C$2:$N$500,MATCH(A37,'Seasonal Calendar'!$A$2:$A$500,0),MONTH(TODAY()))),"") | K37: Verify | L37: 3-pack | M37: 20000 | N37: 1kg | O37: The Fresh Place (thefreshplace.ng), 17 Oct 2026 | Q37: N | R37: Premium | S37: =COUNTIF('Recipe Ingredients'!$F$2:$F$2000,A37) | T37: Fridge | U37: 1-2 weeks | V37: Imported | W37: Wellness
A38: P037 | B38: Pomegranate | D38: Fruit | E38: Imported | F38: Eat as-is + recipes | G38: Year-round | H38: All year | J38: =IFERROR(IF(INDEX('Seasonal Calendar'!$C$2:$N$500,MATCH(A38,'Seasonal Calendar'!$A$2:$A$500,0),MONTH(TODAY()))="","Out",INDEX('Seasonal Calendar'!$C$2:$N$500,MATCH(A38,'Seasonal Calendar'!$A$2:$A$500,0),MONTH(TODAY()))),"") | K38: Verify | L38: Piece | M38: 18000 | N38: 1kg | O38: The Fresh Place (thefreshplace.ng), 17 Oct 2026; listed out of stock | Q38: N | R38: Later | S38: =COUNTIF('Recipe Ingredients'!$F$2:$F$2000,A38) | T38: Fridge | U38: 2-3 weeks | V38: Imported | W38: Wellness
A39: P038 | B39: Dragon fruit | D39: Fruit | E39: Local (limited) + imported | F39: Eat as-is + recipes | G39: Year-round | H39: All year | J39: =IFERROR(IF(INDEX('Seasonal Calendar'!$C$2:$N$500,MATCH(A39,'Seasonal Calendar'!$A$2:$A$500,0),MONTH(TODAY()))="","Out",INDEX('Seasonal Calendar'!$C$2:$N$500,MATCH(A39,'Seasonal Calendar'!$A$2:$A$500,0),MONTH(TODAY()))),"") | K39: Verify | L39: Piece | M39: 40000 | N39: 1kg | O39: The Fresh Place (thefreshplace.ng), 17 Oct 2026; listed out of stock | Q39: N | R39: Later | S39: =COUNTIF('Recipe Ingredients'!$F$2:$F$2000,A39) | T39: Fridge | U39: 5-7 days | V39: A few local farms + imports | W39: Wellness | X39: Price makes it a showpiece, not a staple.
A40: P039 | B40: Star fruit (carambola) | D40: Fruit | E40: Local | F40: Eat as-is + recipes | G40: Year-round | H40: All year | J40: =IFERROR(IF(INDEX('Seasonal Calendar'!$C$2:$N$500,MATCH(A40,'Seasonal Calendar'!$A$2:$A$500,0),MONTH(TODAY()))="","Out",INDEX('Seasonal Calendar'!$C$2:$N$500,MATCH(A40,'Seasonal Calendar'!$A$2:$A$500,0),MONTH(TODAY()))),"") | K40: Verify | L40: Piece | Q40: N | R40: Later | S40: =COUNTIF('Recipe Ingredients'!$F$2:$F$2000,A40) | T40: Room temp / fridge | U40: 3-5 days | V40: South | W40: Snack | X40: Availability is patchy. Verify with suppliers.
A41: P040 | B41: Groundnut (fresh or roasted) | C41: Epa (Yor), Gyada (Hau) | D41: Nut / legume | E41: Local | F41: Recipe ingredient | G41: Year-round | H41: All year | I41: May-Oct | J41: =IFERROR(IF(INDEX('Seasonal Calendar'!$C$2:$N$500,MATCH(A41,'Seasonal Calendar'!$A$2:$A$500,0),MONTH(TODAY()))="","Out",INDEX('Seasonal Calendar'!$C$2:$N$500,MATCH(A41,'Seasonal Calendar'!$A$2:$A$500,0),MONTH(TODAY()))),"") | K41: Sourced | L41: Cup / 250g | Q41: Y | R41: Core | S41: =COUNTIF('Recipe Ingredients'!$F$2:$F$2000,A41) | T41: Airtight | U41: Weeks roasted | V41: Kano, Kaduna, Niger | W41: Training, Plant-based | X41: Fresh groundnuts May-Oct; roasted all year. Replaces pine nuts, walnuts and tahini across the library.
A42: P041 | B42: African walnut | C42: Asala (Yor), Ukpa (Igbo) | D42: Nut | E42: Local | F42: Eat as-is only | G42: Seasonal | H42: Mar-May, Jul-Aug, Oct | J42: =IFERROR(IF(INDEX('Seasonal Calendar'!$C$2:$N$500,MATCH(A42,'Seasonal Calendar'!$A$2:$A$500,0),MONTH(TODAY()))="","Out",INDEX('Seasonal Calendar'!$C$2:$N$500,MATCH(A42,'Seasonal Calendar'!$A$2:$A$500,0),MONTH(TODAY()))),"") | K42: Sourced | L42: Pack | Q42: Seasonal | R42: Seasonal drop | S42: =COUNTIF('Recipe Ingredients'!$F$2:$F$2000,A42) | T42: Cool, dry | U42: 1 week cooked | V42: Southwest, Southeast | W42: Snack | X42: Sold boiled.
A43: P042 | B43: Tomato (plum) | C43: Tumatir (Hau) | D43: Vegetable | E43: Local | F43: Recipe ingredient | G43: Year-round | H43: All year | I43: Dec-Jan, Aug-Sep | J43: =IFERROR(IF(INDEX('Seasonal Calendar'!$C$2:$N$500,MATCH(A43,'Seasonal Calendar'!$A$2:$A$500,0),MONTH(TODAY()))="","Out",INDEX('Seasonal Calendar'!$C$2:$N$500,MATCH(A43,'Seasonal Calendar'!$A$2:$A$500,0),MONTH(TODAY()))),"") | K43: Sourced | L43: 1kg | M43: 4600 | N43: 1kg | O43: Mint Foods (mintfoods.store), 11 Oct 2026; beef tomato N4,375/kg | Q43: Y | R43: Core | S43: =COUNTIF('Recipe Ingredients'!$F$2:$F$2000,A43) | T43: Room temp; fridge only when very ripe | U43: 3-7 days | V43: Kano, Kaduna, Katsina, Plateau | W43: Wellness | X43: Jos tomatoes peak Aug-Sep and Dec-Jan (Kitchen Butterfly). Prices spike in parts of the rainy season, so build price alerts around it.
A44: P043 | B44: Cherry tomato | D44: Vegetable | E44: Local + imported | F44: Eat as-is + recipes | G44: Year-round | H44: All year | J44: =IFERROR(IF(INDEX('Seasonal Calendar'!$C$2:$N$500,MATCH(A44,'Seasonal Calendar'!$A$2:$A$500,0),MONTH(TODAY()))="","Out",INDEX('Seasonal Calendar'!$C$2:$N$500,MATCH(A44,'Seasonal Calendar'!$A$2:$A$500,0),MONTH(TODAY()))),"") | K44: Verify | L44: 250g | M44: 9000 | N44: 250g yellow | O44: Mint Foods (mintfoods.store), 11 Oct 2026 | Q44: N | R44: Premium | S44: =COUNTIF('Recipe Ingredients'!$F$2:$F$2000,A44) | T44: Room temp | U44: 5-7 days | V44: Greenhouses (Lagos, Ogun, Plateau) | W44: Wellness | X44: Plum tomatoes work in every recipe that lists cherry tomatoes.
A45: P044 | B45: Red bell pepper | C45: Tatashe (Yor) | D45: Vegetable | E45: Local | F45: Recipe ingredient | G45: Year-round | H45: All year | J45: =IFERROR(IF(INDEX('Seasonal Calendar'!$C$2:$N$500,MATCH(A45,'Seasonal Calendar'!$A$2:$A$500,0),MONTH(TODAY()))="","Out",INDEX('Seasonal Calendar'!$C$2:$N$500,MATCH(A45,'Seasonal Calendar'!$A$2:$A$500,0),MONTH(TODAY()))),"") | K45: Verify | L45: Piece / 6-pack | M45: 10350 | N45: 6 pcs local | O45: Mint Foods (mintfoods.store), 11 Oct 2026 | Q45: Y | R45: Core | S45: =COUNTIF('Recipe Ingredients'!$F$2:$F$2000,A45) | T45: Fridge | U45: 1 week | V45: Plateau, Kaduna, Kano | W45: Wellness
A46: P045 | B46: Green / yellow bell pepper | D46: Vegetable | E46: Local | F46: Recipe ingredient | G46: Year-round | H46: All year | J46: =IFERROR(IF(INDEX('Seasonal Calendar'!$C$2:$N$500,MATCH(A46,'Seasonal Calendar'!$A$2:$A$500,0),MONTH(TODAY()))="","Out",INDEX('Seasonal Calendar'!$C$2:$N$500,MATCH(A46,'Seasonal Calendar'!$A$2:$A$500,0),MONTH(TODAY()))),"") | K46: Verify | L46: Piece / 6-pack | M46: 9500 | N46: 1kg green | O46: The Fresh Place (thefreshplace.ng), 17 Oct 2026; listed out of stock | Q46: Y | R46: Core | S46: =COUNTIF('Recipe Ingredients'!$F$2:$F$2000,A46) | T46: Fridge | U46: 1 week | V46: Plateau, Kaduna | W46: Wellness
A47: P046 | B47: Scotch bonnet | C47: Ata rodo (Yor) | D47: Vegetable | E47: Local | F47: Recipe ingredient | G47: Year-round | H47: All year | J47: =IFERROR(IF(INDEX('Seasonal Calendar'!$C$2:$N$500,MATCH(A47,'Seasonal Calendar'!$A$2:$A$500,0),MONTH(TODAY()))="","Out",INDEX('Seasonal Calendar'!$C$2:$N$500,MATCH(A47,'Seasonal Calendar'!$A$2:$A$500,0),MONTH(TODAY()))),"") | K47: Verify | L47: Cup / 100g | Q47: Y | R47: Core | S47: =COUNTIF('Recipe Ingredients'!$F$2:$F$2000,A47) | T47: Fridge | U47: 1-2 weeks | V47: Nationwide | W47: Wellness | X47: Every recipe lists a small amount. Let customers dial heat up or down.
A48: P047 | B48: Long red chilli | C48: Shombo (Yor) | D48: Vegetable | E48: Local | F48: Recipe ingredient | G48: Year-round | H48: All year | J48: =IFERROR(IF(INDEX('Seasonal Calendar'!$C$2:$N$500,MATCH(A48,'Seasonal Calendar'!$A$2:$A$500,0),MONTH(TODAY()))="","Out",INDEX('Seasonal Calendar'!$C$2:$N$500,MATCH(A48,'Seasonal Calendar'!$A$2:$A$500,0),MONTH(TODAY()))),"") | K48: Verify | L48: Cup | Q48: N | R48: Later | S48: =COUNTIF('Recipe Ingredients'!$F$2:$F$2000,A48) | T48: Fridge | U48: 1-2 weeks | V48: North | X48: Milder swap for ata rodo.
A49: P048 | B49: Onion (red & white) | C49: Alubosa (Yor), Yabasi (Igbo), Albasa (Hau) | D49: Vegetable | E49: Local | F49: Recipe ingredient | G49: Year-round | H49: All year | J49: =IFERROR(IF(INDEX('Seasonal Calendar'!$C$2:$N$500,MATCH(A49,'Seasonal Calendar'!$A$2:$A$500,0),MONTH(TODAY()))="","Out",INDEX('Seasonal Calendar'!$C$2:$N$500,MATCH(A49,'Seasonal Calendar'!$A$2:$A$500,0),MONTH(TODAY()))),"") | K49: Verify | L49: 1kg / 3 pcs | Q49: Y | R49: Core | S49: =COUNTIF('Recipe Ingredients'!$F$2:$F$2000,A49) | T49: Cool, dry, ventilated | U49: 3-4 weeks | V49: Kano, Sokoto, Kebbi | X49: Red onions for raw dishes, white for cooking.
A50: P049 | B50: Spring onion | C50: Alubosa elewe (Yor) | D50: Vegetable | E50: Local | F50: Recipe ingredient | G50: Year-round | H50: All year | J50: =IFERROR(IF(INDEX('Seasonal Calendar'!$C$2:$N$500,MATCH(A50,'Seasonal Calendar'!$A$2:$A$500,0),MONTH(TODAY()))="","Out",INDEX('Seasonal Calendar'!$C$2:$N$500,MATCH(A50,'Seasonal Calendar'!$A$2:$A$500,0),MONTH(TODAY()))),"") | K50: Verify | L50: Bunch | Q50: Y | R50: Core | S50: =COUNTIF('Recipe Ingredients'!$F$2:$F$2000,A50) | T50: Fridge, wrapped | U50: 5-7 days | V50: Plateau, Lagos
A51: P050 | B51: Shallots | D51: Vegetable | E51: Local + imported | F51: Recipe ingredient | G51: Year-round | H51: All year | J51: =IFERROR(IF(INDEX('Seasonal Calendar'!$C$2:$N$500,MATCH(A51,'Seasonal Calendar'!$A$2:$A$500,0),MONTH(TODAY()))="","Out",INDEX('Seasonal Calendar'!$C$2:$N$500,MATCH(A51,'Seasonal Calendar'!$A$2:$A$500,0),MONTH(TODAY()))),"") | K51: Verify | L51: 250g | M51: 6500 | N51: 250g | O51: Mint Foods (mintfoods.store), 11 Oct 2026 | Q51: N | R51: Later | S51: =COUNTIF('Recipe Ingredients'!$F$2:$F$2000,A51) | T51: Cool, dry | U51: 3-4 weeks | V51: North + imports | X51: Red onion covers every use in this library.
A52: P051 | B52: Garlic | C52: Ayu (Yor), Tafarnuwa (Hau) | D52: Aromatic | E52: Local + imported | F52: Recipe ingredient | G52: Year-round | H52: All year | J52: =IFERROR(IF(INDEX('Seasonal Calendar'!$C$2:$N$500,MATCH(A52,'Seasonal Calendar'!$A$2:$A$500,0),MONTH(TODAY()))="","Out",INDEX('Seasonal Calendar'!$C$2:$N$500,MATCH(A52,'Seasonal Calendar'!$A$2:$A$500,0),MONTH(TODAY()))),"") | K52: Verify | L52: Bulb / 5 bulbs | M52: 10000 | N52: size not stated (likely 1kg) | O52: The Fresh Place (thefreshplace.ng), 17 Oct 2026; listed out of stock | Q52: Y | R52: Core | S52: =COUNTIF('Recipe Ingredients'!$F$2:$F$2000,A52) | T52: Cool, dry | U52: 1-2 months | V52: Kano, Sokoto + imports | W52: Wellness
A53: P052 | B53: Ginger | C53: Ata ile (Yor), Jinja (Igbo), Citta (Hau) | D53: Aromatic | E53: Local | F53: Recipe ingredient | G53: Year-round | H53: All year | I53: Sep-Oct | J53: =IFERROR(IF(INDEX('Seasonal Calendar'!$C$2:$N$500,MATCH(A53,'Seasonal Calendar'!$A$2:$A$500,0),MONTH(TODAY()))="","Out",INDEX('Seasonal Calendar'!$C$2:$N$500,MATCH(A53,'Seasonal Calendar'!$A$2:$A$500,0),MONTH(TODAY()))),"") | K53: Sourced | L53: 100g / hand | M53: 18000 | N53: 1kg | O53: The Fresh Place (thefreshplace.ng), 17 Oct 2026 | Q53: Y | R53: Core | S53: =COUNTIF('Recipe Ingredients'!$F$2:$F$2000,A53) | T53: Cool, dry; fridge | U53: 2-3 weeks | V53: Southern Kaduna (Kafanchan) | W53: Wellness | X53: Fresh harvest Sep-Oct (Kitchen Butterfly); stored ginger all year.
A54: P053 | B54: Turmeric (fresh) | C54: Ata ile pupa (Yor) | D54: Aromatic | E54: Local | F54: Recipe ingredient | G54: Seasonal | H54: Sep-Jun | J54: =IFERROR(IF(INDEX('Seasonal Calendar'!$C$2:$N$500,MATCH(A54,'Seasonal Calendar'!$A$2:$A$500,0),MONTH(TODAY()))="","Out",INDEX('Seasonal Calendar'!$C$2:$N$500,MATCH(A54,'Seasonal Calendar'!$A$2:$A$500,0),MONTH(TODAY()))),"") | K54: Sourced | L54: 100g | Q54: N | R54: Later | S54: =COUNTIF('Recipe Ingredients'!$F$2:$F$2000,A54) | T54: Fridge | U54: 2-3 weeks | V54: Southern Kaduna, Southwest | W54: Wellness | X54: Stains everything. Pack separately.
A55: P054 | B55: Cucumber | C55: Kukumba | D55: Vegetable | E55: Local | F55: Eat as-is + recipes | G55: Year-round | H55: All year | I55: Jan-May | J55: =IFERROR(IF(INDEX('Seasonal Calendar'!$C$2:$N$500,MATCH(A55,'Seasonal Calendar'!$A$2:$A$500,0),MONTH(TODAY()))="","Out",INDEX('Seasonal Calendar'!$C$2:$N$500,MATCH(A55,'Seasonal Calendar'!$A$2:$A$500,0),MONTH(TODAY()))),"") | K55: Sourced | L55: Piece / 3-pack | M55: 600 | N55: 1 pc | O55: The Fresh Place (thefreshplace.ng), 17 Oct 2026 | Q55: Y | R55: Core | S55: =COUNTIF('Recipe Ingredients'!$F$2:$F$2000,A55) | T55: Fridge | U55: 1 week | V55: Plateau, Kaduna, greenhouses | W55: Hydration, Weight management | X55: Second most-used vegetable in the library.
A56: P055 | B56: Carrot | D56: Vegetable | E56: Local | F56: Eat as-is + recipes | G56: Year-round | H56: All year | I56: Sep-May | J56: =IFERROR(IF(INDEX('Seasonal Calendar'!$C$2:$N$500,MATCH(A56,'Seasonal Calendar'!$A$2:$A$500,0),MONTH(TODAY()))="","Out",INDEX('Seasonal Calendar'!$C$2:$N$500,MATCH(A56,'Seasonal Calendar'!$A$2:$A$500,0),MONTH(TODAY()))),"") | K56: Sourced | L56: 1kg / 500g | M56: 4500 | N56: 1kg | O56: The Fresh Place (thefreshplace.ng), 17 Oct 2026 | Q56: Y | R56: Core | S56: =COUNTIF('Recipe Ingredients'!$F$2:$F$2000,A56) | T56: Fridge, dry | U56: 2-3 weeks | V56: Plateau (Jos) | W56: Wellness
A57: P056 | B57: Cabbage (white) | D57: Vegetable | E57: Local | F57: Recipe ingredient | G57: Year-round | H57: All year | J57: =IFERROR(IF(INDEX('Seasonal Calendar'!$C$2:$N$500,MATCH(A57,'Seasonal Calendar'!$A$2:$A$500,0),MONTH(TODAY()))="","Out",INDEX('Seasonal Calendar'!$C$2:$N$500,MATCH(A57,'Seasonal Calendar'!$A$2:$A$500,0),MONTH(TODAY()))),"") | K57: Verify | L57: Head | M57: 2000 | N57: 1kg | O57: The Fresh Place (thefreshplace.ng), 17 Oct 2026 | Q57: Y | R57: Core | S57: =COUNTIF('Recipe Ingredients'!$F$2:$F$2000,A57) | T57: Fridge | U57: 2 weeks | V57: Plateau | W57: Weight management | X57: Cheap, slow to spoil, used in slaws, wraps and soups.
A58: P057 | B58: Purple cabbage | D58: Vegetable | E58: Local | F58: Recipe ingredient | G58: Year-round | H58: All year | J58: =IFERROR(IF(INDEX('Seasonal Calendar'!$C$2:$N$500,MATCH(A58,'Seasonal Calendar'!$A$2:$A$500,0),MONTH(TODAY()))="","Out",INDEX('Seasonal Calendar'!$C$2:$N$500,MATCH(A58,'Seasonal Calendar'!$A$2:$A$500,0),MONTH(TODAY()))),"") | K58: Verify | L58: Head | M58: 6000 | N58: 1kg | O58: The Fresh Place (thefreshplace.ng), 17 Oct 2026 | Q58: Y | R58: Core | S58: =COUNTIF('Recipe Ingredients'!$F$2:$F$2000,A58) | T58: Fridge | U58: 2 weeks | V58: Plateau | W58: Wellness
A59: P058 | B59: Lettuce (iceberg / romaine / local) | D59: Leafy green | E59: Local | F59: Recipe ingredient | G59: Year-round | H59: All year | J59: =IFERROR(IF(INDEX('Seasonal Calendar'!$C$2:$N$500,MATCH(A59,'Seasonal Calendar'!$A$2:$A$500,0),MONTH(TODAY()))="","Out",INDEX('Seasonal Calendar'!$C$2:$N$500,MATCH(A59,'Seasonal Calendar'!$A$2:$A$500,0),MONTH(TODAY()))),"") | K59: Verify | L59: Head | M59: 5500 | N59: 1 unit (size not stated) | O59: The Fresh Place (thefreshplace.ng), 17 Oct 2026; listed out of stock | Q59: Y | R59: Core | S59: =COUNTIF('Recipe Ingredients'!$F$2:$F$2000,A59) | T59: Fridge, wrapped | U59: 4-7 days | V59: Plateau, Lagos hydroponics | W59: Weight management | X59: Local iceberg costs a fraction of romaine. Default recipes to local lettuce.
A60: P059 | B60: Green beans | D60: Vegetable | E60: Local | F60: Recipe ingredient | G60: Year-round | H60: All year | J60: =IFERROR(IF(INDEX('Seasonal Calendar'!$C$2:$N$500,MATCH(A60,'Seasonal Calendar'!$A$2:$A$500,0),MONTH(TODAY()))="","Out",INDEX('Seasonal Calendar'!$C$2:$N$500,MATCH(A60,'Seasonal Calendar'!$A$2:$A$500,0),MONTH(TODAY()))),"") | K60: Verify | L60: 250g | M60: 2500 | N60: 1 pack runner beans (size not stated) | O60: The Fresh Place (thefreshplace.ng), 17 Oct 2026; listed out of stock | Q60: Y | R60: Core | S60: =COUNTIF('Recipe Ingredients'!$F$2:$F$2000,A60) | T60: Fridge | U60: 5-7 days | V60: Plateau | W60: Weight management
A61: P060 | B61: Sweet corn | C61: Agbado (Yor), Oka (Igbo), Masara (Hau) | D61: Vegetable | E61: Local | F61: Eat as-is + recipes | G61: Seasonal | H61: Apr-Aug | I61: Jun-Jul | J61: =IFERROR(IF(INDEX('Seasonal Calendar'!$C$2:$N$500,MATCH(A61,'Seasonal Calendar'!$A$2:$A$500,0),MONTH(TODAY()))="","Out",INDEX('Seasonal Calendar'!$C$2:$N$500,MATCH(A61,'Seasonal Calendar'!$A$2:$A$500,0),MONTH(TODAY()))),"") | K61: Sourced | L61: 3 cobs | M61: 3900 | N61: 3 cobs, peeled | O61: Mint Foods (mintfoods.store), 11 Oct 2026 | Q61: Seasonal | R61: Seasonal drop | S61: =COUNTIF('Recipe Ingredients'!$F$2:$F$2000,A61) | T61: Fridge, in husk | U61: 2-3 days | V61: Nationwide | W61: Energy | X61: Fresh corn Apr-Aug (Kitchen Butterfly). Pair with ube.
A62: P061 | B62: Garden egg | C62: Igba (Yor), Anara (Igbo), Gauta (Hau) | D62: Vegetable | E62: Local | F62: Eat as-is + recipes | G62: Seasonal | H62: Jan-Oct | J62: =IFERROR(IF(INDEX('Seasonal Calendar'!$C$2:$N$500,MATCH(A62,'Seasonal Calendar'!$A$2:$A$500,0),MONTH(TODAY()))="","Out",INDEX('Seasonal Calendar'!$C$2:$N$500,MATCH(A62,'Seasonal Calendar'!$A$2:$A$500,0),MONTH(TODAY()))),"") | K62: Sourced | L62: Pack of 6 | Q62: Y | R62: Core | S62: =COUNTIF('Recipe Ingredients'!$F$2:$F$2000,A62) | T62: Room temp / fridge | U62: 5-7 days | V62: Nationwide | W62: Weight management | X62: Eaten raw as a snack and stands in for aubergine in global recipes.
A63: P062 | B63: Okra | C63: Ila (Yor), Okwuru (Igbo), Kubewa (Hau) | D63: Vegetable | E63: Local | F63: Recipe ingredient | G63: Year-round | H63: All year | J63: =IFERROR(IF(INDEX('Seasonal Calendar'!$C$2:$N$500,MATCH(A63,'Seasonal Calendar'!$A$2:$A$500,0),MONTH(TODAY()))="","Out",INDEX('Seasonal Calendar'!$C$2:$N$500,MATCH(A63,'Seasonal Calendar'!$A$2:$A$500,0),MONTH(TODAY()))),"") | K63: Verify | L63: 250g | Q63: Y | R63: Core | S63: =COUNTIF('Recipe Ingredients'!$F$2:$F$2000,A63) | T63: Fridge, dry | U63: 3-4 days | V63: Nationwide | W63: Gut health
A64: P063 | B64: Broccoli | D64: Vegetable | E64: Local (limited) + imported | F64: Recipe ingredient | G64: Year-round | H64: All year | J64: =IFERROR(IF(INDEX('Seasonal Calendar'!$C$2:$N$500,MATCH(A64,'Seasonal Calendar'!$A$2:$A$500,0),MONTH(TODAY()))="","Out",INDEX('Seasonal Calendar'!$C$2:$N$500,MATCH(A64,'Seasonal Calendar'!$A$2:$A$500,0),MONTH(TODAY()))),"") | K64: Verify | L64: Head | M64: 10000 | N64: 1kg | O64: The Fresh Place (thefreshplace.ng), 17 Oct 2026; listed out of stock | Q64: N | R64: Premium | S64: =COUNTIF('Recipe Ingredients'!$F$2:$F$2000,A64) | T64: Fridge | U64: 5-7 days | V64: Plateau + imports | W64: Training, Weight management | X64: Green beans are the budget swap in every recipe.
A65: P064 | B65: Cauliflower | D65: Vegetable | E65: Local + imported | F65: Recipe ingredient | G65: Year-round | H65: All year | J65: =IFERROR(IF(INDEX('Seasonal Calendar'!$C$2:$N$500,MATCH(A65,'Seasonal Calendar'!$A$2:$A$500,0),MONTH(TODAY()))="","Out",INDEX('Seasonal Calendar'!$C$2:$N$500,MATCH(A65,'Seasonal Calendar'!$A$2:$A$500,0),MONTH(TODAY()))),"") | K65: Verify | L65: Head | M65: 5500 | N65: 1kg | O65: The Fresh Place (thefreshplace.ng), 17 Oct 2026; listed out of stock | Q65: N | R65: Premium | S65: =COUNTIF('Recipe Ingredients'!$F$2:$F$2000,A65) | T65: Fridge | U65: 1 week | V65: Plateau + imports | W65: Weight management | X65: Local heads are 6x cheaper than imported when available.
A66: P065 | B66: Beetroot | D66: Vegetable | E66: Local | F66: Recipe ingredient | G66: Year-round | H66: All year | J66: =IFERROR(IF(INDEX('Seasonal Calendar'!$C$2:$N$500,MATCH(A66,'Seasonal Calendar'!$A$2:$A$500,0),MONTH(TODAY()))="","Out",INDEX('Seasonal Calendar'!$C$2:$N$500,MATCH(A66,'Seasonal Calendar'!$A$2:$A$500,0),MONTH(TODAY()))),"") | K66: Verify | L66: 500g / 1kg | M66: 4500 | N66: 1kg | O66: The Fresh Place (thefreshplace.ng), 17 Oct 2026 | Q66: Y | R66: Core | S66: =COUNTIF('Recipe Ingredients'!$F$2:$F$2000,A66) | T66: Fridge | U66: 2-3 weeks | V66: Plateau | W66: Training (endurance)
A67: P066 | B67: Zucchini (courgette) | D67: Vegetable | E67: Local (limited) + imported | F67: Recipe ingredient | G67: Year-round | H67: All year | J67: =IFERROR(IF(INDEX('Seasonal Calendar'!$C$2:$N$500,MATCH(A67,'Seasonal Calendar'!$A$2:$A$500,0),MONTH(TODAY()))="","Out",INDEX('Seasonal Calendar'!$C$2:$N$500,MATCH(A67,'Seasonal Calendar'!$A$2:$A$500,0),MONTH(TODAY()))),"") | K67: Verify | L67: Piece | Q67: N | R67: Later | S67: =COUNTIF('Recipe Ingredients'!$F$2:$F$2000,A67) | T67: Fridge | U67: 5-7 days | V67: Plateau + imports | W67: Weight management | X67: Optional in every recipe that lists it.
A68: P067 | B68: Mushrooms (oyster / button) | D68: Vegetable | E68: Local + imported | F68: Recipe ingredient | G68: Year-round | H68: All year | J68: =IFERROR(IF(INDEX('Seasonal Calendar'!$C$2:$N$500,MATCH(A68,'Seasonal Calendar'!$A$2:$A$500,0),MONTH(TODAY()))="","Out",INDEX('Seasonal Calendar'!$C$2:$N$500,MATCH(A68,'Seasonal Calendar'!$A$2:$A$500,0),MONTH(TODAY()))),"") | K68: Verify | L68: 250g | M68: 5980 | N68: 250g white button | O68: Mint Foods (mintfoods.store), 11 Oct 2026 | Q68: N | R68: Premium | S68: =COUNTIF('Recipe Ingredients'!$F$2:$F$2000,A68) | T68: Fridge, paper bag | U68: 4-5 days | V68: Local oyster growers + imports | W68: Plant-based | X68: Local oyster mushrooms are the cheaper default.
A69: P068 | B69: Pumpkin (squash) | C69: Elegede (Yor), Kabewa (Hau) | D69: Vegetable | E69: Local | F69: Recipe ingredient | G69: Year-round | H69: All year | J69: =IFERROR(IF(INDEX('Seasonal Calendar'!$C$2:$N$500,MATCH(A69,'Seasonal Calendar'!$A$2:$A$500,0),MONTH(TODAY()))="","Out",INDEX('Seasonal Calendar'!$C$2:$N$500,MATCH(A69,'Seasonal Calendar'!$A$2:$A$500,0),MONTH(TODAY()))),"") | K69: Verify | L69: Wedge / 1kg | Q69: Y | R69: Core | S69: =COUNTIF('Recipe Ingredients'!$F$2:$F$2000,A69) | T69: Whole at room temp | U69: Weeks whole, 5 days cut | V69: North, Southwest | W69: Wellness | X69: Sell as wedges. Season window needs supplier confirmation.
A70: P069 | B70: Sweet potato | C70: Odunkun (Yor), Dankali (Hau) | D70: Tuber | E70: Local | F70: Recipe ingredient | G70: Year-round | H70: All year | J70: =IFERROR(IF(INDEX('Seasonal Calendar'!$C$2:$N$500,MATCH(A70,'Seasonal Calendar'!$A$2:$A$500,0),MONTH(TODAY()))="","Out",INDEX('Seasonal Calendar'!$C$2:$N$500,MATCH(A70,'Seasonal Calendar'!$A$2:$A$500,0),MONTH(TODAY()))),"") | K70: Verify | L70: 1kg | M70: 1200 | N70: ~1kg | O70: Mint Foods (mintfoods.store), 11 Oct 2026 | Q70: Y | R70: Core | S70: =COUNTIF('Recipe Ingredients'!$F$2:$F$2000,A70) | T70: Cool, dry | U70: 2-3 weeks | V70: Benue, Kwara, Kaduna | W70: Training, Energy | X70: Cheap, filling, and the default starch swap for potatoes across the library.
A71: P070 | B71: Irish potato | C71: Dankalin turawa (Hau) | D71: Tuber | E71: Local | F71: Recipe ingredient | G71: Year-round | H71: All year | J71: =IFERROR(IF(INDEX('Seasonal Calendar'!$C$2:$N$500,MATCH(A71,'Seasonal Calendar'!$A$2:$A$500,0),MONTH(TODAY()))="","Out",INDEX('Seasonal Calendar'!$C$2:$N$500,MATCH(A71,'Seasonal Calendar'!$A$2:$A$500,0),MONTH(TODAY()))),"") | K71: Verify | L71: 1kg | M71: 3650 | N71: ~1kg | O71: Mint Foods (mintfoods.store), 11 Oct 2026 | Q71: Y | R71: Core | S71: =COUNTIF('Recipe Ingredients'!$F$2:$F$2000,A71) | T71: Cool, dark | U71: 3-4 weeks | V71: Plateau (Jos) | W71: Training
A72: P071 | B72: Yam | C72: Isu (Yor), Ji (Igbo), Doya (Hau) | D72: Tuber | E72: Local | F72: Recipe ingredient | G72: Year-round | H72: All year | I72: Aug-Oct | J72: =IFERROR(IF(INDEX('Seasonal Calendar'!$C$2:$N$500,MATCH(A72,'Seasonal Calendar'!$A$2:$A$500,0),MONTH(TODAY()))="","Out",INDEX('Seasonal Calendar'!$C$2:$N$500,MATCH(A72,'Seasonal Calendar'!$A$2:$A$500,0),MONTH(TODAY()))),"") | K72: Sourced | L72: Tuber | Q72: N | R72: Later | S72: =COUNTIF('Recipe Ingredients'!$F$2:$F$2000,A72) | T72: Cool, dry | U72: Weeks | V72: Benue, Niger, Oyo | W72: Energy | X72: New yam Aug-Oct. Not used in the light-recipe library yet.
A73: P072 | B73: Fluted pumpkin leaf | C73: Ugu (Igbo) | D73: Leafy green | E73: Local | F73: Recipe ingredient | G73: Year-round | H73: All year | J73: =IFERROR(IF(INDEX('Seasonal Calendar'!$C$2:$N$500,MATCH(A73,'Seasonal Calendar'!$A$2:$A$500,0),MONTH(TODAY()))="","Out",INDEX('Seasonal Calendar'!$C$2:$N$500,MATCH(A73,'Seasonal Calendar'!$A$2:$A$500,0),MONTH(TODAY()))),"") | K73: Verify | L73: Bunch | Q73: Y | R73: Core | S73: =COUNTIF('Recipe Ingredients'!$F$2:$F$2000,A73) | T73: Fridge, wrapped | U73: 3-4 days | V73: Southeast, Lagos | W73: Wellness | X73: Becomes pesto, curry greens and smoothie greens in this library.
A74: P073 | B74: Amaranth greens (Nigerian spinach) | C74: Efo tete (Yor), Alayyahu (Hau) | D74: Leafy green | E74: Local | F74: Recipe ingredient | G74: Year-round | H74: All year | J74: =IFERROR(IF(INDEX('Seasonal Calendar'!$C$2:$N$500,MATCH(A74,'Seasonal Calendar'!$A$2:$A$500,0),MONTH(TODAY()))="","Out",INDEX('Seasonal Calendar'!$C$2:$N$500,MATCH(A74,'Seasonal Calendar'!$A$2:$A$500,0),MONTH(TODAY()))),"") | K74: Verify | L74: Bunch | M74: 1000 | N74: 1 unit, sold as 'Spinach' (size not stated) | O74: The Fresh Place (thefreshplace.ng), 17 Oct 2026; listed out of stock | Q74: Y | R74: Core | S74: =COUNTIF('Recipe Ingredients'!$F$2:$F$2000,A74) | T74: Fridge, wrapped | U74: 3-4 days | V74: Nationwide | W74: Wellness, Training | X74: Becomes pesto and curry greens in this library.
A75: P074 | B75: Waterleaf | C75: Gbure (Yor), Mgbolodi (Igbo) | D75: Leafy green | E75: Local | F75: Recipe ingredient | G75: Year-round | H75: All year | J75: =IFERROR(IF(INDEX('Seasonal Calendar'!$C$2:$N$500,MATCH(A75,'Seasonal Calendar'!$A$2:$A$500,0),MONTH(TODAY()))="","Out",INDEX('Seasonal Calendar'!$C$2:$N$500,MATCH(A75,'Seasonal Calendar'!$A$2:$A$500,0),MONTH(TODAY()))),"") | K75: Verify | L75: Bunch | Q75: N | R75: Later | S75: =COUNTIF('Recipe Ingredients'!$F$2:$F$2000,A75) | T75: Fridge | U75: 2-3 days | V75: South | X75: Mostly a soup green. Not in the current library.
A76: P075 | B76: Baby spinach | D76: Leafy green | E76: Local hydroponic + imported | F76: Recipe ingredient | G76: Year-round | H76: All year | J76: =IFERROR(IF(INDEX('Seasonal Calendar'!$C$2:$N$500,MATCH(A76,'Seasonal Calendar'!$A$2:$A$500,0),MONTH(TODAY()))="","Out",INDEX('Seasonal Calendar'!$C$2:$N$500,MATCH(A76,'Seasonal Calendar'!$A$2:$A$500,0),MONTH(TODAY()))),"") | K76: Verify | L76: 125g | M76: 4950 | N76: 125g | O76: Mint Foods (mintfoods.store), 11 Oct 2026 | Q76: N | R76: Premium | S76: =COUNTIF('Recipe Ingredients'!$F$2:$F$2000,A76) | T76: Fridge | U76: 4-5 days | V76: Lagos hydroponics + imports | W76: Wellness | X76: Efo tete works anywhere this is listed.
A77: P076 | B77: Kale | D77: Leafy green | E77: Local hydroponic + imported | F77: Recipe ingredient | G77: Year-round | H77: All year | J77: =IFERROR(IF(INDEX('Seasonal Calendar'!$C$2:$N$500,MATCH(A77,'Seasonal Calendar'!$A$2:$A$500,0),MONTH(TODAY()))="","Out",INDEX('Seasonal Calendar'!$C$2:$N$500,MATCH(A77,'Seasonal Calendar'!$A$2:$A$500,0),MONTH(TODAY()))),"") | K77: Verify | L77: 125g | M77: 4940 | N77: 125g | O77: Mint Foods (mintfoods.store), 11 Oct 2026 | Q77: N | R77: Later | S77: =COUNTIF('Recipe Ingredients'!$F$2:$F$2000,A77) | T77: Fridge | U77: 5-7 days | V77: Hydroponic farms | W77: Wellness | X77: Not needed while efo tete and ugu cover the same jobs.
A78: P077 | B78: Scent leaf (African basil) | C78: Efirin (Yor), Nchanwu (Igbo), Daidoya (Hau) | D78: Herb | E78: Local | F78: Recipe ingredient | G78: Year-round | H78: All year | J78: =IFERROR(IF(INDEX('Seasonal Calendar'!$C$2:$N$500,MATCH(A78,'Seasonal Calendar'!$A$2:$A$500,0),MONTH(TODAY()))="","Out",INDEX('Seasonal Calendar'!$C$2:$N$500,MATCH(A78,'Seasonal Calendar'!$A$2:$A$500,0),MONTH(TODAY()))),"") | K78: Verify | L78: Bunch | Q78: Y | R78: Core | S78: =COUNTIF('Recipe Ingredients'!$F$2:$F$2000,A78) | T78: Stems in water, room temp | U78: 3-4 days | V78: Nationwide | W78: Wellness | X78: Stands in for Thai basil and parsley in chimichurri. A real point of difference.
A79: P078 | B79: Bitter leaf | C79: Ewuro (Yor), Onugbu (Igbo), Shiwaka (Hau) | D79: Leafy green | E79: Local | F79: Recipe ingredient | G79: Year-round | H79: All year | J79: =IFERROR(IF(INDEX('Seasonal Calendar'!$C$2:$N$500,MATCH(A79,'Seasonal Calendar'!$A$2:$A$500,0),MONTH(TODAY()))="","Out",INDEX('Seasonal Calendar'!$C$2:$N$500,MATCH(A79,'Seasonal Calendar'!$A$2:$A$500,0),MONTH(TODAY()))),"") | K79: Verify | L79: Bunch (washed) | Q79: N | R79: Later | S79: =COUNTIF('Recipe Ingredients'!$F$2:$F$2000,A79) | T79: Fridge | U79: 3-4 days | V79: Nationwide | X79: Soup green. Not in the current library.
A80: P079 | B80: Mint | C80: Na'a na'a (Hau) | D80: Herb | E80: Local | F80: Recipe ingredient | G80: Year-round | H80: All year | J80: =IFERROR(IF(INDEX('Seasonal Calendar'!$C$2:$N$500,MATCH(A80,'Seasonal Calendar'!$A$2:$A$500,0),MONTH(TODAY()))="","Out",INDEX('Seasonal Calendar'!$C$2:$N$500,MATCH(A80,'Seasonal Calendar'!$A$2:$A$500,0),MONTH(TODAY()))),"") | K80: Verify | L80: Bunch | Q80: Y | R80: Core | S80: =COUNTIF('Recipe Ingredients'!$F$2:$F$2000,A80) | T80: Stems in water, fridge | U80: 4-5 days | V80: North, Lagos hydroponics | W80: Hydration
A81: P080 | B81: Coriander (cilantro) | D81: Herb | E81: Local | F81: Recipe ingredient | G81: Year-round | H81: All year | J81: =IFERROR(IF(INDEX('Seasonal Calendar'!$C$2:$N$500,MATCH(A81,'Seasonal Calendar'!$A$2:$A$500,0),MONTH(TODAY()))="","Out",INDEX('Seasonal Calendar'!$C$2:$N$500,MATCH(A81,'Seasonal Calendar'!$A$2:$A$500,0),MONTH(TODAY()))),"") | K81: Verify | L81: Bunch / 100g | M81: 3550 | N81: 100g | O81: Mint Foods (mintfoods.store), 11 Oct 2026 | Q81: Y | R81: Core | S81: =COUNTIF('Recipe Ingredients'!$F$2:$F$2000,A81) | T81: Stems in water, fridge | U81: 4-5 days | V81: Plateau, Lagos
A82: P081 | B82: Parsley | D82: Herb | E82: Local | F82: Recipe ingredient | G82: Year-round | H82: All year | J82: =IFERROR(IF(INDEX('Seasonal Calendar'!$C$2:$N$500,MATCH(A82,'Seasonal Calendar'!$A$2:$A$500,0),MONTH(TODAY()))="","Out",INDEX('Seasonal Calendar'!$C$2:$N$500,MATCH(A82,'Seasonal Calendar'!$A$2:$A$500,0),MONTH(TODAY()))),"") | K82: Verify | L82: Bunch | Q82: Y | R82: Core | S82: =COUNTIF('Recipe Ingredients'!$F$2:$F$2000,A82) | T82: Stems in water, fridge | U82: 5-7 days | V82: Plateau, hydroponics
A83: P082 | B83: Basil (sweet) | D83: Herb | E83: Local hydroponic + imported | F83: Recipe ingredient | G83: Year-round | H83: All year | J83: =IFERROR(IF(INDEX('Seasonal Calendar'!$C$2:$N$500,MATCH(A83,'Seasonal Calendar'!$A$2:$A$500,0),MONTH(TODAY()))="","Out",INDEX('Seasonal Calendar'!$C$2:$N$500,MATCH(A83,'Seasonal Calendar'!$A$2:$A$500,0),MONTH(TODAY()))),"") | K83: Verify | L83: 150g | M83: 3550 | N83: 150g hydroponic | O83: Mint Foods (mintfoods.store), 11 Oct 2026 | Q83: N | R83: Premium | S83: =COUNTIF('Recipe Ingredients'!$F$2:$F$2000,A83) | T83: Room temp, stems in water | U83: 3-4 days | V83: Lagos hydroponics | X83: Scent leaf is the local swap in every recipe.
A84: P083 | B84: Lemongrass | C84: Fever grass | D84: Herb | E84: Local | F84: Recipe ingredient | G84: Year-round | H84: All year | J84: =IFERROR(IF(INDEX('Seasonal Calendar'!$C$2:$N$500,MATCH(A84,'Seasonal Calendar'!$A$2:$A$500,0),MONTH(TODAY()))="","Out",INDEX('Seasonal Calendar'!$C$2:$N$500,MATCH(A84,'Seasonal Calendar'!$A$2:$A$500,0),MONTH(TODAY()))),"") | K84: Verify | L84: Bunch | Q84: Y | R84: Core | S84: =COUNTIF('Recipe Ingredients'!$F$2:$F$2000,A84) | T84: Fridge | U84: 1-2 weeks | V84: Nationwide | W84: Wellness
A85: P084 | B85: Rosemary | D85: Herb | E85: Local hydroponic + imported | F85: Recipe ingredient | G85: Year-round | H85: All year | J85: =IFERROR(IF(INDEX('Seasonal Calendar'!$C$2:$N$500,MATCH(A85,'Seasonal Calendar'!$A$2:$A$500,0),MONTH(TODAY()))="","Out",INDEX('Seasonal Calendar'!$C$2:$N$500,MATCH(A85,'Seasonal Calendar'!$A$2:$A$500,0),MONTH(TODAY()))),"") | K85: Verify | L85: 100g | M85: 5950 | N85: 100g | O85: Mint Foods (mintfoods.store), 11 Oct 2026 | Q85: N | R85: Later | S85: =COUNTIF('Recipe Ingredients'!$F$2:$F$2000,A85) | T85: Fridge | U85: 1-2 weeks | V85: Hydroponics + imports | X85: Scent leaf or dried thyme covers it.

Sheet Seasonal Calendar
A1: ID | B1: Produce | C1: Jan | D1: Feb | E1: Mar | F1: Apr | G1: May | H1: Jun | I1: Jul | J1: Aug | K1: Sep | L1: Oct | M1: Nov | N1: Dec | O1: Months available | P1: Role
A2: P001 | B2: Banana | C2: In | D2: In | E2: In | F2: In | G2: In | H2: In | I2: In | J2: In | K2: In | L2: In | M2: In | N2: In | O2: =COUNTIF(C2:N2,"Peak")+COUNTIF(C2:N2,"In") | P2: Eat as-is + recipes
A3: P002 | B3: Plantain (ripe & unripe) | C3: In | D3: In | E3: In | F3: In | G3: In | H3: In | I3: In | J3: In | K3: In | L3: In | M3: In | N3: In | O3: =COUNTIF(C3:N3,"Peak")+COUNTIF(C3:N3,"In") | P3: Recipe ingredient
A4: P003 | B4: Pineapple | C4: In | D4: In | E4: In | F4: In | G4: In | H4: In | I4: In | J4: In | K4: In | L4: In | M4: In | N4: In | O4: =COUNTIF(C4:N4,"Peak")+COUNTIF(C4:N4,"In") | P4: Eat as-is + recipes
A5: P004 | B5: Watermelon | C5: Peak | D5: Peak | E5: Peak | F5: Peak | G5: In | H5: In | I5: In | J5: In | K5: In | L5: In | M5: In | N5: Peak | O5: =COUNTIF(C5:N5,"Peak")+COUNTIF(C5:N5,"In") | P5: Eat as-is + recipes
A6: P005 | B6: Pawpaw (papaya) | C6: In | D6: In | E6: In | F6: In | G6: In | H6: In | I6: In | J6: In | K6: In | L6: In | M6: In | N6: In | O6: =COUNTIF(C6:N6,"Peak")+COUNTIF(C6:N6,"In") | P6: Eat as-is + recipes
A7: P006 | B7: Mango | D7: In | E7: Peak | F7: Peak | G7: In | J7: In | K7: In | O7: =COUNTIF(C7:N7,"Peak")+COUNTIF(C7:N7,"In") | P7: Eat as-is + recipes
A8: P007 | B8: Orange | C8: Peak | D8: In | E8: In | F8: In | G8: In | H8: In | I8: In | J8: In | K8: In | L8: Peak | M8: Peak | N8: Peak | O8: =COUNTIF(C8:N8,"Peak")+COUNTIF(C8:N8,"In") | P8: Eat as-is + recipes
A9: P008 | B9: Tangerine | C9: Peak | D9: In | E9: In | F9: In | G9: In | H9: In | I9: In | J9: In | K9: In | L9: Peak | M9: Peak | N9: Peak | O9: =COUNTIF(C9:N9,"Peak")+COUNTIF(C9:N9,"In") | P9: Eat as-is + recipes
A10: P009 | B10: Lemon | C10: Peak | D10: In | E10: In | F10: In | G10: In | H10: In | I10: In | J10: In | K10: In | L10: Peak | M10: Peak | N10: Peak | O10: =COUNTIF(C10:N10,"Peak")+COUNTIF(C10:N10,"In") | P10: Recipe ingredient
A11: P010 | B11: Lime | C11: Peak | D11: In | E11: In | F11: In | G11: In | H11: In | I11: In | J11: In | K11: In | L11: Peak | M11: Peak | N11: Peak | O11: =COUNTIF(C11:N11,"Peak")+COUNTIF(C11:N11,"In") | P11: Recipe ingredient
A12: P011 | B12: Grapefruit | C12: Peak | D12: In | E12: In | F12: In | G12: In | H12: In | I12: In | J12: In | K12: In | L12: Peak | M12: Peak | N12: Peak | O12: =COUNTIF(C12:N12,"Peak")+COUNTIF(C12:N12,"In") | P12: Eat as-is + recipes
A13: P012 | B13: Avocado | C13: In | D13: In | E13: In | F13: In | G13: In | H13: In | I13: In | J13: In | K13: In | L13: In | M13: In | N13: In | O13: =COUNTIF(C13:N13,"Peak")+COUNTIF(C13:N13,"In") | P13: Eat as-is + recipes
A14: P013 | B14: Guava | D14: Peak | E14: Peak | J14: In | K14: In | O14: =COUNTIF(C14:N14,"Peak")+COUNTIF(C14:N14,"In") | P14: Eat as-is + recipes
A15: P014 | B15: Soursop | C15: In | D15: Peak | E15: Peak | G15: In | H15: In | I15: In | J15: In | L15: In | N15: In | O15: =COUNTIF(C15:N15,"Peak")+COUNTIF(C15:N15,"In") | P15: Eat as-is + recipes
A16: P015 | B16: Passion fruit | C16: In | D16: In | E16: In | G16: In | H16: In | J16: In | K16: In | L16: In | M16: In | O16: =COUNTIF(C16:N16,"Peak")+COUNTIF(C16:N16,"In") | P16: Recipe ingredient
A17: P016 | B17: Coconut | C17: In | D17: In | E17: In | F17: In | G17: In | H17: In | I17: In | J17: In | K17: In | L17: In | M17: In | N17: In | O17: =COUNTIF(C17:N17,"Peak")+COUNTIF(C17:N17,"In") | P17: Eat as-is + recipes
A18: P017 | B18: Agbalumo (African star apple) | C18: Peak | D18: Peak | E18: Peak | F18: In | G18: In | N18: In | O18: =COUNTIF(C18:N18,"Peak")+COUNTIF(C18:N18,"In") | P18: Eat as-is only
A19: P018 | B19: Cashew apple | D19: Peak | E19: Peak | O19: =COUNTIF(C19:N19,"Peak")+COUNTIF(C19:N19,"In") | P19: Eat as-is only
A20: P019 | B20: Velvet tamarind | C20: In | D20: Peak | E20: Peak | F20: In | G20: In | O20: =COUNTIF(C20:N20,"Peak")+COUNTIF(C20:N20,"In") | P20: Eat as-is only
A21: P020 | B21: Hog plum | I21: Peak | N21: In | O21: =COUNTIF(C21:N21,"Peak")+COUNTIF(C21:N21,"In") | P21: Eat as-is only
A22: P021 | B22: Pepper fruit | D22: In | E22: In | F22: In | G22: In | O22: =COUNTIF(C22:N22,"Peak")+COUNTIF(C22:N22,"In") | P22: Eat as-is only
A23: P022 | B23: Monkey kola | G23: In | H23: In | I23: In | J23: In | O23: =COUNTIF(C23:N23,"Peak")+COUNTIF(C23:N23,"In") | P23: Eat as-is only
A24: P023 | B24: African pear | G24: In | H24: Peak | I24: Peak | J24: Peak | K24: In | O24: =COUNTIF(C24:N24,"Peak")+COUNTIF(C24:N24,"In") | P24: Eat as-is only
A25: P024 | B25: Tiger nut | C25: In | D25: In | E25: In | F25: In | G25: In | I25: In | J25: In | K25: In | M25: In | N25: In | O25: =COUNTIF(C25:N25,"Peak")+COUNTIF(C25:N25,"In") | P25: Eat as-is + recipes
A26: P025 | B26: Sugarcane | C26: In | D26: In | E26: In | J26: In | K26: In | L26: In | M26: In | N26: In | O26: =COUNTIF(C26:N26,"Peak")+COUNTIF(C26:N26,"In") | P26: Eat as-is only
A27: P026 | B27: Custard apple (sweetsop) | D27: In | J27: In | K27: In | O27: =COUNTIF(C27:N27,"Peak")+COUNTIF(C27:N27,"In") | P27: Eat as-is only
A28: P027 | B28: Jackfruit | G28: Peak | H28: In | O28: =COUNTIF(C28:N28,"Peak")+COUNTIF(C28:N28,"In") | P28: Eat as-is + recipes
A29: P028 | B29: June plum | C29: In | N29: In | O29: =COUNTIF(C29:N29,"Peak")+COUNTIF(C29:N29,"In") | P29: Eat as-is only
A30: P029 | B30: Sweet melon (golden / cantaloupe) | C30: Peak | D30: In | E30: In | F30: In | G30: Peak | H30: Peak | I30: In | J30: In | K30: In | L30: In | M30: In | N30: In | O30: =COUNTIF(C30:N30,"Peak")+COUNTIF(C30:N30,"In") | P30: Eat as-is + recipes
A31: P030 | B31: Dates | C31: In | D31: In | E31: In | F31: Peak | G31: Peak | H31: Peak | I31: Peak | J31: In | K31: In | L31: In | M31: In | N31: In | O31: =COUNTIF(C31:N31,"Peak")+COUNTIF(C31:N31,"In") | P31: Eat as-is + recipes
A32: P031 | B32: Apple (red & green) | C32: In | D32: In | E32: In | F32: In | G32: In | H32: In | I32: In | J32: In | K32: In | L32: In | M32: In | N32: In | O32: =COUNTIF(C32:N32,"Peak")+COUNTIF(C32:N32,"In") | P32: Eat as-is + recipes
A33: P032 | B33: Pear | C33: In | D33: In | E33: In | F33: In | G33: In | H33: In | I33: In | J33: In | K33: In | L33: In | M33: In | N33: In | O33: =COUNTIF(C33:N33,"Peak")+COUNTIF(C33:N33,"In") | P33: Eat as-is + recipes
A34: P033 | B34: Grapes (red / black seedless) | C34: In | D34: In | E34: In | F34: In | G34: In | H34: In | I34: In | J34: In | K34: In | L34: In | M34: In | N34: In | O34: =COUNTIF(C34:N34,"Peak")+COUNTIF(C34:N34,"In") | P34: Eat as-is + recipes
A35: P034 | B35: Strawberry | C35: Peak | D35: Peak | E35: In | F35: In | M35: In | N35: Peak | O35: =COUNTIF(C35:N35,"Peak")+COUNTIF(C35:N35,"In") | P35: Eat as-is + recipes
A36: P035 | B36: Blueberry | C36: In | D36: In | E36: In | F36: In | G36: In | H36: In | I36: In | J36: In | K36: In | L36: In | M36: In | N36: In | O36: =COUNTIF(C36:N36,"Peak")+COUNTIF(C36:N36,"In") | P36: Eat as-is + recipes
A37: P036 | B37: Kiwi | C37: In | D37: In | E37: In | F37: In | G37: In | H37: In | I37: In | J37: In | K37: In | L37: In | M37: In | N37: In | O37: =COUNTIF(C37:N37,"Peak")+COUNTIF(C37:N37,"In") | P37: Eat as-is + recipes
A38: P037 | B38: Pomegranate | C38: In | D38: In | E38: In | F38: In | G38: In | H38: In | I38: In | J38: In | K38: In | L38: In | M38: In | N38: In | O38: =COUNTIF(C38:N38,"Peak")+COUNTIF(C38:N38,"In") | P38: Eat as-is + recipes
A39: P038 | B39: Dragon fruit | C39: In | D39: In | E39: In | F39: In | G39: In | H39: In | I39: In | J39: In | K39: In | L39: In | M39: In | N39: In | O39: =COUNTIF(C39:N39,"Peak")+COUNTIF(C39:N39,"In") | P39: Eat as-is + recipes
A40: P039 | B40: Star fruit (carambola) | C40: In | D40: In | E40: In | F40: In | G40: In | H40: In | I40: In | J40: In | K40: In | L40: In | M40: In | N40: In | O40: =COUNTIF(C40:N40,"Peak")+COUNTIF(C40:N40,"In") | P40: Eat as-is + recipes
A41: P040 | B41: Groundnut (fresh or roasted) | C41: In | D41: In | E41: In | F41: In | G41: Peak | H41: Peak | I41: Peak | J41: Peak | K41: Peak | L41: Peak | M41: In | N41: In | O41: =COUNTIF(C41:N41,"Peak")+COUNTIF(C41:N41,"In") | P41: Recipe ingredient
A42: P041 | B42: African walnut | E42: In | F42: In | G42: In | I42: In | J42: In | L42: In | O42: =COUNTIF(C42:N42,"Peak")+COUNTIF(C42:N42,"In") | P42: Eat as-is only
A43: P042 | B43: Tomato (plum) | C43: Peak | D43: In | E43: In | F43: In | G43: In | H43: In | I43: In | J43: Peak | K43: Peak | L43: In | M43: In | N43: Peak | O43: =COUNTIF(C43:N43,"Peak")+COUNTIF(C43:N43,"In") | P43: Recipe ingredient
A44: P043 | B44: Cherry tomato | C44: In | D44: In | E44: In | F44: In | G44: In | H44: In | I44: In | J44: In | K44: In | L44: In | M44: In | N44: In | O44: =COUNTIF(C44:N44,"Peak")+COUNTIF(C44:N44,"In") | P44: Eat as-is + recipes
A45: P044 | B45: Red bell pepper | C45: In | D45: In | E45: In | F45: In | G45: In | H45: In | I45: In | J45: In | K45: In | L45: In | M45: In | N45: In | O45: =COUNTIF(C45:N45,"Peak")+COUNTIF(C45:N45,"In") | P45: Recipe ingredient
A46: P045 | B46: Green / yellow bell pepper | C46: In | D46: In | E46: In | F46: In | G46: In | H46: In | I46: In | J46: In | K46: In | L46: In | M46: In | N46: In | O46: =COUNTIF(C46:N46,"Peak")+COUNTIF(C46:N46,"In") | P46: Recipe ingredient
A47: P046 | B47: Scotch bonnet | C47: In | D47: In | E47: In | F47: In | G47: In | H47: In | I47: In | J47: In | K47: In | L47: In | M47: In | N47: In | O47: =COUNTIF(C47:N47,"Peak")+COUNTIF(C47:N47,"In") | P47: Recipe ingredient
A48: P047 | B48: Long red chilli | C48: In | D48: In | E48: In | F48: In | G48: In | H48: In | I48: In | J48: In | K48: In | L48: In | M48: In | N48: In | O48: =COUNTIF(C48:N48,"Peak")+COUNTIF(C48:N48,"In") | P48: Recipe ingredient
A49: P048 | B49: Onion (red & white) | C49: In | D49: In | E49: In | F49: In | G49: In | H49: In | I49: In | J49: In | K49: In | L49: In | M49: In | N49: In | O49: =COUNTIF(C49:N49,"Peak")+COUNTIF(C49:N49,"In") | P49: Recipe ingredient
A50: P049 | B50: Spring onion | C50: In | D50: In | E50: In | F50: In | G50: In | H50: In | I50: In | J50: In | K50: In | L50: In | M50: In | N50: In | O50: =COUNTIF(C50:N50,"Peak")+COUNTIF(C50:N50,"In") | P50: Recipe ingredient
A51: P050 | B51: Shallots | C51: In | D51: In | E51: In | F51: In | G51: In | H51: In | I51: In | J51: In | K51: In | L51: In | M51: In | N51: In | O51: =COUNTIF(C51:N51,"Peak")+COUNTIF(C51:N51,"In") | P51: Recipe ingredient
A52: P051 | B52: Garlic | C52: In | D52: In | E52: In | F52: In | G52: In | H52: In | I52: In | J52: In | K52: In | L52: In | M52: In | N52: In | O52: =COUNTIF(C52:N52,"Peak")+COUNTIF(C52:N52,"In") | P52: Recipe ingredient
A53: P052 | B53: Ginger | C53: In | D53: In | E53: In | F53: In | G53: In | H53: In | I53: In | J53: In | K53: Peak | L53: Peak | M53: In | N53: In | O53: =COUNTIF(C53:N53,"Peak")+COUNTIF(C53:N53,"In") | P53: Recipe ingredient
A54: P053 | B54: Turmeric (fresh) | C54: In | D54: In | E54: In | F54: In | G54: In | H54: In | K54: In | L54: In | M54: In | N54: In | O54: =COUNTIF(C54:N54,"Peak")+COUNTIF(C54:N54,"In") | P54: Recipe ingredient
A55: P054 | B55: Cucumber | C55: Peak | D55: Peak | E55: Peak | F55: Peak | G55: Peak | H55: In | I55: In | J55: In | K55: In | L55: In | M55: In | N55: In | O55: =COUNTIF(C55:N55,"Peak")+COUNTIF(C55:N55,"In") | P55: Eat as-is + recipes
A56: P055 | B56: Carrot | C56: Peak | D56: Peak | E56: Peak | F56: Peak | G56: Peak | H56: In | I56: In | J56: In | K56: Peak | L56: Peak | M56: Peak | N56: Peak | O56: =COUNTIF(C56:N56,"Peak")+COUNTIF(C56:N56,"In") | P56: Eat as-is + recipes
A57: P056 | B57: Cabbage (white) | C57: In | D57: In | E57: In | F57: In | G57: In | H57: In | I57: In | J57: In | K57: In | L57: In | M57: In | N57: In | O57: =COUNTIF(C57:N57,"Peak")+COUNTIF(C57:N57,"In") | P57: Recipe ingredient
A58: P057 | B58: Purple cabbage | C58: In | D58: In | E58: In | F58: In | G58: In | H58: In | I58: In | J58: In | K58: In | L58: In | M58: In | N58: In | O58: =COUNTIF(C58:N58,"Peak")+COUNTIF(C58:N58,"In") | P58: Recipe ingredient
A59: P058 | B59: Lettuce (iceberg / romaine / local) | C59: In | D59: In | E59: In | F59: In | G59: In | H59: In | I59: In | J59: In | K59: In | L59: In | M59: In | N59: In | O59: =COUNTIF(C59:N59,"Peak")+COUNTIF(C59:N59,"In") | P59: Recipe ingredient
A60: P059 | B60: Green beans | C60: In | D60: In | E60: In | F60: In | G60: In | H60: In | I60: In | J60: In | K60: In | L60: In | M60: In | N60: In | O60: =COUNTIF(C60:N60,"Peak")+COUNTIF(C60:N60,"In") | P60: Recipe ingredient
A61: P060 | B61: Sweet corn | F61: In | G61: In | H61: Peak | I61: Peak | J61: In | O61: =COUNTIF(C61:N61,"Peak")+COUNTIF(C61:N61,"In") | P61: Eat as-is + recipes
A62: P061 | B62: Garden egg | C62: In | D62: In | E62: In | F62: In | G62: In | H62: In | I62: In | J62: In | K62: In | L62: In | O62: =COUNTIF(C62:N62,"Peak")+COUNTIF(C62:N62,"In") | P62: Eat as-is + recipes
A63: P062 | B63: Okra | C63: In | D63: In | E63: In | F63: In | G63: In | H63: In | I63: In | J63: In | K63: In | L63: In | M63: In | N63: In | O63: =COUNTIF(C63:N63,"Peak")+COUNTIF(C63:N63,"In") | P63: Recipe ingredient
A64: P063 | B64: Broccoli | C64: In | D64: In | E64: In | F64: In | G64: In | H64: In | I64: In | J64: In | K64: In | L64: In | M64: In | N64: In | O64: =COUNTIF(C64:N64,"Peak")+COUNTIF(C64:N64,"In") | P64: Recipe ingredient
A65: P064 | B65: Cauliflower | C65: In | D65: In | E65: In | F65: In | G65: In | H65: In | I65: In | J65: In | K65: In | L65: In | M65: In | N65: In | O65: =COUNTIF(C65:N65,"Peak")+COUNTIF(C65:N65,"In") | P65: Recipe ingredient
A66: P065 | B66: Beetroot | C66: In | D66: In | E66: In | F66: In | G66: In | H66: In | I66: In | J66: In | K66: In | L66: In | M66: In | N66: In | O66: =COUNTIF(C66:N66,"Peak")+COUNTIF(C66:N66,"In") | P66: Recipe ingredient
A67: P066 | B67: Zucchini (courgette) | C67: In | D67: In | E67: In | F67: In | G67: In | H67: In | I67: In | J67: In | K67: In | L67: In | M67: In | N67: In | O67: =COUNTIF(C67:N67,"Peak")+COUNTIF(C67:N67,"In") | P67: Recipe ingredient
A68: P067 | B68: Mushrooms (oyster / button) | C68: In | D68: In | E68: In | F68: In | G68: In | H68: In | I68: In | J68: In | K68: In | L68: In | M68: In | N68: In | O68: =COUNTIF(C68:N68,"Peak")+COUNTIF(C68:N68,"In") | P68: Recipe ingredient
A69: P068 | B69: Pumpkin (squash) | C69: In | D69: In | E69: In | F69: In | G69: In | H69: In | I69: In | J69: In | K69: In | L69: In | M69: In | N69: In | O69: =COUNTIF(C69:N69,"Peak")+COUNTIF(C69:N69,"In") | P69: Recipe ingredient
A70: P069 | B70: Sweet potato | C70: In | D70: In | E70: In | F70: In | G70: In | H70: In | I70: In | J70: In | K70: In | L70: In | M70: In | N70: In | O70: =COUNTIF(C70:N70,"Peak")+COUNTIF(C70:N70,"In") | P70: Recipe ingredient
A71: P070 | B71: Irish potato | C71: In | D71: In | E71: In | F71: In | G71: In | H71: In | I71: In | J71: In | K71: In | L71: In | M71: In | N71: In | O71: =COUNTIF(C71:N71,"Peak")+COUNTIF(C71:N71,"In") | P71: Recipe ingredient
A72: P071 | B72: Yam | C72: In | D72: In | E72: In | F72: In | G72: In | H72: In | I72: In | J72: Peak | K72: Peak | L72: Peak | M72: In | N72: In | O72: =COUNTIF(C72:N72,"Peak")+COUNTIF(C72:N72,"In") | P72: Recipe ingredient
A73: P072 | B73: Fluted pumpkin leaf | C73: In | D73: In | E73: In | F73: In | G73: In | H73: In | I73: In | J73: In | K73: In | L73: In | M73: In | N73: In | O73: =COUNTIF(C73:N73,"Peak")+COUNTIF(C73:N73,"In") | P73: Recipe ingredient
A74: P073 | B74: Amaranth greens (Nigerian spinach) | C74: In | D74: In | E74: In | F74: In | G74: In | H74: In | I74: In | J74: In | K74: In | L74: In | M74: In | N74: In | O74: =COUNTIF(C74:N74,"Peak")+COUNTIF(C74:N74,"In") | P74: Recipe ingredient
... A85: P084 | B85: Rosemary | C85: In | D85: In | E85: In | F85: In | G85: In | H85: In | I85: In | J85: In | K85: In | L85: In | M85: In | N85: In | O85: =COUNTIF(C85:N85,"Peak")+COUNTIF(C85:N85,"In") | P85: Recipe ingredient
B87: Peak = best quality and price. In = available. Blank = scarce or out. Nigeria: dry season roughly Oct/Nov-Mar, rainy season Apr-Oct with the 'August break'.

Sheet Recipes
A1: ID | B1: Recipe | C1: Category | D1: Meal | E1: Inspired by | F1: Local adaptation | G1: Goal tags | H1: Diet | I1: Prep (min) | J1: Cook (min) | K1: Total (min) | L1: Effort tier | M1: Servings | N1: Est. kcal / serving | O1: Est. protein (g) / serving | P1: Hero produce | Q1: Basket items | R1: Other items | S1: Basket coverage | T1: Hits target? | U1: Seasonal ingredients | V1: Method | W1: Tip | X1: Status
A2: R015 | B2: Mango & Passion Fruit Overnight Oats | C2: Breakfast | D2: Breakfast | E2: Bircher muesli (Switzerland) / overnight oats | F2: Mango and passion fruit on top, tiger nut milk as an option. | G2: Training, Weight management | H2: Vegetarian | I2: 10 | J2: 0 | K2: =I2+J2 | L2: =IF(J2=0,"No-cook",IF(K2<=25,"Quick","Standard")) | M2: 2 | N2: 380 | O2: 14 | P2: Mango, Passion fruit | Q2: =COUNTIFS('Recipe Ingredients'!$A$2:$A$2000,A2,'Recipe Ingredients'!$G$2:$G$2000,"Basket") | R2: =COUNTIFS('Recipe Ingredients'!$A$2:$A$2000,A2,'Recipe Ingredients'!$G$2:$G$2000,"Protein")+COUNTIFS('Recipe Ingredients'!$A$2:$A$2000,A2,'Recipe Ingredients'!$G$2:$G$2000,"Pantry") | S2: =IFERROR(Q2/(Q2+R2),0) | T2: =IF(S2>='Start Here'!$C$6,"Yes","No") | U2: Mango (Feb-May, Aug-Sep); Passion fruit (Jan-Mar, May-Jun, Aug-Nov) | V2: 1. Stir oats, milk, yoghurt and chia together in two jars. 2. Cover and refrigerate overnight. 3. In the morning, top with diced mango and passion fruit pulp. 4. Drizzle with honey if you like. | W2: Make 3 days at once for a week of grab-and-go breakfasts. | X2: Draft
A3: R016 | B3: Pawpaw Boats with Yoghurt & Groundnut Crunch | C3: Breakfast | D3: Breakfast | E3: Papaya boats (Hawaii / Bali brunch spots) | F3: Crushed groundnuts and pineapple replace imported berries. | G3: Weight management, Wellness | H3: Vegetarian | I3: 5 | J3: 0 | K3: =I3+J3 | L3: =IF(J3=0,"No-cook",IF(K3<=25,"Quick","Standard")) | M3: 2 | N3: 320 | O3: 12 | P3: Pawpaw, Pineapple, Lime, Groundnut | Q3: =COUNTIFS('Recipe Ingredients'!$A$2:$A$2000,A3,'Recipe Ingredients'!$G$2:$G$2000,"Basket") | R3: =COUNTIFS('Recipe Ingredients'!$A$2:$A$2000,A3,'Recipe Ingredients'!$G$2:$G$2000,"Protein")+COUNTIFS('Recipe Ingredients'!$A$2:$A$2000,A3,'Recipe Ingredients'!$G$2:$G$2000,"Pantry") | S3: =IFERROR(Q3/(Q3+R3),0) | T3: =IF(S3>='Start Here'!$C$6,"Yes","No") | U3: Year-round | V3: 1. Halve the pawpaw lengthways and scoop out the seeds. 2. Fill each half with yoghurt. 3. Top with granola, pineapple and crushed groundnuts. 4. Finish with lime zest and a drizzle of honey. | X3: Draft
A4: R017 | B4: Banana Oat Pancakes with Pineapple Compote | C4: Breakfast | D4: Breakfast | E4: Three-ingredient banana pancakes (US fitness) | F4: Warm pineapple compote stands in for maple syrup and berries. | G4: Training | H4: Vegetarian | I4: 10 | J4: 15 | K4: =I4+J4 | L4: =IF(J4=0,"No-cook",IF(K4<=25,"Quick","Standard")) | M4: 2 | N4: 360 | O4: 15 | P4: Banana, Pineapple, Lime | Q4: =COUNTIFS('Recipe Ingredients'!$A$2:$A$2000,A4,'Recipe Ingredients'!$G$2:$G$2000,"Basket") | R4: =COUNTIFS('Recipe Ingredients'!$A$2:$A$2000,A4,'Recipe Ingredients'!$G$2:$G$2000,"Protein")+COUNTIFS('Recipe Ingredients'!$A$2:$A$2000,A4,'Recipe Ingredients'!$G$2:$G$2000,"Pantry") | S4: =IFERROR(Q4/(Q4+R4),0) | T4: =IF(S4>='Start Here'!$C$6,"Yes","No") | U4: Year-round | V4: 1. Blend bananas, eggs, oats and cinnamon into a thick batter. 2. Cook small pancakes in a lightly oiled pan, 2 minutes a side. 3. Simmer pineapple with lime juice for 5 minutes until jammy. 4. Stack the pancakes and spoon the compote over. | X4: Draft
A5: R018 | B5: Shakshuka with Tatashe & Efo | C5: Breakfast | D5: Brunch | E5: Shakshuka (North Africa / Middle East) | F5: The sauce is basically a lighter obe ata. Greens folded in at the end. | G5: Training, Weight management | H5: Vegetarian | I5: 10 | J5: 20 | K5: =I5+J5 | L5: =IF(J5=0,"No-cook",IF(K5<=25,"Quick","Standard")) | M5: 2 | N5: 330 | O5: 17 | P5: Tomato, Red bell pepper, Scotch bonnet, Onion | Q5: =COUNTIFS('Recipe Ingredients'!$A$2:$A$2000,A5,'Recipe Ingredients'!$G$2:$G$2000,"Basket") | R5: =COUNTIFS('Recipe Ingredients'!$A$2:$A$2000,A5,'Recipe Ingredients'!$G$2:$G$2000,"Protein")+COUNTIFS('Recipe Ingredients'!$A$2:$A$2000,A5,'Recipe Ingredients'!$G$2:$G$2000,"Pantry") | S5: =IFERROR(Q5/(Q5+R5),0) | T5: =IF(S5>='Start Here'!$C$6,"Yes","No") | U5: Year-round | V5: 1. Soften chopped onion and garlic in oil. 2. Add chopped tomatoes, tatashe, ata rodo and cumin. Simmer 10 minutes until thick. 3. Stir in the efo tete, then make four wells and crack in the eggs. 4. Cover and cook 5 to 6 minutes until the whites set. Serve with bread. | X5: Draft
A6: R019 | B6: Avocado Toast with Ata Rodo Salsa | C6: Breakfast | D6: Breakfast | E6: Avocado toast (Australian cafe culture) | F6: A fresh tomato, onion and ata rodo salsa on top instead of chilli flakes. | G6: Wellness, Weight management | H6: Vegetarian | I6: 10 | J6: 3 | K6: =I6+J6 | L6: =IF(J6=0,"No-cook",IF(K6<=25,"Quick","Standard")) | M6: 2 | N6: 380 | O6: 13 | P6: Avocado, Tomato, Onion, Scotch bonnet | Q6: =COUNTIFS('Recipe Ingredients'!$A$2:$A$2000,A6,'Recipe Ingredients'!$G$2:$G$2000,"Basket") | R6: =COUNTIFS('Recipe Ingredients'!$A$2:$A$2000,A6,'Recipe Ingredients'!$G$2:$G$2000,"Protein")+COUNTIFS('Recipe Ingredients'!$A$2:$A$2000,A6,'Recipe Ingredients'!$G$2:$G$2000,"Pantry") | S6: =IFERROR(Q6/(Q6+R6),0) | T6: =IF(S6>='Start Here'!$C$6,"Yes","No") | U6: Year-round | V6: 1. Toast the bread. 2. Mash avocado with half the lime juice and a pinch of salt. 3. Dice tomato, onion and ata rodo and toss with the rest of the lime. 4. Spread avocado, spoon over salsa, top with sliced boiled egg if using. | X6: Draft
A7: R020 | B7: Sweet Potato Breakfast Hash | C7: Breakfast | D7: Breakfast | E7: American diner hash | F7: Sweet potato is cheaper locally than Irish potato and keeps you full longer. | G7: Training | H7: Vegetarian | I7: 10 | J7: 20 | K7: =I7+J7 | L7: =IF(J7=0,"No-cook",IF(K7<=25,"Quick","Standard")) | M7: 2 | N7: 420 | O7: 16 | P7: Sweet potato, Onion, Red bell pepper, Amaranth greens | Q7: =COUNTIFS('Recipe Ingredients'!$A$2:$A$2000,A7,'Recipe Ingredients'!$G$2:$G$2000,"Basket") | R7: =COUNTIFS('Recipe Ingredients'!$A$2:$A$2000,A7,'Recipe Ingredients'!$G$2:$G$2000,"Protein")+COUNTIFS('Recipe Ingredients'!$A$2:$A$2000,A7,'Recipe Ingredients'!$G$2:$G$2000,"Pantry") | S7: =IFERROR(Q7/(Q7+R7),0) | T7: =IF(S7>='Start Here'!$C$6,"Yes","No") | U7: Year-round | V7: 1. Dice sweet potatoes small and fry in oil for 10 minutes until golden. 2. Add onion and tatashe, cook 4 minutes. Season with paprika and salt. 3. Stir in efo tete until wilted. 4. Make wells, crack in eggs, cover until set. Finish with spring onion. | X7: Draft
A8: R021 | B8: Plantain & Efo Frittata | C8: Breakfast | D8: Breakfast / Lunch | E8: Spanish tortilla / Italian frittata | F8: Ripe plantain takes the place of potato. Dodo meets tortilla. | G8: Training | H8: Vegetarian | I8: 10 | J8: 20 | K8: =I8+J8 | L8: =IF(J8=0,"No-cook",IF(K8<=25,"Quick","Standard")) | M8: 3 | N8: 350 | O8: 15 | P8: Plantain, Amaranth greens, Onion, Red bell pepper | Q8: =COUNTIFS('Recipe Ingredients'!$A$2:$A$2000,A8,'Recipe Ingredients'!$G$2:$G$2000,"Basket") | R8: =COUNTIFS('Recipe Ingredients'!$A$2:$A$2000,A8,'Recipe Ingredients'!$G$2:$G$2000,"Protein")+COUNTIFS('Recipe Ingredients'!$A$2:$A$2000,A8,'Recipe Ingredients'!$G$2:$G$2000,"Pantry") | S8: =IFERROR(Q8/(Q8+R8),0) | T8: =IF(S8>='Start Here'!$C$6,"Yes","No") | U8: Year-round | V8: 1. Slice the plantain and fry until golden on both sides. 2. Add onion, tatashe and ata rodo, cook 3 minutes, then the efo. 3. Pour over beaten, seasoned eggs. 4. Cook on low with a lid until set, about 8 minutes. Slice like a cake. | W8: Cold slices travel well in a lunch box. | X8: Draft
A9: R022 | B9: Tropical Parfait with Tiger Nut Crumble | C9: Breakfast | D9: Breakfast / Snack | E9: Yoghurt parfait (France / US cafes) | F9: Tiger nut and coconut crumble replaces store-bought granola. | G9: Weight management, Wellness | H9: Vegetarian | I9: 10 | J9: 0 | K9: =I9+J9 | L9: =IF(J9=0,"No-cook",IF(K9<=25,"Quick","Standard")) | M9: 2 | N9: 340 | O9: 14 | P9: Pineapple, Banana, Mango, Tiger nut | Q9: =COUNTIFS('Recipe Ingredients'!$A$2:$A$2000,A9,'Recipe Ingredients'!$G$2:$G$2000,"Basket") | R9: =COUNTIFS('Recipe Ingredients'!$A$2:$A$2000,A9,'Recipe Ingredients'!$G$2:$G$2000,"Protein")+COUNTIFS('Recipe Ingredients'!$A$2:$A$2000,A9,'Recipe Ingredients'!$G$2:$G$2000,"Pantry") | S9: =IFERROR(Q9/(Q9+R9),0) | T9: =IF(S9>='Start Here'!$C$6,"Yes","No") | U9: Mango (Feb-May, Aug-Sep); Tiger nut (Nov-May, Jul-Sep) | V9: 1. Chop tiger nuts roughly and toast with grated coconut in a dry pan for 3 minutes. 2. Dice pineapple, banana and mango. 3. Layer yoghurt, fruit and crumble in two glasses. 4. Finish with honey. | W9: Off season, pawpaw replaces mango. | X9: Draft
A10: R023 | B10: Coconut Chia Pudding with Mango | C10: Breakfast | D10: Breakfast / Dessert | E10: Chia pudding (wellness cafes) | F10: Fresh coconut milk and dates instead of canned milk and maple syrup. | G10: Plant-based, Wellness | H10: Vegan | I10: 10 | J10: 0 | K10: =I10+J10 | L10: =IF(J10=0,"No-cook",IF(K10<=25,"Quick","Standard")) | M10: 2 | N10: 320 | O10: 7 | P10: Coconut, Dates, Mango, Lime | Q10: =COUNTIFS('Recipe Ingredients'!$A$2:$A$2000,A10,'Recipe Ingredients'!$G$2:$G$2000,"Basket") | R10: =COUNTIFS('Recipe Ingredients'!$A$2:$A$2000,A10,'Recipe Ingredients'!$G$2:$G$2000,"Protein")+COUNTIFS('Recipe Ingredients'!$A$2:$A$2000,A10,'Recipe Ingredients'!$G$2:$G$2000,"Pantry") | S10: =IFERROR(Q10/(Q10+R10),0) | T10: =IF(S10>='Start Here'!$C$6,"Yes","No") | U10: Mango (Feb-May, Aug-Sep) | V10: 1. Blend coconut flesh with warm water and dates, then strain to get sweet coconut milk. 2. Stir chia seeds into the milk and leave 10 minutes, then stir again. 3. Refrigerate at least 4 hours. 4. Top with diced mango and lime zest. | X10: Draft
A11: R024 | B11: Chilli-Lime Fruit Cup (Yaji Edition) | C11: Snack | D11: Snack | E11: Mexican fruit cup with chile and lime (Tajin) | F11: Yaji replaces Tajin. Same salty, spicy, sour hit on cold fruit. | G11: Hydration, Weight management | H11: Vegan | I11: 10 | J11: 0 | K11: =I11+J11 | L11: =IF(J11=0,"No-cook",IF(K11<=25,"Quick","Standard")) | M11: 2 | N11: 120 | O11: 2 | P11: Watermelon, Pineapple, Pawpaw, Cucumber | Q11: =COUNTIFS('Recipe Ingredients'!$A$2:$A$2000,A11,'Recipe Ingredients'!$G$2:$G$2000,"Basket") | R11: =COUNTIFS('Recipe Ingredients'!$A$2:$A$2000,A11,'Recipe Ingredients'!$G$2:$G$2000,"Protein")+COUNTIFS('Recipe Ingredients'!$A$2:$A$2000,A11,'Recipe Ingredients'!$G$2:$G$2000,"Pantry") | S11: =IFERROR(Q11/(Q11+R11),0) | T11: =IF(S11>='Start Here'!$C$6,"Yes","No") | U11: Mango (Feb-May, Aug-Sep) | V11: 1. Cut all the fruit and cucumber into spears or chunks. 2. Pile into cups. 3. Squeeze lime over generously. 4. Dust with yaji and a pinch of salt just before eating. | W11: A strong candidate for a ready-to-eat snack box. | X11: Draft
A12: R025 | B12: Garden Egg Chopped Salad | C12: Salad | D12: Lunch / Side | E12: Shirazi / Israeli chopped salad | F12: Raw garden egg adds a crunchy, slightly bitter bite. | G12: Weight management, Wellness | H12: Vegan | I12: 15 | J12: 0 | K12: =I12+J12 | L12: =IF(J12=0,"No-cook",IF(K12<=25,"Quick","Standard")) | M12: 2 | N12: 140 | O12: 3 | P12: Garden egg, Tomato, Cucumber, Onion | Q12: =COUNTIFS('Recipe Ingredients'!$A$2:$A$2000,A12,'Recipe Ingredients'!$G$2:$G$2000,"Basket") | R12: =COUNTIFS('Recipe Ingredients'!$A$2:$A$2000,A12,'Recipe Ingredients'!$G$2:$G$2000,"Protein")+COUNTIFS('Recipe Ingredients'!$A$2:$A$2000,A12,'Recipe Ingredients'!$G$2:$G$2000,"Pantry") | S12: =IFERROR(Q12/(Q12+R12),0) | T12: =IF(S12>='Start Here'!$C$6,"Yes","No") | U12: Garden egg (Jan-Oct) | V12: 1. Dice garden eggs, tomatoes, cucumber and onion into small even pieces. 2. Chop the parsley. 3. Dress with lemon juice, olive oil and salt. 4. Rest 5 minutes before serving. | W12: Scent leaf instead of parsley gives it a distinctly Nigerian finish. | X12: Draft
A13: R026 | B13: Grilled Pineapple & Chicken Salad | C13: Salad | D13: Lunch / Dinner | E13: Hawaiian grilled chicken salad | F13: Yaji-rubbed chicken and local lettuce. | G13: Training, Weight management | H13: Contains meat | I13: 15 | J13: 15 | K13: =I13+J13 | L13: =IF(J13=0,"No-cook",IF(K13<=25,"Quick","Standard")) | M13: 2 | N13: 420 | O13: 35 | P13: Pineapple, Lettuce, Cucumber, Red bell pepper | Q13: =COUNTIFS('Recipe Ingredients'!$A$2:$A$2000,A13,'Recipe Ingredients'!$G$2:$G$2000,"Basket") | R13: =COUNTIFS('Recipe Ingredients'!$A$2:$A$2000,A13,'Recipe Ingredients'!$G$2:$G$2000,"Protein")+COUNTIFS('Recipe Ingredients'!$A$2:$A$2000,A13,'Recipe Ingredients'!$G$2:$G$2000,"Pantry") | S13: =IFERROR(Q13/(Q13+R13),0) | T13: =IF(S13>='Start Here'!$C$6,"Yes","No") | U13: Year-round | V13: 1. Rub chicken with yaji, oil and salt. Grill or pan-fry 6 minutes a side. 2. Grill pineapple rings until charred. 3. Whisk lime juice, honey and oil into a dressing. 4. Toss lettuce, cucumber, tatashe and spring onion with dressing. Top with sliced chicken and pineapple. | X13: Draft
A14: R027 | B14: Avocado, Mango & Cucumber Salad | C14: Salad | D14: Lunch / Side | E14: Mexican mango and avocado salad | F14: Ata rodo for heat, coriander for freshness. | G14: Wellness, Plant-based | H14: Vegan | I14: 15 | J14: 0 | K14: =I14+J14 | L14: =IF(J14=0,"No-cook",IF(K14<=25,"Quick","Standard")) | M14: 2 | N14: 260 | O14: 3 | P14: Avocado, Mango, Cucumber, Onion | Q14: =COUNTIFS('Recipe Ingredients'!$A$2:$A$2000,A14,'Recipe Ingredients'!$G$2:$G$2000,"Basket") | R14: =COUNTIFS('Recipe Ingredients'!$A$2:$A$2000,A14,'Recipe Ingredients'!$G$2:$G$2000,"Protein")+COUNTIFS('Recipe Ingredients'!$A$2:$A$2000,A14,'Recipe Ingredients'!$G$2:$G$2000,"Pantry") | S14: =IFERROR(Q14/(Q14+R14),0) | T14: =IF(S14>='Start Here'!$C$6,"Yes","No") | U14: Mango (Feb-May, Aug-Sep) | V14: 1. Cube avocado, mango and cucumber. 2. Finely slice onion and ata rodo. 3. Toss with lime juice, olive oil and salt. 4. Scatter coriander over the top. | W14: Best Feb to May. Use pineapple off season. | X14: Draft
A15: R028 | B15: Watermelon, Cucumber & Grilled Wara Salad | C15: Salad | D15: Lunch / Side | E15: Watermelon and feta salad (Greece / Levant) | F15: Grilled wara (local soft cheese) replaces feta. | G15: Hydration, Wellness | H15: Vegetarian | I15: 15 | J15: 5 | K15: =I15+J15 | L15: =IF(J15=0,"No-cook",IF(K15<=25,"Quick","Standard")) | M15: 2 | N15: 230 | O15: 12 | P15: Watermelon, Cucumber, Onion, Mint | Q15: =COUNTIFS('Recipe Ingredients'!$A$2:$A$2000,A15,'Recipe Ingredients'!$G$2:$G$2000,"Basket") | R15: =COUNTIFS('Recipe Ingredients'!$A$2:$A$2000,A15,'Recipe Ingredients'!$G$2:$G$2000,"Protein")+COUNTIFS('Recipe Ingredients'!$A$2:$A$2000,A15,'Recipe Ingredients'!$G$2:$G$2000,"Pantry") | S15: =IFERROR(Q15/(Q15+R15),0) | T15: =IF(S15>='Start Here'!$C$6,"Yes","No") | U15: Year-round | V15: 1. Slice wara and sear in a hot pan until golden on both sides. 2. Cube watermelon and cucumber, thinly slice the onion. 3. Toss with lime juice, mint and olive oil. 4. Top with the warm wara and black pepper. | X15: Draft
A16: R029 | B16: Lighter Chicken Caesar | C16: Salad | D16: Lunch / Dinner | E16: Caesar salad (Tijuana, Mexico) | F16: Yoghurt, garlic and lemon dressing instead of a mayo-heavy one. | G16: Training, Weight management | H16: Contains meat | I16: 15 | J16: 15 | K16: =I16+J16 | L16: =IF(J16=0,"No-cook",IF(K16<=25,"Quick","Standard")) | M16: 2 | N16: 430 | O16: 38 | P16: Lettuce, Tomato, Lemon, Garlic | Q16: =COUNTIFS('Recipe Ingredients'!$A$2:$A$2000,A16,'Recipe Ingredients'!$G$2:$G$2000,"Basket") | R16: =COUNTIFS('Recipe Ingredients'!$A$2:$A$2000,A16,'Recipe Ingredients'!$G$2:$G$2000,"Protein")+COUNTIFS('Recipe Ingredients'!$A$2:$A$2000,A16,'Recipe Ingredients'!$G$2:$G$2000,"Pantry") | S16: =IFERROR(Q16/(Q16+R16),0) | T16: =IF(S16>='Start Here'!$C$6,"Yes","No") | U16: Year-round | V16: 1. Season and grill the chicken, then slice. 2. Whisk yoghurt, grated garlic, lemon juice, mustard and half the parmesan. 3. Tear lettuce and toss with tomatoes and dressing. 4. Top with chicken, croutons and the rest of the parmesan. | X16: Draft
A17: R030 | B17: Crunchy Groundnut Cabbage Slaw | C17: Salad | D17: Side / Lunch | E17: Thai / Asian slaw with peanut dressing | F17: Local groundnut paste and both cabbages. | G17: Plant-based, Weight management | H17: Vegan | I17: 20 | J17: 0 | K17: =I17+J17 | L17: =IF(J17=0,"No-cook",IF(K17<=25,"Quick","Standard")) | M17: 4 | N17: 210 | O17: 7 | P17: Cabbage, Purple cabbage, Carrot, Spring onion | Q17: =COUNTIFS('Recipe Ingredients'!$A$2:$A$2000,A17,'Recipe Ingredients'!$G$2:$G$2000,"Basket") | R17: =COUNTIFS('Recipe Ingredients'!$A$2:$A$2000,A17,'Recipe Ingredients'!$G$2:$G$2000,"Protein")+COUNTIFS('Recipe Ingredients'!$A$2:$A$2000,A17,'Recipe Ingredients'!$G$2:$G$2000,"Pantry") | S17: =IFERROR(Q17/(Q17+R17),0) | T17: =IF(S17>='Start Here'!$C$6,"Yes","No") | U17: Year-round | V17: 1. Finely shred both cabbages and julienne the carrots. 2. Whisk groundnut paste, lime juice, grated ginger, soy and honey with a splash of water. 3. Toss vegetables with dressing. 4. Top with spring onion, coriander and roasted groundnuts. | W17: Holds well for 2 days, so it is a good meal-prep side. | X17: Draft
A18: R031 | B18: Greek Salad with Wara | C18: Salad | D18: Lunch / Side | E18: Horiatiki (Greece) | F18: Wara replaces feta, local green pepper stays. | G18: Weight management, Wellness | H18: Vegetarian | I18: 15 | J18: 0 | K18: =I18+J18 | L18: =IF(J18=0,"No-cook",IF(K18<=25,"Quick","Standard")) | M18: 2 | N18: 280 | O18: 12 | P18: Tomato, Cucumber, Green / yellow bell pepper, Onion | Q18: =COUNTIFS('Recipe Ingredients'!$A$2:$A$2000,A18,'Recipe Ingredients'!$G$2:$G$2000,"Basket") | R18: =COUNTIFS('Recipe Ingredients'!$A$2:$A$2000,A18,'Recipe Ingredients'!$G$2:$G$2000,"Protein")+COUNTIFS('Recipe Ingredients'!$A$2:$A$2000,A18,'Recipe Ingredients'!$G$2:$G$2000,"Pantry") | S18: =IFERROR(Q18/(Q18+R18),0) | T18: =IF(S18>='Start Here'!$C$6,"Yes","No") | U18: Year-round | V18: 1. Cut tomatoes and cucumber into chunks. 2. Slice green pepper and onion into rings. 3. Add olives and cubes of wara. 4. Dress with olive oil, lemon and oregano. | X18: Draft
A19: R032 | B19: Orange, Spinach & Tiger Nut Salad | C19: Salad | D19: Lunch / Side | E19: Californian citrus spinach salad | F19: Local oranges or tangerines and tiger nuts for crunch. | G19: Wellness, Plant-based | H19: Vegan | I19: 15 | J19: 0 | K19: =I19+J19 | L19: =IF(J19=0,"No-cook",IF(K19<=25,"Quick","Standard")) | M19: 2 | N19: 220 | O19: 5 | P19: Baby spinach, Orange, Onion, Tiger nut | Q19: =COUNTIFS('Recipe Ingredients'!$A$2:$A$2000,A19,'Recipe Ingredients'!$G$2:$G$2000,"Basket") | R19: =COUNTIFS('Recipe Ingredients'!$A$2:$A$2000,A19,'Recipe Ingredients'!$G$2:$G$2000,"Protein")+COUNTIFS('Recipe Ingredients'!$A$2:$A$2000,A19,'Recipe Ingredients'!$G$2:$G$2000,"Pantry") | S19: =IFERROR(Q19/(Q19+R19),0) | T19: =IF(S19>='Start Here'!$C$6,"Yes","No") | U19: Tiger nut (Nov-May, Jul-Sep) | V19: 1. Peel and segment the oranges, saving the juice. 2. Whisk saved juice with lemon, honey and olive oil. 3. Toss spinach, onion, avocado and orange segments with the dressing. 4. Scatter sliced tiger nuts on top. | W19: Best Oct to Jan when citrus is at its peak. Use dates instead of honey to keep it vegan. | X19: Draft
A20: R033 | B20: Roast Sweet Potato & Efo Salad | C20: Salad | D20: Lunch | E20: Roasted sweet potato and kale salad (US) | F20: Young efo tete or ugu replaces kale. | G20: Training, Wellness | H20: Vegetarian | I20: 10 | J20: 25 | K20: =I20+J20 | L20: =IF(J20=0,"No-cook",IF(K20<=25,"Quick","Standard")) | M20: 2 | N20: 350 | O20: 9 | P20: Sweet potato, Amaranth greens, Onion, Groundnut | Q20: =COUNTIFS('Recipe Ingredients'!$A$2:$A$2000,A20,'Recipe Ingredients'!$G$2:$G$2000,"Basket") | R20: =COUNTIFS('Recipe Ingredients'!$A$2:$A$2000,A20,'Recipe Ingredients'!$G$2:$G$2000,"Protein")+COUNTIFS('Recipe Ingredients'!$A$2:$A$2000,A20,'Recipe Ingredients'!$G$2:$G$2000,"Pantry") | S20: =IFERROR(Q20/(Q20+R20),0) | T20: =IF(S20>='Start Here'!$C$6,"Yes","No") | U20: Year-round | V20: 1. Cube sweet potatoes, toss with oil, paprika and salt. Roast at 200C for 25 minutes. 2. Massage the efo with a little salt and lime juice for 1 minute. 3. Whisk remaining lime with honey and a splash of oil. 4. Toss warm potatoes with greens and onion, top with groundnuts. | X20: Draft
A21: R034 | B21: Black-Eyed Bean 'Lagos Caviar' | C21: Salad | D21: Lunch / Side | E21: Texas caviar (US South) | F21: Black-eyed beans are the original bean in the US recipe. Tatashe and ata rodo bring it home. | G21: Plant-based, Training | H21: Vegan | I21: 15 | J21: 30 | K21: =I21+J21 | L21: =IF(J21=0,"No-cook",IF(K21<=25,"Quick","Standard")) | M21: 4 | N21: 260 | O21: 12 | P21: Sweet corn, Red bell pepper, Tomato, Onion | Q21: =COUNTIFS('Recipe Ingredients'!$A$2:$A$2000,A21,'Recipe Ingredients'!$G$2:$G$2000,"Basket") | R21: =COUNTIFS('Recipe Ingredients'!$A$2:$A$2000,A21,'Recipe Ingredients'!$G$2:$G$2000,"Protein")+COUNTIFS('Recipe Ingredients'!$A$2:$A$2000,A21,'Recipe Ingredients'!$G$2:$G$2000,"Pantry") | S21: =IFERROR(Q21/(Q21+R21),0) | T21: =IF(S21>='Start Here'!$C$6,"Yes","No") | U21: Sweet corn (Apr-Aug) | V21: 1. Cook the beans until just tender (or use leftover beans). Cool. 2. Boil or char the corn and cut off the kernels. 3. Dice tatashe, tomatoes, onion and ata rodo. 4. Toss everything with lime juice, olive oil, salt and coriander. | W21: Even better the next day. | X21: Draft
A22: R035 | B22: Lagos Nicoise | C22: Salad | D22: Lunch / Dinner | E22: Salade nicoise (Nice, France) | F22: Jos potatoes and green beans with canned tuna or sardines. | G22: Training | H22: Pescatarian | I22: 15 | J22: 20 | K22: =I22+J22 | L22: =IF(J22=0,"No-cook",IF(K22<=25,"Quick","Standard")) | M22: 2 | N22: 450 | O22: 30 | P22: Irish potato, Green beans, Tomato, Lettuce | Q22: =COUNTIFS('Recipe Ingredients'!$A$2:$A$2000,A22,'Recipe Ingredients'!$G$2:$G$2000,"Basket") | R22: =COUNTIFS('Recipe Ingredients'!$A$2:$A$2000,A22,'Recipe Ingredients'!$G$2:$G$2000,"Protein")+COUNTIFS('Recipe Ingredients'!$A$2:$A$2000,A22,'Recipe Ingredients'!$G$2:$G$2000,"Pantry") | S22: =IFERROR(Q22/(Q22+R22),0) | T22: =IF(S22>='Start Here'!$C$6,"Yes","No") | U22: Year-round | V22: 1. Boil potatoes until tender. Add green beans for the last 3 minutes. Boil the eggs. 2. Whisk lemon juice, mustard, olive oil and salt. 3. Arrange lettuce, potatoes, beans, tomatoes, onion, tuna, halved eggs and olives. 4. Spoon over the dressing. | X22: Draft
A23: R036 | B23: Green Pawpaw Salad | C23: Salad | D23: Lunch / Side | E23: Som tam (Thailand) | F23: Unripe Nigerian pawpaw is the same fruit Thai cooks use. Groundnuts replace peanuts. | G23: Weight management, Wellness | H23: Pescatarian | I23: 20 | J23: 0 | K23: =I23+J23 | L23: =IF(J23=0,"No-cook",IF(K23<=25,"Quick","Standard")) | M23: 2 | N23: 180 | O23: 5 | P23: Pawpaw, Carrot, Tomato, Garlic | Q23: =COUNTIFS('Recipe Ingredients'!$A$2:$A$2000,A23,'Recipe Ingredients'!$G$2:$G$2000,"Basket") | R23: =COUNTIFS('Recipe Ingredients'!$A$2:$A$2000,A23,'Recipe Ingredients'!$G$2:$G$2000,"Protein")+COUNTIFS('Recipe Ingredients'!$A$2:$A$2000,A23,'Recipe Ingredients'!$G$2:$G$2000,"Pantry") | S23: =IFERROR(Q23/(Q23+R23),0) | T23: =IF(S23>='Start Here'!$C$6,"Yes","No") | U23: Year-round | V23: 1. Peel and finely shred the green pawpaw and carrot. 2. Pound garlic and ata rodo, then add lime, fish sauce and honey. 3. Lightly bruise tomatoes and green beans in the dressing. 4. Toss with pawpaw and carrot. Top with groundnuts. | W23: Use soy sauce instead of fish sauce to make it vegan. | X23: Draft
A24: R037 | B24: Moroccan Carrot & Orange Salad | C24: Salad | D24: Side | E24: Moroccan carrot salad | F24: Jos carrots, local oranges and fresh mint. | G24: Wellness, Plant-based | H24: Vegan | I24: 15 | J24: 0 | K24: =I24+J24 | L24: =IF(J24=0,"No-cook",IF(K24<=25,"Quick","Standard")) | M24: 2 | N24: 150 | O24: 2 | P24: Carrot, Orange, Mint, Lemon | Q24: =COUNTIFS('Recipe Ingredients'!$A$2:$A$2000,A24,'Recipe Ingredients'!$G$2:$G$2000,"Basket") | R24: =COUNTIFS('Recipe Ingredients'!$A$2:$A$2000,A24,'Recipe Ingredients'!$G$2:$G$2000,"Protein")+COUNTIFS('Recipe Ingredients'!$A$2:$A$2000,A24,'Recipe Ingredients'!$G$2:$G$2000,"Pantry") | S24: =IFERROR(Q24/(Q24+R24),0) | T24: =IF(S24>='Start Here'!$C$6,"Yes","No") | U24: Year-round | V24: 1. Coarsely grate the carrots. 2. Segment the orange and add the juice. 3. Season with lemon, cumin, cinnamon, olive oil and salt. 4. Toss with torn mint. | X24: Draft
A25: R038 | B25: Beetroot, Orange & Avocado Salad | C25: Salad | D25: Lunch / Side | E25: Bistro beet and citrus salad | F25: Local beetroot, boiled rather than roasted to save gas. | G25: Training, Wellness | H25: Vegetarian | I25: 15 | J25: 40 | K25: =I25+J25 | L25: =IF(J25=0,"No-cook",IF(K25<=25,"Quick","Standard")) | M25: 2 | N25: 260 | O25: 4 | P25: Beetroot, Orange, Avocado, Lettuce | Q25: =COUNTIFS('Recipe Ingredients'!$A$2:$A$2000,A25,'Recipe Ingredients'!$G$2:$G$2000,"Basket") | R25: =COUNTIFS('Recipe Ingredients'!$A$2:$A$2000,A25,'Recipe Ingredients'!$G$2:$G$2000,"Protein")+COUNTIFS('Recipe Ingredients'!$A$2:$A$2000,A25,'Recipe Ingredients'!$G$2:$G$2000,"Pantry") | S25: =IFERROR(Q25/(Q25+R25),0) | T25: =IF(S25>='Start Here'!$C$6,"Yes","No") | U25: Year-round | V25: 1. Boil beetroot until tender, about 40 minutes. Cool, peel and slice. 2. Segment the orange and slice the avocado. 3. Arrange on lettuce with onion. 4. Dress with lemon, honey and olive oil. Top with groundnuts. | X25: Draft
A26: R039 | B26: Kachumbari | C26: Side | D26: Side | E26: Kachumbari (Kenya / Tanzania) | F26: Ata rodo for heat. Built to sit next to grilled fish, suya or rice. | G26: Weight management, Plant-based | H26: Vegan | I26: 10 | J26: 0 | K26: =I26+J26 | L26: =IF(J26=0,"No-cook",IF(K26<=25,"Quick","Standard")) | M26: 4 | N26: 50 | O26: 1 | P26: Tomato, Onion, Cucumber, Scotch bonnet | Q26: =COUNTIFS('Recipe Ingredients'!$A$2:$A$2000,A26,'Recipe Ingredients'!$G$2:$G$2000,"Basket") | R26: =COUNTIFS('Recipe Ingredients'!$A$2:$A$2000,A26,'Recipe Ingredients'!$G$2:$G$2000,"Protein")+COUNTIFS('Recipe Ingredients'!$A$2:$A$2000,A26,'Recipe Ingredients'!$G$2:$G$2000,"Pantry") | S26: =IFERROR(Q26/(Q26+R26),0) | T26: =IF(S26>='Start Here'!$C$6,"Yes","No") | U26: Year-round | V26: 1. Dice tomatoes and cucumber. 2. Slice onion very thinly and rinse in cold water to tame it. 3. Finely chop ata rodo and coriander. 4. Toss with lime juice and salt. | X26: Draft
A27: R040 | B27: Chicken Suya Power Bowl | C27: Bowl | D27: Lunch / Dinner | E27: Fast-casual grain bowls (US, e.g. Sweetgreen) | F27: Suya-spiced chicken with the classic suya garnish of onion, tomato and cabbage. | G27: Training | H27: Contains meat | I27: 20 | J27: 20 | K27: =I27+J27 | L27: =IF(J27=0,"No-cook",IF(K27<=25,"Quick","Standard")) | M27: 2 | N27: 580 | O27: 42 | P27: Cabbage, Tomato, Onion, Cucumber | Q27: =COUNTIFS('Recipe Ingredients'!$A$2:$A$2000,A27,'Recipe Ingredients'!$G$2:$G$2000,"Basket") | R27: =COUNTIFS('Recipe Ingredients'!$A$2:$A$2000,A27,'Recipe Ingredients'!$G$2:$G$2000,"Protein")+COUNTIFS('Recipe Ingredients'!$A$2:$A$2000,A27,'Recipe Ingredients'!$G$2:$G$2000,"Pantry") | S27: =IFERROR(Q27/(Q27+R27),0) | T27: =IF(S27>='Start Here'!$C$6,"Yes","No") | U27: Year-round | V27: 1. Cook the rice. 2. Coat chicken in yaji and oil, then grill or pan-fry 6 minutes a side. Slice. 3. Shred cabbage, slice tomatoes, onion and cucumber, slice the avocado. 4. Build bowls: rice, vegetables, chicken. Finish with lime and extra yaji. | W27: Swap rice for quinoa or extra cabbage on lower-carb days. | X27: Draft
A28: R041 | B28: Burrito Bowl with Dodo | C28: Bowl | D28: Lunch / Dinner | E28: Burrito bowl (Tex-Mex) | F28: Ripe plantain and black-eyed beans take the place of pinto beans and sweet corn. | G28: Training, Plant-based | H28: Vegan | I28: 20 | J28: 25 | K28: =I28+J28 | L28: =IF(J28=0,"No-cook",IF(K28<=25,"Quick","Standard")) | M28: 2 | N28: 620 | O28: 18 | P28: Plantain, Sweet corn, Tomato, Onion | Q28: =COUNTIFS('Recipe Ingredients'!$A$2:$A$2000,A28,'Recipe Ingredients'!$G$2:$G$2000,"Basket") | R28: =COUNTIFS('Recipe Ingredients'!$A$2:$A$2000,A28,'Recipe Ingredients'!$G$2:$G$2000,"Protein")+COUNTIFS('Recipe Ingredients'!$A$2:$A$2000,A28,'Recipe Ingredients'!$G$2:$G$2000,"Pantry") | S28: =IFERROR(Q28/(Q28+R28),0) | T28: =IF(S28>='Start Here'!$C$6,"Yes","No") | U28: Sweet corn (Apr-Aug) | V28: 1. Cook rice. Warm beans with cumin and salt. 2. Slice plantain and roast or pan-fry until caramelised. Char the corn and slice off the kernels. 3. Make a quick salsa: tomato, onion, ata rodo, coriander, lime. 4. Build bowls with lettuce, rice, beans, plantain, corn, salsa and sliced avocado. | X28: Draft
A29: R042 | B29: Mango Prawn Poke-Style Bowl | C29: Bowl | D29: Lunch / Dinner | E29: Poke (Hawaii) | F29: Cooked prawns instead of raw fish, which is safer for home delivery. Mango for sweetness. | G29: Training, Weight management | H29: Pescatarian | I29: 20 | J29: 20 | K29: =I29+J29 | L29: =IF(J29=0,"No-cook",IF(K29<=25,"Quick","Standard")) | M29: 2 | N29: 520 | O29: 30 | P29: Mango, Cucumber, Carrot, Avocado | Q29: =COUNTIFS('Recipe Ingredients'!$A$2:$A$2000,A29,'Recipe Ingredients'!$G$2:$G$2000,"Basket") | R29: =COUNTIFS('Recipe Ingredients'!$A$2:$A$2000,A29,'Recipe Ingredients'!$G$2:$G$2000,"Protein")+COUNTIFS('Recipe Ingredients'!$A$2:$A$2000,A29,'Recipe Ingredients'!$G$2:$G$2000,"Pantry") | S29: =IFERROR(Q29/(Q29+R29),0) | T29: =IF(S29>='Start Here'!$C$6,"Yes","No") | U29: Mango (Feb-May, Aug-Sep) | V29: 1. Cook rice and let it cool slightly. 2. Saute prawns 2 to 3 minutes until pink. Toss in soy, sesame oil, honey and lime. 3. Dice mango, cucumber and avocado. Shred the carrot. 4. Build bowls and top with spring onion. | X29: Draft
A30: R043 | B30: Teriyaki Chicken & Broccoli Bowl | C30: Bowl | D30: Dinner | E30: Japanese-American teriyaki bowl | F30: Fresh ginger and garlic glaze. Green beans are the budget swap for broccoli. | G30: Training | H30: Contains meat | I30: 15 | J30: 20 | K30: =I30+J30 | L30: =IF(J30=0,"No-cook",IF(K30<=25,"Quick","Standard")) | M30: 2 | N30: 560 | O30: 40 | P30: Broccoli, Carrot, Spring onion, Ginger | Q30: =COUNTIFS('Recipe Ingredients'!$A$2:$A$2000,A30,'Recipe Ingredients'!$G$2:$G$2000,"Basket") | R30: =COUNTIFS('Recipe Ingredients'!$A$2:$A$2000,A30,'Recipe Ingredients'!$G$2:$G$2000,"Protein")+COUNTIFS('Recipe Ingredients'!$A$2:$A$2000,A30,'Recipe Ingredients'!$G$2:$G$2000,"Pantry") | S30: =IFERROR(Q30/(Q30+R30),0) | T30: =IF(S30>='Start Here'!$C$6,"Yes","No") | U30: Year-round | V30: 1. Cook rice. 2. Simmer soy, honey, grated ginger and garlic for 2 minutes to make the glaze. 3. Pan-fry chicken pieces until cooked, then toss in the glaze. 4. Steam broccoli and sliced carrots 4 minutes. Serve over rice with spring onion. | X30: Draft
A31: R044 | B31: Black-Eyed Bean Falafel Bowl | C31: Bowl | D31: Lunch / Dinner | E31: Falafel bowl (Levant) | F31: Black-eyed beans (akara's cousin) replace chickpeas. Scent leaf joins parsley. | G31: Plant-based, Training | H31: Vegetarian | I31: 25 | J31: 20 | K31: =I31+J31 | L31: =IF(J31=0,"No-cook",IF(K31<=25,"Quick","Standard")) | M31: 3 | N31: 540 | O31: 20 | P31: Onion, Garlic, Parsley, Scent leaf | Q31: =COUNTIFS('Recipe Ingredients'!$A$2:$A$2000,A31,'Recipe Ingredients'!$G$2:$G$2000,"Basket") | R31: =COUNTIFS('Recipe Ingredients'!$A$2:$A$2000,A31,'Recipe Ingredients'!$G$2:$G$2000,"Protein")+COUNTIFS('Recipe Ingredients'!$A$2:$A$2000,A31,'Recipe Ingredients'!$G$2:$G$2000,"Pantry") | S31: =IFERROR(Q31/(Q31+R31),0) | T31: =IF(S31>='Start Here'!$C$6,"Yes","No") | U31: Year-round | V31: 1. Blend soaked, peeled beans with onion, garlic, herbs, cumin and salt into a coarse paste. 2. Shape into small patties and bake at 200C for 20 minutes, flipping once (or shallow fry). 3. Mix yoghurt with lemon juice and a little grated garlic. 4. Serve with chopped lettuce, tomatoes, cucumber, pita and the yoghurt sauce. | W31: The paste is basically akara batter with herbs, so most Nigerian cooks nail it first try. | X31: Draft
A32: R045 | B32: Sweet Potato Buddha Bowl with Ugu Pesto | C32: Bowl | D32: Lunch / Dinner | E32: Buddha bowl (US vegan cafes) | F32: Ugu and groundnut pesto replaces tahini dressing. | G32: Plant-based, Wellness | H32: Vegan | I32: 20 | J32: 30 | K32: =I32+J32 | L32: =IF(J32=0,"No-cook",IF(K32<=25,"Quick","Standard")) | M32: 2 | N32: 560 | O32: 18 | P32: Sweet potato, Fluted pumpkin leaf, Groundnut, Garlic | Q32: =COUNTIFS('Recipe Ingredients'!$A$2:$A$2000,A32,'Recipe Ingredients'!$G$2:$G$2000,"Basket") | R32: =COUNTIFS('Recipe Ingredients'!$A$2:$A$2000,A32,'Recipe Ingredients'!$G$2:$G$2000,"Protein")+COUNTIFS('Recipe Ingredients'!$A$2:$A$2000,A32,'Recipe Ingredients'!$G$2:$G$2000,"Pantry") | S32: =IFERROR(Q32/(Q32+R32),0) | T32: =IF(S32>='Start Here'!$C$6,"Yes","No") | U32: Year-round | V32: 1. Roast cubed sweet potato with oil and salt at 200C for 25 to 30 minutes. 2. Cook quinoa or rice. Warm the chickpeas or beans. 3. Blend ugu, groundnuts, garlic, lemon, olive oil and salt into a pesto. 4. Build bowls with grain, sweet potato, beans, cucumber and grated carrot. Spoon over the pesto. | X32: Draft
A33: R046 | B33: Bibimbap-Style Beef Bowl | C33: Bowl | D33: Dinner | E33: Bibimbap (Korea) | F33: Efo tete stands in for spinach. A honey and ata rodo sauce replaces gochujang. | G33: Training | H33: Contains meat | I33: 25 | J33: 20 | K33: =I33+J33 | L33: =IF(J33=0,"No-cook",IF(K33<=25,"Quick","Standard")) | M33: 2 | N33: 610 | O33: 35 | P33: Amaranth greens, Carrot, Cucumber, Mushrooms | Q33: =COUNTIFS('Recipe Ingredients'!$A$2:$A$2000,A33,'Recipe Ingredients'!$G$2:$G$2000,"Basket") | R33: =COUNTIFS('Recipe Ingredients'!$A$2:$A$2000,A33,'Recipe Ingredients'!$G$2:$G$2000,"Protein")+COUNTIFS('Recipe Ingredients'!$A$2:$A$2000,A33,'Recipe Ingredients'!$G$2:$G$2000,"Pantry") | S33: =IFERROR(Q33/(Q33+R33),0) | T33: =IF(S33>='Start Here'!$C$6,"Yes","No") | U33: Year-round | V33: 1. Cook rice. 2. Brown beef with garlic and half the soy. Saute mushrooms, then wilt the efo. 3. Mix the rest of the soy with honey, sesame oil and finely chopped ata rodo. 4. Top rice with julienned carrot and cucumber, the cooked vegetables, beef and a fried egg. Drizzle sauce. | X33: Draft
A34: R047 | B34: Thai Groundnut Wara Bowl | C34: Bowl | D34: Lunch / Dinner | E34: Thai peanut tofu bowl | F34: Wara soya is Nigerian tofu. Groundnut sauce does the rest. | G34: Plant-based, Training | H34: Vegan | I34: 20 | J34: 15 | K34: =I34+J34 | L34: =IF(J34=0,"No-cook",IF(K34<=25,"Quick","Standard")) | M34: 2 | N34: 540 | O34: 24 | P34: Purple cabbage, Carrot, Cucumber, Spring onion | Q34: =COUNTIFS('Recipe Ingredients'!$A$2:$A$2000,A34,'Recipe Ingredients'!$G$2:$G$2000,"Basket") | R34: =COUNTIFS('Recipe Ingredients'!$A$2:$A$2000,A34,'Recipe Ingredients'!$G$2:$G$2000,"Protein")+COUNTIFS('Recipe Ingredients'!$A$2:$A$2000,A34,'Recipe Ingredients'!$G$2:$G$2000,"Pantry") | S34: =IFERROR(Q34/(Q34+R34),0) | T34: =IF(S34>='Start Here'!$C$6,"Yes","No") | U34: Year-round | V34: 1. Press and cube the wara soya, then pan-fry until golden. 2. Blend groundnut paste, soy, lime juice, ginger, garlic, dates and warm water into a pourable sauce. 3. Cook rice or noodles. Shred cabbage and carrot, slice cucumber. 4. Build bowls, pour over sauce, top with spring onion and coriander. | X34: Draft
A35: R048 | B35: Greek Chicken Gyro Bowl with Tzatziki | C35: Bowl | D35: Lunch / Dinner | E35: Gyro (Greece) | F35: Tzatziki made with local cucumber, mint or parsley. | G35: Training, Weight management | H35: Contains meat | I35: 20 | J35: 20 | K35: =I35+J35 | L35: =IF(J35=0,"No-cook",IF(K35<=25,"Quick","Standard")) | M35: 2 | N35: 560 | O35: 42 | P35: Cucumber, Tomato, Onion, Lettuce | Q35: =COUNTIFS('Recipe Ingredients'!$A$2:$A$2000,A35,'Recipe Ingredients'!$G$2:$G$2000,"Basket") | R35: =COUNTIFS('Recipe Ingredients'!$A$2:$A$2000,A35,'Recipe Ingredients'!$G$2:$G$2000,"Protein")+COUNTIFS('Recipe Ingredients'!$A$2:$A$2000,A35,'Recipe Ingredients'!$G$2:$G$2000,"Pantry") | S35: =IFERROR(Q35/(Q35+R35),0) | T35: =IF(S35>='Start Here'!$C$6,"Yes","No") | U35: Year-round | V35: 1. Marinate chicken in lemon juice, garlic, oregano, oil and salt for 10 minutes, then grill and slice. 2. Cook rice. 3. Grate half the cucumber, squeeze dry, mix with yoghurt, garlic and chopped mint. 4. Build bowls with lettuce, tomatoes, onion, the rest of the cucumber, chicken and tzatziki. | X35: Draft
A36: R049 | B36: Coconut Prawn & Mango Rice Bowl | C36: Bowl | D36: Dinner | E36: Caribbean / Thai coconut rice bowls | F36: Rice cooked in fresh coconut milk with a mango salsa. | G36: Training, Wellness | H36: Pescatarian | I36: 20 | J36: 25 | K36: =I36+J36 | L36: =IF(J36=0,"No-cook",IF(K36<=25,"Quick","Standard")) | M36: 2 | N36: 600 | O36: 28 | P36: Coconut, Mango, Onion, Red bell pepper | Q36: =COUNTIFS('Recipe Ingredients'!$A$2:$A$2000,A36,'Recipe Ingredients'!$G$2:$G$2000,"Basket") | R36: =COUNTIFS('Recipe Ingredients'!$A$2:$A$2000,A36,'Recipe Ingredients'!$G$2:$G$2000,"Protein")+COUNTIFS('Recipe Ingredients'!$A$2:$A$2000,A36,'Recipe Ingredients'!$G$2:$G$2000,"Pantry") | S36: =IFERROR(Q36/(Q36+R36),0) | T36: =IF(S36>='Start Here'!$C$6,"Yes","No") | U36: Mango (Feb-May, Aug-Sep) | V36: 1. Cook rice in fresh coconut milk topped up with water. 2. Saute prawns with garlic and a pinch of salt, 3 minutes. 3. Dice mango, tatashe, onion and ata rodo. Toss with lime and coriander. 4. Serve rice topped with prawns and salsa. | X36: Draft
A37: R050 | B37: Lighter Chicken Shawarma | C37: Wrap | D37: Lunch / Dinner | E37: Shawarma (Levant, via Lagos street food) | F37: Grilled not fried, yoghurt-garlic sauce instead of mayo, twice the vegetables. | G37: Training, Weight management | H37: Contains meat | I37: 20 | J37: 15 | K37: =I37+J37 | L37: =IF(J37=0,"No-cook",IF(K37<=25,"Quick","Standard")) | M37: 2 | N37: 520 | O37: 38 | P37: Cabbage, Carrot, Cucumber, Tomato | Q37: =COUNTIFS('Recipe Ingredients'!$A$2:$A$2000,A37,'Recipe Ingredients'!$G$2:$G$2000,"Basket") | R37: =COUNTIFS('Recipe Ingredients'!$A$2:$A$2000,A37,'Recipe Ingredients'!$G$2:$G$2000,"Protein")+COUNTIFS('Recipe Ingredients'!$A$2:$A$2000,A37,'Recipe Ingredients'!$G$2:$G$2000,"Pantry") | S37: =IFERROR(Q37/(Q37+R37),0) | T37: =IF(S37>='Start Here'!$C$6,"Yes","No") | U37: Year-round | V37: 1. Toss sliced chicken with curry powder, paprika, oil and salt. Pan-grill until charred. 2. Mix yoghurt, grated garlic, lemon and salt. 3. Shred cabbage and carrot, slice cucumber, tomatoes and onion. 4. Spread sauce on warm wraps, fill with vegetables and chicken, roll tight and toast seam-side down. | W37: The one people will order every week. Make it the hero of the launch menu. | X37: Draft
A38: R051 | B38: Fish Tacos with Pineapple Salsa | C38: Wrap | D38: Dinner | E38: Baja fish tacos (Mexico) | F38: Croaker or tilapia, pineapple and ata rodo salsa, cabbage slaw. | G38: Training, Weight management | H38: Pescatarian | I38: 20 | J38: 10 | K38: =I38+J38 | L38: =IF(J38=0,"No-cook",IF(K38<=25,"Quick","Standard")) | M38: 2 | N38: 480 | O38: 32 | P38: Pineapple, Onion, Scotch bonnet, Coriander | Q38: =COUNTIFS('Recipe Ingredients'!$A$2:$A$2000,A38,'Recipe Ingredients'!$G$2:$G$2000,"Basket") | R38: =COUNTIFS('Recipe Ingredients'!$A$2:$A$2000,A38,'Recipe Ingredients'!$G$2:$G$2000,"Protein")+COUNTIFS('Recipe Ingredients'!$A$2:$A$2000,A38,'Recipe Ingredients'!$G$2:$G$2000,"Pantry") | S38: =IFERROR(Q38/(Q38+R38),0) | T38: =IF(S38>='Start Here'!$C$6,"Yes","No") | U38: Year-round | V38: 1. Season fish with paprika, salt and lime. Pan-fry 3 minutes a side and flake. 2. Dice pineapple, onion and ata rodo. Mix with coriander and lime. 3. Shred cabbage and toss with lime and salt. 4. Warm tortillas and fill with slaw, fish, salsa and avocado. | X38: Draft
A39: R052 | B39: Chicken Lettuce Cups | C39: Wrap | D39: Lunch / Dinner | E39: San choy bau (Cantonese) | F39: Local iceberg cups with groundnuts for crunch. | G39: Weight management, Training | H39: Contains meat | I39: 15 | J39: 10 | K39: =I39+J39 | L39: =IF(J39=0,"No-cook",IF(K39<=25,"Quick","Standard")) | M39: 2 | N39: 350 | O39: 32 | P39: Lettuce, Carrot, Red bell pepper, Spring onion | Q39: =COUNTIFS('Recipe Ingredients'!$A$2:$A$2000,A39,'Recipe Ingredients'!$G$2:$G$2000,"Basket") | R39: =COUNTIFS('Recipe Ingredients'!$A$2:$A$2000,A39,'Recipe Ingredients'!$G$2:$G$2000,"Protein")+COUNTIFS('Recipe Ingredients'!$A$2:$A$2000,A39,'Recipe Ingredients'!$G$2:$G$2000,"Pantry") | S39: =IFERROR(Q39/(Q39+R39),0) | T39: =IF(S39>='Start Here'!$C$6,"Yes","No") | U39: Year-round | V39: 1. Finely chop or mince the chicken. 2. Stir-fry garlic and ginger for 30 seconds, add chicken, cook until no longer pink. 3. Add diced carrot and tatashe, soy and lime. Cook 2 minutes. 4. Spoon into lettuce cups. Top with spring onion and crushed groundnuts. | W39: Low-carb and quick. A strong pick for the weight-management goal filter. | X39: Draft
A40: R053 | B40: Suya Beef Lettuce Wraps | C40: Wrap | D40: Dinner | E40: Korean ssam (lettuce wraps) | F40: Suya beef with the full suya garnish, wrapped in lettuce. | G40: Training, Weight management | H40: Contains meat | I40: 15 | J40: 10 | K40: =I40+J40 | L40: =IF(J40=0,"No-cook",IF(K40<=25,"Quick","Standard")) | M40: 2 | N40: 380 | O40: 34 | P40: Lettuce, Onion, Tomato, Cucumber | Q40: =COUNTIFS('Recipe Ingredients'!$A$2:$A$2000,A40,'Recipe Ingredients'!$G$2:$G$2000,"Basket") | R40: =COUNTIFS('Recipe Ingredients'!$A$2:$A$2000,A40,'Recipe Ingredients'!$G$2:$G$2000,"Protein")+COUNTIFS('Recipe Ingredients'!$A$2:$A$2000,A40,'Recipe Ingredients'!$G$2:$G$2000,"Pantry") | S40: =IFERROR(Q40/(Q40+R40),0) | T40: =IF(S40>='Start Here'!$C$6,"Yes","No") | U40: Year-round | V40: 1. Rub thin beef slices with yaji, oil and salt. 2. Sear in a very hot pan, 1 to 2 minutes a side. 3. Slice onion, tomatoes and cucumber. 4. Wrap beef and vegetables in lettuce leaves. Squeeze lime over. | X40: Draft
A41: R054 | B41: Corn, Tatashe & Efo Quesadilla | C41: Wrap | D41: Lunch | E41: Quesadilla (Mexico) | F41: Local sweet corn, tatashe and efo inside. | G41: Training | H41: Vegetarian | I41: 10 | J41: 10 | K41: =I41+J41 | L41: =IF(J41=0,"No-cook",IF(K41<=25,"Quick","Standard")) | M41: 2 | N41: 480 | O41: 20 | P41: Sweet corn, Red bell pepper, Onion, Amaranth greens | Q41: =COUNTIFS('Recipe Ingredients'!$A$2:$A$2000,A41,'Recipe Ingredients'!$G$2:$G$2000,"Basket") | R41: =COUNTIFS('Recipe Ingredients'!$A$2:$A$2000,A41,'Recipe Ingredients'!$G$2:$G$2000,"Protein")+COUNTIFS('Recipe Ingredients'!$A$2:$A$2000,A41,'Recipe Ingredients'!$G$2:$G$2000,"Pantry") | S41: =IFERROR(Q41/(Q41+R41),0) | T41: =IF(S41>='Start Here'!$C$6,"Yes","No") | U41: Sweet corn (Apr-Aug) | V41: 1. Slice corn off the cob. Saute with onion, tatashe, ata rodo and cumin for 4 minutes. 2. Stir in efo until wilted. 3. Layer half of each tortilla with cheese and filling, fold, then toast 2 minutes a side. 4. Cut into wedges. Serve with sliced avocado. | X41: Draft
A42: R055 | B42: Egg & Avocado Breakfast Wrap | C42: Wrap | D42: Breakfast | E42: Breakfast burrito (US Southwest) | F42: The filling is a Nigerian egg sauce: tomato, onion and pepper scrambled with eggs. | G42: Training | H42: Vegetarian | I42: 10 | J42: 10 | K42: =I42+J42 | L42: =IF(J42=0,"No-cook",IF(K42<=25,"Quick","Standard")) | M42: 2 | N42: 450 | O42: 20 | P42: Avocado, Tomato, Onion, Scotch bonnet | Q42: =COUNTIFS('Recipe Ingredients'!$A$2:$A$2000,A42,'Recipe Ingredients'!$G$2:$G$2000,"Basket") | R42: =COUNTIFS('Recipe Ingredients'!$A$2:$A$2000,A42,'Recipe Ingredients'!$G$2:$G$2000,"Protein")+COUNTIFS('Recipe Ingredients'!$A$2:$A$2000,A42,'Recipe Ingredients'!$G$2:$G$2000,"Pantry") | S42: =IFERROR(Q42/(Q42+R42),0) | T42: =IF(S42>='Start Here'!$C$6,"Yes","No") | U42: Year-round | V42: 1. Saute diced onion, tomatoes and ata rodo in oil for 3 minutes. 2. Add efo, then the beaten eggs. Scramble softly. 3. Warm the wraps and spread with mashed avocado. 4. Fill with eggs and roll. | X42: Draft
A43: R056 | B43: Bean & Plantain Burrito | C43: Wrap | D43: Lunch / Dinner | E43: Bean burrito (Mexico / US) | F43: Ewa and dodo, the Nigerian favourite, wrapped Mexican-style. | G43: Training, Plant-based | H43: Vegetarian | I43: 15 | J43: 20 | K43: =I43+J43 | L43: =IF(J43=0,"No-cook",IF(K43<=25,"Quick","Standard")) | M43: 2 | N43: 610 | O43: 20 | P43: Plantain, Tomato, Onion, Scotch bonnet | Q43: =COUNTIFS('Recipe Ingredients'!$A$2:$A$2000,A43,'Recipe Ingredients'!$G$2:$G$2000,"Basket") | R43: =COUNTIFS('Recipe Ingredients'!$A$2:$A$2000,A43,'Recipe Ingredients'!$G$2:$G$2000,"Protein")+COUNTIFS('Recipe Ingredients'!$A$2:$A$2000,A43,'Recipe Ingredients'!$G$2:$G$2000,"Pantry") | S43: =IFERROR(Q43/(Q43+R43),0) | T43: =IF(S43>='Start Here'!$C$6,"Yes","No") | U43: Year-round | V43: 1. Warm beans with cumin, lightly mashing half. 2. Slice and fry the plantain until golden. 3. Make a quick salsa with tomato, onion, ata rodo and lime. 4. Fill wraps with beans, plantain, cheese, salsa and lettuce. Roll and toast. | X43: Draft
A44: R057 | B44: Sheet-Pan Lemon Herb Chicken | C44: Main | D44: Dinner | E44: Sheet-pan dinners (HelloFresh / US weeknight staple) | F44: Sweet potato and local green beans on one tray. | G44: Training | H44: Contains meat | I44: 15 | J44: 35 | K44: =I44+J44 | L44: =IF(J44=0,"No-cook",IF(K44<=25,"Quick","Standard")) | M44: 2 | N44: 560 | O44: 42 | P44: Sweet potato, Green beans, Onion, Lemon | Q44: =COUNTIFS('Recipe Ingredients'!$A$2:$A$2000,A44,'Recipe Ingredients'!$G$2:$G$2000,"Basket") | R44: =COUNTIFS('Recipe Ingredients'!$A$2:$A$2000,A44,'Recipe Ingredients'!$G$2:$G$2000,"Protein")+COUNTIFS('Recipe Ingredients'!$A$2:$A$2000,A44,'Recipe Ingredients'!$G$2:$G$2000,"Pantry") | S44: =IFERROR(Q44/(Q44+R44),0) | T44: =IF(S44>='Start Here'!$C$6,"Yes","No") | U44: Year-round | V44: 1. Heat oven to 200C. Cut sweet potatoes into wedges, quarter the onion. 2. Toss chicken and vegetables with oil, paprika, crushed garlic, lemon zest, rosemary and salt. 3. Roast 25 minutes, add green beans, roast 10 more. 4. Squeeze lemon over before serving. | W44: One tray, one wash-up. The format meal-kit customers love most. | X44: Draft
A45: R058 | B45: Ginger Chicken & Veg Stir-Fry | C45: Main | D45: Dinner | E45: Chinese stir-fry | F45: The 'Chinese restaurant' order Lagos loves, made with half the oil. | G45: Training, Weight management | H45: Contains meat | I45: 15 | J45: 12 | K45: =I45+J45 | L45: =IF(J45=0,"No-cook",IF(K45<=25,"Quick","Standard")) | M45: 2 | N45: 480 | O45: 38 | P45: Broccoli, Carrot, Red bell pepper, Green / yellow bell pepper | Q45: =COUNTIFS('Recipe Ingredients'!$A$2:$A$2000,A45,'Recipe Ingredients'!$G$2:$G$2000,"Basket") | R45: =COUNTIFS('Recipe Ingredients'!$A$2:$A$2000,A45,'Recipe Ingredients'!$G$2:$G$2000,"Protein")+COUNTIFS('Recipe Ingredients'!$A$2:$A$2000,A45,'Recipe Ingredients'!$G$2:$G$2000,"Pantry") | S45: =IFERROR(Q45/(Q45+R45),0) | T45: =IF(S45>='Start Here'!$C$6,"Yes","No") | U45: Year-round | V45: 1. Slice chicken thin and toss with 1 tbsp soy and the cornflour. 2. Stir-fry chicken in a very hot pan until browned. Remove. 3. Stir-fry garlic, ginger, broccoli, carrots and peppers for 3 to 4 minutes. 4. Return chicken with the rest of the soy and a splash of water. Toss, top with spring onion. Serve with rice or noodles. | X45: Draft
A46: R059 | B46: Thai Green Curry with Pumpkin & Ugu | C46: Main | D46: Dinner | E46: Thai green curry | F46: Elegede pumpkin, ugu greens and scent leaf, which is a basil, just like Thai basil. | G46: Training, Wellness | H46: Contains meat | I46: 20 | J46: 25 | K46: =I46+J46 | L46: =IF(J46=0,"No-cook",IF(K46<=25,"Quick","Standard")) | M46: 3 | N46: 520 | O46: 30 | P46: Pumpkin, Green beans, Fluted pumpkin leaf, Lemongrass | Q46: =COUNTIFS('Recipe Ingredients'!$A$2:$A$2000,A46,'Recipe Ingredients'!$G$2:$G$2000,"Basket") | R46: =COUNTIFS('Recipe Ingredients'!$A$2:$A$2000,A46,'Recipe Ingredients'!$G$2:$G$2000,"Protein")+COUNTIFS('Recipe Ingredients'!$A$2:$A$2000,A46,'Recipe Ingredients'!$G$2:$G$2000,"Pantry") | S46: =IFERROR(Q46/(Q46+R46),0) | T46: =IF(S46>='Start Here'!$C$6,"Yes","No") | U46: Year-round | V46: 1. Fry curry paste with bruised lemongrass, ginger and garlic for 1 minute. 2. Add chicken and brown lightly, then pour in coconut milk. 3. Add pumpkin and simmer 12 minutes until tender. Add green beans for the last 4. 4. Stir in ugu and scent leaf, season with fish sauce and lime. Serve with rice. | X46: Draft
A47: R060 | B47: Pepper Steak Stir-Fry | C47: Main | D47: Dinner | E47: Chinese-American pepper steak | F47: Tatashe and green pepper with local onions. | G47: Training | H47: Contains meat | I47: 15 | J47: 12 | K47: =I47+J47 | L47: =IF(J47=0,"No-cook",IF(K47<=25,"Quick","Standard")) | M47: 2 | N47: 500 | O47: 36 | P47: Red bell pepper, Green / yellow bell pepper, Onion, Garlic | Q47: =COUNTIFS('Recipe Ingredients'!$A$2:$A$2000,A47,'Recipe Ingredients'!$G$2:$G$2000,"Basket") | R47: =COUNTIFS('Recipe Ingredients'!$A$2:$A$2000,A47,'Recipe Ingredients'!$G$2:$G$2000,"Protein")+COUNTIFS('Recipe Ingredients'!$A$2:$A$2000,A47,'Recipe Ingredients'!$G$2:$G$2000,"Pantry") | S47: =IFERROR(Q47/(Q47+R47),0) | T47: =IF(S47>='Start Here'!$C$6,"Yes","No") | U47: Year-round | V47: 1. Slice beef very thin across the grain. Toss with 1 tbsp soy and cornflour. 2. Sear beef in batches in a very hot pan. Remove. 3. Stir-fry onion, peppers, garlic and ginger for 3 minutes. 4. Return beef with remaining soy and a splash of water. Finish with spring onion. Serve with rice. | X47: Draft
A48: R061 | B48: Prawn Cauliflower Fried 'Rice' | C48: Main | D48: Dinner | E48: Cauliflower rice (low-carb trend) and Chinese fried rice | F48: Party fried rice vegetables, with cauliflower standing in for rice. | G48: Weight management, Training | H48: Pescatarian | I48: 15 | J48: 12 | K48: =I48+J48 | L48: =IF(J48=0,"No-cook",IF(K48<=25,"Quick","Standard")) | M48: 2 | N48: 360 | O48: 30 | P48: Cauliflower, Carrot, Green beans, Spring onion | Q48: =COUNTIFS('Recipe Ingredients'!$A$2:$A$2000,A48,'Recipe Ingredients'!$G$2:$G$2000,"Basket") | R48: =COUNTIFS('Recipe Ingredients'!$A$2:$A$2000,A48,'Recipe Ingredients'!$G$2:$G$2000,"Protein")+COUNTIFS('Recipe Ingredients'!$A$2:$A$2000,A48,'Recipe Ingredients'!$G$2:$G$2000,"Pantry") | S48: =IFERROR(Q48/(Q48+R48),0) | T48: =IF(S48>='Start Here'!$C$6,"Yes","No") | U48: Year-round | V48: 1. Pulse cauliflower in a blender until rice-sized. 2. Stir-fry prawns with garlic and ginger, 2 minutes. Remove. 3. Stir-fry diced carrots and green beans 3 minutes, push aside, scramble the eggs. 4. Add cauliflower and soy, fry 4 minutes. Return prawns, finish with spring onion. | X48: Draft
A49: R062 | B49: Grilled Fish with Mango Salsa & Roast Plantain | C49: Main | D49: Dinner | E49: Caribbean grilled fish with mango salsa | F49: Croaker or tilapia, and plantain roasted rather than fried. | G49: Training | H49: Pescatarian | I49: 15 | J49: 25 | K49: =I49+J49 | L49: =IF(J49=0,"No-cook",IF(K49<=25,"Quick","Standard")) | M49: 2 | N49: 520 | O49: 36 | P49: Plantain, Mango, Onion, Scotch bonnet | Q49: =COUNTIFS('Recipe Ingredients'!$A$2:$A$2000,A49,'Recipe Ingredients'!$G$2:$G$2000,"Basket") | R49: =COUNTIFS('Recipe Ingredients'!$A$2:$A$2000,A49,'Recipe Ingredients'!$G$2:$G$2000,"Protein")+COUNTIFS('Recipe Ingredients'!$A$2:$A$2000,A49,'Recipe Ingredients'!$G$2:$G$2000,"Pantry") | S49: =IFERROR(Q49/(Q49+R49),0) | T49: =IF(S49>='Start Here'!$C$6,"Yes","No") | U49: Mango (Feb-May, Aug-Sep) | V49: 1. Rub fish with grated garlic, ginger, paprika, lime and salt. Rest 10 minutes. 2. Roast plantain slices at 200C for 20 minutes, flipping once. 3. Grill or oven-bake the fish for 15 to 20 minutes. 4. Mix diced mango, onion, ata rodo, coriander and lime. Spoon over the fish. | W49: Mango Feb to May. Pineapple works the rest of the year. | X49: Draft
A50: R063 | B50: Chickpea & Efo Curry | C50: Main | D50: Dinner | E50: Chana saag (India) | F50: Efo tete for spinach, fresh coconut milk for cream. | G50: Plant-based, Training | H50: Vegan | I50: 15 | J50: 25 | K50: =I50+J50 | L50: =IF(J50=0,"No-cook",IF(K50<=25,"Quick","Standard")) | M50: 3 | N50: 430 | O50: 16 | P50: Amaranth greens, Tomato, Onion, Garlic | Q50: =COUNTIFS('Recipe Ingredients'!$A$2:$A$2000,A50,'Recipe Ingredients'!$G$2:$G$2000,"Basket") | R50: =COUNTIFS('Recipe Ingredients'!$A$2:$A$2000,A50,'Recipe Ingredients'!$G$2:$G$2000,"Protein")+COUNTIFS('Recipe Ingredients'!$A$2:$A$2000,A50,'Recipe Ingredients'!$G$2:$G$2000,"Pantry") | S50: =IFERROR(Q50/(Q50+R50),0) | T50: =IF(S50>='Start Here'!$C$6,"Yes","No") | U50: Year-round | V50: 1. Soften onion, then add garlic, ginger, ata rodo, curry powder and cumin for 1 minute. 2. Add chopped tomatoes and cook down 8 minutes. 3. Stir in chickpeas and coconut milk. Simmer 10 minutes. 4. Fold in efo until wilted. Serve with rice or flatbread. | X50: Draft
A51: R064 | B51: Caribbean Curry Chicken & Sweet Potato | C51: Main | D51: Dinner | E51: Jamaican curry chicken | F51: Scotch bonnet is already ours. Sweet potato replaces potato. | G51: Training | H51: Contains meat | I51: 15 | J51: 40 | K51: =I51+J51 | L51: =IF(J51=0,"No-cook",IF(K51<=25,"Quick","Standard")) | M51: 4 | N51: 520 | O51: 35 | P51: Sweet potato, Onion, Garlic, Ginger | Q51: =COUNTIFS('Recipe Ingredients'!$A$2:$A$2000,A51,'Recipe Ingredients'!$G$2:$G$2000,"Basket") | R51: =COUNTIFS('Recipe Ingredients'!$A$2:$A$2000,A51,'Recipe Ingredients'!$G$2:$G$2000,"Protein")+COUNTIFS('Recipe Ingredients'!$A$2:$A$2000,A51,'Recipe Ingredients'!$G$2:$G$2000,"Pantry") | S51: =IFERROR(Q51/(Q51+R51),0) | T51: =IF(S51>='Start Here'!$C$6,"Yes","No") | U51: Year-round | V51: 1. Season chicken with curry powder, thyme, garlic, ginger and salt. 2. Brown chicken in oil, add onion, tomatoes and the whole ata rodo. 3. Add water to half-cover, simmer 20 minutes. 4. Add cubed sweet potato and simmer 15 more until tender. Finish with spring onion. Serve with rice. | W51: Leave the ata rodo whole for flavour without too much heat. | X51: Draft
A52: R065 | B52: Fresh Tomato & Basil Garden Pasta | C52: Main | D52: Dinner | E52: Pasta al pomodoro (Italy) | F52: Plum tomatoes plus tatashe for a sweeter sauce. Scent leaf works if basil is scarce. | G52: Training | H52: Vegetarian | I52: 10 | J52: 20 | K52: =I52+J52 | L52: =IF(J52=0,"No-cook",IF(K52<=25,"Quick","Standard")) | M52: 2 | N52: 520 | O52: 18 | P52: Tomato, Red bell pepper, Onion, Garlic | Q52: =COUNTIFS('Recipe Ingredients'!$A$2:$A$2000,A52,'Recipe Ingredients'!$G$2:$G$2000,"Basket") | R52: =COUNTIFS('Recipe Ingredients'!$A$2:$A$2000,A52,'Recipe Ingredients'!$G$2:$G$2000,"Protein")+COUNTIFS('Recipe Ingredients'!$A$2:$A$2000,A52,'Recipe Ingredients'!$G$2:$G$2000,"Pantry") | S52: =IFERROR(Q52/(Q52+R52),0) | T52: =IF(S52>='Start Here'!$C$6,"Yes","No") | U52: Year-round | V52: 1. Cook pasta. 2. Soften onion and garlic in olive oil, add chopped tomatoes and tatashe. Simmer 12 minutes. 3. Add mushrooms and spinach, cook 2 minutes. 4. Toss with pasta, torn basil and parmesan. | X52: Draft
A53: R066 | B53: Stuffed Tatashe with Beef & Corn | C53: Main | D53: Dinner | E53: Stuffed peppers (US / Mediterranean) | F53: The filling is a jollof-spiced rice and beef mix. | G53: Training | H53: Contains meat | I53: 20 | J53: 35 | K53: =I53+J53 | L53: =IF(J53=0,"No-cook",IF(K53<=25,"Quick","Standard")) | M53: 2 | N53: 540 | O53: 30 | P53: Red bell pepper, Sweet corn, Tomato, Onion | Q53: =COUNTIFS('Recipe Ingredients'!$A$2:$A$2000,A53,'Recipe Ingredients'!$G$2:$G$2000,"Basket") | R53: =COUNTIFS('Recipe Ingredients'!$A$2:$A$2000,A53,'Recipe Ingredients'!$G$2:$G$2000,"Protein")+COUNTIFS('Recipe Ingredients'!$A$2:$A$2000,A53,'Recipe Ingredients'!$G$2:$G$2000,"Pantry") | S53: =IFERROR(Q53/(Q53+R53),0) | T53: =IF(S53>='Start Here'!$C$6,"Yes","No") | U53: Sweet corn (Apr-Aug) | V53: 1. Halve tatashe and remove seeds. 2. Brown beef with onion, garlic, ata rodo, curry and thyme. Add chopped tomatoes and corn, cook 5 minutes. 3. Stir in the cooked rice. 4. Fill the peppers, top with cheese and bake at 190C for 25 minutes. | X53: Draft
A54: R067 | B54: Light Vegetable Egg Fried Rice | C54: Main | D54: Lunch / Dinner | E54: Yangzhou fried rice (China) | F54: Party fried rice vegetables, with a fraction of the oil. | G54: Training | H54: Vegetarian | I54: 15 | J54: 15 | K54: =I54+J54 | L54: =IF(J54=0,"No-cook",IF(K54<=25,"Quick","Standard")) | M54: 3 | N54: 450 | O54: 14 | P54: Carrot, Green beans, Sweet corn, Spring onion | Q54: =COUNTIFS('Recipe Ingredients'!$A$2:$A$2000,A54,'Recipe Ingredients'!$G$2:$G$2000,"Basket") | R54: =COUNTIFS('Recipe Ingredients'!$A$2:$A$2000,A54,'Recipe Ingredients'!$G$2:$G$2000,"Protein")+COUNTIFS('Recipe Ingredients'!$A$2:$A$2000,A54,'Recipe Ingredients'!$G$2:$G$2000,"Pantry") | S54: =IFERROR(Q54/(Q54+R54),0) | T54: =IF(S54>='Start Here'!$C$6,"Yes","No") | U54: Sweet corn (Apr-Aug) | V54: 1. Dice carrots and green beans. Slice corn off the cob. 2. Scramble the eggs in a hot pan, then remove. 3. Stir-fry garlic, ginger and vegetables 4 minutes. 4. Add rice, soy and curry powder. Fry until hot, fold in eggs and spring onion. | W54: Day-old rice fries best. | X54: Draft
A55: R068 | B55: Kerala-Style Okra & Prawn Coconut Curry | C55: Main | D55: Dinner | E55: Kerala prawn curry / bhindi masala (India) | F55: Nigerian okra cooked whole so it stays crisp, not slimy. | G55: Training, Wellness | H55: Pescatarian | I55: 15 | J55: 20 | K55: =I55+J55 | L55: =IF(J55=0,"No-cook",IF(K55<=25,"Quick","Standard")) | M55: 3 | N55: 430 | O55: 26 | P55: Okra, Onion, Tomato, Garlic | Q55: =COUNTIFS('Recipe Ingredients'!$A$2:$A$2000,A55,'Recipe Ingredients'!$G$2:$G$2000,"Basket") | R55: =COUNTIFS('Recipe Ingredients'!$A$2:$A$2000,A55,'Recipe Ingredients'!$G$2:$G$2000,"Protein")+COUNTIFS('Recipe Ingredients'!$A$2:$A$2000,A55,'Recipe Ingredients'!$G$2:$G$2000,"Pantry") | S55: =IFERROR(Q55/(Q55+R55),0) | T55: =IF(S55>='Start Here'!$C$6,"Yes","No") | U55: Turmeric (Sep-Jun) | V55: 1. Trim okra and leave whole. Pan-fry in oil for 4 minutes, then set aside. 2. Soften onion, add garlic, ginger, grated turmeric, ata rodo and curry powder. 3. Add chopped tomatoes and cook 5 minutes, then the coconut milk. 4. Add prawns and okra, simmer 4 minutes. Finish with lime. Serve with rice. | X55: Draft
A56: R069 | B56: Garden Egg Ratatouille | C56: Main | D56: Dinner / Side | E56: Ratatouille (Provence, France) | F56: Garden egg replaces aubergine. Zucchini optional. | G56: Plant-based, Weight management | H56: Vegan | I56: 20 | J56: 40 | K56: =I56+J56 | L56: =IF(J56=0,"No-cook",IF(K56<=25,"Quick","Standard")) | M56: 4 | N56: 180 | O56: 4 | P56: Garden egg, Zucchini, Red bell pepper, Green / yellow bell pepper | Q56: =COUNTIFS('Recipe Ingredients'!$A$2:$A$2000,A56,'Recipe Ingredients'!$G$2:$G$2000,"Basket") | R56: =COUNTIFS('Recipe Ingredients'!$A$2:$A$2000,A56,'Recipe Ingredients'!$G$2:$G$2000,"Protein")+COUNTIFS('Recipe Ingredients'!$A$2:$A$2000,A56,'Recipe Ingredients'!$G$2:$G$2000,"Pantry") | S56: =IFERROR(Q56/(Q56+R56),0) | T56: =IF(S56>='Start Here'!$C$6,"Yes","No") | U56: Garden egg (Jan-Oct) | V56: 1. Cut all vegetables into similar bite-sized chunks. 2. Soften onion and garlic in olive oil, add peppers for 5 minutes. 3. Add garden eggs and zucchini for 5 minutes, then tomatoes and thyme. 4. Simmer gently 25 minutes. Finish with torn scent leaf. | W56: Serve with rice, bread or grilled fish. Better the next day. | X56: Draft
A57: R070 | B57: Grilled Chicken with Scent Leaf Chimichurri | C57: Main | D57: Dinner | E57: Chimichurri (Argentina) | F57: Scent leaf (efirin) and parsley base, ata rodo for heat. | G57: Training | H57: Contains meat | I57: 15 | J57: 20 | K57: =I57+J57 | L57: =IF(J57=0,"No-cook",IF(K57<=25,"Quick","Standard")) | M57: 2 | N57: 560 | O57: 42 | P57: Scent leaf, Parsley, Garlic, Scotch bonnet | Q57: =COUNTIFS('Recipe Ingredients'!$A$2:$A$2000,A57,'Recipe Ingredients'!$G$2:$G$2000,"Basket") | R57: =COUNTIFS('Recipe Ingredients'!$A$2:$A$2000,A57,'Recipe Ingredients'!$G$2:$G$2000,"Protein")+COUNTIFS('Recipe Ingredients'!$A$2:$A$2000,A57,'Recipe Ingredients'!$G$2:$G$2000,"Pantry") | S57: =IFERROR(Q57/(Q57+R57),0) | T57: =IF(S57>='Start Here'!$C$6,"Yes","No") | U57: Year-round | V57: 1. Roast sweet potato wedges at 200C for 25 minutes. 2. Season and grill the chicken. 3. Finely chop scent leaf, parsley, garlic and ata rodo. Mix with vinegar, lime, olive oil and salt. 4. Slice chicken and spoon chimichurri over it. Serve with the wedges. | W57: Chimichurri keeps a week in the fridge. Great on fish and eggs too. | X57: Draft
A58: R071 | B58: Foil-Baked Fish with Lemon, Tomato & Greens | C58: Main | D58: Dinner | E58: Fish en papillote (France) | F58: Local fish, ginger and efo, with potatoes on the side. | G58: Weight management, Training | H58: Pescatarian | I58: 10 | J58: 20 | K58: =I58+J58 | L58: =IF(J58=0,"No-cook",IF(K58<=25,"Quick","Standard")) | M58: 2 | N58: 340 | O58: 36 | P58: Tomato, Lemon, Amaranth greens, Onion | Q58: =COUNTIFS('Recipe Ingredients'!$A$2:$A$2000,A58,'Recipe Ingredients'!$G$2:$G$2000,"Basket") | R58: =COUNTIFS('Recipe Ingredients'!$A$2:$A$2000,A58,'Recipe Ingredients'!$G$2:$G$2000,"Protein")+COUNTIFS('Recipe Ingredients'!$A$2:$A$2000,A58,'Recipe Ingredients'!$G$2:$G$2000,"Pantry") | S58: =IFERROR(Q58/(Q58+R58),0) | T58: =IF(S58>='Start Here'!$C$6,"Yes","No") | U58: Year-round | V58: 1. Boil potatoes until tender. 2. Lay efo on foil, top with fish, sliced tomatoes, onion, garlic, ginger and lemon slices. 3. Drizzle with olive oil, season, scatter herbs and seal the parcels. 4. Bake at 200C for 15 to 18 minutes. Serve with potatoes. | X58: Draft
A59: R072 | B59: Ugu & Groundnut Pesto Pasta | C59: Main | D59: Lunch / Dinner | E59: Pesto alla genovese (Italy) | F59: Ugu and groundnuts replace basil and pine nuts, which cost a fortune here. | G59: Training, Plant-based | H59: Vegetarian | I59: 15 | J59: 12 | K59: =I59+J59 | L59: =IF(J59=0,"No-cook",IF(K59<=25,"Quick","Standard")) | M59: 2 | N59: 580 | O59: 20 | P59: Fluted pumpkin leaf, Scent leaf, Groundnut, Garlic | Q59: =COUNTIFS('Recipe Ingredients'!$A$2:$A$2000,A59,'Recipe Ingredients'!$G$2:$G$2000,"Basket") | R59: =COUNTIFS('Recipe Ingredients'!$A$2:$A$2000,A59,'Recipe Ingredients'!$G$2:$G$2000,"Protein")+COUNTIFS('Recipe Ingredients'!$A$2:$A$2000,A59,'Recipe Ingredients'!$G$2:$G$2000,"Pantry") | S59: =IFERROR(Q59/(Q59+R59),0) | T59: =IF(S59>='Start Here'!$C$6,"Yes","No") | U59: Year-round | V59: 1. Cook pasta. 2. Blanch ugu for 30 seconds, then cool in cold water and squeeze dry. 3. Blend ugu, scent leaf, groundnuts, garlic, lemon, parmesan and olive oil. 4. Toss pasta with pesto and a splash of pasta water. Top with halved tomatoes. | W59: Skip the parmesan and add extra groundnuts to make it vegan. | X59: Draft
A60: R073 | B60: Roasted Pumpkin & Ginger Soup | C60: Soup | D60: Lunch / Dinner | E60: Butternut squash soup | F60: Elegede pumpkin, lots of ginger and fresh coconut milk. | G60: Wellness, Plant-based | H60: Vegan | I60: 15 | J60: 35 | K60: =I60+J60 | L60: =IF(J60=0,"No-cook",IF(K60<=25,"Quick","Standard")) | M60: 4 | N60: 210 | O60: 4 | P60: Pumpkin, Carrot, Onion, Garlic | Q60: =COUNTIFS('Recipe Ingredients'!$A$2:$A$2000,A60,'Recipe Ingredients'!$G$2:$G$2000,"Basket") | R60: =COUNTIFS('Recipe Ingredients'!$A$2:$A$2000,A60,'Recipe Ingredients'!$G$2:$G$2000,"Protein")+COUNTIFS('Recipe Ingredients'!$A$2:$A$2000,A60,'Recipe Ingredients'!$G$2:$G$2000,"Pantry") | S60: =IFERROR(Q60/(Q60+R60),0) | T60: =IF(S60>='Start Here'!$C$6,"Yes","No") | U60: Year-round | V60: 1. Roast pumpkin, carrots, onion and garlic with oil at 200C for 25 minutes. 2. Transfer to a pot with ginger, ata rodo and stock. Simmer 10 minutes. 3. Blend until smooth. 4. Stir in coconut milk and season. | X60: Draft
A61: R074 | B61: Roasted Tomato & Tatashe Soup | C61: Soup | D61: Lunch / Dinner | E61: Roasted red pepper and tomato soup | F61: Basically a smooth, lighter obe ata you eat with a spoon. | G61: Weight management, Wellness | H61: Vegetarian | I61: 10 | J61: 35 | K61: =I61+J61 | L61: =IF(J61=0,"No-cook",IF(K61<=25,"Quick","Standard")) | M61: 4 | N61: 160 | O61: 4 | P61: Tomato, Red bell pepper, Onion, Garlic | Q61: =COUNTIFS('Recipe Ingredients'!$A$2:$A$2000,A61,'Recipe Ingredients'!$G$2:$G$2000,"Basket") | R61: =COUNTIFS('Recipe Ingredients'!$A$2:$A$2000,A61,'Recipe Ingredients'!$G$2:$G$2000,"Protein")+COUNTIFS('Recipe Ingredients'!$A$2:$A$2000,A61,'Recipe Ingredients'!$G$2:$G$2000,"Pantry") | S61: =IFERROR(Q61/(Q61+R61),0) | T61: =IF(S61>='Start Here'!$C$6,"Yes","No") | U61: Year-round | V61: 1. Halve tomatoes and tatashe, roast with onion, garlic and ata rodo at 200C for 25 minutes. 2. Blend with stock until smooth. 3. Simmer 5 minutes and season. 4. Serve with torn basil and crusty bread. | X61: Draft
A62: R075 | B62: Coconut Lemongrass Chicken Soup | C62: Soup | D62: Dinner | E62: Tom kha gai (Thailand) | F62: Fresh coconut milk, local lemongrass, and ginger in place of galangal. | G62: Wellness, Training | H62: Contains meat | I62: 15 | J62: 20 | K62: =I62+J62 | L62: =IF(J62=0,"No-cook",IF(K62<=25,"Quick","Standard")) | M62: 3 | N62: 380 | O62: 26 | P62: Coconut, Lemongrass, Ginger, Mushrooms | Q62: =COUNTIFS('Recipe Ingredients'!$A$2:$A$2000,A62,'Recipe Ingredients'!$G$2:$G$2000,"Basket") | R62: =COUNTIFS('Recipe Ingredients'!$A$2:$A$2000,A62,'Recipe Ingredients'!$G$2:$G$2000,"Protein")+COUNTIFS('Recipe Ingredients'!$A$2:$A$2000,A62,'Recipe Ingredients'!$G$2:$G$2000,"Pantry") | S62: =IFERROR(Q62/(Q62+R62),0) | T62: =IF(S62>='Start Here'!$C$6,"Yes","No") | U62: Year-round | V62: 1. Make fresh coconut milk from the coconut. 2. Simmer stock with bruised lemongrass, sliced ginger and ata rodo for 5 minutes. 3. Add sliced chicken and mushrooms, cook 8 minutes. 4. Stir in coconut milk, fish sauce and lime juice. Top with coriander and spring onion. | X62: Draft
A63: R076 | B63: Garden Minestrone | C63: Soup | D63: Lunch / Dinner | E63: Minestrone (Italy) | F63: Cabbage, green beans and black-eyed beans make it local. | G63: Plant-based, Training | H63: Vegan | I63: 20 | J63: 35 | K63: =I63+J63 | L63: =IF(J63=0,"No-cook",IF(K63<=25,"Quick","Standard")) | M63: 4 | N63: 280 | O63: 12 | P63: Carrot, Onion, Garlic, Cabbage | Q63: =COUNTIFS('Recipe Ingredients'!$A$2:$A$2000,A63,'Recipe Ingredients'!$G$2:$G$2000,"Basket") | R63: =COUNTIFS('Recipe Ingredients'!$A$2:$A$2000,A63,'Recipe Ingredients'!$G$2:$G$2000,"Protein")+COUNTIFS('Recipe Ingredients'!$A$2:$A$2000,A63,'Recipe Ingredients'!$G$2:$G$2000,"Pantry") | S63: =IFERROR(Q63/(Q63+R63),0) | T63: =IF(S63>='Start Here'!$C$6,"Yes","No") | U63: Year-round | V63: 1. Soften diced onion, carrots and garlic in olive oil. 2. Add chopped tomatoes, diced potato and stock. Simmer 15 minutes. 3. Add shredded cabbage, green beans, beans and pasta. Simmer 10 more. 4. Season and finish with herbs. | X63: Draft
A64: R077 | B64: Baked Plantain Chips with Lime & Yaji | C64: Snack | D64: Snack | E64: Tostones / plantain chips (Caribbean, Latin America) | F64: Baked, not deep-fried. | G64: Training, Plant-based | H64: Vegan | I64: 10 | J64: 25 | K64: =I64+J64 | L64: =IF(J64=0,"No-cook",IF(K64<=25,"Quick","Standard")) | M64: 3 | N64: 220 | O64: 2 | P64: Plantain, Lime | Q64: =COUNTIFS('Recipe Ingredients'!$A$2:$A$2000,A64,'Recipe Ingredients'!$G$2:$G$2000,"Basket") | R64: =COUNTIFS('Recipe Ingredients'!$A$2:$A$2000,A64,'Recipe Ingredients'!$G$2:$G$2000,"Protein")+COUNTIFS('Recipe Ingredients'!$A$2:$A$2000,A64,'Recipe Ingredients'!$G$2:$G$2000,"Pantry") | S64: =IFERROR(Q64/(Q64+R64),0) | T64: =IF(S64>='Start Here'!$C$6,"Yes","No") | U64: Year-round | V64: 1. Peel green plantains and slice very thin. 2. Toss with oil and salt, spread on a tray in one layer. 3. Bake at 180C for 20 to 25 minutes, turning once. 4. Finish with lime zest and yaji. | X64: Draft
A65: R078 | B65: Guacamole with Garden Egg Crudites | C65: Snack | D65: Snack / Starter | E65: Guacamole (Mexico) | F65: Garden egg, cucumber and carrot sticks to dip instead of tortilla chips. | G65: Wellness, Weight management | H65: Vegan | I65: 15 | J65: 0 | K65: =I65+J65 | L65: =IF(J65=0,"No-cook",IF(K65<=25,"Quick","Standard")) | M65: 3 | N65: 210 | O65: 4 | P65: Avocado, Tomato, Onion, Scotch bonnet | Q65: =COUNTIFS('Recipe Ingredients'!$A$2:$A$2000,A65,'Recipe Ingredients'!$G$2:$G$2000,"Basket") | R65: =COUNTIFS('Recipe Ingredients'!$A$2:$A$2000,A65,'Recipe Ingredients'!$G$2:$G$2000,"Protein")+COUNTIFS('Recipe Ingredients'!$A$2:$A$2000,A65,'Recipe Ingredients'!$G$2:$G$2000,"Pantry") | S65: =IFERROR(Q65/(Q65+R65),0) | T65: =IF(S65>='Start Here'!$C$6,"Yes","No") | U65: Garden egg (Jan-Oct) | V65: 1. Mash avocados with lime juice and salt. 2. Fold in diced tomato, onion, ata rodo and coriander. 3. Cut garden eggs, cucumber and carrots into sticks. 4. Serve together. | X65: Draft
A66: R079 | B66: Garden Egg Baba Ganoush | C66: Snack | D66: Snack / Side | E66: Baba ganoush (Levant) | F66: Charred garden eggs, with groundnut paste in place of tahini. | G66: Plant-based, Weight management | H66: Vegan | I66: 10 | J66: 20 | K66: =I66+J66 | L66: =IF(J66=0,"No-cook",IF(K66<=25,"Quick","Standard")) | M66: 4 | N66: 140 | O66: 4 | P66: Garden egg, Garlic, Lemon, Parsley | Q66: =COUNTIFS('Recipe Ingredients'!$A$2:$A$2000,A66,'Recipe Ingredients'!$G$2:$G$2000,"Basket") | R66: =COUNTIFS('Recipe Ingredients'!$A$2:$A$2000,A66,'Recipe Ingredients'!$G$2:$G$2000,"Protein")+COUNTIFS('Recipe Ingredients'!$A$2:$A$2000,A66,'Recipe Ingredients'!$G$2:$G$2000,"Pantry") | S66: =IFERROR(Q66/(Q66+R66),0) | T66: =IF(S66>='Start Here'!$C$6,"Yes","No") | U66: Garden egg (Jan-Oct) | V66: 1. Char garden eggs over a flame or under the grill until soft and blackened. 2. Peel and roughly chop. 3. Mash with garlic, lemon, groundnut paste, cumin, olive oil and salt. 4. Top with parsley. Serve with carrot sticks or bread. | X66: Draft
A67: R080 | B67: Sweet Potato Wedges with Yaji Yoghurt | C67: Side | D67: Side / Snack | E67: Sweet potato fries | F67: Yaji-spiced yoghurt dip instead of ketchup. | G67: Training | H67: Vegetarian | I67: 10 | J67: 30 | K67: =I67+J67 | L67: =IF(J67=0,"No-cook",IF(K67<=25,"Quick","Standard")) | M67: 3 | N67: 260 | O67: 6 | P67: Sweet potato, Lime, Garlic | Q67: =COUNTIFS('Recipe Ingredients'!$A$2:$A$2000,A67,'Recipe Ingredients'!$G$2:$G$2000,"Basket") | R67: =COUNTIFS('Recipe Ingredients'!$A$2:$A$2000,A67,'Recipe Ingredients'!$G$2:$G$2000,"Protein")+COUNTIFS('Recipe Ingredients'!$A$2:$A$2000,A67,'Recipe Ingredients'!$G$2:$G$2000,"Pantry") | S67: =IFERROR(Q67/(Q67+R67),0) | T67: =IF(S67>='Start Here'!$C$6,"Yes","No") | U67: Year-round | V67: 1. Cut sweet potatoes into wedges, toss with oil, paprika and salt. 2. Roast at 200C for 25 to 30 minutes. 3. Mix yoghurt with yaji, grated garlic and lime. 4. Serve wedges with the dip. | X67: Draft
A68: R081 | B68: Black-Eyed Bean Hummus with Veggie Sticks | C68: Snack | D68: Snack | E68: Hummus (Levant) | F68: Black-eyed beans and groundnut paste replace chickpeas and tahini. | G68: Plant-based, Training | H68: Vegan | I68: 15 | J68: 0 | K68: =I68+J68 | L68: =IF(J68=0,"No-cook",IF(K68<=25,"Quick","Standard")) | M68: 4 | N68: 230 | O68: 10 | P68: Garlic, Lemon, Carrot, Cucumber | Q68: =COUNTIFS('Recipe Ingredients'!$A$2:$A$2000,A68,'Recipe Ingredients'!$G$2:$G$2000,"Basket") | R68: =COUNTIFS('Recipe Ingredients'!$A$2:$A$2000,A68,'Recipe Ingredients'!$G$2:$G$2000,"Protein")+COUNTIFS('Recipe Ingredients'!$A$2:$A$2000,A68,'Recipe Ingredients'!$G$2:$G$2000,"Pantry") | S68: =IFERROR(Q68/(Q68+R68),0) | T68: =IF(S68>='Start Here'!$C$6,"Yes","No") | U68: Garden egg (Jan-Oct) | V68: 1. Blend beans, groundnut paste, garlic, lemon juice, cumin and olive oil with a splash of cold water until very smooth. 2. Season with salt. 3. Cut carrots, cucumber, tatashe and garden eggs into sticks. 4. Serve together. | X68: Draft
A69: R082 | B69: Roasted Corn with Lime & Yaji Butter | C69: Snack | D69: Snack / Side | E69: Elote (Mexico) | F69: Roadside roasted corn meets yaji and lime. Pair with ube in season. | G69: Training | H69: Vegetarian | I69: 5 | J69: 15 | K69: =I69+J69 | L69: =IF(J69=0,"No-cook",IF(K69<=25,"Quick","Standard")) | M69: 4 | N69: 200 | O69: 5 | P69: Sweet corn, Lime, Coriander | Q69: =COUNTIFS('Recipe Ingredients'!$A$2:$A$2000,A69,'Recipe Ingredients'!$G$2:$G$2000,"Basket") | R69: =COUNTIFS('Recipe Ingredients'!$A$2:$A$2000,A69,'Recipe Ingredients'!$G$2:$G$2000,"Protein")+COUNTIFS('Recipe Ingredients'!$A$2:$A$2000,A69,'Recipe Ingredients'!$G$2:$G$2000,"Pantry") | S69: =IFERROR(Q69/(Q69+R69),0) | T69: =IF(S69>='Start Here'!$C$6,"Yes","No") | U69: Sweet corn (Apr-Aug) | V69: 1. Roast corn over a flame or under the grill until charred all over. 2. Mix soft butter with yaji. 3. Brush corn with yaji butter. 4. Squeeze lime over and scatter coriander and cheese. | W69: Fresh corn Apr to Aug. Bundle with ube as a rainy season drop. | X69: Draft
A70: R083 | B70: Okra & Corn Succotash | C70: Side | D70: Side | E70: Succotash (US South) | F70: Nigerian okra and fresh corn, with ata rodo. | G70: Wellness, Training | H70: Vegetarian | I70: 10 | J70: 15 | K70: =I70+J70 | L70: =IF(J70=0,"No-cook",IF(K70<=25,"Quick","Standard")) | M70: 4 | N70: 150 | O70: 4 | P70: Okra, Sweet corn, Tomato, Onion | Q70: =COUNTIFS('Recipe Ingredients'!$A$2:$A$2000,A70,'Recipe Ingredients'!$G$2:$G$2000,"Basket") | R70: =COUNTIFS('Recipe Ingredients'!$A$2:$A$2000,A70,'Recipe Ingredients'!$G$2:$G$2000,"Protein")+COUNTIFS('Recipe Ingredients'!$A$2:$A$2000,A70,'Recipe Ingredients'!$G$2:$G$2000,"Pantry") | S70: =IFERROR(Q70/(Q70+R70),0) | T70: =IF(S70>='Start Here'!$C$6,"Yes","No") | U70: Sweet corn (Apr-Aug) | V70: 1. Slice okra into rounds and cut kernels off the corn. 2. Soften onion, garlic and tatashe in oil and butter. 3. Add okra and corn, cook 6 minutes on high so the okra stays crisp. 4. Add diced tomatoes and ata rodo, cook 3 minutes. Season. | X70: Draft
A71: R084 | B71: Banana Groundnut Nice Cream | C71: Dessert | D71: Dessert | E71: 'Nice cream' (vegan frozen banana dessert) | F71: Roasted groundnuts and dates make it taste like a Nigerian childhood treat. | G71: Plant-based, Training | H71: Vegan | I71: 10 | J71: 0 | K71: =I71+J71 | L71: =IF(J71=0,"No-cook",IF(K71<=25,"Quick","Standard")) | M71: 2 | N71: 280 | O71: 7 | P71: Banana, Groundnut, Dates | Q71: =COUNTIFS('Recipe Ingredients'!$A$2:$A$2000,A71,'Recipe Ingredients'!$G$2:$G$2000,"Basket") | R71: =COUNTIFS('Recipe Ingredients'!$A$2:$A$2000,A71,'Recipe Ingredients'!$G$2:$G$2000,"Protein")+COUNTIFS('Recipe Ingredients'!$A$2:$A$2000,A71,'Recipe Ingredients'!$G$2:$G$2000,"Pantry") | S71: =IFERROR(Q71/(Q71+R71),0) | T71: =IF(S71>='Start Here'!$C$6,"Yes","No") | U71: Year-round | V71: 1. Slice ripe bananas and freeze for at least 4 hours. 2. Blend frozen banana with dates and a splash of milk until creamy. 3. Pulse in half the groundnuts. 4. Serve straight away, topped with the rest of the groundnuts and cinnamon. | W71: The best use for overripe bananas. Pairs well with a discounted 'smoothie bananas' SKU. | X71: Draft
A72: R085 | B72: Grilled Pineapple with Coconut & Lime | C72: Dessert | D72: Dessert | E72: Abacaxi assado (Brazilian churrasco dessert) | F72: Toasted fresh coconut and lime zest. | G72: Wellness, Plant-based | H72: Vegetarian | I72: 10 | J72: 10 | K72: =I72+J72 | L72: =IF(J72=0,"No-cook",IF(K72<=25,"Quick","Standard")) | M72: 4 | N72: 130 | O72: 1 | P72: Pineapple, Coconut, Lime | Q72: =COUNTIFS('Recipe Ingredients'!$A$2:$A$2000,A72,'Recipe Ingredients'!$G$2:$G$2000,"Basket") | R72: =COUNTIFS('Recipe Ingredients'!$A$2:$A$2000,A72,'Recipe Ingredients'!$G$2:$G$2000,"Protein")+COUNTIFS('Recipe Ingredients'!$A$2:$A$2000,A72,'Recipe Ingredients'!$G$2:$G$2000,"Pantry") | S72: =IFERROR(Q72/(Q72+R72),0) | T72: =IF(S72>='Start Here'!$C$6,"Yes","No") | U72: Year-round | V72: 1. Cut pineapple into thick wedges. 2. Brush with honey and dust with cinnamon. 3. Grill or pan-sear until caramelised, 3 minutes a side. 4. Toast grated coconut in a dry pan. Scatter over with lime zest. | X72: Draft
A73: R086 | B73: Mango Coconut Rice Pudding | C73: Dessert | D73: Dessert | E73: Khao niao mamuang / mango sticky rice (Thailand) | F73: Local rice cooked in fresh coconut milk and sweetened with dates. | G73: Wellness | H73: Vegan | I73: 10 | J73: 30 | K73: =I73+J73 | L73: =IF(J73=0,"No-cook",IF(K73<=25,"Quick","Standard")) | M73: 4 | N73: 350 | O73: 5 | P73: Coconut, Mango, Dates, Lime | Q73: =COUNTIFS('Recipe Ingredients'!$A$2:$A$2000,A73,'Recipe Ingredients'!$G$2:$G$2000,"Basket") | R73: =COUNTIFS('Recipe Ingredients'!$A$2:$A$2000,A73,'Recipe Ingredients'!$G$2:$G$2000,"Protein")+COUNTIFS('Recipe Ingredients'!$A$2:$A$2000,A73,'Recipe Ingredients'!$G$2:$G$2000,"Pantry") | S73: =IFERROR(Q73/(Q73+R73),0) | T73: =IF(S73>='Start Here'!$C$6,"Yes","No") | U73: Mango (Feb-May, Aug-Sep) | V73: 1. Make coconut milk from the coconut, blending in the dates. 2. Simmer rice in the coconut milk with a pinch of salt, stirring often, for 25 to 30 minutes until creamy. 3. Cool slightly and stir in lime zest. 4. Serve topped with sliced mango. | W73: Best Feb to May. | X73: Draft
A74: R087 | B74: Watermelon Lime Ice Pops | C74: Dessert | D74: Snack | E74: Paletas (Mexico) | F74: Watermelon, lime and mint. | G74: Hydration, Weight management | H74: Vegetarian | I74: 10 | J74: 0 | K74: =I74+J74 | L74: =IF(J74=0,"No-cook",IF(K74<=25,"Quick","Standard")) | M74: 6 | N74: 40 | O74: 0 | P74: Watermelon, Lime, Mint | Q74: =COUNTIFS('Recipe Ingredients'!$A$2:$A$2000,A74,'Recipe Ingredients'!$G$2:$G$2000,"Basket") | R74: =COUNTIFS('Recipe Ingredients'!$A$2:$A$2000,A74,'Recipe Ingredients'!$G$2:$G$2000,"Protein")+COUNTIFS('Recipe Ingredients'!$A$2:$A$2000,A74,'Recipe Ingredients'!$G$2:$G$2000,"Pantry") | S74: =IFERROR(Q74/(Q74+R74),0) | T74: =IF(S74>='Start Here'!$C$6,"Yes","No") | U74: Year-round | V74: 1. Blend watermelon with lime juice and honey. 2. Finely chop mint and stir it in. 3. Pour into ice pop moulds or small cups with sticks. 4. Freeze at least 6 hours. | X74: Draft
A75: R088 | B75: No-Churn Mango Passion Sorbet | C75: Dessert | D75: Dessert | E75: Sorbet (Italy / France) | F75: Ripe local mangoes need almost no sugar. | G75: Wellness | H75: Vegetarian | I75: 15 | J75: 0 | K75: =I75+J75 | L75: =IF(J75=0,"No-cook",IF(K75<=25,"Quick","Standard")) | M75: 4 | N75: 120 | O75: 1 | P75: Mango, Passion fruit, Lime | Q75: =COUNTIFS('Recipe Ingredients'!$A$2:$A$2000,A75,'Recipe Ingredients'!$G$2:$G$2000,"Basket") | R75: =COUNTIFS('Recipe Ingredients'!$A$2:$A$2000,A75,'Recipe Ingredients'!$G$2:$G$2000,"Protein")+COUNTIFS('Recipe Ingredients'!$A$2:$A$2000,A75,'Recipe Ingredients'!$G$2:$G$2000,"Pantry") | S75: =IFERROR(Q75/(Q75+R75),0) | T75: =IF(S75>='Start Here'!$C$6,"Yes","No") | U75: Mango (Feb-May, Aug-Sep); Passion fruit (Jan-Mar, May-Jun, Aug-Nov) | V75: 1. Peel and cube mangoes and freeze for 4 hours. 2. Blend frozen mango with passion fruit pulp, lime and honey until smooth. 3. Serve soft, or freeze 1 hour for scoops. | W75: Best Feb to May. | X75: Draft
A76: R089 | B76: Crunchy Apple, Pear & Grape Salad | C76: Salad | D76: Lunch / Snack | E76: Waldorf salad (New York, US) | F76: Roasted groundnuts instead of walnuts, yoghurt instead of mayo. | G76: Weight management | H76: Vegetarian | I76: 15 | J76: 0 | K76: =I76+J76 | L76: =IF(J76=0,"No-cook",IF(K76<=25,"Quick","Standard")) | M76: 2 | N76: 280 | O76: 9 | P76: Apple, Pear, Grapes, Lettuce | Q76: =COUNTIFS('Recipe Ingredients'!$A$2:$A$2000,A76,'Recipe Ingredients'!$G$2:$G$2000,"Basket") | R76: =COUNTIFS('Recipe Ingredients'!$A$2:$A$2000,A76,'Recipe Ingredients'!$G$2:$G$2000,"Protein")+COUNTIFS('Recipe Ingredients'!$A$2:$A$2000,A76,'Recipe Ingredients'!$G$2:$G$2000,"Pantry") | S76: =IFERROR(Q76/(Q76+R76),0) | T76: =IF(S76>='Start Here'!$C$6,"Yes","No") | U76: Year-round | V76: 1. Core and dice apples and pear. Halve the grapes. 2. Mix yoghurt, lemon juice and honey. 3. Toss fruit with lettuce and dressing. 4. Top with roasted groundnuts. | W76: A natural recipe for the premium fruit box. | X76: Draft

Sheet Recipe Ingredients
A1: Recipe ID | B1: Recipe | C1: Ingredient | D1: Qty | E1: Unit | F1: Produce ID | G1: Source | H1: Note
A2: R015 | B2: =IFERROR(INDEX(Recipes!$B$2:$B$500,MATCH(A2,Recipes!$A$2:$A$500,0)),"") | C2: Rolled oats | D2: 1 | E2: cup | G2: Pantry
A3: R015 | B3: =IFERROR(INDEX(Recipes!$B$2:$B$500,MATCH(A3,Recipes!$A$2:$A$500,0)),"") | C3: Milk or tiger nut milk | D3: 1 | E3: cup | G3: Pantry
A4: R015 | B4: =IFERROR(INDEX(Recipes!$B$2:$B$500,MATCH(A4,Recipes!$A$2:$A$500,0)),"") | C4: Plain yoghurt | D4: 0.5 | E4: cup | G4: Pantry
A5: R015 | B5: =IFERROR(INDEX(Recipes!$B$2:$B$500,MATCH(A5,Recipes!$A$2:$A$500,0)),"") | C5: Chia seeds | D5: 1 | E5: tbsp | G5: Pantry
A6: R015 | B6: =IFERROR(INDEX(Recipes!$B$2:$B$500,MATCH(A6,Recipes!$A$2:$A$500,0)),"") | C6: Mango | D6: 1 | E6: pc | F6: P006 | G6: Basket | H6: diced
A7: R015 | B7: =IFERROR(INDEX(Recipes!$B$2:$B$500,MATCH(A7,Recipes!$A$2:$A$500,0)),"") | C7: Passion fruit | D7: 2 | E7: pc | F7: P015 | G7: Basket | H7: pulp
A8: R015 | B8: =IFERROR(INDEX(Recipes!$B$2:$B$500,MATCH(A8,Recipes!$A$2:$A$500,0)),"") | C8: Honey | D8: 1 | E8: tsp | G8: Pantry | H8: optional
A9: R016 | B9: =IFERROR(INDEX(Recipes!$B$2:$B$500,MATCH(A9,Recipes!$A$2:$A$500,0)),"") | C9: Pawpaw (papaya) | D9: 1 | E9: pc | F9: P005 | G9: Basket | H9: small, ripe
A10: R016 | B10: =IFERROR(INDEX(Recipes!$B$2:$B$500,MATCH(A10,Recipes!$A$2:$A$500,0)),"") | C10: Greek yoghurt | D10: 1 | E10: cup | G10: Pantry
A11: R016 | B11: =IFERROR(INDEX(Recipes!$B$2:$B$500,MATCH(A11,Recipes!$A$2:$A$500,0)),"") | C11: Granola | D11: 0.5 | E11: cup | G11: Pantry
A12: R016 | B12: =IFERROR(INDEX(Recipes!$B$2:$B$500,MATCH(A12,Recipes!$A$2:$A$500,0)),"") | C12: Pineapple | D12: 0.5 | E12: cup | F12: P003 | G12: Basket | H12: diced
A13: R016 | B13: =IFERROR(INDEX(Recipes!$B$2:$B$500,MATCH(A13,Recipes!$A$2:$A$500,0)),"") | C13: Lime | D13: 1 | E13: pc | F13: P010 | G13: Basket | H13: zest and juice
A14: R016 | B14: =IFERROR(INDEX(Recipes!$B$2:$B$500,MATCH(A14,Recipes!$A$2:$A$500,0)),"") | C14: Groundnut (fresh or roasted) | D14: 1 | E14: tbsp | F14: P040 | G14: Basket | H14: roasted, crushed
A15: R016 | B15: =IFERROR(INDEX(Recipes!$B$2:$B$500,MATCH(A15,Recipes!$A$2:$A$500,0)),"") | C15: Honey | D15: 1 | E15: tbsp | G15: Pantry
A16: R017 | B16: =IFERROR(INDEX(Recipes!$B$2:$B$500,MATCH(A16,Recipes!$A$2:$A$500,0)),"") | C16: Banana | D16: 2 | E16: pc | F16: P001 | G16: Basket | H16: very ripe
A17: R017 | B17: =IFERROR(INDEX(Recipes!$B$2:$B$500,MATCH(A17,Recipes!$A$2:$A$500,0)),"") | C17: Eggs | D17: 2 | E17: pc | G17: Protein
A18: R017 | B18: =IFERROR(INDEX(Recipes!$B$2:$B$500,MATCH(A18,Recipes!$A$2:$A$500,0)),"") | C18: Rolled oats | D18: 1 | E18: cup | G18: Pantry | H18: blended to flour
A19: R017 | B19: =IFERROR(INDEX(Recipes!$B$2:$B$500,MATCH(A19,Recipes!$A$2:$A$500,0)),"") | C19: Ground cinnamon | D19: 0.5 | E19: tsp | G19: Pantry
A20: R017 | B20: =IFERROR(INDEX(Recipes!$B$2:$B$500,MATCH(A20,Recipes!$A$2:$A$500,0)),"") | C20: Pineapple | D20: 1 | E20: cup | F20: P003 | G20: Basket | H20: finely diced
A21: R017 | B21: =IFERROR(INDEX(Recipes!$B$2:$B$500,MATCH(A21,Recipes!$A$2:$A$500,0)),"") | C21: Lime | D21: 0.5 | E21: pc | F21: P010 | G21: Basket
A22: R017 | B22: =IFERROR(INDEX(Recipes!$B$2:$B$500,MATCH(A22,Recipes!$A$2:$A$500,0)),"") | C22: Oil | D22: 1 | E22: tsp | G22: Staple
A23: R018 | B23: =IFERROR(INDEX(Recipes!$B$2:$B$500,MATCH(A23,Recipes!$A$2:$A$500,0)),"") | C23: Tomato (plum) | D23: 4 | E23: pc | F23: P042 | G23: Basket | H23: plum, chopped
A24: R018 | B24: =IFERROR(INDEX(Recipes!$B$2:$B$500,MATCH(A24,Recipes!$A$2:$A$500,0)),"") | C24: Red bell pepper | D24: 2 | E24: pc | F24: P044 | G24: Basket | H24: chopped
A25: R018 | B25: =IFERROR(INDEX(Recipes!$B$2:$B$500,MATCH(A25,Recipes!$A$2:$A$500,0)),"") | C25: Scotch bonnet | D25: 0.5 | E25: pc | F25: P046 | G25: Basket
A26: R018 | B26: =IFERROR(INDEX(Recipes!$B$2:$B$500,MATCH(A26,Recipes!$A$2:$A$500,0)),"") | C26: Onion (red & white) | D26: 1 | E26: pc | F26: P048 | G26: Basket
A27: R018 | B27: =IFERROR(INDEX(Recipes!$B$2:$B$500,MATCH(A27,Recipes!$A$2:$A$500,0)),"") | C27: Garlic | D27: 2 | E27: cloves | F27: P051 | G27: Basket
A28: R018 | B28: =IFERROR(INDEX(Recipes!$B$2:$B$500,MATCH(A28,Recipes!$A$2:$A$500,0)),"") | C28: Amaranth greens (Nigerian spinach) | D28: 1 | E28: cup | F28: P073 | G28: Basket | H28: chopped
A29: R018 | B29: =IFERROR(INDEX(Recipes!$B$2:$B$500,MATCH(A29,Recipes!$A$2:$A$500,0)),"") | C29: Eggs | D29: 4 | E29: pc | G29: Protein
A30: R018 | B30: =IFERROR(INDEX(Recipes!$B$2:$B$500,MATCH(A30,Recipes!$A$2:$A$500,0)),"") | C30: Cumin or curry powder | D30: 1 | E30: tsp | G30: Pantry
A31: R018 | B31: =IFERROR(INDEX(Recipes!$B$2:$B$500,MATCH(A31,Recipes!$A$2:$A$500,0)),"") | C31: Bread | D31: 4 | E31: slices | G31: Pantry | H31: to serve
A32: R018 | B32: =IFERROR(INDEX(Recipes!$B$2:$B$500,MATCH(A32,Recipes!$A$2:$A$500,0)),"") | C32: Oil | D32: 1 | E32: tbsp | G32: Staple
A33: R018 | B33: =IFERROR(INDEX(Recipes!$B$2:$B$500,MATCH(A33,Recipes!$A$2:$A$500,0)),"") | C33: Salt | D33: 1 | E33: pinch | G33: Staple
A34: R019 | B34: =IFERROR(INDEX(Recipes!$B$2:$B$500,MATCH(A34,Recipes!$A$2:$A$500,0)),"") | C34: Avocado | D34: 1 | E34: pc | F34: P012 | G34: Basket | H34: ripe
A35: R019 | B35: =IFERROR(INDEX(Recipes!$B$2:$B$500,MATCH(A35,Recipes!$A$2:$A$500,0)),"") | C35: Tomato (plum) | D35: 2 | E35: pc | F35: P042 | G35: Basket
A36: R019 | B36: =IFERROR(INDEX(Recipes!$B$2:$B$500,MATCH(A36,Recipes!$A$2:$A$500,0)),"") | C36: Onion (red & white) | D36: 0.25 | E36: pc | F36: P048 | G36: Basket | H36: red
A37: R019 | B37: =IFERROR(INDEX(Recipes!$B$2:$B$500,MATCH(A37,Recipes!$A$2:$A$500,0)),"") | C37: Scotch bonnet | D37: 0.25 | E37: pc | F37: P046 | G37: Basket
A38: R019 | B38: =IFERROR(INDEX(Recipes!$B$2:$B$500,MATCH(A38,Recipes!$A$2:$A$500,0)),"") | C38: Lime | D38: 1 | E38: pc | F38: P010 | G38: Basket
A39: R019 | B39: =IFERROR(INDEX(Recipes!$B$2:$B$500,MATCH(A39,Recipes!$A$2:$A$500,0)),"") | C39: Wholewheat bread | D39: 4 | E39: slices | G39: Pantry
A40: R019 | B40: =IFERROR(INDEX(Recipes!$B$2:$B$500,MATCH(A40,Recipes!$A$2:$A$500,0)),"") | C40: Eggs | D40: 2 | E40: pc | G40: Protein | H40: boiled, optional
A41: R019 | B41: =IFERROR(INDEX(Recipes!$B$2:$B$500,MATCH(A41,Recipes!$A$2:$A$500,0)),"") | C41: Salt | D41: 1 | E41: pinch | G41: Staple
A42: R020 | B42: =IFERROR(INDEX(Recipes!$B$2:$B$500,MATCH(A42,Recipes!$A$2:$A$500,0)),"") | C42: Sweet potato | D42: 2 | E42: pc | F42: P069 | G42: Basket | H42: medium
A43: R020 | B43: =IFERROR(INDEX(Recipes!$B$2:$B$500,MATCH(A43,Recipes!$A$2:$A$500,0)),"") | C43: Onion (red & white) | D43: 1 | E43: pc | F43: P048 | G43: Basket
A44: R020 | B44: =IFERROR(INDEX(Recipes!$B$2:$B$500,MATCH(A44,Recipes!$A$2:$A$500,0)),"") | C44: Red bell pepper | D44: 1 | E44: pc | F44: P044 | G44: Basket
A45: R020 | B45: =IFERROR(INDEX(Recipes!$B$2:$B$500,MATCH(A45,Recipes!$A$2:$A$500,0)),"") | C45: Amaranth greens (Nigerian spinach) | D45: 1 | E45: cup | F45: P073 | G45: Basket
A46: R020 | B46: =IFERROR(INDEX(Recipes!$B$2:$B$500,MATCH(A46,Recipes!$A$2:$A$500,0)),"") | C46: Spring onion | D46: 1 | E46: stalk | F46: P049 | G46: Basket
A47: R020 | B47: =IFERROR(INDEX(Recipes!$B$2:$B$500,MATCH(A47,Recipes!$A$2:$A$500,0)),"") | C47: Eggs | D47: 4 | E47: pc | G47: Protein
A48: R020 | B48: =IFERROR(INDEX(Recipes!$B$2:$B$500,MATCH(A48,Recipes!$A$2:$A$500,0)),"") | C48: Paprika | D48: 0.5 | E48: tsp | G48: Pantry
A49: R020 | B49: =IFERROR(INDEX(Recipes!$B$2:$B$500,MATCH(A49,Recipes!$A$2:$A$500,0)),"") | C49: Oil | D49: 1 | E49: tbsp | G49: Staple
A50: R020 | B50: =IFERROR(INDEX(Recipes!$B$2:$B$500,MATCH(A50,Recipes!$A$2:$A$500,0)),"") | C50: Salt | D50: 1 | E50: pinch | G50: Staple
A51: R021 | B51: =IFERROR(INDEX(Recipes!$B$2:$B$500,MATCH(A51,Recipes!$A$2:$A$500,0)),"") | C51: Plantain (ripe & unripe) | D51: 1 | E51: pc | F51: P002 | G51: Basket | H51: ripe
A52: R021 | B52: =IFERROR(INDEX(Recipes!$B$2:$B$500,MATCH(A52,Recipes!$A$2:$A$500,0)),"") | C52: Eggs | D52: 6 | E52: pc | G52: Protein
A53: R021 | B53: =IFERROR(INDEX(Recipes!$B$2:$B$500,MATCH(A53,Recipes!$A$2:$A$500,0)),"") | C53: Amaranth greens (Nigerian spinach) | D53: 1 | E53: cup | F53: P073 | G53: Basket
A54: R021 | B54: =IFERROR(INDEX(Recipes!$B$2:$B$500,MATCH(A54,Recipes!$A$2:$A$500,0)),"") | C54: Onion (red & white) | D54: 1 | E54: pc | F54: P048 | G54: Basket
A55: R021 | B55: =IFERROR(INDEX(Recipes!$B$2:$B$500,MATCH(A55,Recipes!$A$2:$A$500,0)),"") | C55: Red bell pepper | D55: 1 | E55: pc | F55: P044 | G55: Basket
A56: R021 | B56: =IFERROR(INDEX(Recipes!$B$2:$B$500,MATCH(A56,Recipes!$A$2:$A$500,0)),"") | C56: Scotch bonnet | D56: 0.25 | E56: pc | F56: P046 | G56: Basket
A57: R021 | B57: =IFERROR(INDEX(Recipes!$B$2:$B$500,MATCH(A57,Recipes!$A$2:$A$500,0)),"") | C57: Oil | D57: 1 | E57: tbsp | G57: Staple
A58: R021 | B58: =IFERROR(INDEX(Recipes!$B$2:$B$500,MATCH(A58,Recipes!$A$2:$A$500,0)),"") | C58: Salt | D58: 1 | E58: pinch | G58: Staple
A59: R022 | B59: =IFERROR(INDEX(Recipes!$B$2:$B$500,MATCH(A59,Recipes!$A$2:$A$500,0)),"") | C59: Greek yoghurt | D59: 1.5 | E59: cups | G59: Pantry
A60: R022 | B60: =IFERROR(INDEX(Recipes!$B$2:$B$500,MATCH(A60,Recipes!$A$2:$A$500,0)),"") | C60: Pineapple | D60: 1 | E60: cup | F60: P003 | G60: Basket | H60: diced
A61: R022 | B61: =IFERROR(INDEX(Recipes!$B$2:$B$500,MATCH(A61,Recipes!$A$2:$A$500,0)),"") | C61: Banana | D61: 1 | E61: pc | F61: P001 | G61: Basket
A62: R022 | B62: =IFERROR(INDEX(Recipes!$B$2:$B$500,MATCH(A62,Recipes!$A$2:$A$500,0)),"") | C62: Mango | D62: 0.5 | E62: pc | F62: P006 | G62: Basket
A63: R022 | B63: =IFERROR(INDEX(Recipes!$B$2:$B$500,MATCH(A63,Recipes!$A$2:$A$500,0)),"") | C63: Tiger nut | D63: 3 | E63: tbsp | F63: P024 | G63: Basket | H63: chopped
A64: R022 | B64: =IFERROR(INDEX(Recipes!$B$2:$B$500,MATCH(A64,Recipes!$A$2:$A$500,0)),"") | C64: Coconut | D64: 2 | E64: tbsp | F64: P016 | G64: Basket | H64: grated
A65: R022 | B65: =IFERROR(INDEX(Recipes!$B$2:$B$500,MATCH(A65,Recipes!$A$2:$A$500,0)),"") | C65: Honey | D65: 1 | E65: tbsp | G65: Pantry
A66: R023 | B66: =IFERROR(INDEX(Recipes!$B$2:$B$500,MATCH(A66,Recipes!$A$2:$A$500,0)),"") | C66: Chia seeds | D66: 4 | E66: tbsp | G66: Pantry
A67: R023 | B67: =IFERROR(INDEX(Recipes!$B$2:$B$500,MATCH(A67,Recipes!$A$2:$A$500,0)),"") | C67: Coconut | D67: 0.5 | E67: pc | F67: P016 | G67: Basket | H67: for 1 cup fresh milk
A68: R023 | B68: =IFERROR(INDEX(Recipes!$B$2:$B$500,MATCH(A68,Recipes!$A$2:$A$500,0)),"") | C68: Dates | D68: 2 | E68: pc | F68: P030 | G68: Basket | H68: pitted
A69: R023 | B69: =IFERROR(INDEX(Recipes!$B$2:$B$500,MATCH(A69,Recipes!$A$2:$A$500,0)),"") | C69: Mango | D69: 1 | E69: pc | F69: P006 | G69: Basket | H69: diced
A70: R023 | B70: =IFERROR(INDEX(Recipes!$B$2:$B$500,MATCH(A70,Recipes!$A$2:$A$500,0)),"") | C70: Lime | D70: 1 | E70: pc | F70: P010 | G70: Basket | H70: zest
A71: R024 | B71: =IFERROR(INDEX(Recipes!$B$2:$B$500,MATCH(A71,Recipes!$A$2:$A$500,0)),"") | C71: Watermelon | D71: 2 | E71: cups | F71: P004 | G71: Basket | H71: spears
A72: R024 | B72: =IFERROR(INDEX(Recipes!$B$2:$B$500,MATCH(A72,Recipes!$A$2:$A$500,0)),"") | C72: Pineapple | D72: 1 | E72: cup | F72: P003 | G72: Basket
A73: R024 | B73: =IFERROR(INDEX(Recipes!$B$2:$B$500,MATCH(A73,Recipes!$A$2:$A$500,0)),"") | C73: Pawpaw (papaya) | D73: 1 | E73: cup | F73: P005 | G73: Basket
A74: R024 | B74: =IFERROR(INDEX(Recipes!$B$2:$B$500,MATCH(A74,Recipes!$A$2:$A$500,0)),"") | C74: Cucumber | D74: 1 | E74: pc | F74: P054 | G74: Basket | H74: spears
A75: R024 | B75: =IFERROR(INDEX(Recipes!$B$2:$B$500,MATCH(A75,Recipes!$A$2:$A$500,0)),"") | C75: Mango | D75: 0.5 | E75: pc | F75: P006 | G75: Basket | H75: in season
A76: R024 | B76: =IFERROR(INDEX(Recipes!$B$2:$B$500,MATCH(A76,Recipes!$A$2:$A$500,0)),"") | C76: Lime | D76: 2 | E76: pc | F76: P010 | G76: Basket
A77: R024 | B77: =IFERROR(INDEX(Recipes!$B$2:$B$500,MATCH(A77,Recipes!$A$2:$A$500,0)),"") | C77: Yaji (suya spice) | D77: 1 | E77: tsp | G77: Pantry
A78: R024 | B78: =IFERROR(INDEX(Recipes!$B$2:$B$500,MATCH(A78,Recipes!$A$2:$A$500,0)),"") | C78: Salt | D78: 1 | E78: pinch | G78: Staple
A79: R025 | B79: =IFERROR(INDEX(Recipes!$B$2:$B$500,MATCH(A79,Recipes!$A$2:$A$500,0)),"") | C79: Garden egg | D79: 4 | E79: pc | F79: P061 | G79: Basket
A80: R025 | B80: =IFERROR(INDEX(Recipes!$B$2:$B$500,MATCH(A80,Recipes!$A$2:$A$500,0)),"") | C80: Tomato (plum) | D80: 3 | E80: pc | F80: P042 | G80: Basket
A81: R025 | B81: =IFERROR(INDEX(Recipes!$B$2:$B$500,MATCH(A81,Recipes!$A$2:$A$500,0)),"") | C81: Cucumber | D81: 1 | E81: pc | F81: P054 | G81: Basket
A82: R025 | B82: =IFERROR(INDEX(Recipes!$B$2:$B$500,MATCH(A82,Recipes!$A$2:$A$500,0)),"") | C82: Onion (red & white) | D82: 0.5 | E82: pc | F82: P048 | G82: Basket | H82: red
A83: R025 | B83: =IFERROR(INDEX(Recipes!$B$2:$B$500,MATCH(A83,Recipes!$A$2:$A$500,0)),"") | C83: Parsley | D83: 0.5 | E83: bunch | F83: P081 | G83: Basket | H83: or scent leaf
A84: R025 | B84: =IFERROR(INDEX(Recipes!$B$2:$B$500,MATCH(A84,Recipes!$A$2:$A$500,0)),"") | C84: Lemon | D84: 1 | E84: pc | F84: P009 | G84: Basket | H84: juiced
A85: R025 | B85: =IFERROR(INDEX(Recipes!$B$2:$B$500,MATCH(A85,Recipes!$A$2:$A$500,0)),"") | C85: Olive oil | D85: 2 | E85: tbsp | G85: Staple
A86: R025 | B86: =IFERROR(INDEX(Recipes!$B$2:$B$500,MATCH(A86,Recipes!$A$2:$A$500,0)),"") | C86: Salt | D86: 1 | E86: pinch | G86: Staple
A87: R026 | B87: =IFERROR(INDEX(Recipes!$B$2:$B$500,MATCH(A87,Recipes!$A$2:$A$500,0)),"") | C87: Chicken breast | D87: 2 | E87: pc | G87: Protein
A88: R026 | B88: =IFERROR(INDEX(Recipes!$B$2:$B$500,MATCH(A88,Recipes!$A$2:$A$500,0)),"") | C88: Pineapple | D88: 0.25 | E88: pc | F88: P003 | G88: Basket | H88: in rings
A89: R026 | B89: =IFERROR(INDEX(Recipes!$B$2:$B$500,MATCH(A89,Recipes!$A$2:$A$500,0)),"") | C89: Lettuce (iceberg / romaine / local) | D89: 1 | E89: head | F89: P058 | G89: Basket
A90: R026 | B90: =IFERROR(INDEX(Recipes!$B$2:$B$500,MATCH(A90,Recipes!$A$2:$A$500,0)),"") | C90: Cucumber | D90: 1 | E90: pc | F90: P054 | G90: Basket
A91: R026 | B91: =IFERROR(INDEX(Recipes!$B$2:$B$500,MATCH(A91,Recipes!$A$2:$A$500,0)),"") | C91: Red bell pepper | D91: 1 | E91: pc | F91: P044 | G91: Basket
A92: R026 | B92: =IFERROR(INDEX(Recipes!$B$2:$B$500,MATCH(A92,Recipes!$A$2:$A$500,0)),"") | C92: Spring onion | D92: 1 | E92: stalk | F92: P049 | G92: Basket
A93: R026 | B93: =IFERROR(INDEX(Recipes!$B$2:$B$500,MATCH(A93,Recipes!$A$2:$A$500,0)),"") | C93: Lime | D93: 1 | E93: pc | F93: P010 | G93: Basket
A94: R026 | B94: =IFERROR(INDEX(Recipes!$B$2:$B$500,MATCH(A94,Recipes!$A$2:$A$500,0)),"") | C94: Yaji (suya spice) | D94: 1 | E94: tsp | G94: Pantry
A95: R026 | B95: =IFERROR(INDEX(Recipes!$B$2:$B$500,MATCH(A95,Recipes!$A$2:$A$500,0)),"") | C95: Honey | D95: 1 | E95: tsp | G95: Pantry
A96: R026 | B96: =IFERROR(INDEX(Recipes!$B$2:$B$500,MATCH(A96,Recipes!$A$2:$A$500,0)),"") | C96: Olive oil | D96: 2 | E96: tbsp | G96: Staple
A97: R027 | B97: =IFERROR(INDEX(Recipes!$B$2:$B$500,MATCH(A97,Recipes!$A$2:$A$500,0)),"") | C97: Avocado | D97: 1 | E97: pc | F97: P012 | G97: Basket
A98: R027 | B98: =IFERROR(INDEX(Recipes!$B$2:$B$500,MATCH(A98,Recipes!$A$2:$A$500,0)),"") | C98: Mango | D98: 1 | E98: pc | F98: P006 | G98: Basket
A99: R027 | B99: =IFERROR(INDEX(Recipes!$B$2:$B$500,MATCH(A99,Recipes!$A$2:$A$500,0)),"") | C99: Cucumber | D99: 1 | E99: pc | F99: P054 | G99: Basket
A100: R027 | B100: =IFERROR(INDEX(Recipes!$B$2:$B$500,MATCH(A100,Recipes!$A$2:$A$500,0)),"") | C100: Onion (red & white) | D100: 0.25 | E100: pc | F100: P048 | G100: Basket | H100: red
...

Sheet Box Ideas
A1: Box / drop | B1: Window | C1: What's inside | D1: Recipes it unlocks | E1: Positioning line | F1: Notes
A2: Agbalumo Season Drop | B2: Dec-May (peak Jan-Mar) | C2: Agbalumo x20, velvet tamarind (awin) cup | D2: Eat as-is | E2: The one fruit everybody waits for all year. Back for a few months only. | F2: Grade by size, sell by count. Limited quantity drives urgency. Pair with a 'last week of the season' push.
A3: Harmattan Citrus Box | B3: Oct-Jan | C3: Oranges, tangerines, grapefruit, limes, lemons, ginger, turmeric | D3: R032, R037 | E3: Peak citrus season, at its sweetest. | F3: Citrus is at its best Oct-Dec. Lowest-cost, highest-volume box of the year.
A4: Mango Rush | B4: Feb-May | C4: Two mango varieties (Ogbomoso + cherry), limes, coconut, passion fruit | D4: R015, R027, R086, R088 | E4: It's mango season. Here's what to do with all of them. | F4: Name the varieties on the card. People love knowing where their mangoes are from.
A5: Hydration Box | B5: Year-round (best Dec-Apr) | C5: Watermelon, cucumber, mint, lemons, limes, pineapple | D5: R024, R087 | E5: Built for the heat and for after training. | F5: Strong fit for runners and gym-goers in the Phase 1 audience.
A6: Training Fuel Basket | B6: Year-round | C6: Bananas, plantain, sweet potatoes, avocado, efo tete, dates, groundnuts, tatashe | D6: R020, R021, R040, R041, R064 | E6: The produce side of a training week. | F6: Pair with Kachi's goal-based basket recommendation.
A7: Salad Week Kit | B7: Year-round | C7: Lettuce, tomatoes, cucumber, carrots, both cabbages, red onion, lemons, garden eggs, parsley | D7: R025, R029, R030, R031, R039 | E7: Five different salads, zero wasted leaves. | F7: Lettuce is the shelf-life risk. Deliver early in the week.
A8: Stir-Fry Night Kit | B8: Year-round | C8: Tatashe, green pepper, carrots, spring onion, ginger, garlic, broccoli or green beans | D8: R058, R060, R061, R067 | E8: Takeaway-style dinners in 20 minutes. | F8: Broccoli is premium; green beans are the default swap.
A9: Ube & Corn Drop | B9: May-Sep | C9: Ube x10, sweet corn x6 | D9: R082, eat as-is | E9: The rainy season classic, delivered. | F9: Nostalgia sells. Strong social content angle.
A10: Tiger Nut & Snack Box | B10: Year-round | C10: Tiger nuts, dates, coconut, roasted groundnuts | D10: R022, R084 | E10: Snacks and plant milk from four local staples. | F10: Long shelf life. Easy add-on to any order.
A11: Imported Fruit Box (premium) | B11: Year-round | C11: Apples, pears, grapes, kiwi, blueberries, strawberries | D11: R089 | E11: The fruit bowl, upgraded. | F11: Higher margin, higher price. Keep it an add-on, not the default.

Sheet Market Scan
A1: Player | B1: Type | C1: Market | D1: What they sell / do | E1: Price signals | F1: Recipe or meal approach | G1: Borrow | H1: Gap for Basket | I1: Source
A2: SwanCape Farms | B2: Farm + retail/B2B supplier | C2: Lagos | D2: Own farms in Epe and Irawo plus smallholders. HACCP handling, premium retail packaging, supplies supermarkets, chefs and households. Farm shop in Lekki Scheme 2. WhatsApp ordering. | E2: Weekly Veggie Box N8,000/week. Planner estimates: Egusi for 4 ~N14,000, Jollof for 6 ~N18,000, Pepper soup for 2 ~N8,000. | F2: Meal planner: type a dish and headcount, get a live-priced ingredient list sent to WhatsApp. Menu is traditional Nigerian (Egusi, Ogbono, Jollof, Efo riro). | G2: Dish-to-priced-cart flow. A simple weekly box price anchor. | H2: Their recipes are traditional soups and stews. Basket's library is light global dishes for goal-driven eaters. They also lead with 'AI' in copy, which Basket deliberately does not. | I2: swancapefarms.com, swancapefarms.com/meal-planner
A3: Mint Foods | B3: Online grocery (Shopify) | C3: Lagos | D3: Full grocery plus a strong premium produce range: hydroponic herbs, microgreens, imported berries, local and imported variants of the same item. | E3: Lemons: 4 local N1,900 vs 5 Dutch N13,800. Cauliflower local N2,750 vs imported N16,900. Blueberries 125g N5,720. Pineapple N1,300. | F3: None. Product descriptions suggest uses but there are no recipes. | G3: Origin-tiered variants on one product page. A ready-to-eat 'eat me' avocado pack. | H3: No recipes, no goal framing, no baskets. | I3: mintfoods.store
A4: The Fresh Place | B4: Prepared health food + fruit | C4: Lekki, Lagos | D4: Juices, smoothies, parfaits, salad trays, fruit bundles, detox plans, single fruits and vegetables. Saturday delivery for bundles. | E4: Juices N3,500-N4,500. Salad trays N30,000-N50,000. Family Fruit Bundle N35,000. Local lemon/tangerine N300 each, imported orange N950, avocado N2,000-N2,500. | F4: Finished products (Mango-licious, Avo-Cardio, 24 Carrot Gold) rather than recipes. | G4: Occasion bundles (Work Week Juice Bundle) and fruit hampers. | H4: Their prepared items cost several times the raw produce. Basket recipes let people make the same drinks and salads at home. | I4: thefreshplace.ng
A5: Home Basket by Aduke | B5: Online supermarket | C5: Lagos Island | D5: Groceries and pantry from a Sura market base, curated bundles, WhatsApp support. | E5: Not captured. Catalogue loads client-side. | F5: None visible. | G5: Market-adjacent sourcing story, curated bundles. | H5: Positioned as a general supermarket. Not health-led. | I5: homebasketng.com
A6: Freshcart.ng | B6: Online produce | C6: Lagos | D6: Could not be checked. The site blocks automated access and has no indexed pages. | E6: - | F6: - | G6: - | H6: Check manually and on Instagram. | I6: freshcart.ng
A7: Chef4Me | B7: Chef marketplace + meal delivery | C7: Lagos (US-registered) | D7: Hire private chefs, order home-cooked meals, and an assistant that suggests meals by health goal or by what you have at home. Blog content like a modern jollof guide. | E7: Per chef / per order. | F7: Chef-cooked meals, not cook-at-home recipes. | G7: Dietary preference capture during ordering. | H7: No produce. Basket can be the ingredient layer for people who want to cook themselves. | I7: chef4me.ai, Google Play listing
A8: HelloFresh | B8: Meal kit | C8: US / global | D8: 100+ weekly menu and market items. Menus: Meat & Veggies, Veggie, Family Friendly, Fit & Wholesome, Quick & Easy, Pescatarian. 21+ protein and side swaps. | E8: About $8.99-$11.99 per serving. | F8: ~30 min recipes, Quick & Easy 20 min or less. Step-by-step photo cards with timings. | G8: Goal-named menus. Time on every card. Swap chips. | H8: Imported-ingredient model does not translate to Lagos. Recipe adaptation does. | I8: hellofresh.com, Plated Verdict, MealFan
A9: Sunbasket | B9: Meal kit | C9: US | D9: Organic-leaning kits and semi-prepared meals with diet-led plans. | E9: Premium. | F9: Semi-prepared kits cut cooking time. | G9: Part-prepped produce as an add-on (relevant if Fresh Cuts returns). | H9: Price point far above Lagos mass market. | I9: Taste of Home 2026 review
A10: Home Chef | B10: Meal kit | C10: US | D10: Classic kits, 15-minute kits, oven-ready and microwave meals. 'Customize It' protein swaps. Calorie- and carb-conscious filters. | E10: About $9.99 per serving; family plan minimums. | F10: Several effort levels in one menu. | G10: Effort tiers (no-cook / quick / standard) and protein swaps. Both are in the Recipes tab. | H10: Built around supplied proteins. Basket supplies produce only. | I10: Plated Verdict, The Meal Kit Review, MealDigest
A11: Marley Spoon | B11: Meal kit | C11: US / EU / AU | D11: Martha Stewart-developed recipes. Large weekly menu with add-ons. Diet filters: low-carb, under 650 cal, Mediterranean, vegetarian, vegan, climatarian. | E11: About $9-$13 per serving. | F11: Seasonal, internationally inspired, more technique-heavy. | G11: Seasonal 'what's good this week' editorial. Diet filters. | H11: Basket can do seasonal editorial with real Nigerian seasons, which no international kit can. | I11: MealFan, MealDigest, The Meal Kit Review

Sheet Sources
A1: Source | B1: URL | C1: Used for
A2: SwanCape Farms homepage | B2: https://swancapefarms.com/ | C2: Positioning, Weekly Veggie Box price
A3: SwanCape Farms meal planner | B3: https://swancapefarms.com/meal-planner | C3: Planner flow and dish price estimates
A4: Mint Foods produce collection | B4: https://mintfoods.store/collections/fresh-fruits-vegetables | C4: Product range, local vs imported variants, benchmark prices
A5: The Fresh Place | B5: https://thefreshplace.ng/ | C5: Product range, bundles, juices, benchmark prices
A6: The Fresh Place fruits & vegetables | B6: https://thefreshplace.ng/product-category/fruits-and-vegetables/ | C6: Benchmark prices for 35 produce items, refreshed 17 Oct 2026
A7: Home Basket by Aduke | B7: https://www.homebasketng.com/ | C7: Positioning
A8: Chef4Me | B8: https://chef4me.ai/ | C8: Product description
A9: Chef4Me on Google Play | B9: https://play.google.com/store/apps/details?id=com.chefuser | C9: Product description
A10: Kitchen Butterfly: Nigerian Seasonal Produce Calendar V1.3 (2018) | B10: https://www.kitchenbutterfly.com/wp-content/uploads/2018/01/2018_Nigerian_SeasonalProduceCalendar_V1.3.pdf | C10: Season months for 'Sourced' rows
A11: Kitchen Butterfly: Nigeria's dry season produce | B11: https://www.kitchenbutterfly.com/nigerias-dry-seasons-produce-januaryfebruary/ | C11: Agbalumo, citrus, watermelon notes
A12: Kitchen Butterfly: dry-wet season produce | B12: https://www.kitchenbutterfly.com/nigerias-dry-wet-seasons-produce-februarymarch/ | C12: Soursop, guava, velvet tamarind, local names
... A18: Taste of Home: best meal kits 2026 | B18: https://www.tasteofhome.com/article/best-meal-kit-delivery-2026/ | C18: Sunbasket semi-prepared kits
